Workbook

Sheet Mercado 2025 y 2026
A1: Ficohsa
A4: ESTADO DE RESULTADOS | B4: 45658 | C4: 45689 | D4: 45717 | E4: 45748 | F4: 45778 | G4: ENERO A MAYO | H4: 45809 | I4: 45839 | J4: 45870 | K4: 45901 | L4: 45931 | M4: 45962 | N4: 45992 | O4: ACUMULADO | Q4: 46023 | R4: 46054 | S4: 46082 | T4: 46113 | U4: 46143 | V4: 46174 | W4: 46204 | X4: 46235 | Y4: ACUMULADO
A5: Primas | B5: =IF(OR(SUM($Q5:$U5)=0,COUNTIF($Q5:$U5,"<0")*COUNTIF($Q5:$U5,">0")>0),$G5/5,$G5*Q5/SUM($Q5:$U5)) -> 0 | C5: =IF(OR(SUM($Q5:$U5)=0,COUNTIF($Q5:$U5,"<0")*COUNTIF($Q5:$U5,">0")>0),$G5/5,$G5*R5/SUM($Q5:$U5)) -> 0 | D5: =IF(OR(SUM($Q5:$U5)=0,COUNTIF($Q5:$U5,"<0")*COUNTIF($Q5:$U5,">0")>0),$G5/5,$G5*S5/SUM($Q5:$U5)) -> 0 | E5: =IF(OR(SUM($Q5:$U5)=0,COUNTIF($Q5:$U5,"<0")*COUNTIF($Q5:$U5,">0")>0),$G5/5,$G5*T5/SUM($Q5:$U5)) -> 0 | F5: =IF(OR(SUM($Q5:$U5)=0,COUNTIF($Q5:$U5,"<0")*COUNTIF($Q5:$U5,">0")>0),$G5/5,$G5*U5/SUM($Q5:$U5)) -> 0 | G5: 0 | H5: 0 | I5: 0 | J5: 0 | K5: 0 | L5: 0 | M5: 0 | N5: 0 | O5: =SUM(B5:F5,H5:N5) -> 0 | Q5: 0 | R5: 0 | S5: 0 | T5: 0 | U5: 0 | V5: 0 | W5: 0 | X5: 0 | Y5: =SUM(Q5:X5) -> 0
A6: Seguro Directo | B6: =IF(OR(SUM($Q6:$U6)=0,COUNTIF($Q6:$U6,"<0")*COUNTIF($Q6:$U6,">0")>0),$G6/5,$G6*Q6/SUM($Q6:$U6)) -> 18327417 | C6: =IF(OR(SUM($Q6:$U6)=0,COUNTIF($Q6:$U6,"<0")*COUNTIF($Q6:$U6,">0")>0),$G6/5,$G6*R6/SUM($Q6:$U6)) -> 17092855 | D6: =IF(OR(SUM($Q6:$U6)=0,COUNTIF($Q6:$U6,"<0")*COUNTIF($Q6:$U6,">0")>0),$G6/5,$G6*S6/SUM($Q6:$U6)) -> 15638711 | E6: =IF(OR(SUM($Q6:$U6)=0,COUNTIF($Q6:$U6,"<0")*COUNTIF($Q6:$U6,">0")>0),$G6/5,$G6*T6/SUM($Q6:$U6)) -> 32848248 | F6: =IF(OR(SUM($Q6:$U6)=0,COUNTIF($Q6:$U6,"<0")*COUNTIF($Q6:$U6,">0")>0),$G6/5,$G6*U6/SUM($Q6:$U6)) -> 14593229 | G6: 98500460 | H6: 12856807 | I6: 15869023 | J6: 14136893 | K6: 14833950 | L6: 14088628 | M6: 12282663 | N6: 27000392 | O6: =SUM(B6:F6,H6:N6) -> 2.0956882e+08 | Q6: 16586977 | R6: 15469654 | S6: 14153601 | T6: 29728856 | U6: 13207402 | V6: 41818714 | W6: 16816091 | X6: 16983764 | Y6: =SUM(Q6:X6) -> 1.6476506e+08
A7: (-) Devoluciones y Cancelaciones de Primas | B7: =IF(OR(SUM($Q7:$U7)=0,COUNTIF($Q7:$U7,"<0")*COUNTIF($Q7:$U7,">0")>0),$G7/5,$G7*Q7/SUM($Q7:$U7)) -> 7489396.8 | C7: =IF(OR(SUM($Q7:$U7)=0,COUNTIF($Q7:$U7,"<0")*COUNTIF($Q7:$U7,">0")>0),$G7/5,$G7*R7/SUM($Q7:$U7)) -> 5267864.7 | D7: =IF(OR(SUM($Q7:$U7)=0,COUNTIF($Q7:$U7,"<0")*COUNTIF($Q7:$U7,">0")>0),$G7/5,$G7*S7/SUM($Q7:$U7)) -> 6354688.1 | E7: =IF(OR(SUM($Q7:$U7)=0,COUNTIF($Q7:$U7,"<0")*COUNTIF($Q7:$U7,">0")>0),$G7/5,$G7*T7/SUM($Q7:$U7)) -> 3223066.5 | F7: =IF(OR(SUM($Q7:$U7)=0,COUNTIF($Q7:$U7,"<0")*COUNTIF($Q7:$U7,">0")>0),$G7/5,$G7*U7/SUM($Q7:$U7)) -> 3618639.4 | G7: 25953656 | H7: 2222667.7 | I7: 1492341.1 | J7: 3514623.4 | K7: 4296275.6 | L7: 3601388.3 | M7: 1065162.8 | N7: 590413.92 | O7: =SUM(B7:F7,H7:N7) -> 42736528 | Q7: 3749384.4 | R7: 2637228.3 | S7: 3181320 | T7: 1613549.9 | U7: 1811583.8 | V7: 7920108.8 | W7: 4660953.7 | X7: 2813076.5 | Y7: =SUM(Q7:X7) -> 28387205
A8: PRIMAS DIRECTAS NETAS | B8: =IF(OR(SUM($Q8:$U8)=0,COUNTIF($Q8:$U8,"<0")*COUNTIF($Q8:$U8,">0")>0),$G8/5,$G8*Q8/SUM($Q8:$U8)) -> 12229606 | C8: =IF(OR(SUM($Q8:$U8)=0,COUNTIF($Q8:$U8,"<0")*COUNTIF($Q8:$U8,">0")>0),$G8/5,$G8*R8/SUM($Q8:$U8)) -> 12224683 | D8: =IF(OR(SUM($Q8:$U8)=0,COUNTIF($Q8:$U8,"<0")*COUNTIF($Q8:$U8,">0")>0),$G8/5,$G8*S8/SUM($Q8:$U8)) -> 10452635 | E8: =IF(OR(SUM($Q8:$U8)=0,COUNTIF($Q8:$U8,"<0")*COUNTIF($Q8:$U8,">0")>0),$G8/5,$G8*T8/SUM($Q8:$U8)) -> 26783768 | F8: =IF(OR(SUM($Q8:$U8)=0,COUNTIF($Q8:$U8,"<0")*COUNTIF($Q8:$U8,">0")>0),$G8/5,$G8*U8/SUM($Q8:$U8)) -> 10856113 | G8: 72546804 | H8: 10634139 | I8: 14376682 | J8: 10622269 | K8: 10537675 | L8: 10487240 | M8: 11217500 | N8: 26409978 | O8: =SUM(B8:F8,H8:N8) -> 1.6683229e+08 | Q8: 12837593 | R8: 12832425 | S8: 10972281 | T8: 28115306 | U8: 11395818 | V8: 33898605 | W8: 12155137 | X8: 14170688 | Y8: =SUM(Q8:X8) -> 1.3637785e+08
B9: =IF(OR(SUM($Q9:$U9)=0,COUNTIF($Q9:$U9,"<0")*COUNTIF($Q9:$U9,">0")>0),$G9/5,$G9*Q9/SUM($Q9:$U9)) -> 0 | C9: =IF(OR(SUM($Q9:$U9)=0,COUNTIF($Q9:$U9,"<0")*COUNTIF($Q9:$U9,">0")>0),$G9/5,$G9*R9/SUM($Q9:$U9)) -> 0 | D9: =IF(OR(SUM($Q9:$U9)=0,COUNTIF($Q9:$U9,"<0")*COUNTIF($Q9:$U9,">0")>0),$G9/5,$G9*S9/SUM($Q9:$U9)) -> 0 | E9: =IF(OR(SUM($Q9:$U9)=0,COUNTIF($Q9:$U9,"<0")*COUNTIF($Q9:$U9,">0")>0),$G9/5,$G9*T9/SUM($Q9:$U9)) -> 0 | F9: =IF(OR(SUM($Q9:$U9)=0,COUNTIF($Q9:$U9,"<0")*COUNTIF($Q9:$U9,">0")>0),$G9/5,$G9*U9/SUM($Q9:$U9)) -> 0 | G9: 0 | H9: 0 | I9: 0 | J9: 0 | K9: 0 | L9: 0 | M9: 0 | N9: 0 | O9: =SUM(B9:F9,H9:N9) -> 0 | Q9: 0 | R9: 0 | S9: 0 | T9: 0 | U9: 0 | V9: 0 | W9: 0 | X9: 0 | Y9: =SUM(Q9:X9) -> 0
A10: Primas | B10: =IF(OR(SUM($Q10:$U10)=0,COUNTIF($Q10:$U10,"<0")*COUNTIF($Q10:$U10,">0")>0),$G10/5,$G10*Q10/SUM($Q10:$U10)) -> 0 | C10: =IF(OR(SUM($Q10:$U10)=0,COUNTIF($Q10:$U10,"<0")*COUNTIF($Q10:$U10,">0")>0),$G10/5,$G10*R10/SUM($Q10:$U10)) -> 0 | D10: =IF(OR(SUM($Q10:$U10)=0,COUNTIF($Q10:$U10,"<0")*COUNTIF($Q10:$U10,">0")>0),$G10/5,$G10*S10/SUM($Q10:$U10)) -> 0 | E10: =IF(OR(SUM($Q10:$U10)=0,COUNTIF($Q10:$U10,"<0")*COUNTIF($Q10:$U10,">0")>0),$G10/5,$G10*T10/SUM($Q10:$U10)) -> 0 | F10: =IF(OR(SUM($Q10:$U10)=0,COUNTIF($Q10:$U10,"<0")*COUNTIF($Q10:$U10,">0")>0),$G10/5,$G10*U10/SUM($Q10:$U10)) -> 0 | G10: 0 | H10: 0 | I10: 0 | J10: 0 | K10: 0 | L10: 0 | M10: 0 | N10: 0 | O10: =SUM(B10:F10,H10:N10) -> 0 | Q10: 0 | R10: 0 | S10: 0 | T10: 0 | U10: 0 | V10: 0 | W10: 0 | X10: 0 | Y10: =SUM(Q10:X10) -> 0
A11: (+) Por Reaseguro Tomado Local | B11: =IF(OR(SUM($Q11:$U11)=0,COUNTIF($Q11:$U11,"<0")*COUNTIF($Q11:$U11,">0")>0),$G11/5,$G11*Q11/SUM($Q11:$U11)) -> 0 | C11: =IF(OR(SUM($Q11:$U11)=0,COUNTIF($Q11:$U11,"<0")*COUNTIF($Q11:$U11,">0")>0),$G11/5,$G11*R11/SUM($Q11:$U11)) -> 0 | D11: =IF(OR(SUM($Q11:$U11)=0,COUNTIF($Q11:$U11,"<0")*COUNTIF($Q11:$U11,">0")>0),$G11/5,$G11*S11/SUM($Q11:$U11)) -> 0 | E11: =IF(OR(SUM($Q11:$U11)=0,COUNTIF($Q11:$U11,"<0")*COUNTIF($Q11:$U11,">0")>0),$G11/5,$G11*T11/SUM($Q11:$U11)) -> 0 | F11: =IF(OR(SUM($Q11:$U11)=0,COUNTIF($Q11:$U11,"<0")*COUNTIF($Q11:$U11,">0")>0),$G11/5,$G11*U11/SUM($Q11:$U11)) -> 0 | G11: 0 | H11: 0 | I11: 0 | J11: 0 | K11: 0 | L11: 0 | M11: 0 | N11: 0 | O11: =SUM(B11:F11,H11:N11) -> 0 | Q11: 0 | R11: 0 | S11: 0 | T11: 0 | U11: 0 | V11: 0 | W11: 0 | X11: 0 | Y11: =SUM(Q11:X11) -> 0
A12: (+) Por Reaseguro Tomado del Exterior | B12: =IF(OR(SUM($Q12:$U12)=0,COUNTIF($Q12:$U12,"<0")*COUNTIF($Q12:$U12,">0")>0),$G12/5,$G12*Q12/SUM($Q12:$U12)) -> 0 | C12: =IF(OR(SUM($Q12:$U12)=0,COUNTIF($Q12:$U12,"<0")*COUNTIF($Q12:$U12,">0")>0),$G12/5,$G12*R12/SUM($Q12:$U12)) -> 0 | D12: =IF(OR(SUM($Q12:$U12)=0,COUNTIF($Q12:$U12,"<0")*COUNTIF($Q12:$U12,">0")>0),$G12/5,$G12*S12/SUM($Q12:$U12)) -> 0 | E12: =IF(OR(SUM($Q12:$U12)=0,COUNTIF($Q12:$U12,"<0")*COUNTIF($Q12:$U12,">0")>0),$G12/5,$G12*T12/SUM($Q12:$U12)) -> 0 | F12: =IF(OR(SUM($Q12:$U12)=0,COUNTIF($Q12:$U12,"<0")*COUNTIF($Q12:$U12,">0")>0),$G12/5,$G12*U12/SUM($Q12:$U12)) -> 0 | G12: 0 | H12: 0 | I12: 0 | J12: 0 | K12: 0 | L12: 0 | M12: 0 | N12: 0 | O12: =SUM(B12:F12,H12:N12) -> 0 | Q12: 0 | R12: 0 | S12: 0 | T12: 0 | U12: 0 | V12: 0 | W12: 0 | X12: 0 | Y12: =SUM(Q12:X12) -> 0
A13: (-) Devoluciones y Cancelaciones de Primas | B13: =IF(OR(SUM($Q13:$U13)=0,COUNTIF($Q13:$U13,"<0")*COUNTIF($Q13:$U13,">0")>0),$G13/5,$G13*Q13/SUM($Q13:$U13)) -> 0 | C13: =IF(OR(SUM($Q13:$U13)=0,COUNTIF($Q13:$U13,"<0")*COUNTIF($Q13:$U13,">0")>0),$G13/5,$G13*R13/SUM($Q13:$U13)) -> 0 | D13: =IF(OR(SUM($Q13:$U13)=0,COUNTIF($Q13:$U13,"<0")*COUNTIF($Q13:$U13,">0")>0),$G13/5,$G13*S13/SUM($Q13:$U13)) -> 0 | E13: =IF(OR(SUM($Q13:$U13)=0,COUNTIF($Q13:$U13,"<0")*COUNTIF($Q13:$U13,">0")>0),$G13/5,$G13*T13/SUM($Q13:$U13)) -> 0 | F13: =IF(OR(SUM($Q13:$U13)=0,COUNTIF($Q13:$U13,"<0")*COUNTIF($Q13:$U13,">0")>0),$G13/5,$G13*U13/SUM($Q13:$U13)) -> 0 | G13: 0 | H13: 0 | I13: 0 | J13: 0 | K13: 0 | L13: 0 | M13: 0 | N13: 0 | O13: =SUM(B13:F13,H13:N13) -> 0 | Q13: 0 | R13: 0 | S13: 0 | T13: 0 | U13: 0 | V13: 0 | W13: 0 | X13: 0 | Y13: =SUM(Q13:X13) -> 0
A14: TOTAL DE PRIMAS NETAS | B14: =IF(OR(SUM($Q14:$U14)=0,COUNTIF($Q14:$U14,"<0")*COUNTIF($Q14:$U14,">0")>0),$G14/5,$G14*Q14/SUM($Q14:$U14)) -> 12229606 | C14: =IF(OR(SUM($Q14:$U14)=0,COUNTIF($Q14:$U14,"<0")*COUNTIF($Q14:$U14,">0")>0),$G14/5,$G14*R14/SUM($Q14:$U14)) -> 12224683 | D14: =IF(OR(SUM($Q14:$U14)=0,COUNTIF($Q14:$U14,"<0")*COUNTIF($Q14:$U14,">0")>0),$G14/5,$G14*S14/SUM($Q14:$U14)) -> 10452635 | E14: =IF(OR(SUM($Q14:$U14)=0,COUNTIF($Q14:$U14,"<0")*COUNTIF($Q14:$U14,">0")>0),$G14/5,$G14*T14/SUM($Q14:$U14)) -> 26783768 | F14: =IF(OR(SUM($Q14:$U14)=0,COUNTIF($Q14:$U14,"<0")*COUNTIF($Q14:$U14,">0")>0),$G14/5,$G14*U14/SUM($Q14:$U14)) -> 10856113 | G14: 72546804 | H14: 10634139 | I14: 14376682 | J14: 10622269 | K14: 10537675 | L14: 10487240 | M14: 11217500 | N14: 26409978 | O14: =SUM(B14:F14,H14:N14) -> 1.6683229e+08 | Q14: 12837593 | R14: 12832425 | S14: 10972281 | T14: 28115306 | U14: 11395818 | V14: 33898605 | W14: 12155137 | X14: 14170688 | Y14: =SUM(Q14:X14) -> 1.3637785e+08
B15: =IF(OR(SUM($Q15:$U15)=0,COUNTIF($Q15:$U15,"<0")*COUNTIF($Q15:$U15,">0")>0),$G15/5,$G15*Q15/SUM($Q15:$U15)) -> 0 | C15: =IF(OR(SUM($Q15:$U15)=0,COUNTIF($Q15:$U15,"<0")*COUNTIF($Q15:$U15,">0")>0),$G15/5,$G15*R15/SUM($Q15:$U15)) -> 0 | D15: =IF(OR(SUM($Q15:$U15)=0,COUNTIF($Q15:$U15,"<0")*COUNTIF($Q15:$U15,">0")>0),$G15/5,$G15*S15/SUM($Q15:$U15)) -> 0 | E15: =IF(OR(SUM($Q15:$U15)=0,COUNTIF($Q15:$U15,"<0")*COUNTIF($Q15:$U15,">0")>0),$G15/5,$G15*T15/SUM($Q15:$U15)) -> 0 | F15: =IF(OR(SUM($Q15:$U15)=0,COUNTIF($Q15:$U15,"<0")*COUNTIF($Q15:$U15,">0")>0),$G15/5,$G15*U15/SUM($Q15:$U15)) -> 0 | G15: 0 | H15: 0 | I15: 0 | J15: 0 | K15: 0 | L15: 0 | M15: 0 | N15: 0 | O15: =SUM(B15:F15,H15:N15) -> 0 | Q15: 0 | R15: 0 | S15: 0 | T15: 0 | U15: 0 | V15: 0 | W15: 0 | X15: 0 | Y15: =SUM(Q15:X15) -> 0
A16: (-) Primas por Reaseguro Cedido | B16: =IF(OR(SUM($Q16:$U16)=0,COUNTIF($Q16:$U16,"<0")*COUNTIF($Q16:$U16,">0")>0),$G16/5,$G16*Q16/SUM($Q16:$U16)) -> 6840185.9 | C16: =IF(OR(SUM($Q16:$U16)=0,COUNTIF($Q16:$U16,"<0")*COUNTIF($Q16:$U16,">0")>0),$G16/5,$G16*R16/SUM($Q16:$U16)) -> 6714668.7 | D16: =IF(OR(SUM($Q16:$U16)=0,COUNTIF($Q16:$U16,"<0")*COUNTIF($Q16:$U16,">0")>0),$G16/5,$G16*S16/SUM($Q16:$U16)) -> 4738678.1 | E16: =IF(OR(SUM($Q16:$U16)=0,COUNTIF($Q16:$U16,"<0")*COUNTIF($Q16:$U16,">0")>0),$G16/5,$G16*T16/SUM($Q16:$U16)) -> 21802814 | F16: =IF(OR(SUM($Q16:$U16)=0,COUNTIF($Q16:$U16,"<0")*COUNTIF($Q16:$U16,">0")>0),$G16/5,$G16*U16/SUM($Q16:$U16)) -> 5821907 | G16: 45918254 | H16: 5332461.2 | I16: 9240190.6 | J16: 6278339.1 | K16: 5681899.8 | L16: 5321109.8 | M16: 6384620.3 | N16: 23436890 | O16: =SUM(B16:F16,H16:N16) -> 1.0759376e+08 | Q16: 7416574.9 | R16: 7280480.9 | S16: 5137983.3 | T16: 23640031 | U16: 6312490.6 | V16: 29202471 | W16: 7521151.5 | X16: 9345196.1 | Y16: =SUM(Q16:X16) -> 95856379
B17: =IF(OR(SUM($Q17:$U17)=0,COUNTIF($Q17:$U17,"<0")*COUNTIF($Q17:$U17,">0")>0),$G17/5,$G17*Q17/SUM($Q17:$U17)) -> 0 | C17: =IF(OR(SUM($Q17:$U17)=0,COUNTIF($Q17:$U17,"<0")*COUNTIF($Q17:$U17,">0")>0),$G17/5,$G17*R17/SUM($Q17:$U17)) -> 0 | D17: =IF(OR(SUM($Q17:$U17)=0,COUNTIF($Q17:$U17,"<0")*COUNTIF($Q17:$U17,">0")>0),$G17/5,$G17*S17/SUM($Q17:$U17)) -> 0 | E17: =IF(OR(SUM($Q17:$U17)=0,COUNTIF($Q17:$U17,"<0")*COUNTIF($Q17:$U17,">0")>0),$G17/5,$G17*T17/SUM($Q17:$U17)) -> 0 | F17: =IF(OR(SUM($Q17:$U17)=0,COUNTIF($Q17:$U17,"<0")*COUNTIF($Q17:$U17,">0")>0),$G17/5,$G17*U17/SUM($Q17:$U17)) -> 0 | G17: 0 | H17: 0 | I17: 0 | J17: 0 | K17: 0 | L17: 0 | M17: 0 | N17: 0 | O17: =SUM(B17:F17,H17:N17) -> 0 | Q17: 0 | R17: 0 | S17: 0 | T17: 0 | U17: 0 | V17: 0 | W17: 0 | X17: 0 | Y17: =SUM(Q17:X17) -> 0
A18: PRIMAS NETAS DE RETENCIÓN | B18: =IF(OR(SUM($Q18:$U18)=0,COUNTIF($Q18:$U18,"<0")*COUNTIF($Q18:$U18,">0")>0),$G18/5,$G18*Q18/SUM($Q18:$U18)) -> 5475028.5 | C18: =IF(OR(SUM($Q18:$U18)=0,COUNTIF($Q18:$U18,"<0")*COUNTIF($Q18:$U18,">0")>0),$G18/5,$G18*R18/SUM($Q18:$U18)) -> 5607259.3 | D18: =IF(OR(SUM($Q18:$U18)=0,COUNTIF($Q18:$U18,"<0")*COUNTIF($Q18:$U18,">0")>0),$G18/5,$G18*S18/SUM($Q18:$U18)) -> 5892425.7 | E18: =IF(OR(SUM($Q18:$U18)=0,COUNTIF($Q18:$U18,"<0")*COUNTIF($Q18:$U18,">0")>0),$G18/5,$G18*T18/SUM($Q18:$U18)) -> 4519863.4 | F18: =IF(OR(SUM($Q18:$U18)=0,COUNTIF($Q18:$U18,"<0")*COUNTIF($Q18:$U18,">0")>0),$G18/5,$G18*U18/SUM($Q18:$U18)) -> 5133973.3 | G18: 26628550 | H18: 5301678.3 | I18: 5136490.9 | J18: 4343930.1 | K18: 4855774.8 | L18: 5166130.2 | M18: 4832879.6 | N18: 2973088 | O18: =SUM(B18:F18,H18:N18) -> 59238522 | Q18: 5421018.1 | R18: 5551944.4 | S18: 5834297.7 | T18: 4475275.6 | U18: 5083327.4 | V18: 4696133.8 | W18: 4633985.6 | X18: 4825491.6 | Y18: =SUM(Q18:X18) -> 40521474
B19: =IF(OR(SUM($Q19:$U19)=0,COUNTIF($Q19:$U19,"<0")*COUNTIF($Q19:$U19,">0")>0),$G19/5,$G19*Q19/SUM($Q19:$U19)) -> 0 | C19: =IF(OR(SUM($Q19:$U19)=0,COUNTIF($Q19:$U19,"<0")*COUNTIF($Q19:$U19,">0")>0),$G19/5,$G19*R19/SUM($Q19:$U19)) -> 0 | D19: =IF(OR(SUM($Q19:$U19)=0,COUNTIF($Q19:$U19,"<0")*COUNTIF($Q19:$U19,">0")>0),$G19/5,$G19*S19/SUM($Q19:$U19)) -> 0 | E19: =IF(OR(SUM($Q19:$U19)=0,COUNTIF($Q19:$U19,"<0")*COUNTIF($Q19:$U19,">0")>0),$G19/5,$G19*T19/SUM($Q19:$U19)) -> 0 | F19: =IF(OR(SUM($Q19:$U19)=0,COUNTIF($Q19:$U19,"<0")*COUNTIF($Q19:$U19,">0")>0),$G19/5,$G19*U19/SUM($Q19:$U19)) -> 0 | G19: 0 | H19: 0 | I19: 0 | J19: 0 | K19: 0 | L19: 0 | M19: 0 | N19: 0 | O19: =SUM(B19:F19,H19:N19) -> 0 | Q19: 0 | R19: 0 | S19: 0 | T19: 0 | U19: 0 | V19: 0 | W19: 0 | X19: 0 | Y19: =SUM(Q19:X19) -> 0
A20: VARIACIONES EN RESERVAS TÉCNICAS Y MATEMÁTICAS | B20: =IF(OR(SUM($Q20:$U20)=0,COUNTIF($Q20:$U20,"<0")*COUNTIF($Q20:$U20,">0")>0),$G20/5,$G20*Q20/SUM($Q20:$U20)) -> 314296.11 | C20: =IF(OR(SUM($Q20:$U20)=0,COUNTIF($Q20:$U20,"<0")*COUNTIF($Q20:$U20,">0")>0),$G20/5,$G20*R20/SUM($Q20:$U20)) -> 314296.11 | D20: =IF(OR(SUM($Q20:$U20)=0,COUNTIF($Q20:$U20,"<0")*COUNTIF($Q20:$U20,">0")>0),$G20/5,$G20*S20/SUM($Q20:$U20)) -> 314296.11 | E20: =IF(OR(SUM($Q20:$U20)=0,COUNTIF($Q20:$U20,"<0")*COUNTIF($Q20:$U20,">0")>0),$G20/5,$G20*T20/SUM($Q20:$U20)) -> 314296.11 | F20: =IF(OR(SUM($Q20:$U20)=0,COUNTIF($Q20:$U20,"<0")*COUNTIF($Q20:$U20,">0")>0),$G20/5,$G20*U20/SUM($Q20:$U20)) -> 314296.11 | G20: 1571480.6 | H20: -135634.59 | I20: -153831.09 | J20: -34982.13 | K20: -464571.7 | L20: 909082.78 | M20: -116891.9 | N20: 297725.71 | O20: =SUM(B20:F20,H20:N20) -> 1872377.6 | Q20: 838498.55 | R20: 814014.5 | S20: 480171.88 | T20: 183420.76 | U20: -26680.33 | V20: -195192.12 | W20: -78094.74 | X20: -396325.71 | Y20: =SUM(Q20:X20) -> 1619812.8
A21: (-) Variaciones Gastos | B21: =IF(OR(SUM($Q21:$U21)=0,COUNTIF($Q21:$U21,"<0")*COUNTIF($Q21:$U21,">0")>0),$G21/5,$G21*Q21/SUM($Q21:$U21)) -> 3425537.8 | C21: =IF(OR(SUM($Q21:$U21)=0,COUNTIF($Q21:$U21,"<0")*COUNTIF($Q21:$U21,">0")>0),$G21/5,$G21*R21/SUM($Q21:$U21)) -> 1506283 | D21: =IF(OR(SUM($Q21:$U21)=0,COUNTIF($Q21:$U21,"<0")*COUNTIF($Q21:$U21,">0")>0),$G21/5,$G21*S21/SUM($Q21:$U21)) -> 1539845.3 | E21: =IF(OR(SUM($Q21:$U21)=0,COUNTIF($Q21:$U21,"<0")*COUNTIF($Q21:$U21,">0")>0),$G21/5,$G21*T21/SUM($Q21:$U21)) -> 1129320.7 | F21: =IF(OR(SUM($Q21:$U21)=0,COUNTIF($Q21:$U21,"<0")*COUNTIF($Q21:$U21,">0")>0),$G21/5,$G21*U21/SUM($Q21:$U21)) -> 1260433.6 | G21: 8861420.5 | H21: 1172943.4 | I21: 1463092.4 | J21: 2114371.8 | K21: 1835581.7 | L21: 2053124.8 | M21: 1360517.2 | N21: 1600675 | O21: =SUM(B21:F21,H21:N21) -> 20461727 | Q21: 4648560.5 | R21: 2044072.5 | S21: 2089617.6 | T21: 1532523.1 | U21: 1710447.3 | V21: 1420618.8 | W21: 1519815.4 | X21: 1199790.8 | Y21: =SUM(Q21:X21) -> 16165446
A22: (+) Variaciones Productos | B22: =IF(OR(SUM($Q22:$U22)=0,COUNTIF($Q22:$U22,"<0")*COUNTIF($Q22:$U22,">0")>0),$G22/5,$G22*Q22/SUM($Q22:$U22)) -> 2852886.8 | C22: =IF(OR(SUM($Q22:$U22)=0,COUNTIF($Q22:$U22,"<0")*COUNTIF($Q22:$U22,">0")>0),$G22/5,$G22*R22/SUM($Q22:$U22)) -> 921039.16 | D22: =IF(OR(SUM($Q22:$U22)=0,COUNTIF($Q22:$U22,"<0")*COUNTIF($Q22:$U22,">0")>0),$G22/5,$G22*S22/SUM($Q22:$U22)) -> 1205116 | E22: =IF(OR(SUM($Q22:$U22)=0,COUNTIF($Q22:$U22,"<0")*COUNTIF($Q22:$U22,">0")>0),$G22/5,$G22*T22/SUM($Q22:$U22)) -> 1010176.8 | F22: =IF(OR(SUM($Q22:$U22)=0,COUNTIF($Q22:$U22,"<0")*COUNTIF($Q22:$U22,">0")>0),$G22/5,$G22*U22/SUM($Q22:$U22)) -> 1300721.2 | G22: 7289939.9 | H22: 1308578 | I22: 1616923.5 | J22: 2149353.9 | K22: 2300153.4 | L22: 1144042 | M22: 1477409.1 | N22: 1302949.3 | O22: =SUM(B22:F22,H22:N22) -> 18589349 | Q22: 3810061.9 | R22: 1230058 | S22: 1609445.8 | T22: 1349102.3 | U22: 1737127.6 | V22: 1615811 | W22: 1597910.1 | X22: 1596116.5 | Y22: =SUM(Q22:X22) -> 14545633
A23: PRIMAS NETAS DE RETENCIÓN DEVENGADAS | B23: =IF(OR(SUM($Q23:$U23)=0,COUNTIF($Q23:$U23,"<0")*COUNTIF($Q23:$U23,">0")>0),$G23/5,$G23*Q23/SUM($Q23:$U23)) -> 4769165.2 | C23: =IF(OR(SUM($Q23:$U23)=0,COUNTIF($Q23:$U23,"<0")*COUNTIF($Q23:$U23,">0")>0),$G23/5,$G23*R23/SUM($Q23:$U23)) -> 4930905.5 | D23: =IF(OR(SUM($Q23:$U23)=0,COUNTIF($Q23:$U23,"<0")*COUNTIF($Q23:$U23,">0")>0),$G23/5,$G23*S23/SUM($Q23:$U23)) -> 5572199.1 | E23: =IF(OR(SUM($Q23:$U23)=0,COUNTIF($Q23:$U23,"<0")*COUNTIF($Q23:$U23,">0")>0),$G23/5,$G23*T23/SUM($Q23:$U23)) -> 4466661.8 | F23: =IF(OR(SUM($Q23:$U23)=0,COUNTIF($Q23:$U23,"<0")*COUNTIF($Q23:$U23,">0")>0),$G23/5,$G23*U23/SUM($Q23:$U23)) -> 5318138 | G23: 25057070 | H23: 5437312.9 | I23: 5290322 | J23: 4378912.2 | K23: 5320346.5 | L23: 4257047.4 | M23: 4949771.5 | N23: 2675362.3 | O23: =SUM(B23:F23,H23:N23) -> 57366144 | Q23: 4582519.5 | R23: 4737929.9 | S23: 5354125.9 | T23: 4291854.9 | U23: 5110007.7 | V23: 4891325.9 | W23: 4712080.3 | X23: 5221817.3 | Y23: =SUM(Q23:X23) -> 38901661
B24: =IF(OR(SUM($Q24:$U24)=0,COUNTIF($Q24:$U24,"<0")*COUNTIF($Q24:$U24,">0")>0),$G24/5,$G24*Q24/SUM($Q24:$U24)) -> 0 | C24: =IF(OR(SUM($Q24:$U24)=0,COUNTIF($Q24:$U24,"<0")*COUNTIF($Q24:$U24,">0")>0),$G24/5,$G24*R24/SUM($Q24:$U24)) -> 0 | D24: =IF(OR(SUM($Q24:$U24)=0,COUNTIF($Q24:$U24,"<0")*COUNTIF($Q24:$U24,">0")>0),$G24/5,$G24*S24/SUM($Q24:$U24)) -> 0 | E24: =IF(OR(SUM($Q24:$U24)=0,COUNTIF($Q24:$U24,"<0")*COUNTIF($Q24:$U24,">0")>0),$G24/5,$G24*T24/SUM($Q24:$U24)) -> 0 | F24: =IF(OR(SUM($Q24:$U24)=0,COUNTIF($Q24:$U24,"<0")*COUNTIF($Q24:$U24,">0")>0),$G24/5,$G24*U24/SUM($Q24:$U24)) -> 0 | G24: 0 | H24: 0 | I24: 0 | J24: 0 | K24: 0 | L24: 0 | M24: 0 | N24: 0 | O24: =SUM(B24:F24,H24:N24) -> 0 | Q24: 0 | R24: 0 | S24: 0 | T24: 0 | U24: 0 | V24: 0 | W24: 0 | X24: 0 | Y24: =SUM(Q24:X24) -> 0
A25: (-) COSTO DE ADQUISICIÓN Y SINIESTRALIDAD | B25: =IF(OR(SUM($Q25:$U25)=0,COUNTIF($Q25:$U25,"<0")*COUNTIF($Q25:$U25,">0")>0),$G25/5,$G25*Q25/SUM($Q25:$U25)) -> 164303.92 | C25: =IF(OR(SUM($Q25:$U25)=0,COUNTIF($Q25:$U25,"<0")*COUNTIF($Q25:$U25,">0")>0),$G25/5,$G25*R25/SUM($Q25:$U25)) -> 240830.1 | D25: =IF(OR(SUM($Q25:$U25)=0,COUNTIF($Q25:$U25,"<0")*COUNTIF($Q25:$U25,">0")>0),$G25/5,$G25*S25/SUM($Q25:$U25)) -> 270670.48 | E25: =IF(OR(SUM($Q25:$U25)=0,COUNTIF($Q25:$U25,"<0")*COUNTIF($Q25:$U25,">0")>0),$G25/5,$G25*T25/SUM($Q25:$U25)) -> 318819.31 | F25: =IF(OR(SUM($Q25:$U25)=0,COUNTIF($Q25:$U25,"<0")*COUNTIF($Q25:$U25,">0")>0),$G25/5,$G25*U25/SUM($Q25:$U25)) -> 214291.62 | G25: 1208915.4 | H25: 1063644.8 | I25: 435519.9 | J25: 1327989.1 | K25: 1183296.7 | L25: 1032883.2 | M25: 383966.96 | N25: 924714.52 | O25: =SUM(B25:F25,H25:N25) -> 7560930.6 | Q25: 676646.22 | R25: 991800.92 | S25: 1114691.4 | T25: 1312980.8 | U25: 882508.56 | V25: 874443.27 | W25: -225298.98 | X25: 2357603.1 | Y25: =SUM(Q25:X25) -> 7985375.2
A26: ADQUISICIÓN | B26: =IF(OR(SUM($Q26:$U26)=0,COUNTIF($Q26:$U26,"<0")*COUNTIF($Q26:$U26,">0")>0),$G26/5,$G26*Q26/SUM($Q26:$U26)) -> -129036.28 | C26: =IF(OR(SUM($Q26:$U26)=0,COUNTIF($Q26:$U26,"<0")*COUNTIF($Q26:$U26,">0")>0),$G26/5,$G26*R26/SUM($Q26:$U26)) -> -129036.28 | D26: =IF(OR(SUM($Q26:$U26)=0,COUNTIF($Q26:$U26,"<0")*COUNTIF($Q26:$U26,">0")>0),$G26/5,$G26*S26/SUM($Q26:$U26)) -> -129036.28 | E26: =IF(OR(SUM($Q26:$U26)=0,COUNTIF($Q26:$U26,"<0")*COUNTIF($Q26:$U26,">0")>0),$G26/5,$G26*T26/SUM($Q26:$U26)) -> -129036.28 | F26: =IF(OR(SUM($Q26:$U26)=0,COUNTIF($Q26:$U26,"<0")*COUNTIF($Q26:$U26,">0")>0),$G26/5,$G26*U26/SUM($Q26:$U26)) -> -129036.28 | G26: -645181.38 | H26: 398917.38 | I26: 52411.17 | J26: 125744.51 | K26: 536292.23 | L26: 609577.07 | M26: -728140.02 | N26: -301098.24 | O26: =SUM(B26:F26,H26:N26) -> 48522.72 | Q26: 64843.15 | R26: 67707.22 | S26: 15677.6 | T26: 316734.26 | U26: -261306.68 | V26: -167891.65 | W26: 365577.8 | X26: 549618.85 | Y26: =SUM(Q26:X26) -> 950960.55
A27: (+) Gastos de Adquisición y Renovación | B27: =IF(OR(SUM($Q27:$U27)=0,COUNTIF($Q27:$U27,"<0")*COUNTIF($Q27:$U27,">0")>0),$G27/5,$G27*Q27/SUM($Q27:$U27)) -> 1683128.8 | C27: =IF(OR(SUM($Q27:$U27)=0,COUNTIF($Q27:$U27,"<0")*COUNTIF($Q27:$U27,">0")>0),$G27/5,$G27*R27/SUM($Q27:$U27)) -> 1614278.2 | D27: =IF(OR(SUM($Q27:$U27)=0,COUNTIF($Q27:$U27,"<0")*COUNTIF($Q27:$U27,">0")>0),$G27/5,$G27*S27/SUM($Q27:$U27)) -> 1377431.5 | E27: =IF(OR(SUM($Q27:$U27)=0,COUNTIF($Q27:$U27,"<0")*COUNTIF($Q27:$U27,">0")>0),$G27/5,$G27*T27/SUM($Q27:$U27)) -> 2138947.6 | F27: =IF(OR(SUM($Q27:$U27)=0,COUNTIF($Q27:$U27,"<0")*COUNTIF($Q27:$U27,">0")>0),$G27/5,$G27*U27/SUM($Q27:$U27)) -> 1695349.3 | G27: 8509135.4 | H27: 1430908.3 | I27: 1675048.1 | J27: 1717279.3 | K27: 1783506.2 | L27: 1350012 | M27: 688668.2 | N27: 3648254 | O27: =SUM(B27:F27,H27:N27) -> 20802812 | Q27: 2019888.8 | R27: 1937262.6 | S27: 1653027.8 | T27: 2566907.8 | U27: 2034554.4 | V27: 1494772 | W27: 2015394.9 | X27: 2268495.5 | Y27: =SUM(Q27:X27) -> 15990304
A28: (-) Comisiones y Participaciones por Reaseguro Cedido | B28: =IF(OR(SUM($Q28:$U28)=0,COUNTIF($Q28:$U28,"<0")*COUNTIF($Q28:$U28,">0")>0),$G28/5,$G28*Q28/SUM($Q28:$U28)) -> 1788282.6 | C28: =IF(OR(SUM($Q28:$U28)=0,COUNTIF($Q28:$U28,"<0")*COUNTIF($Q28:$U28,">0")>0),$G28/5,$G28*R28/SUM($Q28:$U28)) -> 1710084.6 | D28: =IF(OR(SUM($Q28:$U28)=0,COUNTIF($Q28:$U28,"<0")*COUNTIF($Q28:$U28,">0")>0),$G28/5,$G28*S28/SUM($Q28:$U28)) -> 1497686.2 | E28: =IF(OR(SUM($Q28:$U28)=0,COUNTIF($Q28:$U28,"<0")*COUNTIF($Q28:$U28,">0")>0),$G28/5,$G28*T28/SUM($Q28:$U28)) -> 2058236.5 | F28: =IF(OR(SUM($Q28:$U28)=0,COUNTIF($Q28:$U28,"<0")*COUNTIF($Q28:$U28,">0")>0),$G28/5,$G28*U28/SUM($Q28:$U28)) -> 2100026.9 | G28: 9154316.8 | H28: 1031991 | I28: 1622636.9 | J28: 1591534.8 | K28: 1247214 | L28: 740434.9 | M28: 1416808.2 | N28: 3949352.2 | O28: =SUM(B28:F28,H28:N28) -> 20754289 | Q28: 1955045.7 | R28: 1869555.4 | S28: 1637350.2 | T28: 2250173.5 | U28: 2295861.1 | V28: 1662663.7 | W28: 1649817.1 | X28: 1718876.7 | Y28: =SUM(Q28:X28) -> 15039343
A29: SINIESTRALIDAD | B29: =IF(OR(SUM($Q29:$U29)=0,COUNTIF($Q29:$U29,"<0")*COUNTIF($Q29:$U29,">0")>0),$G29/5,$G29*Q29/SUM($Q29:$U29)) -> 237559.94 | C29: =IF(OR(SUM($Q29:$U29)=0,COUNTIF($Q29:$U29,"<0")*COUNTIF($Q29:$U29,">0")>0),$G29/5,$G29*R29/SUM($Q29:$U29)) -> 358820.76 | D29: =IF(OR(SUM($Q29:$U29)=0,COUNTIF($Q29:$U29,"<0")*COUNTIF($Q29:$U29,">0")>0),$G29/5,$G29*S29/SUM($Q29:$U29)) -> 426741.3 | E29: =IF(OR(SUM($Q29:$U29)=0,COUNTIF($Q29:$U29,"<0")*COUNTIF($Q29:$U29,">0")>0),$G29/5,$G29*T29/SUM($Q29:$U29)) -> 386837.32 | F29: =IF(OR(SUM($Q29:$U29)=0,COUNTIF($Q29:$U29,"<0")*COUNTIF($Q29:$U29,">0")>0),$G29/5,$G29*U29/SUM($Q29:$U29)) -> 444137.49 | G29: 1854096.8 | H29: 664727.42 | I29: 383108.73 | J29: 1202244.6 | K29: 647004.48 | L29: 423306.16 | M29: 1112107 | N29: 1225812.8 | O29: =SUM(B29:F29,H29:N29) -> 7512407.9 | Q29: 611803.07 | R29: 924093.7 | S29: 1099013.8 | T29: 996246.5 | U29: 1143815.2 | V29: 1042334.9 | W29: -590876.78 | X29: 1807984.2 | Y29: =SUM(Q29:X29) -> 7034414.6
A30: (+) Gastos Por Obligaciones Contractuales | B30: =IF(OR(SUM($Q30:$U30)=0,COUNTIF($Q30:$U30,"<0")*COUNTIF($Q30:$U30,">0")>0),$G30/5,$G30*Q30/SUM($Q30:$U30)) -> 1066032.4 | C30: =IF(OR(SUM($Q30:$U30)=0,COUNTIF($Q30:$U30,"<0")*COUNTIF($Q30:$U30,">0")>0),$G30/5,$G30*R30/SUM($Q30:$U30)) -> 1341878.6 | D30: =IF(OR(SUM($Q30:$U30)=0,COUNTIF($Q30:$U30,"<0")*COUNTIF($Q30:$U30,">0")>0),$G30/5,$G30*S30/SUM($Q30:$U30)) -> 1631248.4 | E30: =IF(OR(SUM($Q30:$U30)=0,COUNTIF($Q30:$U30,"<0")*COUNTIF($Q30:$U30,">0")>0),$G30/5,$G30*T30/SUM($Q30:$U30)) -> 1255471.9 | F30: =IF(OR(SUM($Q30:$U30)=0,COUNTIF($Q30:$U30,"<0")*COUNTIF($Q30:$U30,">0")>0),$G30/5,$G30*U30/SUM($Q30:$U30)) -> 1074098.1 | G30: 6368729.4 | H30: 3706019.3 | I30: 16095670 | J30: 36824121 | K30: 13977736 | L30: 4427131.3 | M30: 5855169.9 | N30: -21565323 | O30: =SUM(B30:F30,H30:N30) -> 65689254 | Q30: 3814554.2 | R30: 4801607.3 | S30: 5837051.3 | T30: 4492420.5 | U30: 3843415.6 | V30: 4994499 | W30: 4938376.9 | X30: 7820157 | Y30: =SUM(Q30:X30) -> 40542082
A31: (+) Participa. Reaseguradoras en Salvamentos y Recup. | B31: =IF(OR(SUM($Q31:$U31)=0,COUNTIF($Q31:$U31,"<0")*COUNTIF($Q31:$U31,">0")>0),$G31/5,$G31*Q31/SUM($Q31:$U31)) -> 284220.11 | C31: =IF(OR(SUM($Q31:$U31)=0,COUNTIF($Q31:$U31,"<0")*COUNTIF($Q31:$U31,">0")>0),$G31/5,$G31*R31/SUM($Q31:$U31)) -> 234585.09 | D31: =IF(OR(SUM($Q31:$U31)=0,COUNTIF($Q31:$U31,"<0")*COUNTIF($Q31:$U31,">0")>0),$G31/5,$G31*S31/SUM($Q31:$U31)) -> 664227.48 | E31: =IF(OR(SUM($Q31:$U31)=0,COUNTIF($Q31:$U31,"<0")*COUNTIF($Q31:$U31,">0")>0),$G31/5,$G31*T31/SUM($Q31:$U31)) -> 937074.42 | F31: =IF(OR(SUM($Q31:$U31)=0,COUNTIF($Q31:$U31,"<0")*COUNTIF($Q31:$U31,">0")>0),$G31/5,$G31*U31/SUM($Q31:$U31)) -> 633385.24 | G31: 2753492.3 | H31: 501809.54 | I31: 304547.35 | J31: 257490.34 | K31: 1428087.7 | L31: 319384.54 | M31: 551962.07 | N31: 439507.8 | O31: =SUM(B31:F31,H31:N31) -> 6556281.6 | Q31: 163569.15 | R31: 135004.11 | S31: 382264.03 | T31: 539287.9 | U31: 364514.27 | V31: 298496.35 | W31: 680146.03 | X31: 428071.1 | Y31: =SUM(Q31:X31) -> 2991352.9
A32: (+) Variación en Reservas de Reclamaciones de Seguro de Caución (Neto) | B32: =IF(OR(SUM($Q32:$U32)=0,COUNTIF($Q32:$U32,"<0")*COUNTIF($Q32:$U32,">0")>0),$G32/5,$G32*Q32/SUM($Q32:$U32)) -> 0 | C32: =IF(OR(SUM($Q32:$U32)=0,COUNTIF($Q32:$U32,"<0")*COUNTIF($Q32:$U32,">0")>0),$G32/5,$G32*R32/SUM($Q32:$U32)) -> 0 | D32: =IF(OR(SUM($Q32:$U32)=0,COUNTIF($Q32:$U32,"<0")*COUNTIF($Q32:$U32,">0")>0),$G32/5,$G32*S32/SUM($Q32:$U32)) -> 0 | E32: =IF(OR(SUM($Q32:$U32)=0,COUNTIF($Q32:$U32,"<0")*COUNTIF($Q32:$U32,">0")>0),$G32/5,$G32*T32/SUM($Q32:$U32)) -> 0 | F32: =IF(OR(SUM($Q32:$U32)=0,COUNTIF($Q32:$U32,"<0")*COUNTIF($Q32:$U32,">0")>0),$G32/5,$G32*U32/SUM($Q32:$U32)) -> 0 | G32: 0 | H32: 0 | I32: 0 | J32: 0 | K32: 0 | L32: 0 | M32: 0 | N32: 0 | O32: =SUM(B32:F32,H32:N32) -> 0 | Q32: 0 | R32: 0 | S32: 0 | T32: 0 | U32: 0 | V32: 0 | W32: 0 | X32: 0 | Y32: =SUM(Q32:X32) -> 0
A33: (-) Recuperaciones por Reaseguro Cedido | B33: =IF(OR(SUM($Q33:$U33)=0,COUNTIF($Q33:$U33,"<0")*COUNTIF($Q33:$U33,">0")>0),$G33/5,$G33*Q33/SUM($Q33:$U33)) -> 481634.12 | C33: =IF(OR(SUM($Q33:$U33)=0,COUNTIF($Q33:$U33,"<0")*COUNTIF($Q33:$U33,">0")>0),$G33/5,$G33*R33/SUM($Q33:$U33)) -> 600963.13 | D33: =IF(OR(SUM($Q33:$U33)=0,COUNTIF($Q33:$U33,"<0")*COUNTIF($Q33:$U33,">0")>0),$G33/5,$G33*S33/SUM($Q33:$U33)) -> 730003.68 | E33: =IF(OR(SUM($Q33:$U33)=0,COUNTIF($Q33:$U33,"<0")*COUNTIF($Q33:$U33,">0")>0),$G33/5,$G33*T33/SUM($Q33:$U33)) -> 538949.36 | F33: =IF(OR(SUM($Q33:$U33)=0,COUNTIF($Q33:$U33,"<0")*COUNTIF($Q33:$U33,">0")>0),$G33/5,$G33*U33/SUM($Q33:$U33)) -> 390170.25 | G33: 2741720.5 | H33: 2748141.3 | I33: 15438857 | J33: 35397355 | K33: 13119396 | L33: 3706290.5 | M33: 4585760.6 | N33: -24056629 | O33: =SUM(B33:F33,H33:N33) -> 53680893 | Q33: 2947903 | R33: 3678271.5 | S33: 4468080.6 | T33: 3298708.3 | U33: 2388086.8 | V33: 3321704.3 | W33: 3439087.6 | X33: 5752786.2 | Y33: =SUM(Q33:X33) -> 29294628
A34: (-) Salvamentos y Recuperaciones | B34: =IF(OR(SUM($Q34:$U34)=0,COUNTIF($Q34:$U34,"<0")*COUNTIF($Q34:$U34,">0")>0),$G34/5,$G34*Q34/SUM($Q34:$U34)) -> 672161.17 | C34: =IF(OR(SUM($Q34:$U34)=0,COUNTIF($Q34:$U34,"<0")*COUNTIF($Q34:$U34,">0")>0),$G34/5,$G34*R34/SUM($Q34:$U34)) -> 536945.75 | D34: =IF(OR(SUM($Q34:$U34)=0,COUNTIF($Q34:$U34,"<0")*COUNTIF($Q34:$U34,">0")>0),$G34/5,$G34*S34/SUM($Q34:$U34)) -> 1047752.2 | E34: =IF(OR(SUM($Q34:$U34)=0,COUNTIF($Q34:$U34,"<0")*COUNTIF($Q34:$U34,">0")>0),$G34/5,$G34*T34/SUM($Q34:$U34)) -> 1183548.7 | F34: =IF(OR(SUM($Q34:$U34)=0,COUNTIF($Q34:$U34,"<0")*COUNTIF($Q34:$U34,">0")>0),$G34/5,$G34*U34/SUM($Q34:$U34)) -> 1085996.5 | G34: 4526404.3 | H34: 794960.15 | I34: 578251.57 | J34: 482011.86 | K34: 1639423.2 | L34: 616919.22 | M34: 709264.37 | N34: 1705000.4 | O34: =SUM(B34:F34,H34:N34) -> 11052235 | Q34: 418417.23 | R34: 334246.25 | S34: 652220.91 | T34: 736753.59 | U34: 676027.84 | V34: 928956.04 | W34: 2770312.2 | X34: 687457.72 | Y34: =SUM(Q34:X34) -> 7204391.7
B35: =IF(OR(SUM($Q35:$U35)=0,COUNTIF($Q35:$U35,"<0")*COUNTIF($Q35:$U35,">0")>0),$G35/5,$G35*Q35/SUM($Q35:$U35)) -> 0 | C35: =IF(OR(SUM($Q35:$U35)=0,COUNTIF($Q35:$U35,"<0")*COUNTIF($Q35:$U35,">0")>0),$G35/5,$G35*R35/SUM($Q35:$U35)) -> 0 | D35: =IF(OR(SUM($Q35:$U35)=0,COUNTIF($Q35:$U35,"<0")*COUNTIF($Q35:$U35,">0")>0),$G35/5,$G35*S35/SUM($Q35:$U35)) -> 0 | E35: =IF(OR(SUM($Q35:$U35)=0,COUNTIF($Q35:$U35,"<0")*COUNTIF($Q35:$U35,">0")>0),$G35/5,$G35*T35/SUM($Q35:$U35)) -> 0 | F35: =IF(OR(SUM($Q35:$U35)=0,COUNTIF($Q35:$U35,"<0")*COUNTIF($Q35:$U35,">0")>0),$G35/5,$G35*U35/SUM($Q35:$U35)) -> 0 | G35: 0 | H35: 0 | I35: 0 | J35: 0 | K35: 0 | L35: 0 | M35: 0 | N35: 0 | O35: =SUM(B35:F35,H35:N35) -> 0 | Q35: 0 | R35: 0 | S35: 0 | T35: 0 | U35: 0 | V35: 0 | W35: 0 | X35: 0 | Y35: =SUM(Q35:X35) -> 0
A36: UTILIDAD BRUTA EN OPERACIONES DE SEGUROS | B36: =IF(OR(SUM($Q36:$U36)=0,COUNTIF($Q36:$U36,"<0")*COUNTIF($Q36:$U36,">0")>0),$G36/5,$G36*Q36/SUM($Q36:$U36)) -> 4877411 | C36: =IF(OR(SUM($Q36:$U36)=0,COUNTIF($Q36:$U36,"<0")*COUNTIF($Q36:$U36,">0")>0),$G36/5,$G36*R36/SUM($Q36:$U36)) -> 4677932.3 | D36: =IF(OR(SUM($Q36:$U36)=0,COUNTIF($Q36:$U36,"<0")*COUNTIF($Q36:$U36,">0")>0),$G36/5,$G36*S36/SUM($Q36:$U36)) -> 5293941.4 | E36: =IF(OR(SUM($Q36:$U36)=0,COUNTIF($Q36:$U36,"<0")*COUNTIF($Q36:$U36,">0")>0),$G36/5,$G36*T36/SUM($Q36:$U36)) -> 3719832.2 | F36: =IF(OR(SUM($Q36:$U36)=0,COUNTIF($Q36:$U36,"<0")*COUNTIF($Q36:$U36,">0")>0),$G36/5,$G36*U36/SUM($Q36:$U36)) -> 5279037.3 | G36: 23848154 | H36: 4373668.1 | I36: 4854802.1 | J36: 3050923.1 | K36: 4137049.8 | L36: 3224164.2 | M36: 4565804.5 | N36: 1750647.8 | O36: =SUM(B36:F36,H36:N36) -> 49805214 | Q36: 3905873.3 | R36: 3746129 | S36: 4239434.5 | T36: 2978874.1 | U36: 4227499.2 | V36: 4016882.6 | W36: 4937379.3 | X36: 2864214.2 | Y36: =SUM(Q36:X36) -> 30916286
A37: (-) GASTOS Y PRODUCTOS DE OPERACIONES | B37: =IF(OR(SUM($Q37:$U37)=0,COUNTIF($Q37:$U37,"<0")*COUNTIF($Q37:$U37,">0")>0),$G37/5,$G37*Q37/SUM($Q37:$U37)) -> 3928629.6 | C37: =IF(OR(SUM($Q37:$U37)=0,COUNTIF($Q37:$U37,"<0")*COUNTIF($Q37:$U37,">0")>0),$G37/5,$G37*R37/SUM($Q37:$U37)) -> 3596784.5 | D37: =IF(OR(SUM($Q37:$U37)=0,COUNTIF($Q37:$U37,"<0")*COUNTIF($Q37:$U37,">0")>0),$G37/5,$G37*S37/SUM($Q37:$U37)) -> 3680797.8 | E37: =IF(OR(SUM($Q37:$U37)=0,COUNTIF($Q37:$U37,"<0")*COUNTIF($Q37:$U37,">0")>0),$G37/5,$G37*T37/SUM($Q37:$U37)) -> 3374405.1 | F37: =IF(OR(SUM($Q37:$U37)=0,COUNTIF($Q37:$U37,"<0")*COUNTIF($Q37:$U37,">0")>0),$G37/5,$G37*U37/SUM($Q37:$U37)) -> 3523494.2 | G37: 18104111 | H37: 3557207.5 | I37: 3369378 | J37: 3384760 | K37: 3461068.7 | L37: 2952864 | M37: 3748911.7 | N37: 3173549.2 | O37: =SUM(B37:F37,H37:N37) -> 41751850 | Q37: 3900040.5 | R37: 3570610.3 | S37: 3654012.2 | T37: 3349849.2 | U37: 3497853.4 | V37: 3175304.6 | W37: 4098391.4 | X37: 2954141.6 | Y37: =SUM(Q37:X37) -> 28200203
A38: (+) Egresos por Inversiones | B38: =IF(OR(SUM($Q38:$U38)=0,COUNTIF($Q38:$U38,"<0")*COUNTIF($Q38:$U38,">0")>0),$G38/5,$G38*Q38/SUM($Q38:$U38)) -> 51698.082 | C38: =IF(OR(SUM($Q38:$U38)=0,COUNTIF($Q38:$U38,"<0")*COUNTIF($Q38:$U38,">0")>0),$G38/5,$G38*R38/SUM($Q38:$U38)) -> 40744.473 | D38: =IF(OR(SUM($Q38:$U38)=0,COUNTIF($Q38:$U38,"<0")*COUNTIF($Q38:$U38,">0")>0),$G38/5,$G38*S38/SUM($Q38:$U38)) -> 42112.21 | E38: =IF(OR(SUM($Q38:$U38)=0,COUNTIF($Q38:$U38,"<0")*COUNTIF($Q38:$U38,">0")>0),$G38/5,$G38*T38/SUM($Q38:$U38)) -> 53801.378 | F38: =IF(OR(SUM($Q38:$U38)=0,COUNTIF($Q38:$U38,"<0")*COUNTIF($Q38:$U38,">0")>0),$G38/5,$G38*U38/SUM($Q38:$U38)) -> 52219.107 | G38: 240575.25 | H38: 47738.92 | I38: 63134.34 | J38: 59731.42 | K38: 58352.1 | L38: 32724.25 | M38: 73098.65 | N38: 87990.76 | O38: =SUM(B38:F38,H38:N38) -> 663345.69 | Q38: 67895.87 | R38: 53510.33 | S38: 55306.6 | T38: 70658.16 | U38: 68580.14 | V38: 58791.34 | W38: 83318.89 | X38: 52339.96 | Y38: =SUM(Q38:X38) -> 510401.29
A39: (+) Gastos de Administración | B39: =IF(OR(SUM($Q39:$U39)=0,COUNTIF($Q39:$U39,"<0")*COUNTIF($Q39:$U39,">0")>0),$G39/5,$G39*Q39/SUM($Q39:$U39)) -> 4806922.2 | C39: =IF(OR(SUM($Q39:$U39)=0,COUNTIF($Q39:$U39,"<0")*COUNTIF($Q39:$U39,">0")>0),$G39/5,$G39*R39/SUM($Q39:$U39)) -> 4474658.4 | D39: =IF(OR(SUM($Q39:$U39)=0,COUNTIF($Q39:$U39,"<0")*COUNTIF($Q39:$U39,">0")>0),$G39/5,$G39*S39/SUM($Q39:$U39)) -> 4435703.8 | E39: =IF(OR(SUM($Q39:$U39)=0,COUNTIF($Q39:$U39,"<0")*COUNTIF($Q39:$U39,">0")>0),$G39/5,$G39*T39/SUM($Q39:$U39)) -> 4487152 | F39: =IF(OR(SUM($Q39:$U39)=0,COUNTIF($Q39:$U39,"<0")*COUNTIF($Q39:$U39,">0")>0),$G39/5,$G39*U39/SUM($Q39:$U39)) -> 4361363.3 | G39: 22565800 | H39: 4312301.6 | I39: 4263284.6 | J39: 4117224.5 | K39: 4219699 | L39: 3810952.2 | M39: 4393202.7 | N39: 4390513.8 | O39: =SUM(B39:F39,H39:N39) -> 52072978 | Q39: 4657304.4 | R39: 4335382.5 | S39: 4297640.3 | T39: 4347487.2 | U39: 4225613.7 | V39: 4526186.6 | W39: 4832549.6 | X39: 3811321.8 | Y39: =SUM(Q39:X39) -> 35033486
A40: (-) Derechos de Emisión de Pólizas (Neto) | B40: =IF(OR(SUM($Q40:$U40)=0,COUNTIF($Q40:$U40,"<0")*COUNTIF($Q40:$U40,">0")>0),$G40/5,$G40*Q40/SUM($Q40:$U40)) -> 624215.54 | C40: =IF(OR(SUM($Q40:$U40)=0,COUNTIF($Q40:$U40,"<0")*COUNTIF($Q40:$U40,">0")>0),$G40/5,$G40*R40/SUM($Q40:$U40)) -> 619505.69 | D40: =IF(OR(SUM($Q40:$U40)=0,COUNTIF($Q40:$U40,"<0")*COUNTIF($Q40:$U40,">0")>0),$G40/5,$G40*S40/SUM($Q40:$U40)) -> 466579.41 | E40: =IF(OR(SUM($Q40:$U40)=0,COUNTIF($Q40:$U40,"<0")*COUNTIF($Q40:$U40,">0")>0),$G40/5,$G40*T40/SUM($Q40:$U40)) -> 860803.24 | F40: =IF(OR(SUM($Q40:$U40)=0,COUNTIF($Q40:$U40,"<0")*COUNTIF($Q40:$U40,">0")>0),$G40/5,$G40*U40/SUM($Q40:$U40)) -> 536532.25 | G40: 3107636.1 | H40: 466988.51 | I40: 637926.41 | J40: 451743.83 | K40: 478928.95 | L40: 433152.9 | M40: 453384.19 | N40: 1206676.3 | O40: =SUM(B40:F40,H40:N40) -> 7236437.2 | Q40: 585552.35 | R40: 581134.22 | S40: 437680.02 | T40: 807486.08 | U40: 503300.06 | V40: 1121084.8 | W40: 521909.75 | X40: 609779.2 | Y40: =SUM(Q40:X40) -> 5167926.4
A41: (-) Productos de Inversiones | B41: =IF(OR(SUM($Q41:$U41)=0,COUNTIF($Q41:$U41,"<0")*COUNTIF($Q41:$U41,">0")>0),$G41/5,$G41*Q41/SUM($Q41:$U41)) -> 295762.85 | C41: =IF(OR(SUM($Q41:$U41)=0,COUNTIF($Q41:$U41,"<0")*COUNTIF($Q41:$U41,">0")>0),$G41/5,$G41*R41/SUM($Q41:$U41)) -> 292727.45 | D41: =IF(OR(SUM($Q41:$U41)=0,COUNTIF($Q41:$U41,"<0")*COUNTIF($Q41:$U41,">0")>0),$G41/5,$G41*S41/SUM($Q41:$U41)) -> 322483.6 | E41: =IF(OR(SUM($Q41:$U41)=0,COUNTIF($Q41:$U41,"<0")*COUNTIF($Q41:$U41,">0")>0),$G41/5,$G41*T41/SUM($Q41:$U41)) -> 321934.83 | F41: =IF(OR(SUM($Q41:$U41)=0,COUNTIF($Q41:$U41,"<0")*COUNTIF($Q41:$U41,">0")>0),$G41/5,$G41*U41/SUM($Q41:$U41)) -> 361718.8 | G41: 1594627.5 | H41: 335844.6 | I41: 319114.56 | J41: 340452.07 | K41: 338053.42 | L41: 457659.57 | M41: 264005.44 | N41: 98279.12 | O41: =SUM(B41:F41,H41:N41) -> 3748036.3 | Q41: 239607.33 | R41: 237148.25 | S41: 261254.7 | T41: 260810.12 | U41: 293040.44 | V41: 288588.62 | W41: 295567.28 | X41: 299741 | Y41: =SUM(Q41:X41) -> 2175757.7
B42: =IF(OR(SUM($Q42:$U42)=0,COUNTIF($Q42:$U42,"<0")*COUNTIF($Q42:$U42,">0")>0),$G42/5,$G42*Q42/SUM($Q42:$U42)) -> 0 | C42: =IF(OR(SUM($Q42:$U42)=0,COUNTIF($Q42:$U42,"<0")*COUNTIF($Q42:$U42,">0")>0),$G42/5,$G42*R42/SUM($Q42:$U42)) -> 0 | D42: =IF(OR(SUM($Q42:$U42)=0,COUNTIF($Q42:$U42,"<0")*COUNTIF($Q42:$U42,">0")>0),$G42/5,$G42*S42/SUM($Q42:$U42)) -> 0 | E42: =IF(OR(SUM($Q42:$U42)=0,COUNTIF($Q42:$U42,"<0")*COUNTIF($Q42:$U42,">0")>0),$G42/5,$G42*T42/SUM($Q42:$U42)) -> 0 | F42: =IF(OR(SUM($Q42:$U42)=0,COUNTIF($Q42:$U42,"<0")*COUNTIF($Q42:$U42,">0")>0),$G42/5,$G42*U42/SUM($Q42:$U42)) -> 0 | G42: 0 | H42: 0 | I42: 0 | J42: 0 | K42: 0 | L42: 0 | M42: 0 | N42: 0 | O42: =SUM(B42:F42,H42:N42) -> 0 | Q42: 0 | R42: 0 | S42: 0 | T42: 0 | U42: 0 | V42: 0 | W42: 0 | X42: 0 | Y42: =SUM(Q42:X42) -> 0
A43: UTILIDAD (PÉRDIDA) EN OPERACIÓN | B43: =IF(OR(SUM($Q43:$U43)=0,COUNTIF($Q43:$U43,"<0")*COUNTIF($Q43:$U43,">0")>0),$G43/5,$G43*Q43/SUM($Q43:$U43)) -> 1148808.6 | C43: =IF(OR(SUM($Q43:$U43)=0,COUNTIF($Q43:$U43,"<0")*COUNTIF($Q43:$U43,">0")>0),$G43/5,$G43*R43/SUM($Q43:$U43)) -> 1148808.6 | D43: =IF(OR(SUM($Q43:$U43)=0,COUNTIF($Q43:$U43,"<0")*COUNTIF($Q43:$U43,">0")>0),$G43/5,$G43*S43/SUM($Q43:$U43)) -> 1148808.6 | E43: =IF(OR(SUM($Q43:$U43)=0,COUNTIF($Q43:$U43,"<0")*COUNTIF($Q43:$U43,">0")>0),$G43/5,$G43*T43/SUM($Q43:$U43)) -> 1148808.6 | F43: =IF(OR(SUM($Q43:$U43)=0,COUNTIF($Q43:$U43,"<0")*COUNTIF($Q43:$U43,">0")>0),$G43/5,$G43*U43/SUM($Q43:$U43)) -> 1148808.6 | G43: 5744043 | H43: 816460.64 | I43: 1485424.2 | J43: -333836.9 | K43: 675981.09 | L43: 271300.19 | M43: 816892.81 | N43: -1422901.4 | O43: =SUM(B43:F43,H43:N43) -> 8053363.5 | Q43: 5832.75 | R43: 175518.69 | S43: 585422.32 | T43: -370975.06 | U43: 729645.8 | V43: 841578.1 | W43: 838987.9 | X43: -89927.41 | Y43: =SUM(Q43:X43) -> 2716083.1
A44: OTROS PRODUCTOS Y GASTOS | B44: =IF(OR(SUM($Q44:$U44)=0,COUNTIF($Q44:$U44,"<0")*COUNTIF($Q44:$U44,">0")>0),$G44/5,$G44*Q44/SUM($Q44:$U44)) -> 340514.48 | C44: =IF(OR(SUM($Q44:$U44)=0,COUNTIF($Q44:$U44,"<0")*COUNTIF($Q44:$U44,">0")>0),$G44/5,$G44*R44/SUM($Q44:$U44)) -> 332994.78 | D44: =IF(OR(SUM($Q44:$U44)=0,COUNTIF($Q44:$U44,"<0")*COUNTIF($Q44:$U44,">0")>0),$G44/5,$G44*S44/SUM($Q44:$U44)) -> 224184.73 | E44: =IF(OR(SUM($Q44:$U44)=0,COUNTIF($Q44:$U44,"<0")*COUNTIF($Q44:$U44,">0")>0),$G44/5,$G44*T44/SUM($Q44:$U44)) -> 287938.62 | F44: =IF(OR(SUM($Q44:$U44)=0,COUNTIF($Q44:$U44,"<0")*COUNTIF($Q44:$U44,">0")>0),$G44/5,$G44*U44/SUM($Q44:$U44)) -> 281850.15 | G44: 1467482.8 | H44: 202382.88 | I44: 149720.32 | J44: -400495.02 | K44: 683512.13 | L44: 148606.88 | M44: 103895.82 | N44: 255348.71 | O44: =SUM(B44:F44,H44:N44) -> 2610454.5 | Q44: 432624.52 | R44: 423070.72 | S44: 284827.27 | T44: 365826.75 | U44: 358091.34 | V44: 247757.21 | W44: 381584.79 | X44: 406463.09 | Y44: =SUM(Q44:X44) -> 2900245.7
A45: (+) Otros Productos | B45: =IF(OR(SUM($Q45:$U45)=0,COUNTIF($Q45:$U45,"<0")*COUNTIF($Q45:$U45,">0")>0),$G45/5,$G45*Q45/SUM($Q45:$U45)) -> 386069.97 | C45: =IF(OR(SUM($Q45:$U45)=0,COUNTIF($Q45:$U45,"<0")*COUNTIF($Q45:$U45,">0")>0),$G45/5,$G45*R45/SUM($Q45:$U45)) -> 344471.36 | D45: =IF(OR(SUM($Q45:$U45)=0,COUNTIF($Q45:$U45,"<0")*COUNTIF($Q45:$U45,">0")>0),$G45/5,$G45*S45/SUM($Q45:$U45)) -> 255479.65 | E45: =IF(OR(SUM($Q45:$U45)=0,COUNTIF($Q45:$U45,"<0")*COUNTIF($Q45:$U45,">0")>0),$G45/5,$G45*T45/SUM($Q45:$U45)) -> 338335.4 | F45: =IF(OR(SUM($Q45:$U45)=0,COUNTIF($Q45:$U45,"<0")*COUNTIF($Q45:$U45,">0")>0),$G45/5,$G45*U45/SUM($Q45:$U45)) -> 305991.18 | G45: 1630347.6 | H45: 204783.03 | I45: 173547.84 | J45: 190902.53 | K45: 134237.69 | L45: 154585.47 | M45: 123061.66 | N45: 275581.22 | O45: =SUM(B45:F45,H45:N45) -> 2887047 | Q45: 477966.6 | R45: 426466.23 | S45: 316291.73 | T45: 418869.72 | U45: 378826.58 | V45: 379174.59 | W45: 402593.61 | X45: 433710.42 | Y45: =SUM(Q45:X45) -> 3233899.5
A46: (-) Otros Gastos | B46: =IF(OR(SUM($Q46:$U46)=0,COUNTIF($Q46:$U46,"<0")*COUNTIF($Q46:$U46,">0")>0),$G46/5,$G46*Q46/SUM($Q46:$U46)) -> 47958.285 | C46: =IF(OR(SUM($Q46:$U46)=0,COUNTIF($Q46:$U46,"<0")*COUNTIF($Q46:$U46,">0")>0),$G46/5,$G46*R46/SUM($Q46:$U46)) -> 3591.4285 | D46: =IF(OR(SUM($Q46:$U46)=0,COUNTIF($Q46:$U46,"<0")*COUNTIF($Q46:$U46,">0")>0),$G46/5,$G46*S46/SUM($Q46:$U46)) -> 33279.937 | E46: =IF(OR(SUM($Q46:$U46)=0,COUNTIF($Q46:$U46,"<0")*COUNTIF($Q46:$U46,">0")>0),$G46/5,$G46*T46/SUM($Q46:$U46)) -> 56103.511 | F46: =IF(OR(SUM($Q46:$U46)=0,COUNTIF($Q46:$U46,"<0")*COUNTIF($Q46:$U46,">0")>0),$G46/5,$G46*U46/SUM($Q46:$U46)) -> 21931.648 | G46: 162864.81 | H46: 2400.15 | I46: 23827.52 | J46: 591397.55 | K46: -549274.44 | L46: 5978.59 | M46: 19165.84 | N46: 20232.51 | O46: =SUM(B46:F46,H46:N46) -> 276592.53 | Q46: 45342.08 | R46: 3395.51 | S46: 31464.46 | T46: 53042.97 | U46: 20735.24 | V46: 131417.38 | W46: 21008.82 | X46: 27247.33 | Y46: =SUM(Q46:X46) -> 333653.79
B47: =IF(OR(SUM($Q47:$U47)=0,COUNTIF($Q47:$U47,"<0")*COUNTIF($Q47:$U47,">0")>0),$G47/5,$G47*Q47/SUM($Q47:$U47)) -> 0 | C47: =IF(OR(SUM($Q47:$U47)=0,COUNTIF($Q47:$U47,"<0")*COUNTIF($Q47:$U47,">0")>0),$G47/5,$G47*R47/SUM($Q47:$U47)) -> 0 | D47: =IF(OR(SUM($Q47:$U47)=0,COUNTIF($Q47:$U47,"<0")*COUNTIF($Q47:$U47,">0")>0),$G47/5,$G47*S47/SUM($Q47:$U47)) -> 0 | E47: =IF(OR(SUM($Q47:$U47)=0,COUNTIF($Q47:$U47,"<0")*COUNTIF($Q47:$U47,">0")>0),$G47/5,$G47*T47/SUM($Q47:$U47)) -> 0 | F47: =IF(OR(SUM($Q47:$U47)=0,COUNTIF($Q47:$U47,"<0")*COUNTIF($Q47:$U47,">0")>0),$G47/5,$G47*U47/SUM($Q47:$U47)) -> 0 | G47: 0 | H47: 0 | I47: 0 | J47: 0 | K47: 0 | L47: 0 | M47: 0 | N47: 0 | O47: =SUM(B47:F47,H47:N47) -> 0 | Q47: 0 | R47: 0 | S47: 0 | T47: 0 | U47: 0 | V47: 0 | W47: 0 | X47: 0 | Y47: =SUM(Q47:X47) -> 0
A48: UTILIDAD NETA (PÉRDIDA) EN OPERACIÓN | B48: =IF(OR(SUM($Q48:$U48)=0,COUNTIF($Q48:$U48,"<0")*COUNTIF($Q48:$U48,">0")>0),$G48/5,$G48*Q48/SUM($Q48:$U48)) -> 1442305.1 | C48: =IF(OR(SUM($Q48:$U48)=0,COUNTIF($Q48:$U48,"<0")*COUNTIF($Q48:$U48,">0")>0),$G48/5,$G48*R48/SUM($Q48:$U48)) -> 1442305.1 | D48: =IF(OR(SUM($Q48:$U48)=0,COUNTIF($Q48:$U48,"<0")*COUNTIF($Q48:$U48,">0")>0),$G48/5,$G48*S48/SUM($Q48:$U48)) -> 1442305.1 | E48: =IF(OR(SUM($Q48:$U48)=0,COUNTIF($Q48:$U48,"<0")*COUNTIF($Q48:$U48,">0")>0),$G48/5,$G48*T48/SUM($Q48:$U48)) -> 1442305.1 | F48: =IF(OR(SUM($Q48:$U48)=0,COUNTIF($Q48:$U48,"<0")*COUNTIF($Q48:$U48,">0")>0),$G48/5,$G48*U48/SUM($Q48:$U48)) -> 1442305.1 | G48: 7211525.7 | H48: 1018843.5 | I48: 1635144.5 | J48: -734331.92 | K48: 1359493.2 | L48: 419907.07 | M48: 920788.63 | N48: -1167552.7 | O48: =SUM(B48:F48,H48:N48) -> 10663818 | Q48: 438457.27 | R48: 598589.41 | S48: 870249.59 | T48: -5148.31 | U48: 1087737.1 | V48: 1089335.3 | W48: 1220572.7 | X48: 316535.68 | Y48: =SUM(Q48:X48) -> 5616328.8
A49: (+) Productos de Ejercicios Anteriores | B49: =IF(OR(SUM($Q49:$U49)=0,COUNTIF($Q49:$U49,"<0")*COUNTIF($Q49:$U49,">0")>0),$G49/5,$G49*Q49/SUM($Q49:$U49)) -> 11557.202 | C49: =IF(OR(SUM($Q49:$U49)=0,COUNTIF($Q49:$U49,"<0")*COUNTIF($Q49:$U49,">0")>0),$G49/5,$G49*R49/SUM($Q49:$U49)) -> 551.31822 | D49: =IF(OR(SUM($Q49:$U49)=0,COUNTIF($Q49:$U49,"<0")*COUNTIF($Q49:$U49,">0")>0),$G49/5,$G49*S49/SUM($Q49:$U49)) -> 30.091038 | E49: =IF(OR(SUM($Q49:$U49)=0,COUNTIF($Q49:$U49,"<0")*COUNTIF($Q49:$U49,">0")>0),$G49/5,$G49*T49/SUM($Q49:$U49)) -> 73312.315 | F49: =IF(OR(SUM($Q49:$U49)=0,COUNTIF($Q49:$U49,"<0")*COUNTIF($Q49:$U49,">0")>0),$G49/5,$G49*U49/SUM($Q49:$U49)) -> 943.34366 | G49: 86394.27 | H49: 1160.03 | I49: 0 | J49: 205889.79 | K49: 0 | L49: 0 | M49: 0 | N49: 929.64 | O49: =SUM(B49:F49,H49:N49) -> 294373.73 | Q49: 162524.99 | R49: 7753 | S49: 423.16 | T49: 1030966.1 | U49: 13265.92 | V49: 0 | W49: 0 | X49: 0 | Y49: =SUM(Q49:X49) -> 1214933.1
A50: (-) Gastos de Ejercicios Anteriores | B50: =IF(OR(SUM($Q50:$U50)=0,COUNTIF($Q50:$U50,"<0")*COUNTIF($Q50:$U50,">0")>0),$G50/5,$G50*Q50/SUM($Q50:$U50)) -> 407497.89 | C50: =IF(OR(SUM($Q50:$U50)=0,COUNTIF($Q50:$U50,"<0")*COUNTIF($Q50:$U50,">0")>0),$G50/5,$G50*R50/SUM($Q50:$U50)) -> 9652.2185 | D50: =IF(OR(SUM($Q50:$U50)=0,COUNTIF($Q50:$U50,"<0")*COUNTIF($Q50:$U50,">0")>0),$G50/5,$G50*S50/SUM($Q50:$U50)) -> 176.45013 | E50: =IF(OR(SUM($Q50:$U50)=0,COUNTIF($Q50:$U50,"<0")*COUNTIF($Q50:$U50,">0")>0),$G50/5,$G50*T50/SUM($Q50:$U50)) -> 0 | F50: =IF(OR(SUM($Q50:$U50)=0,COUNTIF($Q50:$U50,"<0")*COUNTIF($Q50:$U50,">0")>0),$G50/5,$G50*U50/SUM($Q50:$U50)) -> 0 | G50: 417326.56 | H50: 2242.37 | I50: 154622.8 | J50: -574191.73 | K50: 574191.73 | L50: 84576.29 | M50: 0 | N50: 0 | O50: =SUM(B50:F50,H50:N50) -> 658768.02 | Q50: 41107.72 | R50: 973.7 | S50: 17.8 | T50: 0 | U50: 0 | V50: 0 | W50: 0 | X50: 0 | Y50: =SUM(Q50:X50) -> 42099.22
B51: =IF(OR(SUM($Q51:$U51)=0,COUNTIF($Q51:$U51,"<0")*COUNTIF($Q51:$U51,">0")>0),$G51/5,$G51*Q51/SUM($Q51:$U51)) -> 0 | C51: =IF(OR(SUM($Q51:$U51)=0,COUNTIF($Q51:$U51,"<0")*COUNTIF($Q51:$U51,">0")>0),$G51/5,$G51*R51/SUM($Q51:$U51)) -> 0 | D51: =IF(OR(SUM($Q51:$U51)=0,COUNTIF($Q51:$U51,"<0")*COUNTIF($Q51:$U51,">0")>0),$G51/5,$G51*S51/SUM($Q51:$U51)) -> 0 | E51: =IF(OR(SUM($Q51:$U51)=0,COUNTIF($Q51:$U51,"<0")*COUNTIF($Q51:$U51,">0")>0),$G51/5,$G51*T51/SUM($Q51:$U51)) -> 0 | F51: =IF(OR(SUM($Q51:$U51)=0,COUNTIF($Q51:$U51,"<0")*COUNTIF($Q51:$U51,">0")>0),$G51/5,$G51*U51/SUM($Q51:$U51)) -> 0 | G51: 0 | H51: 0 | I51: 0 | J51: 0 | K51: 0 | L51: 0 | M51: 0 | N51: 0 | O51: =SUM(B51:F51,H51:N51) -> 0 | Q51: 0 | R51: 0 | S51: 0 | T51: 0 | U51: 0 | V51: 0 | W51: 0 | X51: 0 | Y51: =SUM(Q51:X51) -> 0
A52: UTILIDAD (PÉRDIDA) | B52: =IF(OR(SUM($Q52:$U52)=0,COUNTIF($Q52:$U52,"<0")*COUNTIF($Q52:$U52,">0")>0),$G52/5,$G52*Q52/SUM($Q52:$U52)) -> 925421.35 | C52: =IF(OR(SUM($Q52:$U52)=0,COUNTIF($Q52:$U52,"<0")*COUNTIF($Q52:$U52,">0")>0),$G52/5,$G52*R52/SUM($Q52:$U52)) -> 1000619.1 | D52: =IF(OR(SUM($Q52:$U52)=0,COUNTIF($Q52:$U52,"<0")*COUNTIF($Q52:$U52,">0")>0),$G52/5,$G52*S52/SUM($Q52:$U52)) -> 1439112.9 | E52: =IF(OR(SUM($Q52:$U52)=0,COUNTIF($Q52:$U52,"<0")*COUNTIF($Q52:$U52,">0")>0),$G52/5,$G52*T52/SUM($Q52:$U52)) -> 1695582.8 | F52: =IF(OR(SUM($Q52:$U52)=0,COUNTIF($Q52:$U52,"<0")*COUNTIF($Q52:$U52,">0")>0),$G52/5,$G52*U52/SUM($Q52:$U52)) -> 1819857.3 | G52: 6880593.4 | H52: 1017761.2 | I52: 1480521.7 | J52: 45749.6 | K52: 785301.49 | L52: 335330.78 | M52: 920788.63 | N52: -1166623.1 | O52: =SUM(B52:F52,H52:N52) -> 10299424 | Q52: 559874.54 | R52: 605368.71 | S52: 870654.95 | T52: 1025817.8 | U52: 1101003.1 | V52: 1089335.3 | W52: 1220572.7 | X52: 316535.68 | Y52: =SUM(Q52:X52) -> 6789162.7
A53: (-) Impuesto Sobre la Renta | B53: =IF(OR(SUM($Q53:$U53)=0,COUNTIF($Q53:$U53,"<0")*COUNTIF($Q53:$U53,">0")>0),$G53/5,$G53*Q53/SUM($Q53:$U53)) -> 291913.92 | C53: =IF(OR(SUM($Q53:$U53)=0,COUNTIF($Q53:$U53,"<0")*COUNTIF($Q53:$U53,">0")>0),$G53/5,$G53*R53/SUM($Q53:$U53)) -> 165878.03 | D53: =IF(OR(SUM($Q53:$U53)=0,COUNTIF($Q53:$U53,"<0")*COUNTIF($Q53:$U53,">0")>0),$G53/5,$G53*S53/SUM($Q53:$U53)) -> 394007.8 | E53: =IF(OR(SUM($Q53:$U53)=0,COUNTIF($Q53:$U53,"<0")*COUNTIF($Q53:$U53,">0")>0),$G53/5,$G53*T53/SUM($Q53:$U53)) -> 320717.6 | F53: =IF(OR(SUM($Q53:$U53)=0,COUNTIF($Q53:$U53,"<0")*COUNTIF($Q53:$U53,">0")>0),$G53/5,$G53*U53/SUM($Q53:$U53)) -> 346003.06 | G53: 1518520.4 | H53: 188579.78 | I53: 352142.81 | J53: -49484.21 | K53: 132001.39 | L53: 5508.05 | M53: 181035.09 | N53: -303510.81 | O53: =SUM(B53:F53,H53:N53) -> 2024792.5 | Q53: 188431.72 | R53: 107075 | S53: 254333.77 | T53: 207024.62 | U53: 223346.5 | V53: 214231.44 | W53: 251595.89 | X53: 22364.77 | Y53: =SUM(Q53:X53) -> 1468403.7
A54: UTILIDAD (PÉRDIDA) NETA | B54: =IF(OR(SUM($Q54:$U54)=0,COUNTIF($Q54:$U54,"<0")*COUNTIF($Q54:$U54,">0")>0),$G54/5,$G54*Q54/SUM($Q54:$U54)) -> 625828.4 | C54: =IF(OR(SUM($Q54:$U54)=0,COUNTIF($Q54:$U54,"<0")*COUNTIF($Q54:$U54,">0")>0),$G54/5,$G54*R54/SUM($Q54:$U54)) -> 839554.13 | D54: =IF(OR(SUM($Q54:$U54)=0,COUNTIF($Q54:$U54,"<0")*COUNTIF($Q54:$U54,">0")>0),$G54/5,$G54*S54/SUM($Q54:$U54)) -> 1038413.7 | E54: =IF(OR(SUM($Q54:$U54)=0,COUNTIF($Q54:$U54,"<0")*COUNTIF($Q54:$U54,">0")>0),$G54/5,$G54*T54/SUM($Q54:$U54)) -> 1379550.2 | F54: =IF(OR(SUM($Q54:$U54)=0,COUNTIF($Q54:$U54,"<0")*COUNTIF($Q54:$U54,">0")>0),$G54/5,$G54*U54/SUM($Q54:$U54)) -> 1478726.7 | G54: 5362073 | H54: 829181.4 | I54: 1128378.9 | J54: 95233.81 | K54: 653300.1 | L54: 329822.73 | M54: 739753.54 | N54: -863112.26 | O54: =SUM(B54:F54,H54:N54) -> 8274631.2 | Q54: 371442.82 | R54: 498293.71 | S54: 616321.18 | T54: 818793.14 | U54: 877656.56 | V54: 875103.87 | W54: 968976.8 | X54: 294170.91 | Y54: =SUM(Q54:X54) -> 5320759
R56: 0
R57: 0
A59: G&T
A62: ESTADO DE RESULTADOS | B62: 45658 | C62: 45689 | D62: 45717 | E62: 45748 | F62: 45778 | G62: ENERO A MAYO | H62: 45809 | I62: 45839 | J62: 45870 | K62: 45901 | L62: 45931 | M62: 45962 | N62: 45992 | O62: ACUMULADO | Q62: 46023 | R62: 46054 | S62: 46082 | T62: 46113 | U62: 46143 | V62: 46174 | W62: 46204 | X62: 46235 | Y62: ACUMULADO
A63: Primas | B63: =IF(OR(SUM($Q63:$U63)=0,COUNTIF($Q63:$U63,"<0")*COUNTIF($Q63:$U63,">0")>0),$G63/5,$G63*Q63/SUM($Q63:$U63)) -> 0 | C63: =IF(OR(SUM($Q63:$U63)=0,COUNTIF($Q63:$U63,"<0")*COUNTIF($Q63:$U63,">0")>0),$G63/5,$G63*R63/SUM($Q63:$U63)) -> 0 | D63: =IF(OR(SUM($Q63:$U63)=0,COUNTIF($Q63:$U63,"<0")*COUNTIF($Q63:$U63,">0")>0),$G63/5,$G63*S63/SUM($Q63:$U63)) -> 0 | E63: =IF(OR(SUM($Q63:$U63)=0,COUNTIF($Q63:$U63,"<0")*COUNTIF($Q63:$U63,">0")>0),$G63/5,$G63*T63/SUM($Q63:$U63)) -> 0 | F63: =IF(OR(SUM($Q63:$U63)=0,COUNTIF($Q63:$U63,"<0")*COUNTIF($Q63:$U63,">0")>0),$G63/5,$G63*U63/SUM($Q63:$U63)) -> 0 | G63: 0 | H63: 0 | I63: 0 | J63: 0 | K63: 0 | L63: 0 | M63: 0 | N63: 0 | O63: =SUM(B63:F63,H63:N63) -> 0 | Q63: 0 | R63: 0 | S63: 0 | T63: 0 | U63: 0 | V63: 0 | W63: 0 | X63: 0 | Y63: =SUM(Q63:X63) -> 0
A64: Seguro Directo | B64: =IF(OR(SUM($Q64:$U64)=0,COUNTIF($Q64:$U64,"<0")*COUNTIF($Q64:$U64,">0")>0),$G64/5,$G64*Q64/SUM($Q64:$U64)) -> 3.7032635e+08 | C64: =IF(OR(SUM($Q64:$U64)=0,COUNTIF($Q64:$U64,"<0")*COUNTIF($Q64:$U64,">0")>0),$G64/5,$G64*R64/SUM($Q64:$U64)) -> 1.8617061e+08 | D64: =IF(OR(SUM($Q64:$U64)=0,COUNTIF($Q64:$U64,"<0")*COUNTIF($Q64:$U64,">0")>0),$G64/5,$G64*S64/SUM($Q64:$U64)) -> 1.6328337e+08 | E64: =IF(OR(SUM($Q64:$U64)=0,COUNTIF($Q64:$U64,"<0")*COUNTIF($Q64:$U64,">0")>0),$G64/5,$G64*T64/SUM($Q64:$U64)) -> 1.2481973e+08 | F64: =IF(OR(SUM($Q64:$U64)=0,COUNTIF($Q64:$U64,"<0")*COUNTIF($Q64:$U64,">0")>0),$G64/5,$G64*U64/SUM($Q64:$U64)) -> 1.5682738e+08 | G64: 1.0014274e+09 | H64: 1.7378078e+08 | I64: 2.2563379e+08 | J64: 1.3981057e+08 | K64: 1.3580466e+08 | L64: 1.3451223e+08 | M64: 1.482133e+08 | N64: 1.6456183e+08 | O64: =SUM(B64:F64,H64:N64) -> 2.1237446e+09 | Q64: 4.3372612e+08 | R64: 2.1804297e+08 | S64: 1.9123744e+08 | T64: 1.4618883e+08 | U64: 1.8367619e+08 | V64: 1.8677459e+08 | W64: 2.3119146e+08 | X64: 1.4629744e+08 | Y64: =SUM(Q64:X64) -> 1.737135e+09
A65: (-) Devoluciones y Cancelaciones de Primas | B65: =IF(OR(SUM($Q65:$U65)=0,COUNTIF($Q65:$U65,"<0")*COUNTIF($Q65:$U65,">0")>0),$G65/5,$G65*Q65/SUM($Q65:$U65)) -> 56247893 | C65: =IF(OR(SUM($Q65:$U65)=0,COUNTIF($Q65:$U65,"<0")*COUNTIF($Q65:$U65,">0")>0),$G65/5,$G65*R65/SUM($Q65:$U65)) -> 32870463 | D65: =IF(OR(SUM($Q65:$U65)=0,COUNTIF($Q65:$U65,"<0")*COUNTIF($Q65:$U65,">0")>0),$G65/5,$G65*S65/SUM($Q65:$U65)) -> 28365699 | E65: =IF(OR(SUM($Q65:$U65)=0,COUNTIF($Q65:$U65,"<0")*COUNTIF($Q65:$U65,">0")>0),$G65/5,$G65*T65/SUM($Q65:$U65)) -> 18978141 | F65: =IF(OR(SUM($Q65:$U65)=0,COUNTIF($Q65:$U65,"<0")*COUNTIF($Q65:$U65,">0")>0),$G65/5,$G65*U65/SUM($Q65:$U65)) -> 24828531 | G65: 1.6129073e+08 | H65: 25846210 | I65: 59858041 | J65: 16152011 | K65: 28228407 | L65: 23951502 | M65: 24328316 | N65: 22818648 | O65: =SUM(B65:F65,H65:N65) -> 3.6247386e+08 | Q65: 74875415 | R65: 43756119 | S65: 37759520 | T65: 25263100 | U65: 33050955 | V65: 27640106 | W65: 48584920 | X65: 40032649 | Y65: =SUM(Q65:X65) -> 3.3096278e+08
A66: PRIMAS DIRECTAS NETAS | B66: =IF(OR(SUM($Q66:$U66)=0,COUNTIF($Q66:$U66,"<0")*COUNTIF($Q66:$U66,">0")>0),$G66/5,$G66*Q66/SUM($Q66:$U66)) -> 3.1464643e+08 | C66: =IF(OR(SUM($Q66:$U66)=0,COUNTIF($Q66:$U66,"<0")*COUNTIF($Q66:$U66,">0")>0),$G66/5,$G66*R66/SUM($Q66:$U66)) -> 1.5281769e+08 | D66: =IF(OR(SUM($Q66:$U66)=0,COUNTIF($Q66:$U66,"<0")*COUNTIF($Q66:$U66,">0")>0),$G66/5,$G66*S66/SUM($Q66:$U66)) -> 1.3457206e+08 | E66: =IF(OR(SUM($Q66:$U66)=0,COUNTIF($Q66:$U66,"<0")*COUNTIF($Q66:$U66,">0")>0),$G66/5,$G66*T66/SUM($Q66:$U66)) -> 1.0602975e+08 | F66: =IF(OR(SUM($Q66:$U66)=0,COUNTIF($Q66:$U66,"<0")*COUNTIF($Q66:$U66,">0")>0),$G66/5,$G66*U66/SUM($Q66:$U66)) -> 1.3207078e+08 | G66: 8.4013672e+08 | H66: 1.4793457e+08 | I66: 1.6577575e+08 | J66: 1.2365856e+08 | K66: 1.0757626e+08 | L66: 1.1056073e+08 | M66: 1.2388499e+08 | N66: 1.4174318e+08 | O66: =SUM(B66:F66,H66:N66) -> 1.7612708e+09 | Q66: 3.588507e+08 | R66: 1.7428685e+08 | S66: 1.5347792e+08 | T66: 1.2092573e+08 | U66: 1.5062524e+08 | V66: 1.5913448e+08 | W66: 1.8260654e+08 | X66: 1.0626479e+08 | Y66: =SUM(Q66:X66) -> 1.4061723e+09
B67: =IF(OR(SUM($Q67:$U67)=0,COUNTIF($Q67:$U67,"<0")*COUNTIF($Q67:$U67,">0")>0),$G67/5,$G67*Q67/SUM($Q67:$U67)) -> 0 | C67: =IF(OR(SUM($Q67:$U67)=0,COUNTIF($Q67:$U67,"<0")*COUNTIF($Q67:$U67,">0")>0),$G67/5,$G67*R67/SUM($Q67:$U67)) -> 0 | D67: =IF(OR(SUM($Q67:$U67)=0,COUNTIF($Q67:$U67,"<0")*COUNTIF($Q67:$U67,">0")>0),$G67/5,$G67*S67/SUM($Q67:$U67)) -> 0 | E67: =IF(OR(SUM($Q67:$U67)=0,COUNTIF($Q67:$U67,"<0")*COUNTIF($Q67:$U67,">0")>0),$G67/5,$G67*T67/SUM($Q67:$U67)) -> 0 | F67: =IF(OR(SUM($Q67:$U67)=0,COUNTIF($Q67:$U67,"<0")*COUNTIF($Q67:$U67,">0")>0),$G67/5,$G67*U67/SUM($Q67:$U67)) -> 0 | G67: 0 | H67: 0 | I67: 0 | J67: 0 | K67: 0 | L67: 0 | M67: 0 | N67: 0 | O67: =SUM(B67:F67,H67:N67) -> 0 | Q67: 0 | R67: 0 | S67: 0 | T67: 0 | U67: 0 | V67: 0 | W67: 0 | X67: 0 | Y67: =SUM(Q67:X67) -> 0
A68: Primas | B68: =IF(OR(SUM($Q68:$U68)=0,COUNTIF($Q68:$U68,"<0")*COUNTIF($Q68:$U68,">0")>0),$G68/5,$G68*Q68/SUM($Q68:$U68)) -> 635936.11 | C68: =IF(OR(SUM($Q68:$U68)=0,COUNTIF($Q68:$U68,"<0")*COUNTIF($Q68:$U68,">0")>0),$G68/5,$G68*R68/SUM($Q68:$U68)) -> 1926283.3 | D68: =IF(OR(SUM($Q68:$U68)=0,COUNTIF($Q68:$U68,"<0")*COUNTIF($Q68:$U68,">0")>0),$G68/5,$G68*S68/SUM($Q68:$U68)) -> 5451567.8 | E68: =IF(OR(SUM($Q68:$U68)=0,COUNTIF($Q68:$U68,"<0")*COUNTIF($Q68:$U68,">0")>0),$G68/5,$G68*T68/SUM($Q68:$U68)) -> 1010923.6 | F68: =IF(OR(SUM($Q68:$U68)=0,COUNTIF($Q68:$U68,"<0")*COUNTIF($Q68:$U68,">0")>0),$G68/5,$G68*U68/SUM($Q68:$U68)) -> 9648400.8 | G68: 18673112 | H68: 4653068.7 | I68: 2046375 | J68: 5591289.6 | K68: 946627.59 | L68: 1676480.1 | M68: 2627127.1 | N68: 1661079.2 | O68: =SUM(B68:F68,H68:N68) -> 37875159 | Q68: 383624.74 | R68: 1162019.1 | S68: 3288626.4 | T68: 609833.75 | U68: 5820341.4 | V68: 1170107.4 | W68: 3478386.5 | X68: 5833685.2 | Y68: =SUM(Q68:X68) -> 21746625
A69: (+) Por Reaseguro Tomado Local | B69: =IF(OR(SUM($Q69:$U69)=0,COUNTIF($Q69:$U69,"<0")*COUNTIF($Q69:$U69,">0")>0),$G69/5,$G69*Q69/SUM($Q69:$U69)) -> 818680.96 | C69: =IF(OR(SUM($Q69:$U69)=0,COUNTIF($Q69:$U69,"<0")*COUNTIF($Q69:$U69,">0")>0),$G69/5,$G69*R69/SUM($Q69:$U69)) -> 2223224.5 | D69: =IF(OR(SUM($Q69:$U69)=0,COUNTIF($Q69:$U69,"<0")*COUNTIF($Q69:$U69,">0")>0),$G69/5,$G69*S69/SUM($Q69:$U69)) -> 6454981.8 | E69: =IF(OR(SUM($Q69:$U69)=0,COUNTIF($Q69:$U69,"<0")*COUNTIF($Q69:$U69,">0")>0),$G69/5,$G69*T69/SUM($Q69:$U69)) -> 3054736.5 | F69: =IF(OR(SUM($Q69:$U69)=0,COUNTIF($Q69:$U69,"<0")*COUNTIF($Q69:$U69,">0")>0),$G69/5,$G69*U69/SUM($Q69:$U69)) -> 13307704 | G69: 25859328 | H69: 4732869.1 | I69: 2429262.8 | J69: 6361840.7 | K69: 4090213.7 | L69: 2049914.9 | M69: 3577544 | N69: 2378299.6 | O69: =SUM(B69:F69,H69:N69) -> 51479273 | Q69: 427902.33 | R69: 1162019.1 | S69: 3373843.9 | T69: 1596627.9 | U69: 6955576 | V69: 1608648.7 | W69: 3696011.2 | X69: 6010511.1 | Y69: =SUM(Q69:X69) -> 24831140
A70: (+) Por Reaseguro Tomado del Exterior | B70: =IF(OR(SUM($Q70:$U70)=0,COUNTIF($Q70:$U70,"<0")*COUNTIF($Q70:$U70,">0")>0),$G70/5,$G70*Q70/SUM($Q70:$U70)) -> 0 | C70: =IF(OR(SUM($Q70:$U70)=0,COUNTIF($Q70:$U70,"<0")*COUNTIF($Q70:$U70,">0")>0),$G70/5,$G70*R70/SUM($Q70:$U70)) -> 0 | D70: =IF(OR(SUM($Q70:$U70)=0,COUNTIF($Q70:$U70,"<0")*COUNTIF($Q70:$U70,">0")>0),$G70/5,$G70*S70/SUM($Q70:$U70)) -> 0 | E70: =IF(OR(SUM($Q70:$U70)=0,COUNTIF($Q70:$U70,"<0")*COUNTIF($Q70:$U70,">0")>0),$G70/5,$G70*T70/SUM($Q70:$U70)) -> 0 | F70: =IF(OR(SUM($Q70:$U70)=0,COUNTIF($Q70:$U70,"<0")*COUNTIF($Q70:$U70,">0")>0),$G70/5,$G70*U70/SUM($Q70:$U70)) -> 0 | G70: 0 | H70: 0 | I70: 0 | J70: 0 | K70: 0 | L70: 0 | M70: 0 | N70: 0 | O70: =SUM(B70:F70,H70:N70) -> 0 | Q70: 0 | R70: 0 | S70: 0 | T70: 0 | U70: 0 | V70: 0 | W70: 0 | X70: 0 | Y70: =SUM(Q70:X70) -> 0
A71: (-) Devoluciones y Cancelaciones de Primas | B71: =IF(OR(SUM($Q71:$U71)=0,COUNTIF($Q71:$U71,"<0")*COUNTIF($Q71:$U71,">0")>0),$G71/5,$G71*Q71/SUM($Q71:$U71)) -> 141321.33 | C71: =IF(OR(SUM($Q71:$U71)=0,COUNTIF($Q71:$U71,"<0")*COUNTIF($Q71:$U71,">0")>0),$G71/5,$G71*R71/SUM($Q71:$U71)) -> 0 | D71: =IF(OR(SUM($Q71:$U71)=0,COUNTIF($Q71:$U71,"<0")*COUNTIF($Q71:$U71,">0")>0),$G71/5,$G71*S71/SUM($Q71:$U71)) -> 271989.53 | E71: =IF(OR(SUM($Q71:$U71)=0,COUNTIF($Q71:$U71,"<0")*COUNTIF($Q71:$U71,">0")>0),$G71/5,$G71*T71/SUM($Q71:$U71)) -> 3149563.1 | F71: =IF(OR(SUM($Q71:$U71)=0,COUNTIF($Q71:$U71,"<0")*COUNTIF($Q71:$U71,">0")>0),$G71/5,$G71*U71/SUM($Q71:$U71)) -> 3623342.4 | G71: 7186216.4 | H71: 79800.36 | I71: 382887.8 | J71: 770551 | K71: 3143586.1 | L71: 373434.8 | M71: 950416.93 | N71: 717220.4 | O71: =SUM(B71:F71,H71:N71) -> 13604114 | Q71: 44277.59 | R71: 0 | S71: 85217.43 | T71: 986794.16 | U71: 1135234.6 | V71: 438541.31 | W71: 217624.73 | X71: 176825.86 | Y71: =SUM(Q71:X71) -> 3084515.7
A72: TOTAL DE PRIMAS NETAS | B72: =IF(OR(SUM($Q72:$U72)=0,COUNTIF($Q72:$U72,"<0")*COUNTIF($Q72:$U72,">0")>0),$G72/5,$G72*Q72/SUM($Q72:$U72)) -> 3.1824236e+08 | C72: =IF(OR(SUM($Q72:$U72)=0,COUNTIF($Q72:$U72,"<0")*COUNTIF($Q72:$U72,">0")>0),$G72/5,$G72*R72/SUM($Q72:$U72)) -> 1.5542853e+08 | D72: =IF(OR(SUM($Q72:$U72)=0,COUNTIF($Q72:$U72,"<0")*COUNTIF($Q72:$U72,">0")>0),$G72/5,$G72*S72/SUM($Q72:$U72)) -> 1.3887803e+08 | E72: =IF(OR(SUM($Q72:$U72)=0,COUNTIF($Q72:$U72,"<0")*COUNTIF($Q72:$U72,">0")>0),$G72/5,$G72*T72/SUM($Q72:$U72)) -> 1.0766723e+08 | F72: =IF(OR(SUM($Q72:$U72)=0,COUNTIF($Q72:$U72,"<0")*COUNTIF($Q72:$U72,">0")>0),$G72/5,$G72*U72/SUM($Q72:$U72)) -> 1.3859369e+08 | G72: 8.5880983e+08 | H72: 1.5258764e+08 | I72: 1.6782212e+08 | J72: 1.2924985e+08 | K72: 1.0852288e+08 | L72: 1.1223721e+08 | M72: 1.2651211e+08 | N72: 1.4340426e+08 | O72: =SUM(B72:F72,H72:N72) -> 1.7991459e+09 | Q72: 3.5923433e+08 | R72: 1.7544887e+08 | S72: 1.5676655e+08 | T72: 1.2153557e+08 | U72: 1.5644558e+08 | V72: 1.6030459e+08 | W72: 1.8608492e+08 | X72: 1.1209848e+08 | Y72: =SUM(Q72:X72) -> 1.4279189e+09
B73: =IF(OR(SUM($Q73:$U73)=0,COUNTIF($Q73:$U73,"<0")*COUNTIF($Q73:$U73,">0")>0),$G73/5,$G73*Q73/SUM($Q73:$U73)) -> 0 | C73: =IF(OR(SUM($Q73:$U73)=0,COUNTIF($Q73:$U73,"<0")*COUNTIF($Q73:$U73,">0")>0),$G73/5,$G73*R73/SUM($Q73:$U73)) -> 0 | D73: =IF(OR(SUM($Q73:$U73)=0,COUNTIF($Q73:$U73,"<0")*COUNTIF($Q73:$U73,">0")>0),$G73/5,$G73*S73/SUM($Q73:$U73)) -> 0 | E73: =IF(OR(SUM($Q73:$U73)=0,COUNTIF($Q73:$U73,"<0")*COUNTIF($Q73:$U73,">0")>0),$G73/5,$G73*T73/SUM($Q73:$U73)) -> 0 | F73: =IF(OR(SUM($Q73:$U73)=0,COUNTIF($Q73:$U73,"<0")*COUNTIF($Q73:$U73,">0")>0),$G73/5,$G73*U73/SUM($Q73:$U73)) -> 0 | G73: 0 | H73: 0 | I73: 0 | J73: 0 | K73: 0 | L73: 0 | M73: 0 | N73: 0 | O73: =SUM(B73:F73,H73:N73) -> 0 | Q73: 0 | R73: 0 | S73: 0 | T73: 0 | U73: 0 | V73: 0 | W73: 0 | X73: 0 | Y73: =SUM(Q73:X73) -> 0
A74: (-) Primas por Reaseguro Cedido | B74: =IF(OR(SUM($Q74:$U74)=0,COUNTIF($Q74:$U74,"<0")*COUNTIF($Q74:$U74,">0")>0),$G74/5,$G74*Q74/SUM($Q74:$U74)) -> 69750526 | C74: =IF(OR(SUM($Q74:$U74)=0,COUNTIF($Q74:$U74,"<0")*COUNTIF($Q74:$U74,">0")>0),$G74/5,$G74*R74/SUM($Q74:$U74)) -> 63149020 | D74: =IF(OR(SUM($Q74:$U74)=0,COUNTIF($Q74:$U74,"<0")*COUNTIF($Q74:$U74,">0")>0),$G74/5,$G74*S74/SUM($Q74:$U74)) -> 41061378 | E74: =IF(OR(SUM($Q74:$U74)=0,COUNTIF($Q74:$U74,"<0")*COUNTIF($Q74:$U74,">0")>0),$G74/5,$G74*T74/SUM($Q74:$U74)) -> 38301097 | F74: =IF(OR(SUM($Q74:$U74)=0,COUNTIF($Q74:$U74,"<0")*COUNTIF($Q74:$U74,">0")>0),$G74/5,$G74*U74/SUM($Q74:$U74)) -> 42140938 | G74: 2.5440296e+08 | H74: 58632959 | I74: 92721506 | J74: 48051580 | K74: 30647773 | L74: 42482261 | M74: 42446885 | N74: 53119822 | O74: =SUM(B74:F74,H74:N74) -> 6.2250575e+08 | Q74: 99923227 | R74: 90466039 | S74: 58823719 | T74: 54869395 | U74: 60370276 | V74: 70723362 | W74: 93734466 | X74: 45967782 | Y74: =SUM(Q74:X74) -> 5.7487827e+08
B75: =IF(OR(SUM($Q75:$U75)=0,COUNTIF($Q75:$U75,"<0")*COUNTIF($Q75:$U75,">0")>0),$G75/5,$G75*Q75/SUM($Q75:$U75)) -> 0 | C75: =IF(OR(SUM($Q75:$U75)=0,COUNTIF($Q75:$U75,"<0")*COUNTIF($Q75:$U75,">0")>0),$G75/5,$G75*R75/SUM($Q75:$U75)) -> 0 | D75: =IF(OR(SUM($Q75:$U75)=0,COUNTIF($Q75:$U75,"<0")*COUNTIF($Q75:$U75,">0")>0),$G75/5,$G75*S75/SUM($Q75:$U75)) -> 0 | E75: =IF(OR(SUM($Q75:$U75)=0,COUNTIF($Q75:$U75,"<0")*COUNTIF($Q75:$U75,">0")>0),$G75/5,$G75*T75/SUM($Q75:$U75)) -> 0 | F75: =IF(OR(SUM($Q75:$U75)=0,COUNTIF($Q75:$U75,"<0")*COUNTIF($Q75:$U75,">0")>0),$G75/5,$G75*U75/SUM($Q75:$U75)) -> 0 | G75: 0 | H75: 0 | I75: 0 | J75: 0 | K75: 0 | L75: 0 | M75: 0 | N75: 0 | O75: =SUM(B75:F75,H75:N75) -> 0 | Q75: 0 | R75: 0 | S75: 0 | T75: 0 | U75: 0 | V75: 0 | W75: 0 | X75: 0 | Y75: =SUM(Q75:X75) -> 0
A76: PRIMAS NETAS DE RETENCIÓN | B76: =IF(OR(SUM($Q76:$U76)=0,COUNTIF($Q76:$U76,"<0")*COUNTIF($Q76:$U76,">0")>0),$G76/5,$G76*Q76/SUM($Q76:$U76)) -> 2.590662e+08 | C76: =IF(OR(SUM($Q76:$U76)=0,COUNTIF($Q76:$U76,"<0")*COUNTIF($Q76:$U76,">0")>0),$G76/5,$G76*R76/SUM($Q76:$U76)) -> 84902570 | D76: =IF(OR(SUM($Q76:$U76)=0,COUNTIF($Q76:$U76,"<0")*COUNTIF($Q76:$U76,">0")>0),$G76/5,$G76*S76/SUM($Q76:$U76)) -> 97850326 | E76: =IF(OR(SUM($Q76:$U76)=0,COUNTIF($Q76:$U76,"<0")*COUNTIF($Q76:$U76,">0")>0),$G76/5,$G76*T76/SUM($Q76:$U76)) -> 66603211 | F76: =IF(OR(SUM($Q76:$U76)=0,COUNTIF($Q76:$U76,"<0")*COUNTIF($Q76:$U76,">0")>0),$G76/5,$G76*U76/SUM($Q76:$U76)) -> 95984564 | G76: 6.0440687e+08 | H76: 93954679 | I76: 75100617 | J76: 81198273 | K76: 77875111 | L76: 69754950 | M76: 84065227 | N76: 90284440 | O76: =SUM(B76:F76,H76:N76) -> 1.1766402e+09 | Q76: 2.593111e+08 | R76: 84982831 | S76: 97942827 | T76: 66666173 | U76: 96075301 | V76: 89581228 | W76: 92350455 | X76: 66130697 | Y76: =SUM(Q76:X76) -> 8.5304061e+08
B77: =IF(OR(SUM($Q77:$U77)=0,COUNTIF($Q77:$U77,"<0")*COUNTIF($Q77:$U77,">0")>0),$G77/5,$G77*Q77/SUM($Q77:$U77)) -> 0 | C77: =IF(OR(SUM($Q77:$U77)=0,COUNTIF($Q77:$U77,"<0")*COUNTIF($Q77:$U77,">0")>0),$G77/5,$G77*R77/SUM($Q77:$U77)) -> 0 | D77: =IF(OR(SUM($Q77:$U77)=0,COUNTIF($Q77:$U77,"<0")*COUNTIF($Q77:$U77,">0")>0),$G77/5,$G77*S77/SUM($Q77:$U77)) -> 0 | E77: =IF(OR(SUM($Q77:$U77)=0,COUNTIF($Q77:$U77,"<0")*COUNTIF($Q77:$U77,">0")>0),$G77/5,$G77*T77/SUM($Q77:$U77)) -> 0 | F77: =IF(OR(SUM($Q77:$U77)=0,COUNTIF($Q77:$U77,"<0")*COUNTIF($Q77:$U77,">0")>0),$G77/5,$G77*U77/SUM($Q77:$U77)) -> 0 | G77: 0 | H77: 0 | I77: 0 | J77: 0 | K77: 0 | L77: 0 | M77: 0 | N77: 0 | O77: =SUM(B77:F77,H77:N77) -> 0 | Q77: 0 | R77: 0 | S77: 0 | T77: 0 | U77: 0 | V77: 0 | W77: 0 | X77: 0 | Y77: =SUM(Q77:X77) -> 0
A78: VARIACIONES EN RESERVAS TÉCNICAS Y MATEMÁTICAS | B78: =IF(OR(SUM($Q78:$U78)=0,COUNTIF($Q78:$U78,"<0")*COUNTIF($Q78:$U78,">0")>0),$G78/5,$G78*Q78/SUM($Q78:$U78)) -> 27167887 | C78: =IF(OR(SUM($Q78:$U78)=0,COUNTIF($Q78:$U78,"<0")*COUNTIF($Q78:$U78,">0")>0),$G78/5,$G78*R78/SUM($Q78:$U78)) -> 27167887 | D78: =IF(OR(SUM($Q78:$U78)=0,COUNTIF($Q78:$U78,"<0")*COUNTIF($Q78:$U78,">0")>0),$G78/5,$G78*S78/SUM($Q78:$U78)) -> 27167887 | E78: =IF(OR(SUM($Q78:$U78)=0,COUNTIF($Q78:$U78,"<0")*COUNTIF($Q78:$U78,">0")>0),$G78/5,$G78*T78/SUM($Q78:$U78)) -> 27167887 | F78: =IF(OR(SUM($Q78:$U78)=0,COUNTIF($Q78:$U78,"<0")*COUNTIF($Q78:$U78,">0")>0),$G78/5,$G78*U78/SUM($Q78:$U78)) -> 27167887 | G78: 1.3583943e+08 | H78: -196423.89 | I78: -21029718 | J78: -17164365 | K78: -18998919 | L78: -36076931 | M78: -129514.56 | N78: -9034078 | O78: =SUM(B78:F78,H78:N78) -> 33209485 | Q78: 1.7419786e+08 | R78: -6502996.5 | S78: -4235999 | T78: -25852998 | U78: -26077233 | V78: -7817798.2 | W78: -9853969 | X78: -34340863 | Y78: =SUM(Q78:X78) -> 59516007
A79: (-) Variaciones Gastos | B79: =IF(OR(SUM($Q79:$U79)=0,COUNTIF($Q79:$U79,"<0")*COUNTIF($Q79:$U79,">0")>0),$G79/5,$G79*Q79/SUM($Q79:$U79)) -> 1.8930283e+08 | C79: =IF(OR(SUM($Q79:$U79)=0,COUNTIF($Q79:$U79,"<0")*COUNTIF($Q79:$U79,">0")>0),$G79/5,$G79*R79/SUM($Q79:$U79)) -> 19996192 | D79: =IF(OR(SUM($Q79:$U79)=0,COUNTIF($Q79:$U79,"<0")*COUNTIF($Q79:$U79,">0")>0),$G79/5,$G79*S79/SUM($Q79:$U79)) -> 4113717.2 | E79: =IF(OR(SUM($Q79:$U79)=0,COUNTIF($Q79:$U79,"<0")*COUNTIF($Q79:$U79,">0")>0),$G79/5,$G79*T79/SUM($Q79:$U79)) -> 3492255.8 | F79: =IF(OR(SUM($Q79:$U79)=0,COUNTIF($Q79:$U79,"<0")*COUNTIF($Q79:$U79,">0")>0),$G79/5,$G79*U79/SUM($Q79:$U79)) -> 3222763.4 | G79: 2.2012776e+08 | H79: 3919867.6 | I79: 4338113.4 | J79: 9873908.4 | K79: 5325574.3 | L79: 2000897.6 | M79: 8327083.5 | N79: 18945204 | O79: =SUM(B79:F79,H79:N79) -> 2.7285841e+08 | Q79: 1.7922688e+08 | R79: 18931862 | S79: 3894758 | T79: 3306374.9 | U79: 3051226.6 | V79: 1401581.2 | W79: 4299320.4 | X79: 3679203.3 | Y79: =SUM(Q79:X79) -> 2.1779121e+08
A80: (+) Variaciones Productos | B80: =IF(OR(SUM($Q80:$U80)=0,COUNTIF($Q80:$U80,"<0")*COUNTIF($Q80:$U80,">0")>0),$G80/5,$G80*Q80/SUM($Q80:$U80)) -> 4375275.8 | C80: =IF(OR(SUM($Q80:$U80)=0,COUNTIF($Q80:$U80,"<0")*COUNTIF($Q80:$U80,">0")>0),$G80/5,$G80*R80/SUM($Q80:$U80)) -> 22128479 | D80: =IF(OR(SUM($Q80:$U80)=0,COUNTIF($Q80:$U80,"<0")*COUNTIF($Q80:$U80,">0")>0),$G80/5,$G80*S80/SUM($Q80:$U80)) -> 7073807.2 | E80: =IF(OR(SUM($Q80:$U80)=0,COUNTIF($Q80:$U80,"<0")*COUNTIF($Q80:$U80,">0")>0),$G80/5,$G80*T80/SUM($Q80:$U80)) -> 25368829 | F80: =IF(OR(SUM($Q80:$U80)=0,COUNTIF($Q80:$U80,"<0")*COUNTIF($Q80:$U80,">0")>0),$G80/5,$G80*U80/SUM($Q80:$U80)) -> 25341934 | G80: 84288325 | H80: 4116291.5 | I80: 25367832 | J80: 27038274 | K80: 24324493 | L80: 38077828 | M80: 8456598.1 | N80: 27979282 | O80: =SUM(B80:F80,H80:N80) -> 2.3964892e+08 | Q80: 5029018.1 | R80: 25434859 | S80: 8130757 | T80: 29159373 | U80: 29128460 | V80: 9219379.4 | W80: 14153289 | X80: 38020066 | Y80: =SUM(Q80:X80) -> 1.582752e+08
A81: PRIMAS NETAS DE RETENCIÓN DEVENGADAS | B81: =IF(OR(SUM($Q81:$U81)=0,COUNTIF($Q81:$U81,"<0")*COUNTIF($Q81:$U81,">0")>0),$G81/5,$G81*Q81/SUM($Q81:$U81)) -> 80821407 | C81: =IF(OR(SUM($Q81:$U81)=0,COUNTIF($Q81:$U81,"<0")*COUNTIF($Q81:$U81,">0")>0),$G81/5,$G81*R81/SUM($Q81:$U81)) -> 86872661 | D81: =IF(OR(SUM($Q81:$U81)=0,COUNTIF($Q81:$U81,"<0")*COUNTIF($Q81:$U81,">0")>0),$G81/5,$G81*S81/SUM($Q81:$U81)) -> 97026465 | E81: =IF(OR(SUM($Q81:$U81)=0,COUNTIF($Q81:$U81,"<0")*COUNTIF($Q81:$U81,">0")>0),$G81/5,$G81*T81/SUM($Q81:$U81)) -> 87853899 | F81: =IF(OR(SUM($Q81:$U81)=0,COUNTIF($Q81:$U81,"<0")*COUNTIF($Q81:$U81,">0")>0),$G81/5,$G81*U81/SUM($Q81:$U81)) -> 1.15993e+08 | G81: 4.6856743e+08 | H81: 94151103 | I81: 96130336 | J81: 98362639 | K81: 96874029 | L81: 1.0583188e+08 | M81: 84194742 | N81: 99318518 | O81: =SUM(B81:F81,H81:N81) -> 1.1434307e+09 | Q81: 85113236 | R81: 91485827 | S81: 1.0217883e+08 | T81: 92519171 | U81: 1.2215253e+08 | V81: 97399026 | W81: 1.0220442e+08 | X81: 1.0047156e+08 | Y81: =SUM(Q81:X81) -> 7.935246e+08
B82: =IF(OR(SUM($Q82:$U82)=0,COUNTIF($Q82:$U82,"<0")*COUNTIF($Q82:$U82,">0")>0),$G82/5,$G82*Q82/SUM($Q82:$U82)) -> 0 | C82: =IF(OR(SUM($Q82:$U82)=0,COUNTIF($Q82:$U82,"<0")*COUNTIF($Q82:$U82,">0")>0),$G82/5,$G82*R82/SUM($Q82:$U82)) -> 0 | D82: =IF(OR(SUM($Q82:$U82)=0,COUNTIF($Q82:$U82,"<0")*COUNTIF($Q82:$U82,">0")>0),$G82/5,$G82*S82/SUM($Q82:$U82)) -> 0 | E82: =IF(OR(SUM($Q82:$U82)=0,COUNTIF($Q82:$U82,"<0")*COUNTIF($Q82:$U82,">0")>0),$G82/5,$G82*T82/SUM($Q82:$U82)) -> 0 | F82: =IF(OR(SUM($Q82:$U82)=0,COUNTIF($Q82:$U82,"<0")*COUNTIF($Q82:$U82,">0")>0),$G82/5,$G82*U82/SUM($Q82:$U82)) -> 0 | G82: 0 | H82: 0 | I82: 0 | J82: 0 | K82: 0 | L82: 0 | M82: 0 | N82: 0 | O82: =SUM(B82:F82,H82:N82) -> 0 | Q82: 0 | R82: 0 | S82: 0 | T82: 0 | U82: 0 | V82: 0 | W82: 0 | X82: 0 | Y82: =SUM(Q82:X82) -> 0
A83: (-) COSTO DE ADQUISICIÓN Y SINIESTRALIDAD | B83: =IF(OR(SUM($Q83:$U83)=0,COUNTIF($Q83:$U83,"<0")*COUNTIF($Q83:$U83,">0")>0),$G83/5,$G83*Q83/SUM($Q83:$U83)) -> 88537998 | C83: =IF(OR(SUM($Q83:$U83)=0,COUNTIF($Q83:$U83,"<0")*COUNTIF($Q83:$U83,">0")>0),$G83/5,$G83*R83/SUM($Q83:$U83)) -> 68035599 | D83: =IF(OR(SUM($Q83:$U83)=0,COUNTIF($Q83:$U83,"<0")*COUNTIF($Q83:$U83,">0")>0),$G83/5,$G83*S83/SUM($Q83:$U83)) -> 75219329 | E83: =IF(OR(SUM($Q83:$U83)=0,COUNTIF($Q83:$U83,"<0")*COUNTIF($Q83:$U83,">0")>0),$G83/5,$G83*T83/SUM($Q83:$U83)) -> 56873556 | F83: =IF(OR(SUM($Q83:$U83)=0,COUNTIF($Q83:$U83,"<0")*COUNTIF($Q83:$U83,">0")>0),$G83/5,$G83*U83/SUM($Q83:$U83)) -> 73112676 | G83: 3.6177916e+08 | H83: 68503828 | I83: 75882074 | J83: 71612902 | K83: 61278954 | L83: 76342049 | M83: 65993992 | N83: 76382778 | O83: =SUM(B83:F83,H83:N83) -> 8.5777574e+08 | Q83: 90295569 | R83: 69386176 | S83: 76712511 | T83: 58002556 | U83: 74564039 | V83: 71540612 | W83: 75665007 | X83: 72085483 | Y83: =SUM(Q83:X83) -> 5.8825195e+08
A84: ADQUISICIÓN | B84: =IF(OR(SUM($Q84:$U84)=0,COUNTIF($Q84:$U84,"<0")*COUNTIF($Q84:$U84,">0")>0),$G84/5,$G84*Q84/SUM($Q84:$U84)) -> 36463198 | C84: =IF(OR(SUM($Q84:$U84)=0,COUNTIF($Q84:$U84,"<0")*COUNTIF($Q84:$U84,">0")>0),$G84/5,$G84*R84/SUM($Q84:$U84)) -> 16250767 | D84: =IF(OR(SUM($Q84:$U84)=0,COUNTIF($Q84:$U84,"<0")*COUNTIF($Q84:$U84,">0")>0),$G84/5,$G84*S84/SUM($Q84:$U84)) -> 19149027 | E84: =IF(OR(SUM($Q84:$U84)=0,COUNTIF($Q84:$U84,"<0")*COUNTIF($Q84:$U84,">0")>0),$G84/5,$G84*T84/SUM($Q84:$U84)) -> 1339414.3 | F84: =IF(OR(SUM($Q84:$U84)=0,COUNTIF($Q84:$U84,"<0")*COUNTIF($Q84:$U84,">0")>0),$G84/5,$G84*U84/SUM($Q84:$U84)) -> 22042892 | G84: 95245298 | H84: 14339317 | I84: 15367263 | J84: 14994663 | K84: 15856542 | L84: 16296652 | M84: 11703508 | N84: 21865410 | O84: =SUM(B84:F84,H84:N84) -> 2.0566865e+08 | Q84: 30289770 | R84: 13499419 | S84: 15906987 | T84: 1112643.8 | U84: 18310904 | V84: 15747016 | W84: 16057540 | X84: 14232168 | Y84: =SUM(Q84:X84) -> 1.2515645e+08
A85: (+) Gastos de Adquisición y Renovación | B85: =IF(OR(SUM($Q85:$U85)=0,COUNTIF($Q85:$U85,"<0")*COUNTIF($Q85:$U85,">0")>0),$G85/5,$G85*Q85/SUM($Q85:$U85)) -> 39223367 | C85: =IF(OR(SUM($Q85:$U85)=0,COUNTIF($Q85:$U85,"<0")*COUNTIF($Q85:$U85,">0")>0),$G85/5,$G85*R85/SUM($Q85:$U85)) -> 21012620 | D85: =IF(OR(SUM($Q85:$U85)=0,COUNTIF($Q85:$U85,"<0")*COUNTIF($Q85:$U85,">0")>0),$G85/5,$G85*S85/SUM($Q85:$U85)) -> 27435288 | E85: =IF(OR(SUM($Q85:$U85)=0,COUNTIF($Q85:$U85,"<0")*COUNTIF($Q85:$U85,">0")>0),$G85/5,$G85*T85/SUM($Q85:$U85)) -> 22308949 | F85: =IF(OR(SUM($Q85:$U85)=0,COUNTIF($Q85:$U85,"<0")*COUNTIF($Q85:$U85,">0")>0),$G85/5,$G85*U85/SUM($Q85:$U85)) -> 24307751 | G85: 1.3428797e+08 | H85: 25099615 | I85: 26685629 | J85: 23394575 | K85: 22581512 | L85: 24333653 | M85: 19207457 | N85: 31783383 | O85: =SUM(B85:F85,H85:N85) -> 3.073738e+08 | Q85: 41222600 | R85: 22083643 | S85: 28833677 | T85: 23446046 | U85: 25546728 | V85: 27020705 | W85: 27996309 | X85: 22360179 | Y85: =SUM(Q85:X85) -> 2.1850989e+08
A86: (-) Comisiones y Participaciones por Reaseguro Cedido | B86: =IF(OR(SUM($Q86:$U86)=0,COUNTIF($Q86:$U86,"<0")*COUNTIF($Q86:$U86,">0")>0),$G86/5,$G86*Q86/SUM($Q86:$U86)) -> 6883187.8 | C86: =IF(OR(SUM($Q86:$U86)=0,COUNTIF($Q86:$U86,"<0")*COUNTIF($Q86:$U86,">0")>0),$G86/5,$G86*R86/SUM($Q86:$U86)) -> 5404532.2 | D86: =IF(OR(SUM($Q86:$U86)=0,COUNTIF($Q86:$U86,"<0")*COUNTIF($Q86:$U86,">0")>0),$G86/5,$G86*S86/SUM($Q86:$U86)) -> 8138500 | E86: =IF(OR(SUM($Q86:$U86)=0,COUNTIF($Q86:$U86,"<0")*COUNTIF($Q86:$U86,">0")>0),$G86/5,$G86*T86/SUM($Q86:$U86)) -> 14060862 | F86: =IF(OR(SUM($Q86:$U86)=0,COUNTIF($Q86:$U86,"<0")*COUNTIF($Q86:$U86,">0")>0),$G86/5,$G86*U86/SUM($Q86:$U86)) -> 4555594.3 | G86: 39042676 | H86: 10760297 | I86: 11318366 | J86: 8399912.6 | K86: 6724969.8 | L86: 8037001 | M86: 7503949 | N86: 9917973 | O86: =SUM(B86:F86,H86:N86) -> 1.0170515e+08 | Q86: 10932829 | R86: 8584224.4 | S86: 12926690 | T86: 22333403 | U86: 7235824 | V86: 11273690 | W86: 11938769 | X86: 8128010.9 | Y86: =SUM(Q86:X86) -> 93353440
A87: SINIESTRALIDAD | B87: =IF(OR(SUM($Q87:$U87)=0,COUNTIF($Q87:$U87,"<0")*COUNTIF($Q87:$U87,">0")>0),$G87/5,$G87*Q87/SUM($Q87:$U87)) -> 55180496 | C87: =IF(OR(SUM($Q87:$U87)=0,COUNTIF($Q87:$U87,"<0")*COUNTIF($Q87:$U87,">0")>0),$G87/5,$G87*R87/SUM($Q87:$U87)) -> 51392683 | D87: =IF(OR(SUM($Q87:$U87)=0,COUNTIF($Q87:$U87,"<0")*COUNTIF($Q87:$U87,">0")>0),$G87/5,$G87*S87/SUM($Q87:$U87)) -> 55915912 | E87: =IF(OR(SUM($Q87:$U87)=0,COUNTIF($Q87:$U87,"<0")*COUNTIF($Q87:$U87,">0")>0),$G87/5,$G87*T87/SUM($Q87:$U87)) -> 52315170 | F87: =IF(OR(SUM($Q87:$U87)=0,COUNTIF($Q87:$U87,"<0")*COUNTIF($Q87:$U87,">0")>0),$G87/5,$G87*U87/SUM($Q87:$U87)) -> 51729599 | G87: 2.6653386e+08 | H87: 54164511 | I87: 60514811 | J87: 56618239 | K87: 45422412 | L87: 60045397 | M87: 54290484 | N87: 54517368 | O87: =SUM(B87:F87,H87:N87) -> 6.5210708e+08 | Q87: 60005798 | R87: 55886758 | S87: 60805524 | T87: 56889912 | U87: 56253135 | V87: 55793597 | W87: 59607467 | X87: 57853315 | Y87: =SUM(Q87:X87) -> 4.630955e+08
A88: (+) Gastos Por Obligaciones Contractuales | B88: =IF(OR(SUM($Q88:$U88)=0,COUNTIF($Q88:$U88,"<0")*COUNTIF($Q88:$U88,">0")>0),$G88/5,$G88*Q88/SUM($Q88:$U88)) -> 61241690 | C88: =IF(OR(SUM($Q88:$U88)=0,COUNTIF($Q88:$U88,"<0")*COUNTIF($Q88:$U88,">0")>0),$G88/5,$G88*R88/SUM($Q88:$U88)) -> 62541661 | D88: =IF(OR(SUM($Q88:$U88)=0,COUNTIF($Q88:$U88,"<0")*COUNTIF($Q88:$U88,">0")>0),$G88/5,$G88*S88/SUM($Q88:$U88)) -> 63955147 | E88: =IF(OR(SUM($Q88:$U88)=0,COUNTIF($Q88:$U88,"<0")*COUNTIF($Q88:$U88,">0")>0),$G88/5,$G88*T88/SUM($Q88:$U88)) -> 64019371 | F88: =IF(OR(SUM($Q88:$U88)=0,COUNTIF($Q88:$U88,"<0")*COUNTIF($Q88:$U88,">0")>0),$G88/5,$G88*U88/SUM($Q88:$U88)) -> 59188617 | G88: 3.1094649e+08 | H88: 66552573 | I88: 77591513 | J88: 73305465 | K88: 49497401 | L88: 69893411 | M88: 66193587 | N88: 72183406 | O88: =SUM(B88:F88,H88:N88) -> 7.8616384e+08 | Q88: 71688459 | R88: 73210183 | S88: 74864784 | T88: 74939964 | U88: 69285168 | V88: 81018816 | W88: 87465473 | X88: 83990850 | Y88: =SUM(Q88:X88) -> 6.164637e+08
A89: (+) Participa. Reaseguradoras en Salvamentos y Recup. | B89: =IF(OR(SUM($Q89:$U89)=0,COUNTIF($Q89:$U89,"<0")*COUNTIF($Q89:$U89,">0")>0),$G89/5,$G89*Q89/SUM($Q89:$U89)) -> 208169.32 | C89: =IF(OR(SUM($Q89:$U89)=0,COUNTIF($Q89:$U89,"<0")*COUNTIF($Q89:$U89,">0")>0),$G89/5,$G89*R89/SUM($Q89:$U89)) -> 156669.18 | D89: =IF(OR(SUM($Q89:$U89)=0,COUNTIF($Q89:$U89,"<0")*COUNTIF($Q89:$U89,">0")>0),$G89/5,$G89*S89/SUM($Q89:$U89)) -> 23218.258 | E89: =IF(OR(SUM($Q89:$U89)=0,COUNTIF($Q89:$U89,"<0")*COUNTIF($Q89:$U89,">0")>0),$G89/5,$G89*T89/SUM($Q89:$U89)) -> 737623.07 | F89: =IF(OR(SUM($Q89:$U89)=0,COUNTIF($Q89:$U89,"<0")*COUNTIF($Q89:$U89,">0")>0),$G89/5,$G89*U89/SUM($Q89:$U89)) -> 283731.43 | G89: 1409411.3 | H89: 34303.57 | I89: 9041.63 | J89: 23677.91 | K89: 9517.02 | L89: 25801.41 | M89: 32559.01 | N89: 91760.47 | O89: =SUM(B89:F89,H89:N89) -> 1636072.3 | Q89: 20300.9 | R89: 15278.55 | S89: 2264.27 | T89: 71933.81 | U89: 27669.8 | V89: 15874.8 | W89: 1585.7 | X89: -1579.22 | Y89: =SUM(Q89:X89) -> 153328.61
A90: (+) Variación en Reservas de Reclamaciones de Seguro de Caución (Neto) | B90: =IF(OR(SUM($Q90:$U90)=0,COUNTIF($Q90:$U90,"<0")*COUNTIF($Q90:$U90,">0")>0),$G90/5,$G90*Q90/SUM($Q90:$U90)) -> 0 | C90: =IF(OR(SUM($Q90:$U90)=0,COUNTIF($Q90:$U90,"<0")*COUNTIF($Q90:$U90,">0")>0),$G90/5,$G90*R90/SUM($Q90:$U90)) -> 0 | D90: =IF(OR(SUM($Q90:$U90)=0,COUNTIF($Q90:$U90,"<0")*COUNTIF($Q90:$U90,">0")>0),$G90/5,$G90*S90/SUM($Q90:$U90)) -> 0 | E90: =IF(OR(SUM($Q90:$U90)=0,COUNTIF($Q90:$U90,"<0")*COUNTIF($Q90:$U90,">0")>0),$G90/5,$G90*T90/SUM($Q90:$U90)) -> 0 | F90: =IF(OR(SUM($Q90:$U90)=0,COUNTIF($Q90:$U90,"<0")*COUNTIF($Q90:$U90,">0")>0),$G90/5,$G90*U90/SUM($Q90:$U90)) -> 0 | G90: 0 | H90: 0 | I90: 0 | J90: -3266176 | K90: -17556 | L90: -47204 | M90: -40546 | N90: 2555.83 | O90: =SUM(B90:F90,H90:N90) -> -3368926.1 | Q90: -28893 | R90: 220108.47 | S90: 17272.89 | T90: 2236.04 | U90: 0 | V90: 0 | W90: 0 | X90: 0 | Y90: =SUM(Q90:X90) -> 210724.4
A91: (-) Recuperaciones por Reaseguro Cedido | B91: =IF(OR(SUM($Q91:$U91)=0,COUNTIF($Q91:$U91,"<0")*COUNTIF($Q91:$U91,">0")>0),$G91/5,$G91*Q91/SUM($Q91:$U91)) -> 3717183.5 | C91: =IF(OR(SUM($Q91:$U91)=0,COUNTIF($Q91:$U91,"<0")*COUNTIF($Q91:$U91,">0")>0),$G91/5,$G91*R91/SUM($Q91:$U91)) -> 6008300.7 | D91: =IF(OR(SUM($Q91:$U91)=0,COUNTIF($Q91:$U91,"<0")*COUNTIF($Q91:$U91,">0")>0),$G91/5,$G91*S91/SUM($Q91:$U91)) -> 4082444.3 | E91: =IF(OR(SUM($Q91:$U91)=0,COUNTIF($Q91:$U91,"<0")*COUNTIF($Q91:$U91,">0")>0),$G91/5,$G91*T91/SUM($Q91:$U91)) -> 5788607.2 | F91: =IF(OR(SUM($Q91:$U91)=0,COUNTIF($Q91:$U91,"<0")*COUNTIF($Q91:$U91,">0")>0),$G91/5,$G91*U91/SUM($Q91:$U91)) -> 4464340.2 | G91: 24060876 | H91: 7388823.9 | I91: 12989318 | J91: 8552064.1 | K91: -1376567 | L91: 3639328.9 | M91: 6118689.4 | N91: 8516049.7 | O91: =SUM(B91:F91,H91:N91) -> 69888583 | Q91: 7806354.8 | R91: 12617867 | S91: 8573428.8 | T91: 12156494 | U91: 9375437.9 | V91: 20739930 | W91: 22985698 | X91: 21402330 | Y91: =SUM(Q91:X91) -> 1.1565754e+08
A92: (-) Salvamentos y Recuperaciones | B92: =IF(OR(SUM($Q92:$U92)=0,COUNTIF($Q92:$U92,"<0")*COUNTIF($Q92:$U92,">0")>0),$G92/5,$G92*Q92/SUM($Q92:$U92)) -> 3511886.3 | C92: =IF(OR(SUM($Q92:$U92)=0,COUNTIF($Q92:$U92,"<0")*COUNTIF($Q92:$U92,">0")>0),$G92/5,$G92*R92/SUM($Q92:$U92)) -> 4486381.5 | D92: =IF(OR(SUM($Q92:$U92)=0,COUNTIF($Q92:$U92,"<0")*COUNTIF($Q92:$U92,">0")>0),$G92/5,$G92*S92/SUM($Q92:$U92)) -> 4998878 | E92: =IF(OR(SUM($Q92:$U92)=0,COUNTIF($Q92:$U92,"<0")*COUNTIF($Q92:$U92,">0")>0),$G92/5,$G92*T92/SUM($Q92:$U92)) -> 5418700.3 | F92: =IF(OR(SUM($Q92:$U92)=0,COUNTIF($Q92:$U92,"<0")*COUNTIF($Q92:$U92,">0")>0),$G92/5,$G92*U92/SUM($Q92:$U92)) -> 3345314.7 | G92: 21761161 | H92: 5033542.1 | I92: 4096425.6 | J92: 4892663.8 | K92: 5443516.8 | L92: 6187282.3 | M92: 5776426.5 | N92: 9244304.2 | O92: =SUM(B92:F92,H92:N92) -> 62435322 | Q92: 3867713.6 | R92: 4940945.4 | S92: 5505368.6 | T92: 5967727.6 | U92: 3684264.8 | V92: 4501164.1 | W92: 4873894.5 | X92: 4733625.3 | Y92: =SUM(Q92:X92) -> 38074704
B93: =IF(OR(SUM($Q93:$U93)=0,COUNTIF($Q93:$U93,"<0")*COUNTIF($Q93:$U93,">0")>0),$G93/5,$G93*Q93/SUM($Q93:$U93)) -> 0 | C93: =IF(OR(SUM($Q93:$U93)=0,COUNTIF($Q93:$U93,"<0")*COUNTIF($Q93:$U93,">0")>0),$G93/5,$G93*R93/SUM($Q93:$U93)) -> 0 | D93: =IF(OR(SUM($Q93:$U93)=0,COUNTIF($Q93:$U93,"<0")*COUNTIF($Q93:$U93,">0")>0),$G93/5,$G93*S93/SUM($Q93:$U93)) -> 0 | E93: =IF(OR(SUM($Q93:$U93)=0,COUNTIF($Q93:$U93,"<0")*COUNTIF($Q93:$U93,">0")>0),$G93/5,$G93*T93/SUM($Q93:$U93)) -> 0 | F93: =IF(OR(SUM($Q93:$U93)=0,COUNTIF($Q93:$U93,"<0")*COUNTIF($Q93:$U93,">0")>0),$G93/5,$G93*U93/SUM($Q93:$U93)) -> 0 | G93: 0 | H93: 0 | I93: 0 | J93: 0 | K93: 0 | L93: 0 | M93: 0 | N93: 0 | O93: =SUM(B93:F93,H93:N93) -> 0 | Q93: 0 | R93: 0 | S93: 0 | T93: 0 | U93: 0 | V93: 0 | W93: 0 | X93: 0 | Y93: =SUM(Q93:X93) -> 0
A94: UTILIDAD BRUTA EN OPERACIONES DE SEGUROS | B94: =IF(OR(SUM($Q94:$U94)=0,COUNTIF($Q94:$U94,"<0")*COUNTIF($Q94:$U94,">0")>0),$G94/5,$G94*Q94/SUM($Q94:$U94)) -> 21357655 | C94: =IF(OR(SUM($Q94:$U94)=0,COUNTIF($Q94:$U94,"<0")*COUNTIF($Q94:$U94,">0")>0),$G94/5,$G94*R94/SUM($Q94:$U94)) -> 21357655 | D94: =IF(OR(SUM($Q94:$U94)=0,COUNTIF($Q94:$U94,"<0")*COUNTIF($Q94:$U94,">0")>0),$G94/5,$G94*S94/SUM($Q94:$U94)) -> 21357655 | E94: =IF(OR(SUM($Q94:$U94)=0,COUNTIF($Q94:$U94,"<0")*COUNTIF($Q94:$U94,">0")>0),$G94/5,$G94*T94/SUM($Q94:$U94)) -> 21357655 | F94: =IF(OR(SUM($Q94:$U94)=0,COUNTIF($Q94:$U94,"<0")*COUNTIF($Q94:$U94,">0")>0),$G94/5,$G94*U94/SUM($Q94:$U94)) -> 21357655 | G94: 1.0678827e+08 | H94: 25647274 | I94: 20248262 | J94: 26749737 | K94: 35595075 | L94: 29489831 | M94: 18200750 | N94: 22935740 | O94: =SUM(B94:F94,H94:N94) -> 2.8565494e+08 | Q94: -5182333.1 | R94: 22099651 | S94: 25466315 | T94: 34516616 | U94: 47588496 | V94: 25858414 | W94: 26539418 | X94: 28386078 | Y94: =SUM(Q94:X94) -> 2.0527265e+08
A95: (-) GASTOS Y PRODUCTOS DE OPERACIONES | B95: =IF(OR(SUM($Q95:$U95)=0,COUNTIF($Q95:$U95,"<0")*COUNTIF($Q95:$U95,">0")>0),$G95/5,$G95*Q95/SUM($Q95:$U95)) -> -1575281.2 | C95: =IF(OR(SUM($Q95:$U95)=0,COUNTIF($Q95:$U95,"<0")*COUNTIF($Q95:$U95,">0")>0),$G95/5,$G95*R95/SUM($Q95:$U95)) -> -1575281.2 | D95: =IF(OR(SUM($Q95:$U95)=0,COUNTIF($Q95:$U95,"<0")*COUNTIF($Q95:$U95,">0")>0),$G95/5,$G95*S95/SUM($Q95:$U95)) -> -1575281.2 | E95: =IF(OR(SUM($Q95:$U95)=0,COUNTIF($Q95:$U95,"<0")*COUNTIF($Q95:$U95,">0")>0),$G95/5,$G95*T95/SUM($Q95:$U95)) -> -1575281.2 | F95: =IF(OR(SUM($Q95:$U95)=0,COUNTIF($Q95:$U95,"<0")*COUNTIF($Q95:$U95,">0")>0),$G95/5,$G95*U95/SUM($Q95:$U95)) -> -1575281.2 | G95: -7876406 | H95: 805862.85 | I95: 3548445.2 | J95: 1919566.3 | K95: 2861730.2 | L95: 1213097.5 | M95: 466948.74 | N95: 2110339.8 | O95: =SUM(B95:F95,H95:N95) -> 5049584.6 | Q95: -7654149.7 | R95: 661095.81 | S95: -6411838.4 | T95: 2185275.5 | U95: 686916.1 | V95: -322162.52 | W95: 2456501.1 | X95: 2477928.6 | Y95: =SUM(Q95:X95) -> -5920433.4
A96: (+) Egresos por Inversiones | B96: =IF(OR(SUM($Q96:$U96)=0,COUNTIF($Q96:$U96,"<0")*COUNTIF($Q96:$U96,">0")>0),$G96/5,$G96*Q96/SUM($Q96:$U96)) -> 422639.31 | C96: =IF(OR(SUM($Q96:$U96)=0,COUNTIF($Q96:$U96,"<0")*COUNTIF($Q96:$U96,">0")>0),$G96/5,$G96*R96/SUM($Q96:$U96)) -> 431176.43 | D96: =IF(OR(SUM($Q96:$U96)=0,COUNTIF($Q96:$U96,"<0")*COUNTIF($Q96:$U96,">0")>0),$G96/5,$G96*S96/SUM($Q96:$U96)) -> 487587.14 | E96: =IF(OR(SUM($Q96:$U96)=0,COUNTIF($Q96:$U96,"<0")*COUNTIF($Q96:$U96,">0")>0),$G96/5,$G96*T96/SUM($Q96:$U96)) -> 547502.6 | F96: =IF(OR(SUM($Q96:$U96)=0,COUNTIF($Q96:$U96,"<0")*COUNTIF($Q96:$U96,">0")>0),$G96/5,$G96*U96/SUM($Q96:$U96)) -> 632616.6 | G96: 2521522.1 | H96: 531930.35 | I96: 506033.58 | J96: 496700.61 | K96: 823846.3 | L96: 832709.24 | M96: 831115.51 | N96: 1235036.6 | O96: =SUM(B96:F96,H96:N96) -> 7778894.3 | Q96: 813848.93 | R96: 830288.31 | S96: 938914.72 | T96: 1054290 | U96: 1218188.5 | V96: 1341459.8 | W96: 1302385.7 | X96: 1329533.2 | Y96: =SUM(Q96:X96) -> 8828909.1
A97: (+) Gastos de Administración | B97: =IF(OR(SUM($Q97:$U97)=0,COUNTIF($Q97:$U97,"<0")*COUNTIF($Q97:$U97,">0")>0),$G97/5,$G97*Q97/SUM($Q97:$U97)) -> 15964225 | C97: =IF(OR(SUM($Q97:$U97)=0,COUNTIF($Q97:$U97,"<0")*COUNTIF($Q97:$U97,">0")>0),$G97/5,$G97*R97/SUM($Q97:$U97)) -> 17941571 | D97: =IF(OR(SUM($Q97:$U97)=0,COUNTIF($Q97:$U97,"<0")*COUNTIF($Q97:$U97,">0")>0),$G97/5,$G97*S97/SUM($Q97:$U97)) -> 16237577 | E97: =IF(OR(SUM($Q97:$U97)=0,COUNTIF($Q97:$U97,"<0")*COUNTIF($Q97:$U97,">0")>0),$G97/5,$G97*T97/SUM($Q97:$U97)) -> 17304291 | F97: =IF(OR(SUM($Q97:$U97)=0,COUNTIF($Q97:$U97,"<0")*COUNTIF($Q97:$U97,">0")>0),$G97/5,$G97*U97/SUM($Q97:$U97)) -> 17081772 | G97: 84529437 | H97: 16673960 | I97: 18620760 | J97: 17053322 | K97: 16522058 | L97: 16133635 | M97: 14929521 | N97: 17021941 | O97: =SUM(B97:F97,H97:N97) -> 2.0148463e+08 | Q97: 15691450 | R97: 17635010 | S97: 15960131 | T97: 17008619 | U97: 16789902 | V97: 17083892 | W97: 17692458 | X97: 16481026 | Y97: =SUM(Q97:X97) -> 1.3434249e+08
A98: (-) Derechos de Emisión de Pólizas (Neto) | B98: =IF(OR(SUM($Q98:$U98)=0,COUNTIF($Q98:$U98,"<0")*COUNTIF($Q98:$U98,">0")>0),$G98/5,$G98*Q98/SUM($Q98:$U98)) -> 13143713 | C98: =IF(OR(SUM($Q98:$U98)=0,COUNTIF($Q98:$U98,"<0")*COUNTIF($Q98:$U98,">0")>0),$G98/5,$G98*R98/SUM($Q98:$U98)) -> 7599217.4 | D98: =IF(OR(SUM($Q98:$U98)=0,COUNTIF($Q98:$U98,"<0")*COUNTIF($Q98:$U98,">0")>0),$G98/5,$G98*S98/SUM($Q98:$U98)) -> 6152372.6 | E98: =IF(OR(SUM($Q98:$U98)=0,COUNTIF($Q98:$U98,"<0")*COUNTIF($Q98:$U98,">0")>0),$G98/5,$G98*T98/SUM($Q98:$U98)) -> 5023146.6 | F98: =IF(OR(SUM($Q98:$U98)=0,COUNTIF($Q98:$U98,"<0")*COUNTIF($Q98:$U98,">0")>0),$G98/5,$G98*U98/SUM($Q98:$U98)) -> 5805608.6 | G98: 37724058 | H98: 6821349 | I98: 5912686.2 | J98: 5903834.3 | K98: 5169919.5 | L98: 5120369.7 | M98: 5751279.6 | N98: 7003094.9 | O98: =SUM(B98:F98,H98:N98) -> 79406592 | Q98: 14984102 | R98: 8663263.4 | S98: 7013830.7 | T98: 5726489.9 | U98: 6618512.6 | V98: 7882045.6 | W98: 5666835.7 | X98: 5135377 | Y98: =SUM(Q98:X98) -> 61690457
A99: (-) Productos de Inversiones | B99: =IF(OR(SUM($Q99:$U99)=0,COUNTIF($Q99:$U99,"<0")*COUNTIF($Q99:$U99,">0")>0),$G99/5,$G99*Q99/SUM($Q99:$U99)) -> 9462541.3 | C99: =IF(OR(SUM($Q99:$U99)=0,COUNTIF($Q99:$U99,"<0")*COUNTIF($Q99:$U99,">0")>0),$G99/5,$G99*R99/SUM($Q99:$U99)) -> 9427057.1 | D99: =IF(OR(SUM($Q99:$U99)=0,COUNTIF($Q99:$U99,"<0")*COUNTIF($Q99:$U99,">0")>0),$G99/5,$G99*S99/SUM($Q99:$U99)) -> 16807164 | E99: =IF(OR(SUM($Q99:$U99)=0,COUNTIF($Q99:$U99,"<0")*COUNTIF($Q99:$U99,">0")>0),$G99/5,$G99*T99/SUM($Q99:$U99)) -> 10468882 | F99: =IF(OR(SUM($Q99:$U99)=0,COUNTIF($Q99:$U99,"<0")*COUNTIF($Q99:$U99,">0")>0),$G99/5,$G99*U99/SUM($Q99:$U99)) -> 11037663 | G99: 57203306 | H99: 9578678.1 | I99: 9665662.1 | J99: 9726621.9 | K99: 9314254.9 | L99: 10632877 | M99: 9542408.5 | N99: 9143542.6 | O99: =SUM(B99:F99,H99:N99) -> 1.2480735e+08 | Q99: 9175346.1 | R99: 9140938.9 | S99: 16297053 | T99: 10151143 | U99: 10702661 | V99: 10865469 | W99: 10871507 | X99: 10197253 | Y99: =SUM(Q99:X99) -> 87401372
B100: =IF(OR(SUM($Q100:$U100)=0,COUNTIF($Q100:$U100,"<0")*COUNTIF($Q100:$U100,">0")>0),$G100/5,$G100*Q100/SUM($Q100:$U100)) -> 0 | C100: =IF(OR(SUM($Q100:$U100)=0,COUNTIF($Q100:$U100,"<0")*COUNTIF($Q100:$U100,">0")>0),$G100/5,$G100*R100/SUM($Q100:$U100)) -> 0 | D100: =IF(OR(SUM($Q100:$U100)=0,COUNTIF($Q100:$U100,"<0")*COUNTIF($Q100:$U100,">0")>0),$G100/5,$G100*S100/SUM($Q100:$U100)) -> 0 | E100: =IF(OR(SUM($Q100:$U100)=0,COUNTIF($Q100:$U100,"<0")*COUNTIF($Q100:$U100,">0")>0),$G100/5,$G100*T100/SUM($Q100:$U100)) -> 0 | F100: =IF(OR(SUM($Q100:$U100)=0,COUNTIF($Q100:$U100,"<0")*COUNTIF($Q100:$U100,">0")>0),$G100/5,$G100*U100/SUM($Q100:$U100)) -> 0 | G100: 0 | H100: 0 | I100: 0 | J100: 0 | K100: 0 | L100: 0 | M100: 0 | N100: 0 | O100: =SUM(B100:F100,H100:N100) -> 0 | Q100: 0 | R100: 0 | S100: 0 | T100: 0 | U100: 0 | V100: 0 | W100: 0 | X100: 0 | Y100: =SUM(Q100:X100) -> 0
A101: UTILIDAD (PÉRDIDA) EN OPERACIÓN | B101: =IF(OR(SUM($Q101:$U101)=0,COUNTIF($Q101:$U101,"<0")*COUNTIF($Q101:$U101,">0")>0),$G101/5,$G101*Q101/SUM($Q101:$U101)) -> 2099148.5 | C101: =IF(OR(SUM($Q101:$U101)=0,COUNTIF($Q101:$U101,"<0")*COUNTIF($Q101:$U101,">0")>0),$G101/5,$G101*R101/SUM($Q101:$U101)) -> 18206331 | D101: =IF(OR(SUM($Q101:$U101)=0,COUNTIF($Q101:$U101,"<0")*COUNTIF($Q101:$U101,">0")>0),$G101/5,$G101*S101/SUM($Q101:$U101)) -> 27071983 | E101: =IF(OR(SUM($Q101:$U101)=0,COUNTIF($Q101:$U101,"<0")*COUNTIF($Q101:$U101,">0")>0),$G101/5,$G101*T101/SUM($Q101:$U101)) -> 27456844 | F101: =IF(OR(SUM($Q101:$U101)=0,COUNTIF($Q101:$U101,"<0")*COUNTIF($Q101:$U101,">0")>0),$G101/5,$G101*U101/SUM($Q101:$U101)) -> 39830374 | G101: 1.1466468e+08 | H101: 24841411 | I101: 16699817 | J101: 24830170 | K101: 32733345 | L101: 28276734 | M101: 17733801 | N101: 20825400 | O101: =SUM(B101:F101,H101:N101) -> 2.8060536e+08 | Q101: 2471816.6 | R101: 21438555 | S101: 31878153 | T101: 32331340 | U101: 46901580 | V101: 26180576 | W101: 24082917 | X101: 25908149 | Y101: =SUM(Q101:X101) -> 2.1119309e+08
A102: OTROS PRODUCTOS Y GASTOS | B102: =IF(OR(SUM($Q102:$U102)=0,COUNTIF($Q102:$U102,"<0")*COUNTIF($Q102:$U102,">0")>0),$G102/5,$G102*Q102/SUM($Q102:$U102)) -> 6107951.3 | C102: =IF(OR(SUM($Q102:$U102)=0,COUNTIF($Q102:$U102,"<0")*COUNTIF($Q102:$U102,">0")>0),$G102/5,$G102*R102/SUM($Q102:$U102)) -> 4490690.5 | D102: =IF(OR(SUM($Q102:$U102)=0,COUNTIF($Q102:$U102,"<0")*COUNTIF($Q102:$U102,">0")>0),$G102/5,$G102*S102/SUM($Q102:$U102)) -> 4235886.8 | E102: =IF(OR(SUM($Q102:$U102)=0,COUNTIF($Q102:$U102,"<0")*COUNTIF($Q102:$U102,">0")>0),$G102/5,$G102*T102/SUM($Q102:$U102)) -> 3107559.3 | F102: =IF(OR(SUM($Q102:$U102)=0,COUNTIF($Q102:$U102,"<0")*COUNTIF($Q102:$U102,">0")>0),$G102/5,$G102*U102/SUM($Q102:$U102)) -> 2953744.9 | G102: 20895833 | H102: 3976342.9 | I102: 4030785.2 | J102: 3594698.7 | K102: 4131661.7 | L102: 3854291.1 | M102: 4008599.8 | N102: 8340146.6 | O102: =SUM(B102:F102,H102:N102) -> 52832359 | Q102: 6758765.7 | R102: 4969182.5 | S102: 4687229 | T102: 3438675.9 | U102: 3268472.3 | V102: 3244895.7 | W102: 3610995.1 | X102: 4005520.5 | Y102: =SUM(Q102:X102) -> 33983737
A103: (+) Otros Productos | B103: =IF(OR(SUM($Q103:$U103)=0,COUNTIF($Q103:$U103,"<0")*COUNTIF($Q103:$U103,">0")>0),$G103/5,$G103*Q103/SUM($Q103:$U103)) -> 7493657.7 | C103: =IF(OR(SUM($Q103:$U103)=0,COUNTIF($Q103:$U103,"<0")*COUNTIF($Q103:$U103,">0")>0),$G103/5,$G103*R103/SUM($Q103:$U103)) -> 5518088.7 | D103: =IF(OR(SUM($Q103:$U103)=0,COUNTIF($Q103:$U103,"<0")*COUNTIF($Q103:$U103,">0")>0),$G103/5,$G103*S103/SUM($Q103:$U103)) -> 5890613.5 | E103: =IF(OR(SUM($Q103:$U103)=0,COUNTIF($Q103:$U103,"<0")*COUNTIF($Q103:$U103,">0")>0),$G103/5,$G103*T103/SUM($Q103:$U103)) -> 4920215.5 | F103: =IF(OR(SUM($Q103:$U103)=0,COUNTIF($Q103:$U103,"<0")*COUNTIF($Q103:$U103,">0")>0),$G103/5,$G103*U103/SUM($Q103:$U103)) -> 4743823.9 | G103: 28566399 | H103: 5168048.9 | I103: 5498992.8 | J103: 5157343.2 | K103: 5252629.2 | L103: 5033929 | M103: 4921114.2 | N103: 9070484.5 | O103: =SUM(B103:F103,H103:N103) -> 68668941 | Q103: 8017051.5 | R103: 5903499.1 | S103: 6302042.8 | T103: 5263867.5 | U103: 5075155.9 | V103: 5268858.7 | W103: 5713507.9 | X103: 5765499.8 | Y103: =SUM(Q103:X103) -> 47309483
A104: (-) Otros Gastos | B104: =IF(OR(SUM($Q104:$U104)=0,COUNTIF($Q104:$U104,"<0")*COUNTIF($Q104:$U104,">0")>0),$G104/5,$G104*Q104/SUM($Q104:$U104)) -> 1297403.9 | C104: =IF(OR(SUM($Q104:$U104)=0,COUNTIF($Q104:$U104,"<0")*COUNTIF($Q104:$U104,">0")>0),$G104/5,$G104*R104/SUM($Q104:$U104)) -> 963362.88 | D104: =IF(OR(SUM($Q104:$U104)=0,COUNTIF($Q104:$U104,"<0")*COUNTIF($Q104:$U104,">0")>0),$G104/5,$G104*S104/SUM($Q104:$U104)) -> 1665015.7 | E104: =IF(OR(SUM($Q104:$U104)=0,COUNTIF($Q104:$U104,"<0")*COUNTIF($Q104:$U104,">0")>0),$G104/5,$G104*T104/SUM($Q104:$U104)) -> 1881933.8 | F104: =IF(OR(SUM($Q104:$U104)=0,COUNTIF($Q104:$U104,"<0")*COUNTIF($Q104:$U104,">0")>0),$G104/5,$G104*U104/SUM($Q104:$U104)) -> 1862850.4 | G104: 7670566.6 | H104: 1191706 | I104: 1468207.6 | J104: 1562644.4 | K104: 1120967.5 | L104: 1179638 | M104: 912514.39 | N104: 730337.97 | O104: =SUM(B104:F104,H104:N104) -> 15836582 | Q104: 1258285.9 | R104: 934316.54 | S104: 1614813.9 | T104: 1825191.6 | U104: 1806683.6 | V104: 2023962.9 | W104: 2102512.8 | X104: 1759979.3 | Y104: =SUM(Q104:X104) -> 13325747
B105: =IF(OR(SUM($Q105:$U105)=0,COUNTIF($Q105:$U105,"<0")*COUNTIF($Q105:$U105,">0")>0),$G105/5,$G105*Q105/SUM($Q105:$U105)) -> 0 | C105: =IF(OR(SUM($Q105:$U105)=0,COUNTIF($Q105:$U105,"<0")*COUNTIF($Q105:$U105,">0")>0),$G105/5,$G105*R105/SUM($Q105:$U105)) -> 0 | D105: =IF(OR(SUM($Q105:$U105)=0,COUNTIF($Q105:$U105,"<0")*COUNTIF($Q105:$U105,">0")>0),$G105/5,$G105*S105/SUM($Q105:$U105)) -> 0 | E105: =IF(OR(SUM($Q105:$U105)=0,COUNTIF($Q105:$U105,"<0")*COUNTIF($Q105:$U105,">0")>0),$G105/5,$G105*T105/SUM($Q105:$U105)) -> 0 | F105: =IF(OR(SUM($Q105:$U105)=0,COUNTIF($Q105:$U105,"<0")*COUNTIF($Q105:$U105,">0")>0),$G105/5,$G105*U105/SUM($Q105:$U105)) -> 0 | G105: 0 | H105: 0 | I105: 0 | J105: 0 | K105: 0 | L105: 0 | M105: 0 | N105: 0 | O105: =SUM(B105:F105,H105:N105) -> 0 | Q105: 0 | R105: 0 | S105: 0 | T105: 0 | U105: 0 | V105: 0 | W105: 0 | X105: 0 | Y105: =SUM(Q105:X105) -> 0
A106: UTILIDAD NETA (PÉRDIDA) EN OPERACIÓN | B106: =IF(OR(SUM($Q106:$U106)=0,COUNTIF($Q106:$U106,"<0")*COUNTIF($Q106:$U106,">0")>0),$G106/5,$G106*Q106/SUM($Q106:$U106)) -> 7912436.1 | C106: =IF(OR(SUM($Q106:$U106)=0,COUNTIF($Q106:$U106,"<0")*COUNTIF($Q106:$U106,">0")>0),$G106/5,$G106*R106/SUM($Q106:$U106)) -> 22636658 | D106: =IF(OR(SUM($Q106:$U106)=0,COUNTIF($Q106:$U106,"<0")*COUNTIF($Q106:$U106,">0")>0),$G106/5,$G106*S106/SUM($Q106:$U106)) -> 31343770 | E106: =IF(OR(SUM($Q106:$U106)=0,COUNTIF($Q106:$U106,"<0")*COUNTIF($Q106:$U106,">0")>0),$G106/5,$G106*T106/SUM($Q106:$U106)) -> 30661984 | F106: =IF(OR(SUM($Q106:$U106)=0,COUNTIF($Q106:$U106,"<0")*COUNTIF($Q106:$U106,">0")>0),$G106/5,$G106*U106/SUM($Q106:$U106)) -> 43005665 | G106: 1.3556051e+08 | H106: 28817754 | I106: 20730602 | J106: 28424869 | K106: 36865007 | L106: 32131025 | M106: 21742401 | N106: 29165547 | O106: =SUM(B106:F106,H106:N106) -> 3.3343772e+08 | Q106: 9230582.3 | R106: 26407738 | S106: 36565382 | T106: 35770016 | U106: 50170052 | V106: 29425472 | W106: 27693912 | X106: 29913670 | Y106: =SUM(Q106:X106) -> 2.4517682e+08
...

Sheet Informacion de Sam
A1: Concepto | B1: 43831 | C1: 43862 | D1: 43891 | E1: 43922 | F1: 43952 | G1: 43983 | H1: 44013 | I1: 44044 | J1: 44075 | K1: 44105 | L1: 44136 | M1: 44166 | N1: 44197 | O1: 44228 | P1: 44256 | Q1: 44287 | R1: 44317 | S1: 44348 | T1: 44378 | U1: 44409 | V1: 44440 | W1: 44470 | X1: 44501 | Y1: 44531 | Z1: 44562 | AA1: 44593 | AB1: 44621 | AC1: 44652 | AD1: 44682 | AE1: 44713 | AF1: 44743 | AG1: 44774 | AH1: 44805 | AI1: 44835 | AJ1: 44866 | AK1: 44896 | AL1: 44927 | AM1: 44958 | AN1: 44986 | AO1: 45017 | AP1: 45047 | AQ1: 45078 | AR1: 45108 | AS1: 45139 | AT1: 45170 | AU1: 45200 | AV1: 45231 | AW1: 45261 | AX1: 45292 | AY1: 45323 | AZ1: 45352 | BA1: 45383 | BB1: 45413 | BC1: 45444 | BD1: 45474 | BE1: 45505 | BF1: 45536 | BG1: 45566 | BH1: 45597 | BI1: 45627 | BJ1: 45658 | BK1: 45689 | BL1: 45717 | BM1: 45748 | BN1: 45778 | BO1: 45809 | BP1: 45839 | BQ1: 45870 | BR1: 45901 | BS1: 45931 | BT1: 45962 | BU1: 45992 | BV1: 46023 | BW1: 46054 | BX1: 46082 | BY1: 46113 | BZ1: 46143 | CA1: 46174 | CB1: 46204 | CC1: 46235
A2: Primas Brutas | F2: 31102521 | G2: 35112660 | H2: 31479548 | I2: 66674857 | J2: 34490069 | K2: 33559997 | L2: 34613138 | M2: 39773343 | N2: 33573625 | O2: 38470535 | P2: 48669164 | Q2: 32979431 | R2: 30459725 | S2: 39378124 | T2: 32040782 | U2: 70471823 | V2: 35548483 | W2: 34734938 | X2: 35070487 | Y2: 35257319 | Z2: 38869210 | AA2: 66747425 | AB2: 43201477 | AC2: 44933269 | AD2: 50850685 | AE2: 60657568 | AF2: 84933444 | AG2: 51764632 | AH2: 55571672 | AI2: 50856757 | AJ2: 44718445 | AK2: 40379470 | AL2: 52439627 | AM2: 69263142 | AN2: 51811531 | AO2: 62661126 | AP2: 50407674 | AQ2: 49407530 | AR2: 45400084 | AS2: 91397458 | AT2: 47241820 | AU2: 46387362 | AV2: 59746928 | AW2: 50707767 | AX2: 56235002 | AY2: 80447760 | AZ2: 52367160 | BA2: 66079228 | BB2: 59278999 | BC2: 56553219 | BD2: 58223920 | BE2: 1.1064099e+08 | BF2: 55409769 | BG2: 66117728 | BH2: 64628560 | BI2: 48945421 | BJ2: 76596366 | BK2: 85461451 | BL2: 71128531 | BM2: 69878133 | BN2: 55430646 | BO2: 58031052 | BP2: 65154984 | BQ2: 63173458 | BR2: 62428610 | BS2: 56527550 | BT2: 52458789 | BU2: 44957199 | BV2: 55492142 | BW2: 79909300 | BX2: 68348604 | BY2: 59814608 | BZ2: 55508522 | CA2: 48704702 | CB2: 50585028 | CC2: 51181162
A3: (-) Devoluciones y Cancelaciones | F3: 4659794.7 | G3: 5419389.9 | H3: 2648916.9 | I3: 4234333.7 | J3: 4317614.6 | K3: 3761815.5 | L3: 5524123.7 | M3: 3038103.4 | N3: 9599889.3 | O3: 1533431.1 | P3: 9082355 | Q3: 1325005.7 | R3: 3474913.1 | S3: 4784771 | T3: 1934480.6 | U3: 4062122.1 | V3: 3703477.3 | W3: 4707037.1 | X3: 3367874 | Y3: 1732603.8 | Z3: 3979552.8 | AA3: 4167832.6 | AB3: 4223660.7 | AC3: 4713693.4 | AD3: 10753126 | AE3: 12703756 | AF3: 4489698.6 | AG3: 4106829.5 | AH3: 3335831.5 | AI3: 5524300.5 | AJ3: 2687448.7 | AK3: 3188867.5 | AL3: 3521007.7 | AM3: 3738419.8 | AN3: 5926629.8 | AO3: 4526167 | AP3: 6231474 | AQ3: 3210753.5 | AR3: 4498219.3 | AS3: 8734528.6 | AT3: 4148949 | AU3: 4428107.2 | AV3: 7104043.5 | AW3: 1606880.8 | AX3: 4862255.1 | AY3: 3860281.5 | AZ3: 6032483.7 | BA3: 6856463.4 | BB3: 13910858 | BC3: 4182202.1 | BD3: 7075816.3 | BE3: 5588606.9 | BF3: 6656176.5 | BG3: 5820628.2 | BH3: 2532174.5 | BI3: 8667983.1 | BJ3: 5104873.8 | BK3: 8253616.2 | BL3: 15211032 | BM3: 16855330 | BN3: 6041157.9 | BO3: 2776640.2 | BP3: 7434936.9 | BQ3: 5885393.3 | BR3: 4937725.4 | BS3: 8068454.7 | BT3: 5595818.5 | BU3: 6450448.6 | BV3: 4299628.6 | BW3: 5793714.4 | BX3: 5852794 | BY3: 18388453 | BZ3: 15132048 | CA3: 5995997.3 | CB3: 4451830 | CC3: 5089122.2
A5: Primas Netas | B5: 29627738 | C5: 44729547 | D5: 29073920 | E5: 26448703 | F5: 27557156 | G5: 29693270 | H5: 28830631 | I5: 62440523 | J5: 30172454 | K5: 29798182 | L5: 29089015 | M5: 36735239 | N5: 23973736 | O5: 36937104 | P5: 39586809 | Q5: 31654425 | R5: 26984812 | S5: 34593353 | T5: 30106302 | U5: 66409701 | V5: 31845005 | W5: 30027901 | X5: 31702613 | Y5: 33524715 | Z5: 34889657 | AA5: 62579592 | AB5: 38977816 | AC5: 40219576 | AD5: 40097559 | AE5: 47953812 | AF5: 80443745 | AG5: 47657803 | AH5: 52235840 | AI5: 45332456 | AJ5: 42030997 | AK5: 37190603 | AL5: 48918619 | AM5: 65524723 | AN5: 45884901 | AO5: 58134959 | AP5: 44176200 | AQ5: 46196777 | AR5: 40901864 | AS5: 82662929 | AT5: 43092871 | AU5: 41959254 | AV5: 52642884 | AW5: 49100886 | AX5: 51372747 | AY5: 76587478 | AZ5: 46334676 | BA5: 59222765 | BB5: 45368141 | BC5: 52371017 | BD5: 51148104 | BE5: 1.0505238e+08 | BF5: 48753592 | BG5: 60297100 | BH5: 62096386 | BI5: 40277438 | BJ5: 71491492 | BK5: 77207835 | BL5: 55917499 | BM5: 53022803 | BN5: 49389488 | BO5: 55254412 | BP5: 57720047 | BQ5: 57288065 | BR5: 57490885 | BS5: 48459095 | BT5: 46862971 | BU5: 38506750 | BV5: 51192513 | BW5: 74115586 | BX5: 62495810 | BY5: 41426155 | BZ5: 40376474 | CA5: 42708705 | CB5: 46133198 | CC5: 46092040
A7: Primas por Reaseguro Cedido | B7: 14280524 | C7: 20373376 | D7: 10166879 | E7: 13703221 | F7: 11344553 | G7: 15047318 | H7: 12554282 | I7: 40743734 | J7: 14983191 | K7: 13668092 | L7: 15383656 | M7: 22289748 | N7: 9378417.9 | O7: 16670613 | P7: 12486903 | Q7: 16295074 | R7: 13304568 | S7: 19038865 | T7: 12751977 | U7: 44566200 | V7: 15772985 | W7: 13891808 | X7: 16310863 | Y7: 22118731 | Z7: 16161408 | AA7: 21265640 | AB7: 16196181 | AC7: 20673260 | AD7: 20973793 | AE7: 27064111 | AF7: 50344784 | AG7: 21490423 | AH7: 23590907 | AI7: 20203933 | AJ7: 17762188 | AK7: 20607699 | AL7: 20973062 | AM7: 20894148 | AN7: 21309639 | AO7: 27340889 | AP7: 21760373 | AQ7: 22836101 | AR7: 18103322 | AS7: 52523853 | AT7: 18250226 | AU7: 18027089 | AV7: 31768978 | AW7: 21573703 | AX7: 21351896 | AY7: 22787927 | AZ7: 22759221 | BA7: 27280443 | BB7: 21019483 | BC7: 26164305 | BD7: 18476477 | BE7: 67036234 | BF7: 19109453 | BG7: 28140488 | BH7: 33307340 | BI7: 20682510 | BJ7: 33364683 | BK7: 28047520 | BL7: 26293104 | BM7: 19630589 | BN7: 20732604 | BO7: 24480040 | BP7: 27234464 | BQ7: 20124405 | BR7: 21237599 | BS7: 23685552 | BT7: 23183097 | BU7: 23708610 | BV7: 18254565 | BW7: 26621037 | BX7: 33028070 | BY7: 15146108 | BZ7: 15850704 | CA7: 21920937 | CB7: 23762795 | CC7: 19178662
A9: PRIMAS NETAS DE RETENCION | B9: 15347214 | C9: 24356172 | D9: 18907041 | E9: 12745482 | F9: 16212603 | G9: 14645953 | H9: 16276349 | I9: 21696789 | J9: 15189263 | K9: 16130090 | L9: 13705358 | M9: 14445491 | N9: 14595318 | O9: 20266491 | P9: 27099906 | Q9: 15359352 | R9: 13680244 | S9: 15554489 | T9: 17354325 | U9: 21843501 | V9: 16072021 | W9: 16136093 | X9: 15391750 | Y9: 11405984 | Z9: 18728249 | AA9: 41313952 | AB9: 22781635 | AC9: 19546315 | AD9: 19123766 | AE9: 20889701 | AF9: 30098961 | AG9: 26167380 | AH9: 28644933 | AI9: 25128523 | AJ9: 24268808 | AK9: 16582904 | AL9: 27945557 | AM9: 44630574 | AN9: 24575261 | AO9: 30794070 | AP9: 22415827 | AQ9: 23360675 | AR9: 22798542 | AS9: 30139077 | AT9: 24842645 | AU9: 23932166 | AV9: 20873907 | AW9: 27527182 | AX9: 30020851 | AY9: 53799551 | AZ9: 23575456 | BA9: 31942321 | BB9: 24348658 | BC9: 26206712 | BD9: 32671627 | BE9: 38016144 | BF9: 29644140 | BG9: 32156611 | BH9: 28789045 | BI9: 19594928 | BJ9: 38126810 | BK9: 49160315 | BL9: 29624395 | BM9: 33392214 | BN9: 28656884 | BO9: 30774372 | BP9: 30485583 | BQ9: 37163660 | BR9: 36253286 | BS9: 24773543 | BT9: 23679874 | BU9: 14798141 | BV9: 32937948 | BW9: 47494549 | BX9: 29467739 | BY9: 26280047 | BZ9: 24525770 | CA9: 20787768 | CB9: 22370403 | CC9: 26913378
A11: VARIACIONES EN RESERVAS TECNICAS Y MATEMÁTICAS
A12: Menos:
A13: Variaciones Gastos | B13: -412861.05 | C13: 7122851.1 | D13: 2169790.6 | E13: -1076894.7 | F13: 97680.49 | G13: -1038554.5 | H13: -502418.95 | I13: 1418651 | J13: -3130.25 | K13: 1324282.8 | L13: -3818277.4 | M13: -748399.27 | N13: -994677.32 | O13: 1567826 | P13: 12919415 | Q13: -172532.49 | R13: -3228718.7 | S13: -822329.72 | T13: -311327.01 | U13: -1169971.9 | V13: -263423.92 | W13: -450442.25 | X13: -1754874.1 | Y13: -3129441.2 | Z13: 3561213.3 | AA13: 22231159 | AB13: 1259462.8 | AC13: -3749.55 | AD13: -1249167.4 | AE13: -2881266.1 | AF13: 3497611.2 | AG13: 2295923 | AH13: 6262139.3 | AI13: 4947017.9 | AJ13: 312162.42 | AK13: -3606698.1 | AL13: 7965130.9 | AM13: 18470604 | AN13: 2519877.5 | AO13: 5823588.9 | AP13: -2147734.7 | AQ13: -3142430 | AR13: 1102759.8 | AS13: -230429.83 | AT13: 87775.81 | AU13: -2038780 | AV13: -3084811.6 | AW13: -4593961.6 | AX13: 6142339 | AY13: 25304716 | AZ13: -1859668.2 | BA13: 4973325.6 | BB13: -4622358.7 | BC13: -1191281 | BD13: 2119109.6 | BE13: 1128183.6 | BF13: 515791.02 | BG13: -2032376.7 | BH13: -3940349.8 | BI13: -6007286.4 | BJ13: 5905450.1 | BK13: 21969661 | BL13: -885553.12 | BM13: 3592943.5 | BN13: -3584336.1 | BO13: -3202225.6 | BP13: 2216721.2 | BQ13: 7638925.7 | BR13: 4443104.1 | BS13: -3199160.5 | BT13: -7245626.1 | BU13: -10796070 | BV13: 1184257.6 | BW13: 16481580 | BX13: -1458432.3 | BY13: -2173653.3 | BZ13: -4869557.7 | CA13: -8047144.3 | CB13: -2151335.5 | CC13: 234537.22
A14: PRIMAS NETAS DE RETENCION DEVENGADAS | B14: 15760075 | C14: 17233321 | D14: 16737250 | E14: 13822377 | F14: 16114922 | G14: 15684507 | H14: 16778768 | I14: 20278138 | J14: 15192393 | K14: 14805807 | L14: 17523636 | M14: 15193890 | N14: 15589995 | O14: 18698665 | P14: 14180492 | Q14: 15531884 | R14: 16908963 | S14: 16376818 | T14: 17665652 | U14: 23013472 | V14: 16335445 | W14: 16586536 | X14: 17146624 | Y14: 14535425 | Z14: 15167036 | AA14: 19082793 | AB14: 21522172 | AC14: 19550065 | AD14: 20372934 | AE14: 23770967 | AF14: 26601350 | AG14: 23871457 | AH14: 22382794 | AI14: 20181505 | AJ14: 23956646 | AK14: 20189602 | AL14: 19980426 | AM14: 26159971 | AN14: 22055384 | AO14: 24970481 | AP14: 24563562 | AQ14: 26503105 | AR14: 21695783 | AS14: 30369506 | AT14: 24754870 | AU14: 25970946 | AV14: 23958718 | AW14: 32121144 | AX14: 23878512 | AY14: 28494834 | AZ14: 25435124 | BA14: 26968996 | BB14: 28971017 | BC14: 27397993 | BD14: 30552517 | BE14: 36887961 | BF14: 29128349 | BG14: 34188988 | BH14: 32729395 | BI14: 25602214 | BJ14: 32221359 | BK14: 27190655 | BL14: 30509949 | BM14: 29799271 | BN14: 32241220 | BO14: 33976598 | BP14: 28268862 | BQ14: 29524734 | BR14: 31810182 | BS14: 27972704 | BT14: 30925500 | BU14: 25594211 | BV14: 31753690 | BW14: 31012970 | BX14: 30926172 | BY14: 28453700 | BZ14: 29395327 | CA14: 28834912 | CB14: 24521739 | CC14: 26678841
A16: Menos:
A17: COSTO DE ADQUISICION Y SINIESTRALIDAD | B17: 7113966.5 | C17: 9884371 | D17: 8697480.3 | E17: 3809018.8 | F17: 7727115.8 | G17: 4590399.4 | H17: 6983276.7 | I17: 10972814 | J17: 11352547 | K17: 7555087.7 | L17: 10053199 | M17: 6308006.8 | N17: 6824439 | O17: 8900427.4 | P17: 9951874.3 | Q17: 7841328.9 | R17: 10143574 | S17: 9170230.4 | T17: 9322903.1 | U17: 12742738 | V17: 10344680 | W17: 9185294.1 | X17: 9735815.1 | Y17: 6996590 | Z17: 7710739.8 | AA17: 8832035.4 | AB17: 9281109.9 | AC17: 9373805.4 | AD17: 11637366 | AE17: 9384408.7 | AF17: 13723422 | AG17: 11123792 | AH17: 9254343.4 | AI17: 6756314 | AJ17: 14090958 | AK17: 2297884.5 | AL17: 6765513.8 | AM17: 11321924 | AN17: 10321990 | AO17: 8254533.2 | AP17: 10854006 | AQ17: 12829760 | AR17: 11820769 | AS17: 18611648 | AT17: 12555130 | AU17: 15253616 | AV17: 14732272 | AW17: 9039569.9 | AX17: 13932467 | AY17: 16630569 | AZ17: 14694317 | BA17: 10081775 | BB17: 17196724 | BC17: 12580388 | BD17: 16360572 | BE17: 18734342 | BF17: 17676142 | BG17: 13516191 | BH17: 25291571 | BI17: -301999.37 | BJ17: 18337740 | BK17: 13878685 | BL17: 18932473 | BM17: 16094575 | BN17: 16440400 | BO17: 17529443 | BP17: 19621431 | BQ17: 15231023 | BR17: =BR18+BR23 -> 14789919 | BS17: =BS18+BS23 -> 15192433 | BT17: 13634829 | BU17: 11775673 | BV17: 15752668 | BW17: 14115381 | BX17: 12785419 | BY17: 15516205 | BZ17: 13686701 | CA17: 13813410 | CB17: 9587218.3 | CC17: 15275230
A18: ADQUISICION | B18: 120313.72 | C18: 835532.52 | D18: 791832.42 | E18: 355082.02 | F18: 573945.24 | G18: -1061358.5 | H18: -169681.64 | I18: 3570095.9 | J18: 313364.39 | K18: 343585 | L18: -321694.77 | M18: -2663435.8 | N18: 53832.16 | O18: 3772.66 | P18: 502572.29 | Q18: 523176.09 | R18: 230908.08 | S18: -284830.73 | T18: 492714.78 | U18: 4159186.3 | V18: -1974352.4 | W18: -58498.9 | X18: -468636.27 | Y18: -3595350.2 | Z18: -8793.31 | AA18: -118575.89 | AB18: -92167.78 | AC18: -322021.82 | AD18: 563112.17 | AE18: -215711.47 | AF18: 4283849.5 | AG18: -321241.16 | AH18: -2727989 | AI18: -1446275.1 | AJ18: 284526.18 | AK18: -10221039 | AL18: -1008272.7 | AM18: -24332.86 | AN18: -690419.26 | AO18: -1568306.4 | AP18: -470607.8 | AQ18: -436152.55 | AR18: 2808892.8 | AS18: 6237026.9 | AT18: 1210060.1 | AU18: 1824871.6 | AV18: 2075392.7 | AW18: -7634489 | AX18: 2721926.1 | AY18: 1085733.4 | AZ18: 555719.43 | BA18: 398073.61 | BB18: 1431667.4 | BC18: -1328774.4 | BD18: -27025.95 | BE18: 5727733.1 | BF18: 577340.1 | BG18: 104109.89 | BH18: 1493657.7 | BI18: -3315632.3 | BJ18: 1094836.9 | BK18: 1315905.4 | BL18: 2202353.5 | BM18: -1569898.1 | BN18: -696884.21 | BO18: 111189.22 | BP18: 620885.78 | BQ18: 232381.13 | BR18: 810350.9 | BS18: -439432.14 | BT18: -266080.74 | BU18: -3163330.3 | BV18: 707888.92 | BW18: 1088468.7 | BX18: 93216.23 | BY18: 1006077 | BZ18: 679772.01 | CA18: -973590.81 | CB18: -1793446.5 | CC18: -589713.58
A19: Gastos de Adquisicion y Renovacion | B19: 3024484.5 | C19: 3498757.3 | D19: 3751273.4 | E19: 3425475.1 | F19: 3044231.7 | G19: 2587761.3 | H19: 3276083.6 | I19: 6923983.3 | J19: 3564924.1 | K19: 3698943.1 | L19: 3926752.3 | M19: 3300743.5 | N19: 3277858 | O19: 3554252.5 | P19: 4027396.4 | Q19: 3316764.4 | R19: 3364876.7 | S19: 3613173.4 | T19: 3858499.8 | U19: 7592182.8 | V19: 2019611.9 | W19: 3785578.7 | X19: 3905050.6 | Y19: 2221386.5 | Z19: 3830851.8 | AA19: 4798084.5 | AB19: 4301116.8 | AC19: 3992240.3 | AD19: 4204417 | AE19: 4483427.5 | AF19: 9109704.1 | AG19: 5942813.4 | AH19: 3999655.8 | AI19: 4138935.9 | AJ19: 5269448.3 | AK19: 793401.27 | AL19: 4240265.3 | AM19: 4963076.2 | AN19: 4741762.4 | AO19: 3228950 | AP19: 4863788.5 | AQ19: 5259635.1 | AR19: 7478272.7 | AS19: 11192491 | AT19: 6454812.9 | AU19: 6090431.6 | AV19: 6737528.9 | AW19: 5083506 | AX19: 7924344 | AY19: 6512949.7 | AZ19: 5290897.4 | BA19: 5516307.4 | BB19: 6240834.7 | BC19: 4524763.3 | BD19: 4608769.3 | BE19: 12529887 | BF19: 5625694.6 | BG19: 5829959 | BH19: 7402726.2 | BI19: 4799851.9 | BJ19: 6580103.1 | BK19: 6094848.7 | BL19: 7072791.6 | BM19: 2982831.3 | BN19: 4745092 | BO19: 5170294.2 | BP19: 5789330.3 | BQ19: 5605692.4 | BR19: 5699791.1 | BS19: 4546605.9 | BT19: 4531253.9 | BU19: 2897551.3 | BV19: 4980433 | BW19: 5846745 | BX19: 5075350.1 | BY19: 4581437.4 | BZ19: 4315722.9 | CA19: 4104502 | CB19: 2903721.5 | CC19: 4370450.3
A20: Menos:
A21: Comisiones y Participaciones por Reaseguro Cedido | B21: 2904170.7 | C21: 2663224.8 | D21: 2959441 | E21: 3070393.1 | F21: 2470286.4 | G21: 3649119.8 | H21: 3445765.2 | I21: 3353887.4 | J21: 3251559.7 | K21: 3355358.1 | L21: 4248447.1 | M21: 5964179.3 | N21: 3224025.9 | O21: 3550479.9 | P21: 3524824.1 | Q21: 2793588.4 | R21: 3133968.6 | S21: 3898004.1 | T21: 3365785 | U21: 3432996.5 | V21: 3993964.3 | W21: 3844077.6 | X21: 4373686.8 | Y21: 5816736.7 | Z21: 3839645.1 | AA21: 4916660.4 | AB21: 4393284.6 | AC21: 4314262.2 | AD21: 3641304.8 | AE21: 4699139 | AF21: 4825854.6 | AG21: 6264054.5 | AH21: 6727644.8 | AI21: 5585211 | AJ21: 4984922.1 | AK21: 11014440 | AL21: 5248538 | AM21: 4987409.1 | AN21: 5432181.6 | AO21: 4797256.4 | AP21: 5334396.3 | AQ21: 5695787.7 | AR21: 4669379.9 | AS21: 4955464.2 | AT21: 5244752.8 | AU21: 4265560 | AV21: 4662136.2 | AW21: 12717995 | AX21: 5202417.9 | AY21: 5427216.3 | AZ21: 4735178 | BA21: 5118233.8 | BB21: 4809167.3 | BC21: 5853537.6 | BD21: 4635795.3 | BE21: 6802153.9 | BF21: 5048354.5 | BG21: 5725849.1 | BH21: 5909068.6 | BI21: 8115484.2 | BJ21: 5485266.2 | BK21: 4778943.3 | BL21: 4870438 | BM21: 4552729.5 | BN21: 5441976.2 | BO21: 5059105 | BP21: 5168444.5 | BQ21: 5373311.2 | BR21: 4889440.2 | BS21: 4986038.1 | BT21: 4797334.6 | BU21: 6060881.5 | BV21: 4272544.1 | BW21: 4758276.3 | BX21: 4982133.8 | BY21: 3575360.4 | BZ21: 3635950.9 | CA21: 5078092.8 | CB21: 4697168 | CC21: 4960163.9
A23: SINIESTRALIDAD | B23: 6993652.8 | C23: 9048838.5 | D23: 7905647.9 | E23: 3453936.8 | F23: 7153170.6 | G23: 5651757.9 | H23: 7152958.3 | I23: 7402718.2 | J23: 11039182 | K23: 7211502.7 | L23: 10374894 | M23: 8971442.7 | N23: 6770606.9 | O23: 8896654.7 | P23: 9449302 | Q23: 7318152.8 | R23: 9912665.8 | S23: 9455061.2 | T23: 8830188.3 | U23: 8583551.6 | V23: 12319033 | W23: 9243793 | X23: 10204451 | Y23: 10591940 | Z23: 7719533.1 | AA23: 8950611.3 | AB23: 9373277.7 | AC23: 9695827.2 | AD23: 11074253 | AE23: 9600120.2 | AF23: 9439572.1 | AG23: 11445033 | AH23: 11982332 | AI23: 8202589.1 | AJ23: 13806432 | AK23: 12518923 | AL23: 7773786.5 | AM23: 11346257 | AN23: 11012409 | AO23: 9822839.6 | AP23: 11324614 | AQ23: 13265913 | AR23: 9011876.2 | AS23: 12374622 | AT23: 11345070 | AU23: 13428744 | AV23: 12656879 | AW23: 16674059 | AX23: 11210541 | AY23: 15544835 | AZ23: 14138597 | BA23: 9683701.8 | BB23: 15765057 | BC23: 13909162 | BD23: 16387598 | BE23: 13006609 | BF23: 17098802 | BG23: 13412081 | BH23: 23797913 | BI23: 3013632.9 | BJ23: 17242903 | BK23: 12562780 | BL23: 16730119 | BM23: 17664474 | BN23: 17137284 | BO23: 17418254 | BP23: 19000545 | BQ23: 14998641 | BR23: 13979568 | BS23: 15631865 | BT23: 13900910 | BU23: 14939004 | BV23: 15044779 | BW23: 13026913 | BX23: 12692203 | BY23: 14510128 | BZ23: 13006929 | CA23: 14787000 | CB23: 11380665 | CC23: 15864943
A24: Gastos por Obligaciones Contractuales | B24: 8807887 | C24: 13308891 | D24: 11157094 | E24: 3336605 | F24: 15816541 | G24: 10023695 | H24: 7229379.4 | I24: 10283222 | J24: 18626219 | K24: 10458917 | L24: 7108287.6 | M24: 11607340 | N24: -2363060.3 | O24: 6859612.1 | P24: 14626038 | Q24: 929620.82 | R24: 18686187 | S24: 19329578 | T24: 13222829 | U24: 9309938.3 | V24: 21724533 | W24: 25805005 | X24: 21819525 | Y24: 7345269.4 | Z24: 13452822 | AA24: 14749289 | AB24: 12607380 | AC24: 16197631 | AD24: 19325734 | AE24: 14509473 | AF24: 14400913 | AG24: 17705657 | AH24: 14774008 | AI24: 8181337.6 | AJ24: 16909083 | AK24: 30291025 | AL24: 11698822 | AM24: 15072245 | AN24: 6337585.4 | AO24: 17730309 | AP24: 17229648 | AQ24: 19099974 | AR24: 9926828.7 | AS24: 15796761 | AT24: 15226314 | AU24: 16875391 | AV24: 15460558 | AW24: 1.2549813e+08 | AX24: 14362330 | AY24: 17790518 | AZ24: 17791578 | BA24: 16659308 | BB24: -8407518.7 | BC24: 25468166 | BD24: 1.4572591e+08 | BE24: 22577832 | BF24: 20705039 | BG24: 35030634 | BH24: 32925522 | BI24: 25394509 | BJ24: 22034379 | BK24: 14666846 | BL24: 21620718 | BM24: 21406870 | BN24: 21652480 | BO24: 3943592.5 | BP24: 34552418 | BQ24: 10177573 | BR24: 22863189 | BS24: 28994761 | BT24: 12159722 | BU24: 12590910 | BV24: 13837550 | BW24: 21843014 | BX24: 18092761 | BY24: 19922549 | BZ24: 38130339 | CA24: 22021218 | CB24: 14759001 | CC24: 17157227
A25: Participacion de reaseguradoras en salvamentos y recuperaciones | B25: 0 | C25: 0 | D25: 0 | E25: 0 | F25: 0 | G25: 0 | H25: 0 | I25: 0 | J25: 0 | K25: 0 | L25: 0 | M25: 0 | N25: 0 | O25: 0 | P25: 0 | Q25: 0 | R25: 0 | S25: 0 | T25: 0 | U25: 0 | V25: 0 | W25: 0 | X25: 0 | Y25: 1101607.6 | Z25: 0 | AA25: 0 | AB25: 0 | AC25: 0 | AD25: 0 | AE25: 0 | AF25: 0 | AG25: 0 | AH25: 0 | AI25: 0 | AJ25: 0 | AK25: 312577.81 | AL25: 0 | AM25: 0 | AN25: 0 | AO25: 0 | AP25: 0 | AQ25: 0 | AR25: 0 | AS25: 0 | AT25: 0 | AU25: 0 | AV25: 0 | AW25: 0 | AX25: 0 | AY25: 0 | AZ25: 0 | BA25: 0 | BB25: 0 | BC25: 0 | BD25: 0 | BE25: 0 | BF25: 0 | BG25: 0 | BH25: 0 | BI25: 0 | BJ25: 0 | BK25: 0 | BL25: 18722.36 | BM25: 63801.24 | BN25: 0 | BO25: 0 | BP25: 0 | BQ25: 0 | BR25: 0 | BS25: 0 | BT25: 0 | BU25: 0 | BV25: 0 | BW25: 0 | BX25: 0 | BY25: 0 | BZ25: 0 | CA25: 0 | CB25: 0 | CC25: 0
A26: Menos:
A27: Recuperaciones por Reaseguro Cedido | B27: 1543260.8 | C27: 3900398 | D27: 2998170.8 | E27: -315893.76 | F27: 8636491.8 | G27: 4299856.7 | H27: -44154.69 | I27: 2625547.4 | J27: 7293362.8 | K27: 2794268.4 | L27: -3598072.4 | M27: 2359784.1 | N27: -9582587.2 | O27: -2172865.6 | P27: 5046003.1 | Q27: -6510894.9 | R27: 8267090.5 | S27: 9492920.3 | T27: 4293702.6 | U27: -61035.43 | V27: 9197678.3 | W27: 16365239 | X27: 11341754 | Y27: -3388893.5 | Z27: 5491848.5 | AA27: 5556463.3 | AB27: 2777084.5 | AC27: 6358082.1 | AD27: 8190817 | AE27: 3952137.7 | AF27: 4414286.3 | AG27: 5376414.6 | AH27: 2173934.6 | AI27: -349851.99 | AJ27: 2834716.4 | AK27: 16748058 | AL27: 2440858.6 | AM27: 2891476.4 | AN27: -5175973.5 | AO27: 7198825.1 | AP27: 5475219.4 | AQ27: 5399546.2 | AR27: 245090.5 | AS27: 3005050.3 | AT27: 2834203.4 | AU27: 3378460.4 | AV27: 2201242.5 | AW27: 1.0824728e+08 | AX27: 2960618.7 | AY27: 1755583.3 | AZ27: 3346091.3 | BA27: 6820825.3 | BB27: -25087599 | BC27: 11321450 | BD27: 1.2906256e+08 | BE27: 9111567.2 | BF27: 3225936.8 | BG27: 21110185 | BH27: 9064848.3 | BI27: 20250168 | BJ27: 4237501.4 | BK27: 1639162.1 | BL27: 4757020.3 | BM27: 3600261.3 | BN27: 4444209 | BO27: -15037499 | BP27: 15535458 | BQ27: -5859761.9 | BR27: 7988485.1 | BS27: 12478295 | BT27: -2150392 | BU27: -3613806.5 | BV27: -1531942 | BW27: 8184883.8 | BX27: 4600770.2 | BY27: 5332596.8 | BZ27: 23935766 | CA27: 6748592.9 | CB27: 3165074.5 | CC27: 1273334
A28: Salvamento y recuperaciones | B28: 270973.39 | C28: 359654.89 | D28: 253275.68 | E28: 198562.02 | F28: 26878.57 | G28: 72080.38 | H28: 120575.77 | I28: 254956.25 | J28: 293673.56 | K28: 453145.9 | L28: 331466.18 | M28: 276113.01 | N28: 448919.99 | O28: 135822.89 | P28: 130732.46 | Q28: 122362.93 | R28: 506430.59 | S28: 381596.19 | T28: 98937.89 | U28: 787422.14 | V28: 207822 | W28: 195972.83 | X28: 273319.07 | Y28: 1243830.4 | Z28: 241440.64 | AA28: 242214.76 | AB28: 457018.2 | AC28: 143721.58 | AD28: 60663.23 | AE28: 957215.17 | AF28: 547055.08 | AG28: 884209 | AH28: 617741 | AI28: 328600.44 | AJ28: 267934.74 | AK28: 1336621.2 | AL28: 1484177.2 | AM28: 834510.79 | AN28: 501150.08 | AO28: 708644.03 | AP28: 429814.3 | AQ28: 434515.11 | AR28: 669862.03 | AS28: 417089.44 | AT28: 1047040.7 | AU28: 68186.23 | AV28: 602435.92 | AW28: 576800 | AX28: 191170.23 | AY28: 490099.51 | AZ28: 306889.71 | BA28: 154780.94 | BB28: 915023.37 | BC28: 237553.45 | BD28: 275755.9 | BE28: 459655.1 | BF28: 380300 | BG28: 508367.63 | BH28: 62760.02 | BI28: 2130707.8 | BJ28: 553974.6 | BK28: 464904.45 | BL28: 152301.24 | BM28: 205936.48 | BN28: 70986.58 | BO28: 1562837.7 | BP28: 16413.95 | BQ28: 1038693.3 | BR28: 895135.51 | BS28: 884601.79 | BT28: 409203.58 | BU28: 1265712.8 | BV28: 324713.49 | BW28: 631216.87 | BX28: 799787.71 | BY28: 79824.5 | BZ28: 1187644.7 | CA28: 485624.79 | CB28: 213262.05 | CC28: 18950
A30: UTILIDAD BRUTA EN OPERACIONES DE SEGUROS | B30: 8646108.7 | C30: 7348949.6 | D30: 8039770.1 | E30: 10013358 | F30: 8387806.6 | G30: 11094108 | H30: 9795491.4 | I30: 9305323.6 | J30: 3839846.8 | K30: 7250719.5 | L30: 7470436.6 | M30: 8885883.3 | N30: 8765556.2 | O30: 9798237.4 | P30: 4228617.5 | Q30: 7690555.1 | R30: 6765389 | S30: 7206588.1 | T30: 8342749.1 | U30: 10270735 | V30: 5990764.4 | W30: 7401241.5 | X30: 7410809.1 | Y30: 7538835.4 | Z30: 7456296.2 | AA30: 10250758 | AB30: 12241063 | AC30: 10176259 | AD30: 8735568 | AE30: 14386558 | AF30: 12877928 | AG30: 12747665 | AH30: 13128450 | AI30: 13425191 | AJ30: 9865688.1 | AK30: 17891718 | AL30: 13214912 | AM30: 14838046 | AN30: 11733394 | AO30: 16715948 | AP30: 13709556 | AQ30: 13673345 | AR30: 9875013.7 | AS30: 11757858 | AT30: 12199740 | AU30: 10717330 | AV30: 9226446.2 | AW30: 23081574 | AX30: 9946044.7 | AY30: 11864265 | AZ30: 10740807 | BA30: 16887220 | BB30: 11774293 | BC30: 14817605 | BD30: 14191945 | BE30: 18153618 | BF30: 11452207 | BG30: 20672797 | BH30: 7437824 | BI30: 25904214 | BJ30: 13883620 | BK30: 13311969 | BL30: 11577476 | BM30: 13704696 | BN30: 15800820 | BO30: 16447155 | BP30: 8647430.6 | BQ30: 14293712 | BR30: =BR14-BR17 -> 17020262 | BS30: =BS14-BS17 -> 12780271 | BT30: 17290670 | BU30: 13818537 | BV30: 16001023 | BW30: 16897588 | BX30: 18140753 | BY30: 12937495 | BZ30: 15708626 | CA30: 15021502 | CB30: 14934521 | CC30: 11403611
A32: Menos:
A33: GASTOS Y PRODUCTOS DE OPERACIONES | B33: 4151877.5 | C33: 4331507.1 | D33: 4790436.3 | E33: 5182629 | F33: 5024827 | G33: 4603350 | H33: 4730665 | I33: 4074020.7 | J33: 4708382.5 | K33: 4433544.9 | L33: 5991779.9 | M33: 4817219.7 | N33: 4629111.2 | O33: 3947231.5 | P33: 4855657.1 | Q33: 6308787.2 | R33: 6407786 | S33: 6205304.4 | T33: 5967088.6 | U33: 5882060.3 | V33: 6072528.8 | W33: 6448739.4 | X33: 6791953.3 | Y33: 7205579 | Z33: 6148689.9 | AA33: 7128561.5 | AB33: 7300036.8 | AC33: 6845923.2 | AD33: 6958194.6 | AE33: 9090165 | AF33: 9567318.6 | AG33: 10549373 | AH33: 13147497 | AI33: 10799158 | AJ33: 10448041 | AK33: 11051336 | AL33: 7197653 | AM33: 10730829 | AN33: 9971404.1 | AO33: 9784328.9 | AP33: 9822268.7 | AQ33: 10700912 | AR33: 6625690.8 | AS33: 7910867.6 | AT33: 9848949.5 | AU33: 8964511.6 | AV33: 8802214.9 | AW33: 15050366 | AX33: 7041704.3 | AY33: 10704118 | AZ33: 11860472 | BA33: 9879670 | BB33: 10952234 | BC33: 10263623 | BD33: 12469038 | BE33: 13299367 | BF33: 11261178 | BG33: 12016925 | BH33: 10446796 | BI33: 34103061 | BJ33: 10245096 | BK33: 11737219 | BL33: 12534293 | BM33: 12843258 | BN33: 13800761 | BO33: 14473850 | BP33: 12856753 | BQ33: 12666601 | BR33: 10877158 | BS33: 12615500 | BT33: 12539847 | BU33: 12367863 | BV33: 11955999 | BW33: 9640930 | BX33: 11775213 | BY33: 11386496 | BZ33: 11955222 | CA33: 11747574 | CB33: 11759742 | CC33: 11392521
A34: Egresos por Inversiones | B34: 29916.38 | C34: 28502.42 | D34: 29916.38 | E34: 29209.4 | F34: 32640.41 | G34: 39877.97 | H34: 48450.05 | I34: 48451.59 | J34: 47146.7 | K34: 48451.59 | L34: 47146.7 | M34: 48451.56 | N34: 48450.75 | O34: 47145.8 | P34: 48450.66 | Q34: 47145.8 | R34: 48450.66 | S34: 47145.8 | T34: 48316.46 | U34: 47618.62 | V34: 46340.6 | W34: 47618.62 | X34: 46340.6 | Y34: 47618.62 | Z34: 47618.62 | AA34: 46340.6 | AB34: 47618.62 | AC34: 46340.6 | AD34: 47618.62 | AE34: 46340.6 | AF34: 47617.6 | AG34: 47608.08 | AH34: 46330.4 | AI34: 47608.08 | AJ34: 46330.4 | AK34: 47608.08 | AL34: 47608.08 | AM34: 46330.4 | AN34: 47608.08 | AO34: 46330.4 | AP34: 47608.08 | AQ34: 46330.4 | AR34: 47608.08 | AS34: 47608.08 | AT34: 46330.4 | AU34: 47608.08 | AV34: 46330.4 | AW34: 47608.08 | AX34: 47608.08 | AY34: 45052.72 | AZ34: 47608.08 | BA34: 46330.4 | BB34: 47608.08 | BC34: 46330.4 | BD34: 47608.08 | BE34: 47608.08 | BF34: 46330.4 | BG34: 47608.08 | BH34: 46330.4 | BI34: 47608.08 | BJ34: 47608.08 | BK34: 43775.04 | BL34: 47608.08 | BM34: 46330.4 | BN34: 47608.08 | BO34: 46330.4 | BP34: 47608.08 | BQ34: 47608.08 | BR34: 46330.4 | BS34: 46820.13 | BT34: 45680.6 | BU34: 57937.17 | BV34: 69671.09 | BW34: 63702.92 | BX34: 69671.09 | BY34: 67681.7 | BZ34: 69671.09 | CA34: 83067.5 | CB34: 87923.6 | CC34: 106296.97
A35: Gastos de Administración | B35: 5902881.7 | C35: 6508623.5 | D35: 6209637.7 | E35: 6512152.4 | F35: 6427136.5 | G35: 6198363.8 | H35: 6290797.1 | I35: 6037182.9 | J35: 6343906.5 | K35: 6094544.1 | L35: 7629314.9 | M35: 7014196.4 | N35: 6172708.4 | O35: 5755153.9 | P35: 7087800.5 | Q35: 7811667.9 | R35: 7804320 | S35: 8014190.4 | T35: 7492493.1 | U35: 7901600 | V35: 7628597.5 | W35: 8009223.2 | X35: 8335822 | Y35: 8968199.7 | Z35: 7836443.2 | AA35: 9887018.8 | AB35: 9052072.2 | AC35: 8693863.4 | AD35: 8663218.4 | AE35: 11543607 | AF35: 11695761 | AG35: 12393524 | AH35: 15039419 | AI35: 12695513 | AJ35: 12157589 | AK35: 13209591 | AL35: 9420444.7 | AM35: 13690063 | AN35: 12029962 | AO35: 12156008 | AP35: 12181762 | AQ35: 13213059 | AR35: 8908107.9 | AS35: 10590289 | AT35: 12037596 | AU35: 11490612 | AV35: 11775315 | AW35: 17863364 | AX35: 9830180.1 | AY35: 14377790 | AZ35: 14278943 | BA35: 12524375 | BB35: 13513565 | BC35: 13089265 | BD35: 15292252 | BE35: 16482911 | BF35: 13734695 | BG35: 15266214 | BH35: 13588906 | BI35: 36726828 | BJ35: 13807953 | BK35: 15311882 | BL35: 15063945 | BM35: 15304299 | BN35: 16299729 | BO35: 17101720 | BP35: 15621187 | BQ35: 15352011 | BR35: 14488660 | BS35: 15150969 | BT35: 15113841 | BU35: 14685121 | BV35: 14568305 | BW35: 13390696 | BX35: 14718066 | BY35: 13476611 | BZ35: 14032591 | CA35: 13925198 | CB35: 14104537 | CC35: 13591362
A36: Menos:
A37: Derechos de Emisión de Pólizas (Neto) | B37: 1200000.5 | C37: 1627584.3 | D37: 894964.44 | E37: 827568 | F37: 832851.63 | G37: 962456.2 | H37: 951479.56 | I37: 1349393.6 | J37: 1030992.3 | K37: 953565.74 | L37: 1025057.6 | M37: 1575323 | N37: 927248.91 | O37: 1243041.4 | P37: 1606867.5 | Q37: 901338.51 | R37: 802949.19 | S37: 1174491.1 | T37: 943930.71 | U37: 1451617.6 | V37: 998882.93 | W37: 929498.39 | X37: 996977.34 | Y37: 1122442.8 | Z37: 1125308.6 | AA37: 2166354.1 | AB37: 1185900.3 | AC37: 1243643.8 | AD37: 1081387.4 | AE37: 1807967.5 | AF37: 1530037.6 | AG37: 1253467 | AH37: 1266923 | AI37: 1156436.4 | AJ37: 1070552.5 | AK37: 1148718.5 | AL37: 1419581.3 | AM37: 2191044.3 | AN37: 1276373.1 | AO37: 1481203.7 | AP37: 1380895.6 | AQ37: 1490407.2 | AR37: 1287190 | AS37: 1683881.2 | AT37: 1273709.7 | AU37: 1407716.5 | AV37: 1910493.6 | AW37: 1675268.9 | AX37: 1677218.6 | AY37: 2607731.8 | AZ37: 1374760.3 | BA37: 1501556.7 | BB37: 1394899.8 | BC37: 1569887.5 | BD37: 1659507.1 | BE37: 2015139 | BF37: 1488892.3 | BG37: 1795350 | BH37: 2062317.3 | BI37: 1334486.9 | BJ37: 2409684 | BK37: 2591779 | BL37: 1703738.6 | BM37: 1406250.9 | BN37: 1321922.5 | BO37: 1649469.6 | BP37: 1586503.5 | BQ37: 1568421.3 | BR37: 1864506.2 | BS37: 1359650.4 | BT37: 1469935.7 | BU37: 1161308.8 | BV37: 1446077.5 | BW37: 2646245.3 | BX37: 1452361.6 | BY37: 1006211.8 | BZ37: 983873.35 | CA37: 1162652.5 | CB37: 1218717.7 | CC37: 1099866
A38: Productos de Inversiones | B38: 580920.13 | C38: 578034.43 | D38: 554153.29 | E38: 531164.82 | F38: 602098.28 | G38: 672435.48 | H38: 657102.58 | I38: 662220.15 | J38: 651678.36 | K38: 755885.04 | L38: 659624.14 | M38: 670105.27 | N38: 664799.07 | O38: 612026.83 | P38: 673726.55 | Q38: 648688.05 | R38: 642035.48 | S38: 681540.77 | T38: 629790.24 | U38: 615540.65 | V38: 603526.29 | W38: 678604 | X38: 593232 | Y38: 687796.48 | Z38: 610063.37 | AA38: 638443.82 | AB38: 613753.71 | AC38: 650637.02 | AD38: 671255.03 | AE38: 691815.03 | AF38: 646022.3 | AG38: 638292.83 | AH38: 671329.61 | AI38: 787526.67 | AJ38: 685325.12 | AK38: 1057145 | AL38: 850818.5 | AM38: 814519.94 | AN38: 829792.85 | AO38: 936805.84 | AP38: 1026205.3 | AQ38: 1068070.6 | AR38: 1042835.2 | AS38: 1043148.4 | AT38: 961267.52 | AU38: 1165992.3 | AV38: 1108937.1 | AW38: 1185337.3 | AX38: 1158865.4 | AY38: 1110992.7 | AZ38: 1091319.2 | BA38: 1189478.2 | BB38: 1214039.8 | BC38: 1302085.3 | BD38: 1211314.3 | BE38: 1216012.4 | BF38: 1030954.7 | BG38: 1501547.1 | BH38: 1126123.5 | BI38: 1336888.6 | BJ38: 1200780.5 | BK38: 1026659.2 | BL38: 873521.84 | BM38: 1101120.6 | BN38: 1224653.8 | BO38: 1024730.8 | BP38: 1225538.6 | BQ38: 1164596.4 | BR38: 1793326.2 | BS38: 1222638.3 | BT38: 1149739.4 | BU38: 1213886.3 | BV38: 1235900.4 | BW38: 1167223.8 | BX38: 1560161.8 | BY38: 1151584.5 | BZ38: 1163166.3 | CA38: 1098038.3 | CB38: 1214001.5 | CC38: 1205272.1
A39: UTILIDAD (PERDIDA) OPERACIÓN | B39: 4494231.2 | C39: 3017442.5 | D39: 3249333.8 | E39: 4830728.9 | F39: 3362979.6 | G39: 6490757.6 | H39: 5064826.4 | I39: 5231302.9 | J39: -868535.78 | K39: 2817174.5 | L39: 1478656.8 | M39: 4068663.6 | N39: 4136445 | O39: 5851005.9 | P39: -627039.54 | Q39: 1381767.9 | R39: 357603 | S39: 1001283.7 | T39: 2375660.5 | U39: 4388674.3 | V39: -81764.44 | W39: 952502.1 | X39: 618855.77 | Y39: 333256.4 | Z39: 1307606.3 | AA39: 3122196.2 | AB39: 4941025.7 | AC39: 3330336.2 | AD39: 1777373.4 | AE39: 5296393.4 | AF39: 3310609.9 | AG39: 2198292.4 | AH39: -19046.68 | AI39: 2626033.5 | AJ39: -582353.18 | AK39: 6840382.2 | AL39: 6017259.2 | AM39: 4107217.4 | AN39: 1761990.3 | AO39: 6931619.1 | AP39: 3887287 | AQ39: 2972433.1 | AR39: 3249322.9 | AS39: 3846990.4 | AT39: 2350790.1 | AU39: 1752818.5 | AV39: 424231.31 | AW39: 8031207.9 | AX39: 2904340.5 | AY39: 1160146.9 | AZ39: -1119664 | BA39: 7007550.3 | BB39: 822059.04 | BC39: 4553982.5 | BD39: 1722906.8 | BE39: 4854251.3 | BF39: 191028.09 | BG39: 8655872.7 | BH39: -3008971.7 | BI39: -8198847 | BJ39: 3638523.6 | BK39: 1574750.6 | BL39: -956817.08 | BM39: 861437.27 | BN39: 2000059.5 | BO39: 1973304.6 | BP39: -4209322.8 | BQ39: 1627110.6 | BR39: =BR30-BR33 -> 6143104.7 | BS39: =BS30-BS33 -> 164771.02 | BT39: 4750823.3 | BU39: 1450674.3 | BV39: 4045024.1 | BW39: 7256658 | BX39: 6365539.8 | BY39: 1550999 | BZ39: 3753404.1 | CA39: 3273928.3 | CB39: 3174779.1 | CC39: 11090.64
A41: OTROS PRODUCTOS Y GASTOS | B41: 498163.82 | C41: 335694.24 | D41: 399417.54 | E41: 388356.8 | F41: 289282 | G41: 394289.54 | H41: 329208.41 | I41: 963261.33 | J41: 614190.89 | K41: 395623.85 | L41: 548393.4 | M41: 736196.05 | N41: 346549.79 | O41: 54334.11 | P41: 411270.74 | Q41: 271669.5 | R41: 310258.43 | S41: 498941.59 | T41: 318798.93 | U41: 527415.57 | V41: 314476.47 | W41: 249915.56 | X41: 524899.46 | Y41: 425850.77 | Z41: 199326.65 | AA41: 529815.76 | AB41: -7333.06 | AC41: 141074.49 | AD41: 342732.48 | AE41: 662251.03 | AF41: 359693.76 | AG41: 41436.03 | AH41: 843234.46 | AI41: 36715.99 | AJ41: 376935.21 | AK41: 776671.67 | AL41: 203007.75 | AM41: 329722.99 | AN41: 474465.9 | AO41: 213358.15 | AP41: 961361.17 | AQ41: 42465.64 | AR41: 460033.5 | AS41: 579382.14 | AT41: 228199.77 | AU41: 110408.12 | AV41: 235211.45 | AW41: 1020893.3 | AX41: 294199.89 | AY41: 261668.05 | AZ41: 80538.12 | BA41: -103651.16 | BB41: 25387.96 | BC41: 262696.95 | BD41: 228211.98 | BE41: 383694.48 | BF41: 339006.64 | BG41: 250236.89 | BH41: 700872.31 | BI41: 281115.65 | BJ41: 336190 | BK41: 50808.72 | BL41: 644509.96 | BM41: 407734.89 | BN41: 167822.87 | BO41: 164354.85 | BP41: 167541 | BQ41: 112902.04 | BR41: 138680 | BS41: 235782.93 | BT41: 170872.4 | BU41: -477604.95 | BV41: -1521705.8 | BW41: 460386.49 | BX41: 1021026 | BY41: 216952.06 | BZ41: 72726.35 | CA41: 382322.3 | CB41: 426705.8 | CC41: 90361.52
A42: Mas:
A43: Otros Productos | B43: 756598.98 | C43: 327136.63 | D43: 647825.23 | E43: 467217.98 | F43: 374218.38 | G43: 499327.69 | H43: 497476.31 | I43: 1032555.9 | J43: 734816.34 | K43: 451989.27 | L43: 724575.03 | M43: 827750.46 | N43: 450202.38 | O43: 392331.31 | P43: 505502.85 | Q43: 326695.16 | R43: 345594.46 | S43: 450723.33 | T43: 390806.52 | U43: 709851.9 | V43: 345482.36 | W43: 340685.08 | X43: 564015.49 | Y43: 539973.62 | Z43: 406159.83 | AA43: 490251.92 | AB43: 1065482.6 | AC43: 260842.1 | AD43: 336188.25 | AE43: 649026.07 | AF43: 416385.2 | AG43: 1713263.3 | AH43: 923631.72 | AI43: 262979.05 | AJ43: 495044.29 | AK43: 881338.6 | AL43: 353481.41 | AM43: 526045.04 | AN43: 575849.83 | AO43: 257462.92 | AP43: 979879.38 | AQ43: 77019.73 | AR43: 450003.54 | AS43: 654197.04 | AT43: 304395.34 | AU43: 432063.39 | AV43: 330501.05 | AW43: 1176100.3 | AX43: 451554.09 | AY43: 266254.95 | AZ43: 394778.38 | BA43: 235715 | BB43: 261227.12 | BC43: 309543.79 | BD43: 390321.79 | BE43: 521203.73 | BF43: 261330.68 | BG43: 363524.34 | BH43: 860360.57 | BI43: 362365.03 | BJ43: 574209.01 | BK43: 215087.22 | BL43: 738158.38 | BM43: 729482.31 | BN43: 220552.47 | BO43: 250953.25 | BP43: 271688.66 | BQ43: 199177.72 | BR43: 198037.41 | BS43: 327356.42 | BT43: 303654.25 | BU43: 115001.29 | BV43: 1029539.8 | BW43: 581480.86 | BX43: 1155984.6 | BY43: 339670.92 | BZ43: 270037.77 | CA43: 505385.4 | CB43: 474341.88 | CC43: 181083.28
A44: Menos
A45: Otros Gastos | B45: 258435.16 | C45: -8557.61 | D45: 248407.69 | E45: 78861.18 | F45: 84936.38 | G45: 105038.15 | H45: 168267.9 | I45: 69294.58 | J45: 120625.45 | K45: 56365.42 | L45: 176181.63 | M45: 91554.41 | N45: 103652.59 | O45: 337997.2 | P45: 94232.11 | Q45: 55025.66 | R45: 35336.03 | S45: -48218.26 | T45: 72007.59 | U45: 182436.33 | V45: 31005.89 | W45: 90769.52 | X45: 39116.03 | Y45: 114122.85 | Z45: 206833.18 | AA45: -39563.84 | AB45: 1072815.6 | AC45: 119767.61 | AD45: -6544.23 | AE45: -13224.96 | AF45: 56691.44 | AG45: 1671827.2 | AH45: 80397.26 | AI45: 226263.06 | AJ45: 118109.08 | AK45: 104666.93 | AL45: 150473.66 | AM45: 196322.05 | AN45: 101383.93 | AO45: 44104.77 | AP45: 18518.21 | AQ45: 34554.09 | AR45: -10029.96 | AS45: 74814.9 | AT45: 76195.57 | AU45: 321655.27 | AV45: 95289.6 | AW45: 155207.07 | AX45: 157354.2 | AY45: 4586.9 | AZ45: 314240.26 | BA45: 339366.16 | BB45: 235839.16 | BC45: 46846.84 | BD45: 162109.81 | BE45: 137509.25 | BF45: -77675.96 | BG45: 113287.45 | BH45: 159488.26 | BI45: 81249.38 | BJ45: 238019.01 | BK45: 164278.5 | BL45: 93648.42 | BM45: 321747.42 | BN45: 52729.6 | BO45: 86598.4 | BP45: 104147.66 | BQ45: 86275.68 | BR45: 59357.41 | BS45: 91573.49 | BT45: 132781.85 | BU45: 592606.24 | BV45: 2551245.7 | BW45: 121094.37 | BX45: 134958.53 | BY45: 122718.86 | BZ45: 197311.42 | CA45: 123063.1 | CB45: 47636.08 | CC45: 90721.76
A46: UTILIDAD (PERDIDA) NETA ANTES DE IMPUESTO | B46: 4992395 | C46: 3353136.7 | D46: 3648751.4 | E46: 5219085.7 | F46: 3652261.6 | G46: 6885047.1 | H46: 5394034.8 | I46: 6194564.2 | J46: -254344.89 | K46: 3212798.4 | L46: 2027050.2 | M46: 4804859.6 | N46: 4482994.8 | O46: 5905340 | P46: -215768.8 | Q46: 1653437.4 | R46: 667861.43 | S46: 1500225.3 | T46: 2694459.4 | U46: 4916089.8 | V46: 232712.03 | W46: 1202417.7 | X46: 1143755.2 | Y46: 759107.17 | Z46: 1506933 | AA46: 3652012 | AB46: 4933692.7 | AC46: 3471410.7 | AD46: 2120105.8 | AE46: 5958644.5 | AF46: 3670303.7 | AG46: 2239728.4 | AH46: 824187.78 | AI46: 2662749.5 | AJ46: -205417.97 | AK46: 7617053.9 | AL46: 6220267 | AM46: 4436940.4 | AN46: 2236456.2 | AO46: 7144977.3 | AP46: 4848648.2 | AQ46: 3014898.8 | AR46: 3709356.4 | AS46: 4426372.5 | AT46: 2578989.8 | AU46: 1863226.6 | AV46: 659442.76 | AW46: 9052101.2 | AX46: 3198540.3 | AY46: 1421814.9 | AZ46: -1039125.9 | BA46: 6903899.1 | BB46: 847447 | BC46: 4816679.5 | BD46: 1951118.8 | BE46: 5237945.8 | BF46: 530034.73 | BG46: 8906109.6 | BH46: -2308099.4 | BI46: -7917731.4 | BJ46: 3974713.6 | BK46: 1625559.3 | BL46: -312307.12 | BM46: 1269172.2 | BN46: 2167882.4 | BO46: 2137659.4 | BP46: -4041781.8 | BQ46: 1740012.6 | BR46: =BR39+BR41 -> 6281784.7 | BS46: =BS39+BS41 -> 400553.95 | BT46: 4921695.7 | BU46: 973069.39 | BV46: 2523318.3 | BW46: 7717044.5 | BX46: 7386565.8 | BY46: 1767951 | BZ46: 3826130.4 | CA46: 3656250.6 | CB46: 3601484.9 | CC46: 101452.16
A48: ISR | B48: 1181956 | C48: 734999.54 | D48: 784678.91 | E48: 1175543.1 | F48: 789597.08 | G48: 1597677.8 | H48: 1202674.5 | I48: 1405655.8 | J48: -172444.9 | K48: 641657.78 | L48: 361632.97 | M48: 1128827.1 | N48: 980189.68 | O48: 1411598 | P48: -193193.33 | Q48: 270229.01 | R48: 16142.41 | S48: 239121.74 | T48: 527562.56 | U48: 1109048 | V48: -59655.24 | W48: 157108.3 | X48: 162043.92 | Y48: 123076.13 | Z48: 284428.92 | AA48: 790717.73 | AB48: 1428346.6 | AC48: 751886.46 | AD48: 381323.42 | AE48: 1332422.4 | AF48: 788799.49 | AG48: 843181.19 | AH48: 81694.69 | AI48: 559567.89 | AJ48: -168422.31 | AK48: 1729168.2 | AL48: 1407275.1 | AM48: 999042.26 | AN48: 432440.61 | AO48: 1629564.1 | AP48: 1037435.7 | AQ48: 581279.1 | AR48: 744445.71 | AS48: 937280.27 | AT48: 497436.42 | AU48: 321922.97 | AV48: 59472.52 | AW48: 2080329.3 | AX48: 706272.21 | AY48: 140921.03 | AZ48: -379232.75 | BA48: 1591285 | BB48: 74655.8 | BC48: 980770.56 | BD48: 386636.08 | BE48: 1136526.6 | BF48: -82810.28 | BG48: 1994468.2 | BH48: -729735.31 | BI48: -2198778.9 | BJ48: 833439.02 | BK48: 255957.89 | BL48: -222292.52 | BM48: 187248.16 | BN48: 329821.95 | BO48: 378271.63 | BP48: -1207920.7 | BQ48: 243006.01 | BR48: 1282409.9 | BS48: -100279.44 | BT48: 1047259.4 | BU48: 174846.93 | BV48: 1047984.7 | BW48: 1719645.9 | BX48: 1599314.7 | BY48: 246319.31 | BZ48: 787674.13 | CA48: 707736.12 | CB48: 731996.74 | CC48: -211352.1
A50: Resultado despues de Impuesto | B50: 3810439 | C50: 2618137.2 | D50: 2864072.5 | E50: 4043542.6 | F50: 2862664.5 | G50: 5287369.3 | H50: 4191360.3 | I50: 4788908.4 | J50: -81899.99 | K50: 2571140.6 | L50: 1665417.2 | M50: 3676032.5 | N50: 3502805.1 | O50: 4493742 | P50: -22575.47 | Q50: 1383208.4 | R50: 651719.02 | S50: 1261103.6 | T50: 2166896.9 | U50: 3807041.8 | V50: 292367.27 | W50: 1045309.4 | X50: 981711.31 | Y50: 636031.04 | Z50: 1222504.1 | AA50: 2861294.2 | AB50: 3505346.1 | AC50: 2719524.2 | AD50: 1738782.4 | AE50: 4626222.1 | AF50: 2881504.2 | AG50: 1396547.2 | AH50: 742493.09 | AI50: 2103181.6 | AJ50: -36995.66 | AK50: 5887885.6 | AL50: 4812991.8 | AM50: 3437898.1 | AN50: 1804015.6 | AO50: 5515413.2 | AP50: 3811212.5 | AQ50: 2433619.7 | AR50: 2964910.7 | AS50: 3489092.3 | AT50: 2081553.4 | AU50: 1541303.6 | AV50: 599970.24 | AW50: 6971771.9 | AX50: 2492268.1 | AY50: 1280893.9 | AZ50: -659893.17 | BA50: 5312614.1 | BB50: 772791.2 | BC50: 3835908.9 | BD50: 1564482.7 | BE50: 4101419.2 | BF50: 612845.01 | BG50: 6911641.5 | BH50: -1578364 | BI50: -5718952.4 | BJ50: 3141274.6 | BK50: 1369601.4 | BL50: -90014.6 | BM50: 1081924 | BN50: 1838060.5 | BO50: 1759387.8 | BP50: -2833861.2 | BQ50: 1497006.6 | BR50: 4999374.8 | BS50: 500833.39 | BT50: 3874436.4 | BU50: 798222.46 | BV50: 1475333.6 | BW50: 5997398.6 | BX50: 5787251.1 | BY50: 1521631.7 | BZ50: 3038456.3 | CA50: 2948514.5 | CB50: 2869488.2 | CC50: 312804.26

Sheet Supuestos Proyeccion
A1: SUPUESTOS DE PROYECCIÓN – SEGUROS AGROMERCANTIL
A3: 1. PARÁMETROS GENERALES
A4: Crecimiento anual compuesto propio de Primas Netas (2020-2025) | B4: =(C42/SUMIFS('Informacion de Sam'!$5:$5,'Informacion de Sam'!$1:$1,">="&DATE($A$14,1,1),'Informacion de Sam'!$1:$1,"<="&DATE($A$14,12,31)))^(1/5)-1 -> 0.10590103
A5: Crecimiento del mercado (Total Primas Netas ene-ago 2026 vs ene-ago 2025) | B5: ='Mercado 2025 y 2026'!Y478/(SUM('Mercado 2025 y 2026'!B478:F478)+SUM('Mercado 2025 y 2026'!H478:J478))-1 -> 0.070818486
A6: Peso de la información propia (vs. mercado) | B6: 0.5
A7: Crecimiento anual combinado (referencia inicial – el crecimiento por año se define en la sección 4) | B7: =B6*B4+(1-B6)*B5 -> 0.08835976
A8: Tasa de ISR | B8: 0.25
A9: Último mes real disponible | B9: {=LOOKUP(2,1/('Informacion de Sam'!$B$5:$ZZ$5<>""),'Informacion de Sam'!$B$1:$ZZ$1)} -> 46235
A10: Inicio ventana histórica (últimos 24 meses) | B10: =EDATE(B9,-23) -> 45536
A12: 2. ESTACIONALIDAD (peso de cada mes en las Primas Netas del año)
A13: Año | B13: Ene | C13: Feb | D13: Mar | E13: Abr | F13: May | G13: Jun | H13: Jul | I13: Ago | J13: Sep | K13: Oct | L13: Nov | M13: Dic | N13: Total
A14: 2020 | B14: =SUMIFS('Informacion de Sam'!$5:$5,'Informacion de Sam'!$1:$1,DATE($A14,1,1))/SUMIFS('Informacion de Sam'!$5:$5,'Informacion de Sam'!$1:$1,">="&DATE($A14,1,1),'Informacion de Sam'!$1:$1,"<="&DATE($A14,12,31)) -> 0.073300355 | C14: =SUMIFS('Informacion de Sam'!$5:$5,'Informacion de Sam'!$1:$1,DATE($A14,2,1))/SUMIFS('Informacion de Sam'!$5:$5,'Informacion de Sam'!$1:$1,">="&DATE($A14,1,1),'Informacion de Sam'!$1:$1,"<="&DATE($A14,12,31)) -> 0.11066291 | D14: =SUMIFS('Informacion de Sam'!$5:$5,'Informacion de Sam'!$1:$1,DATE($A14,3,1))/SUMIFS('Informacion de Sam'!$5:$5,'Informacion de Sam'!$1:$1,">="&DATE($A14,1,1),'Informacion de Sam'!$1:$1,"<="&DATE($A14,12,31)) -> 0.071930184 | E14: =SUMIFS('Informacion de Sam'!$5:$5,'Informacion de Sam'!$1:$1,DATE($A14,4,1))/SUMIFS('Informacion de Sam'!$5:$5,'Informacion de Sam'!$1:$1,">="&DATE($A14,1,1),'Informacion de Sam'!$1:$1,"<="&DATE($A14,12,31)) -> 0.065435278 | F14: =SUMIFS('Informacion de Sam'!$5:$5,'Informacion de Sam'!$1:$1,DATE($A14,5,1))/SUMIFS('Informacion de Sam'!$5:$5,'Informacion de Sam'!$1:$1,">="&DATE($A14,1,1),'Informacion de Sam'!$1:$1,"<="&DATE($A14,12,31)) -> 0.068177642 | G14: =SUMIFS('Informacion de Sam'!$5:$5,'Informacion de Sam'!$1:$1,DATE($A14,6,1))/SUMIFS('Informacion de Sam'!$5:$5,'Informacion de Sam'!$1:$1,">="&DATE($A14,1,1),'Informacion de Sam'!$1:$1,"<="&DATE($A14,12,31)) -> 0.073462484 | H14: =SUMIFS('Informacion de Sam'!$5:$5,'Informacion de Sam'!$1:$1,DATE($A14,7,1))/SUMIFS('Informacion de Sam'!$5:$5,'Informacion de Sam'!$1:$1,">="&DATE($A14,1,1),'Informacion de Sam'!$1:$1,"<="&DATE($A14,12,31)) -> 0.071328277 | I14: =SUMIFS('Informacion de Sam'!$5:$5,'Informacion de Sam'!$1:$1,DATE($A14,8,1))/SUMIFS('Informacion de Sam'!$5:$5,'Informacion de Sam'!$1:$1,">="&DATE($A14,1,1),'Informacion de Sam'!$1:$1,"<="&DATE($A14,12,31)) -> 0.15448066 | J14: =SUMIFS('Informacion de Sam'!$5:$5,'Informacion de Sam'!$1:$1,DATE($A14,9,1))/SUMIFS('Informacion de Sam'!$5:$5,'Informacion de Sam'!$1:$1,">="&DATE($A14,1,1),'Informacion de Sam'!$1:$1,"<="&DATE($A14,12,31)) -> 0.074648007 | K14: =SUMIFS('Informacion de Sam'!$5:$5,'Informacion de Sam'!$1:$1,DATE($A14,10,1))/SUMIFS('Informacion de Sam'!$5:$5,'Informacion de Sam'!$1:$1,">="&DATE($A14,1,1),'Informacion de Sam'!$1:$1,"<="&DATE($A14,12,31)) -> 0.073722041 | L14: =SUMIFS('Informacion de Sam'!$5:$5,'Informacion de Sam'!$1:$1,DATE($A14,11,1))/SUMIFS('Informacion de Sam'!$5:$5,'Informacion de Sam'!$1:$1,">="&DATE($A14,1,1),'Informacion de Sam'!$1:$1,"<="&DATE($A14,12,31)) -> 0.07196753 | M14: =SUMIFS('Informacion de Sam'!$5:$5,'Informacion de Sam'!$1:$1,DATE($A14,12,1))/SUMIFS('Informacion de Sam'!$5:$5,'Informacion de Sam'!$1:$1,">="&DATE($A14,1,1),'Informacion de Sam'!$1:$1,"<="&DATE($A14,12,31)) -> 0.090884632 | N14: =SUM(B14:M14) -> 1
A15: 2021 | B15: =SUMIFS('Informacion de Sam'!$5:$5,'Informacion de Sam'!$1:$1,DATE($A15,1,1))/SUMIFS('Informacion de Sam'!$5:$5,'Informacion de Sam'!$1:$1,">="&DATE($A15,1,1),'Informacion de Sam'!$1:$1,"<="&DATE($A15,12,31)) -> 0.057443245 | C15: =SUMIFS('Informacion de Sam'!$5:$5,'Informacion de Sam'!$1:$1,DATE($A15,2,1))/SUMIFS('Informacion de Sam'!$5:$5,'Informacion de Sam'!$1:$1,">="&DATE($A15,1,1),'Informacion de Sam'!$1:$1,"<="&DATE($A15,12,31)) -> 0.08850465 | D15: =SUMIFS('Informacion de Sam'!$5:$5,'Informacion de Sam'!$1:$1,DATE($A15,3,1))/SUMIFS('Informacion de Sam'!$5:$5,'Informacion de Sam'!$1:$1,">="&DATE($A15,1,1),'Informacion de Sam'!$1:$1,"<="&DATE($A15,12,31)) -> 0.094853585 | E15: =SUMIFS('Informacion de Sam'!$5:$5,'Informacion de Sam'!$1:$1,DATE($A15,4,1))/SUMIFS('Informacion de Sam'!$5:$5,'Informacion de Sam'!$1:$1,">="&DATE($A15,1,1),'Informacion de Sam'!$1:$1,"<="&DATE($A15,12,31)) -> 0.075846872 | F15: =SUMIFS('Informacion de Sam'!$5:$5,'Informacion de Sam'!$1:$1,DATE($A15,5,1))/SUMIFS('Informacion de Sam'!$5:$5,'Informacion de Sam'!$1:$1,">="&DATE($A15,1,1),'Informacion de Sam'!$1:$1,"<="&DATE($A15,12,31)) -> 0.064658056 | G15: =SUMIFS('Informacion de Sam'!$5:$5,'Informacion de Sam'!$1:$1,DATE($A15,6,1))/SUMIFS('Informacion de Sam'!$5:$5,'Informacion de Sam'!$1:$1,">="&DATE($A15,1,1),'Informacion de Sam'!$1:$1,"<="&DATE($A15,12,31)) -> 0.082888811 | H15: =SUMIFS('Informacion de Sam'!$5:$5,'Informacion de Sam'!$1:$1,DATE($A15,7,1))/SUMIFS('Informacion de Sam'!$5:$5,'Informacion de Sam'!$1:$1,">="&DATE($A15,1,1),'Informacion de Sam'!$1:$1,"<="&DATE($A15,12,31)) -> 0.072137429 | I15: =SUMIFS('Informacion de Sam'!$5:$5,'Informacion de Sam'!$1:$1,DATE($A15,8,1))/SUMIFS('Informacion de Sam'!$5:$5,'Informacion de Sam'!$1:$1,">="&DATE($A15,1,1),'Informacion de Sam'!$1:$1,"<="&DATE($A15,12,31)) -> 0.15912366 | J15: =SUMIFS('Informacion de Sam'!$5:$5,'Informacion de Sam'!$1:$1,DATE($A15,9,1))/SUMIFS('Informacion de Sam'!$5:$5,'Informacion de Sam'!$1:$1,">="&DATE($A15,1,1),'Informacion de Sam'!$1:$1,"<="&DATE($A15,12,31)) -> 0.07630352 | K15: =SUMIFS('Informacion de Sam'!$5:$5,'Informacion de Sam'!$1:$1,DATE($A15,10,1))/SUMIFS('Informacion de Sam'!$5:$5,'Informacion de Sam'!$1:$1,">="&DATE($A15,1,1),'Informacion de Sam'!$1:$1,"<="&DATE($A15,12,31)) -> 0.071949574 | L15: =SUMIFS('Informacion de Sam'!$5:$5,'Informacion de Sam'!$1:$1,DATE($A15,11,1))/SUMIFS('Informacion de Sam'!$5:$5,'Informacion de Sam'!$1:$1,">="&DATE($A15,1,1),'Informacion de Sam'!$1:$1,"<="&DATE($A15,12,31)) -> 0.075962335 | M15: =SUMIFS('Informacion de Sam'!$5:$5,'Informacion de Sam'!$1:$1,DATE($A15,12,1))/SUMIFS('Informacion de Sam'!$5:$5,'Informacion de Sam'!$1:$1,">="&DATE($A15,1,1),'Informacion de Sam'!$1:$1,"<="&DATE($A15,12,31)) -> 0.080328257 | N15: =SUM(B15:M15) -> 1
A16: 2022 | B16: =SUMIFS('Informacion de Sam'!$5:$5,'Informacion de Sam'!$1:$1,DATE($A16,1,1))/SUMIFS('Informacion de Sam'!$5:$5,'Informacion de Sam'!$1:$1,">="&DATE($A16,1,1),'Informacion de Sam'!$1:$1,"<="&DATE($A16,12,31)) -> 0.061251892 | C16: =SUMIFS('Informacion de Sam'!$5:$5,'Informacion de Sam'!$1:$1,DATE($A16,2,1))/SUMIFS('Informacion de Sam'!$5:$5,'Informacion de Sam'!$1:$1,">="&DATE($A16,1,1),'Informacion de Sam'!$1:$1,"<="&DATE($A16,12,31)) -> 0.10986403 | D16: =SUMIFS('Informacion de Sam'!$5:$5,'Informacion de Sam'!$1:$1,DATE($A16,3,1))/SUMIFS('Informacion de Sam'!$5:$5,'Informacion de Sam'!$1:$1,">="&DATE($A16,1,1),'Informacion de Sam'!$1:$1,"<="&DATE($A16,12,31)) -> 0.068429019 | E16: =SUMIFS('Informacion de Sam'!$5:$5,'Informacion de Sam'!$1:$1,DATE($A16,4,1))/SUMIFS('Informacion de Sam'!$5:$5,'Informacion de Sam'!$1:$1,">="&DATE($A16,1,1),'Informacion de Sam'!$1:$1,"<="&DATE($A16,12,31)) -> 0.070609038 | F16: =SUMIFS('Informacion de Sam'!$5:$5,'Informacion de Sam'!$1:$1,DATE($A16,5,1))/SUMIFS('Informacion de Sam'!$5:$5,'Informacion de Sam'!$1:$1,">="&DATE($A16,1,1),'Informacion de Sam'!$1:$1,"<="&DATE($A16,12,31)) -> 0.070394827 | G16: =SUMIFS('Informacion de Sam'!$5:$5,'Informacion de Sam'!$1:$1,DATE($A16,6,1))/SUMIFS('Informacion de Sam'!$5:$5,'Informacion de Sam'!$1:$1,">="&DATE($A16,1,1),'Informacion de Sam'!$1:$1,"<="&DATE($A16,12,31)) -> 0.084187177 | H16: =SUMIFS('Informacion de Sam'!$5:$5,'Informacion de Sam'!$1:$1,DATE($A16,7,1))/SUMIFS('Informacion de Sam'!$5:$5,'Informacion de Sam'!$1:$1,">="&DATE($A16,1,1),'Informacion de Sam'!$1:$1,"<="&DATE($A16,12,31)) -> 0.14122614 | I16: =SUMIFS('Informacion de Sam'!$5:$5,'Informacion de Sam'!$1:$1,DATE($A16,8,1))/SUMIFS('Informacion de Sam'!$5:$5,'Informacion de Sam'!$1:$1,">="&DATE($A16,1,1),'Informacion de Sam'!$1:$1,"<="&DATE($A16,12,31)) -> 0.083667506 | J16: =SUMIFS('Informacion de Sam'!$5:$5,'Informacion de Sam'!$1:$1,DATE($A16,9,1))/SUMIFS('Informacion de Sam'!$5:$5,'Informacion de Sam'!$1:$1,">="&DATE($A16,1,1),'Informacion de Sam'!$1:$1,"<="&DATE($A16,12,31)) -> 0.091704658 | K16: =SUMIFS('Informacion de Sam'!$5:$5,'Informacion de Sam'!$1:$1,DATE($A16,10,1))/SUMIFS('Informacion de Sam'!$5:$5,'Informacion de Sam'!$1:$1,">="&DATE($A16,1,1),'Informacion de Sam'!$1:$1,"<="&DATE($A16,12,31)) -> 0.079585154 | L16: =SUMIFS('Informacion de Sam'!$5:$5,'Informacion de Sam'!$1:$1,DATE($A16,11,1))/SUMIFS('Informacion de Sam'!$5:$5,'Informacion de Sam'!$1:$1,">="&DATE($A16,1,1),'Informacion de Sam'!$1:$1,"<="&DATE($A16,12,31)) -> 0.073789148 | M16: =SUMIFS('Informacion de Sam'!$5:$5,'Informacion de Sam'!$1:$1,DATE($A16,12,1))/SUMIFS('Informacion de Sam'!$5:$5,'Informacion de Sam'!$1:$1,">="&DATE($A16,1,1),'Informacion de Sam'!$1:$1,"<="&DATE($A16,12,31)) -> 0.065291407 | N16: =SUM(B16:M16) -> 1
A17: 2023 | B17: =SUMIFS('Informacion de Sam'!$5:$5,'Informacion de Sam'!$1:$1,DATE($A17,1,1))/SUMIFS('Informacion de Sam'!$5:$5,'Informacion de Sam'!$1:$1,">="&DATE($A17,1,1),'Informacion de Sam'!$1:$1,"<="&DATE($A17,12,31)) -> 0.079003338 | C17: =SUMIFS('Informacion de Sam'!$5:$5,'Informacion de Sam'!$1:$1,DATE($A17,2,1))/SUMIFS('Informacion de Sam'!$5:$5,'Informacion de Sam'!$1:$1,">="&DATE($A17,1,1),'Informacion de Sam'!$1:$1,"<="&DATE($A17,12,31)) -> 0.10582212 | D17: =SUMIFS('Informacion de Sam'!$5:$5,'Informacion de Sam'!$1:$1,DATE($A17,3,1))/SUMIFS('Informacion de Sam'!$5:$5,'Informacion de Sam'!$1:$1,">="&DATE($A17,1,1),'Informacion de Sam'!$1:$1,"<="&DATE($A17,12,31)) -> 0.074103897 | E17: =SUMIFS('Informacion de Sam'!$5:$5,'Informacion de Sam'!$1:$1,DATE($A17,4,1))/SUMIFS('Informacion de Sam'!$5:$5,'Informacion de Sam'!$1:$1,">="&DATE($A17,1,1),'Informacion de Sam'!$1:$1,"<="&DATE($A17,12,31)) -> 0.093887683 | F17: =SUMIFS('Informacion de Sam'!$5:$5,'Informacion de Sam'!$1:$1,DATE($A17,5,1))/SUMIFS('Informacion de Sam'!$5:$5,'Informacion de Sam'!$1:$1,">="&DATE($A17,1,1),'Informacion de Sam'!$1:$1,"<="&DATE($A17,12,31)) -> 0.071344353 | G17: =SUMIFS('Informacion de Sam'!$5:$5,'Informacion de Sam'!$1:$1,DATE($A17,6,1))/SUMIFS('Informacion de Sam'!$5:$5,'Informacion de Sam'!$1:$1,">="&DATE($A17,1,1),'Informacion de Sam'!$1:$1,"<="&DATE($A17,12,31)) -> 0.074607575 | H17: =SUMIFS('Informacion de Sam'!$5:$5,'Informacion de Sam'!$1:$1,DATE($A17,7,1))/SUMIFS('Informacion de Sam'!$5:$5,'Informacion de Sam'!$1:$1,">="&DATE($A17,1,1),'Informacion de Sam'!$1:$1,"<="&DATE($A17,12,31)) -> 0.066056317 | I17: =SUMIFS('Informacion de Sam'!$5:$5,'Informacion de Sam'!$1:$1,DATE($A17,8,1))/SUMIFS('Informacion de Sam'!$5:$5,'Informacion de Sam'!$1:$1,">="&DATE($A17,1,1),'Informacion de Sam'!$1:$1,"<="&DATE($A17,12,31)) -> 0.13350024 | J17: =SUMIFS('Informacion de Sam'!$5:$5,'Informacion de Sam'!$1:$1,DATE($A17,9,1))/SUMIFS('Informacion de Sam'!$5:$5,'Informacion de Sam'!$1:$1,">="&DATE($A17,1,1),'Informacion de Sam'!$1:$1,"<="&DATE($A17,12,31)) -> 0.069594782 | K17: =SUMIFS('Informacion de Sam'!$5:$5,'Informacion de Sam'!$1:$1,DATE($A17,10,1))/SUMIFS('Informacion de Sam'!$5:$5,'Informacion de Sam'!$1:$1,">="&DATE($A17,1,1),'Informacion de Sam'!$1:$1,"<="&DATE($A17,12,31)) -> 0.067763996 | L17: =SUMIFS('Informacion de Sam'!$5:$5,'Informacion de Sam'!$1:$1,DATE($A17,11,1))/SUMIFS('Informacion de Sam'!$5:$5,'Informacion de Sam'!$1:$1,">="&DATE($A17,1,1),'Informacion de Sam'!$1:$1,"<="&DATE($A17,12,31)) -> 0.085018008 | M17: =SUMIFS('Informacion de Sam'!$5:$5,'Informacion de Sam'!$1:$1,DATE($A17,12,1))/SUMIFS('Informacion de Sam'!$5:$5,'Informacion de Sam'!$1:$1,">="&DATE($A17,1,1),'Informacion de Sam'!$1:$1,"<="&DATE($A17,12,31)) -> 0.079297697 | N17: =SUM(B17:M17) -> 1
A18: 2024 | B18: =SUMIFS('Informacion de Sam'!$5:$5,'Informacion de Sam'!$1:$1,DATE($A18,1,1))/SUMIFS('Informacion de Sam'!$5:$5,'Informacion de Sam'!$1:$1,">="&DATE($A18,1,1),'Informacion de Sam'!$1:$1,"<="&DATE($A18,12,31)) -> 0.073507058 | C18: =SUMIFS('Informacion de Sam'!$5:$5,'Informacion de Sam'!$1:$1,DATE($A18,2,1))/SUMIFS('Informacion de Sam'!$5:$5,'Informacion de Sam'!$1:$1,">="&DATE($A18,1,1),'Informacion de Sam'!$1:$1,"<="&DATE($A18,12,31)) -> 0.10958573 | D18: =SUMIFS('Informacion de Sam'!$5:$5,'Informacion de Sam'!$1:$1,DATE($A18,3,1))/SUMIFS('Informacion de Sam'!$5:$5,'Informacion de Sam'!$1:$1,">="&DATE($A18,1,1),'Informacion de Sam'!$1:$1,"<="&DATE($A18,12,31)) -> 0.0662983 | E18: =SUMIFS('Informacion de Sam'!$5:$5,'Informacion de Sam'!$1:$1,DATE($A18,4,1))/SUMIFS('Informacion de Sam'!$5:$5,'Informacion de Sam'!$1:$1,">="&DATE($A18,1,1),'Informacion de Sam'!$1:$1,"<="&DATE($A18,12,31)) -> 0.084739312 | F18: =SUMIFS('Informacion de Sam'!$5:$5,'Informacion de Sam'!$1:$1,DATE($A18,5,1))/SUMIFS('Informacion de Sam'!$5:$5,'Informacion de Sam'!$1:$1,">="&DATE($A18,1,1),'Informacion de Sam'!$1:$1,"<="&DATE($A18,12,31)) -> 0.064915326 | G18: =SUMIFS('Informacion de Sam'!$5:$5,'Informacion de Sam'!$1:$1,DATE($A18,6,1))/SUMIFS('Informacion de Sam'!$5:$5,'Informacion de Sam'!$1:$1,">="&DATE($A18,1,1),'Informacion de Sam'!$1:$1,"<="&DATE($A18,12,31)) -> 0.07493544 | H18: =SUMIFS('Informacion de Sam'!$5:$5,'Informacion de Sam'!$1:$1,DATE($A18,7,1))/SUMIFS('Informacion de Sam'!$5:$5,'Informacion de Sam'!$1:$1,">="&DATE($A18,1,1),'Informacion de Sam'!$1:$1,"<="&DATE($A18,12,31)) -> 0.073185626 | I18: =SUMIFS('Informacion de Sam'!$5:$5,'Informacion de Sam'!$1:$1,DATE($A18,8,1))/SUMIFS('Informacion de Sam'!$5:$5,'Informacion de Sam'!$1:$1,">="&DATE($A18,1,1),'Informacion de Sam'!$1:$1,"<="&DATE($A18,12,31)) -> 0.15031494 | J18: =SUMIFS('Informacion de Sam'!$5:$5,'Informacion de Sam'!$1:$1,DATE($A18,9,1))/SUMIFS('Informacion de Sam'!$5:$5,'Informacion de Sam'!$1:$1,">="&DATE($A18,1,1),'Informacion de Sam'!$1:$1,"<="&DATE($A18,12,31)) -> 0.069759422 | K18: =SUMIFS('Informacion de Sam'!$5:$5,'Informacion de Sam'!$1:$1,DATE($A18,10,1))/SUMIFS('Informacion de Sam'!$5:$5,'Informacion de Sam'!$1:$1,">="&DATE($A18,1,1),'Informacion de Sam'!$1:$1,"<="&DATE($A18,12,31)) -> 0.086276532 | L18: =SUMIFS('Informacion de Sam'!$5:$5,'Informacion de Sam'!$1:$1,DATE($A18,11,1))/SUMIFS('Informacion de Sam'!$5:$5,'Informacion de Sam'!$1:$1,">="&DATE($A18,1,1),'Informacion de Sam'!$1:$1,"<="&DATE($A18,12,31)) -> 0.088851053 | M18: =SUMIFS('Informacion de Sam'!$5:$5,'Informacion de Sam'!$1:$1,DATE($A18,12,1))/SUMIFS('Informacion de Sam'!$5:$5,'Informacion de Sam'!$1:$1,">="&DATE($A18,1,1),'Informacion de Sam'!$1:$1,"<="&DATE($A18,12,31)) -> 0.057631257 | N18: =SUM(B18:M18) -> 1
A19: 2025 | B19: =SUMIFS('Informacion de Sam'!$5:$5,'Informacion de Sam'!$1:$1,DATE($A19,1,1))/SUMIFS('Informacion de Sam'!$5:$5,'Informacion de Sam'!$1:$1,">="&DATE($A19,1,1),'Informacion de Sam'!$1:$1,"<="&DATE($A19,12,31)) -> 0.10692534 | C19: =SUMIFS('Informacion de Sam'!$5:$5,'Informacion de Sam'!$1:$1,DATE($A19,2,1))/SUMIFS('Informacion de Sam'!$5:$5,'Informacion de Sam'!$1:$1,">="&DATE($A19,1,1),'Informacion de Sam'!$1:$1,"<="&DATE($A19,12,31)) -> 0.11547491 | D19: =SUMIFS('Informacion de Sam'!$5:$5,'Informacion de Sam'!$1:$1,DATE($A19,3,1))/SUMIFS('Informacion de Sam'!$5:$5,'Informacion de Sam'!$1:$1,">="&DATE($A19,1,1),'Informacion de Sam'!$1:$1,"<="&DATE($A19,12,31)) -> 0.083632293 | E19: =SUMIFS('Informacion de Sam'!$5:$5,'Informacion de Sam'!$1:$1,DATE($A19,4,1))/SUMIFS('Informacion de Sam'!$5:$5,'Informacion de Sam'!$1:$1,">="&DATE($A19,1,1),'Informacion de Sam'!$1:$1,"<="&DATE($A19,12,31)) -> 0.079302877 | F19: =SUMIFS('Informacion de Sam'!$5:$5,'Informacion de Sam'!$1:$1,DATE($A19,5,1))/SUMIFS('Informacion de Sam'!$5:$5,'Informacion de Sam'!$1:$1,">="&DATE($A19,1,1),'Informacion de Sam'!$1:$1,"<="&DATE($A19,12,31)) -> 0.073868755 | G19: =SUMIFS('Informacion de Sam'!$5:$5,'Informacion de Sam'!$1:$1,DATE($A19,6,1))/SUMIFS('Informacion de Sam'!$5:$5,'Informacion de Sam'!$1:$1,">="&DATE($A19,1,1),'Informacion de Sam'!$1:$1,"<="&DATE($A19,12,31)) -> 0.082640554 | H19: =SUMIFS('Informacion de Sam'!$5:$5,'Informacion de Sam'!$1:$1,DATE($A19,7,1))/SUMIFS('Informacion de Sam'!$5:$5,'Informacion de Sam'!$1:$1,">="&DATE($A19,1,1),'Informacion de Sam'!$1:$1,"<="&DATE($A19,12,31)) -> 0.08632825 | I19: =SUMIFS('Informacion de Sam'!$5:$5,'Informacion de Sam'!$1:$1,DATE($A19,8,1))/SUMIFS('Informacion de Sam'!$5:$5,'Informacion de Sam'!$1:$1,">="&DATE($A19,1,1),'Informacion de Sam'!$1:$1,"<="&DATE($A19,12,31)) -> 0.085682161 | J19: =SUMIFS('Informacion de Sam'!$5:$5,'Informacion de Sam'!$1:$1,DATE($A19,9,1))/SUMIFS('Informacion de Sam'!$5:$5,'Informacion de Sam'!$1:$1,">="&DATE($A19,1,1),'Informacion de Sam'!$1:$1,"<="&DATE($A19,12,31)) -> 0.085985506 | K19: =SUMIFS('Informacion de Sam'!$5:$5,'Informacion de Sam'!$1:$1,DATE($A19,10,1))/SUMIFS('Informacion de Sam'!$5:$5,'Informacion de Sam'!$1:$1,">="&DATE($A19,1,1),'Informacion de Sam'!$1:$1,"<="&DATE($A19,12,31)) -> 0.072477226 | L19: =SUMIFS('Informacion de Sam'!$5:$5,'Informacion de Sam'!$1:$1,DATE($A19,11,1))/SUMIFS('Informacion de Sam'!$5:$5,'Informacion de Sam'!$1:$1,">="&DATE($A19,1,1),'Informacion de Sam'!$1:$1,"<="&DATE($A19,12,31)) -> 0.070090003 | M19: =SUMIFS('Informacion de Sam'!$5:$5,'Informacion de Sam'!$1:$1,DATE($A19,12,1))/SUMIFS('Informacion de Sam'!$5:$5,'Informacion de Sam'!$1:$1,">="&DATE($A19,1,1),'Informacion de Sam'!$1:$1,"<="&DATE($A19,12,31)) -> 0.057592128 | N19: =SUM(B19:M19) -> 1
A20: Peso promedio utilizado | B20: =AVERAGE(B14:B19) -> 0.075238537 | C20: =AVERAGE(C14:C19) -> 0.10665239 | D20: =AVERAGE(D14:D19) -> 0.076541213 | E20: =AVERAGE(E14:E19) -> 0.07830351 | F20: =AVERAGE(F14:F19) -> 0.06889316 | G20: =AVERAGE(G14:G19) -> 0.078787007 | H20: =AVERAGE(H14:H19) -> 0.085043673 | I20: =AVERAGE(I14:I19) -> 0.12779486 | ... M20: =AVERAGE(M14:M19) -> 0.071837563 | N20: =SUM(B20:M20) -> 1
A22: 3. RUBROS COMO % DE SU BASE (punto medio propio / mercado)
A23: Rubro | B23: Base | C23: % Propio (últimos 24 meses) | D23: % Mercado (2025 + ene-ago 2026) | E23: Peso propio | F23: % Utilizado
A24: Devoluciones y Cancelaciones | B24: % de Primas Brutas | C24: =SUMIFS('Informacion de Sam'!$3:$3,'Informacion de Sam'!$1:$1,">="&$B$10,'Informacion de Sam'!$1:$1,"<="&$B$9)/SUMIFS('Informacion de Sam'!$2:$2,'Informacion de Sam'!$1:$1,">="&$B$10,'Informacion de Sam'!$1:$1,"<="&$B$9) -> 0.12367788 | D24: =('Mercado 2025 y 2026'!$O$471+'Mercado 2025 y 2026'!$Y$471+'Mercado 2025 y 2026'!$O$477+'Mercado 2025 y 2026'!$Y$477)/('Mercado 2025 y 2026'!$O$470+'Mercado 2025 y 2026'!$Y$470+'Mercado 2025 y 2026'!$O$475+'Mercado 2025 y 2026'!$Y$475+'Mercado 2025 y 2026'!$O$476+'Mercado 2025 y 2026'!$Y$476) -> 0.12399375 | E24: =$B$6 -> 0.5 | F24: =E24*C24+(1-E24)*D24 -> 0.12383582
A25: Primas por Reaseguro Cedido | B25: % de Primas Netas (comportamiento 2026) | C25: =SUMIFS('Informacion de Sam'!$7:$7,'Informacion de Sam'!$1:$1,">="&DATE(YEAR($B$9),1,1),'Informacion de Sam'!$1:$1,"<="&$B$9)/SUMIFS('Informacion de Sam'!$5:$5,'Informacion de Sam'!$1:$1,">="&DATE(YEAR($B$9),1,1),'Informacion de Sam'!$1:$1,"<="&$B$9) -> 0.4295315 | D25: =('Mercado 2025 y 2026'!$O$480+'Mercado 2025 y 2026'!$Y$480)/('Mercado 2025 y 2026'!$O$478+'Mercado 2025 y 2026'!$Y$478) -> 0.36307519 | E25: 1 | F25: =E25*C25+(1-E25)*D25 -> 0.4295315
A26: Variaciones en Reservas Técnicas (neto) | B26: Factor sobre el aumento de Primas Netas de Retención vs mismo mes año anterior | C26: =SUMIFS('Informacion de Sam'!$13:$13,'Informacion de Sam'!$1:$1,">="&DATE(2021,1,1),'Informacion de Sam'!$1:$1,"<="&DATE(2025,12,31))/(SUMIFS('Informacion de Sam'!$9:$9,'Informacion de Sam'!$1:$1,">="&DATE(2025,1,1),'Informacion de Sam'!$1:$1,"<="&DATE(2025,12,31))-SUMIFS('Informacion de Sam'!$9:$9,'Informacion de Sam'!$1:$1,">="&DATE(2020,1,1),'Informacion de Sam'!$1:$1,"<="&DATE(2020,12,31))) -> 0.54691746 | D26: ='Mercado 2025 y 2026'!Y484/('Mercado 2025 y 2026'!Y482-(SUM('Mercado 2025 y 2026'!B482:F482)+SUM('Mercado 2025 y 2026'!H482:J482))) -> 0.42006915 | E26: =$B$6 -> 0.5 | F26: =E26*C26+(1-E26)*D26 -> 0.4834933
A27: Gastos de Adquisición y Renovación | B27: % de Primas Netas | C27: =SUMIFS('Informacion de Sam'!$19:$19,'Informacion de Sam'!$1:$1,">="&$B$10,'Informacion de Sam'!$1:$1,"<="&$B$9)/SUMIFS('Informacion de Sam'!$5:$5,'Informacion de Sam'!$1:$1,">="&$B$10,'Informacion de Sam'!$1:$1,"<="&$B$9) -> 0.0946248 | D27: =('Mercado 2025 y 2026'!$O$491+'Mercado 2025 y 2026'!$Y$491)/('Mercado 2025 y 2026'!$O$478+'Mercado 2025 y 2026'!$Y$478) -> 0.16559489 | E27: 1 | F27: =E27*C27+(1-E27)*D27 -> 0.0946248
A28: Comisiones y Participaciones por Reaseguro Cedido | B28: % de Primas Cedidas | C28: =SUMIFS('Informacion de Sam'!$21:$21,'Informacion de Sam'!$1:$1,">="&$B$10,'Informacion de Sam'!$1:$1,"<="&$B$9)/SUMIFS('Informacion de Sam'!$7:$7,'Informacion de Sam'!$1:$1,">="&$B$10,'Informacion de Sam'!$1:$1,"<="&$B$9) -> 0.21566433 | D28: =('Mercado 2025 y 2026'!$O$492+'Mercado 2025 y 2026'!$Y$492)/('Mercado 2025 y 2026'!$O$480+'Mercado 2025 y 2026'!$Y$480) -> 0.14931228 | E28: =$B$6 -> 0.5 | F28: =E28*C28+(1-E28)*D28 -> 0.18248831
A29: Gastos por Obligaciones Contractuales | B29: % de Primas Netas | C29: =SUMIFS('Informacion de Sam'!$24:$24,'Informacion de Sam'!$1:$1,">="&$B$10,'Informacion de Sam'!$1:$1,"<="&$B$9)/SUMIFS('Informacion de Sam'!$5:$5,'Informacion de Sam'!$1:$1,">="&$B$10,'Informacion de Sam'!$1:$1,"<="&$B$9) -> 0.39428005 | D29: =('Mercado 2025 y 2026'!$O$494+'Mercado 2025 y 2026'!$Y$494)/('Mercado 2025 y 2026'!$O$478+'Mercado 2025 y 2026'!$Y$478) -> 0.43996318 | E29: =$B$6 -> 0.5 | F29: =E29*C29+(1-E29)*D29 -> 0.41712161
A30: Participación de reaseguradoras en salvamentos | B30: % de Primas Netas | C30: =SUMIFS('Informacion de Sam'!$25:$25,'Informacion de Sam'!$1:$1,">="&$B$10,'Informacion de Sam'!$1:$1,"<="&$B$9)/SUMIFS('Informacion de Sam'!$5:$5,'Informacion de Sam'!$1:$1,">="&$B$10,'Informacion de Sam'!$1:$1,"<="&$B$9) -> 6.4241881e-05 | D30: =('Mercado 2025 y 2026'!$O$495+'Mercado 2025 y 2026'!$Y$495)/('Mercado 2025 y 2026'!$O$478+'Mercado 2025 y 2026'!$Y$478) -> 0.00083898111 | E30: =$B$6 -> 0.5 | F30: =E30*C30+(1-E30)*D30 -> 0.00045161149
A31: Recuperaciones por Reaseguro Cedido | B31: % de Gastos por Oblig. Contractuales | C31: =SUMIFS('Informacion de Sam'!$27:$27,'Informacion de Sam'!$1:$1,">="&$B$10,'Informacion de Sam'!$1:$1,"<="&$B$9)/SUMIFS('Informacion de Sam'!$24:$24,'Informacion de Sam'!$1:$1,">="&$B$10,'Informacion de Sam'!$1:$1,"<="&$B$9) -> 0.26334387 | D31: =('Mercado 2025 y 2026'!$O$497+'Mercado 2025 y 2026'!$Y$497)/('Mercado 2025 y 2026'!$O$494+'Mercado 2025 y 2026'!$Y$494) -> 0.21897031 | E31: =$B$6 -> 0.5 | F31: =E31*C31+(1-E31)*D31 -> 0.24115709
A32: Salvamento y recuperaciones | B32: % de Gastos por Oblig. Contractuales | C32: =SUMIFS('Informacion de Sam'!$28:$28,'Informacion de Sam'!$1:$1,">="&$B$10,'Informacion de Sam'!$1:$1,"<="&$B$9)/SUMIFS('Informacion de Sam'!$24:$24,'Informacion de Sam'!$1:$1,">="&$B$10,'Informacion de Sam'!$1:$1,"<="&$B$9) -> 0.028320529 | D32: =('Mercado 2025 y 2026'!$O$498+'Mercado 2025 y 2026'!$Y$498)/('Mercado 2025 y 2026'!$O$494+'Mercado 2025 y 2026'!$Y$494) -> 0.042040814 | E32: =$B$6 -> 0.5 | F32: =E32*C32+(1-E32)*D32 -> 0.035180672
A33: Egresos por Inversiones | B33: % de Primas Netas | C33: =SUMIFS('Informacion de Sam'!$34:$34,'Informacion de Sam'!$1:$1,">="&$B$10,'Informacion de Sam'!$1:$1,"<="&$B$9)/SUMIFS('Informacion de Sam'!$5:$5,'Informacion de Sam'!$1:$1,">="&$B$10,'Informacion de Sam'!$1:$1,"<="&$B$9) -> 0.0010717989 | D33: =('Mercado 2025 y 2026'!$O$502+'Mercado 2025 y 2026'!$Y$502)/('Mercado 2025 y 2026'!$O$478+'Mercado 2025 y 2026'!$Y$478) -> 0.0033822633 | E33: =$B$6 -> 0.5 | F33: =E33*C33+(1-E33)*D33 -> 0.0022270311
A34: Gastos de Administración | B34: % de Primas Netas | C34: =SUMIFS('Informacion de Sam'!$35:$35,'Informacion de Sam'!$1:$1,">="&$B$10,'Informacion de Sam'!$1:$1,"<="&$B$9)/SUMIFS('Informacion de Sam'!$5:$5,'Informacion de Sam'!$1:$1,">="&$B$10,'Informacion de Sam'!$1:$1,"<="&$B$9) -> 0.29147768 | D34: =('Mercado 2025 y 2026'!$O$503+'Mercado 2025 y 2026'!$Y$503)/('Mercado 2025 y 2026'!$O$478+'Mercado 2025 y 2026'!$Y$478) -> 0.11354207 | E34: 0.7 | F34: =E34*C34+(1-E34)*D34 -> 0.23809699
A35: Derechos de Emisión de Pólizas (Neto) | B35: % de Primas Netas | C35: =SUMIFS('Informacion de Sam'!$37:$37,'Informacion de Sam'!$1:$1,">="&$B$10,'Informacion de Sam'!$1:$1,"<="&$B$9)/SUMIFS('Informacion de Sam'!$5:$5,'Informacion de Sam'!$1:$1,">="&$B$10,'Informacion de Sam'!$1:$1,"<="&$B$9) -> 0.029418433 | D35: =('Mercado 2025 y 2026'!$O$504+'Mercado 2025 y 2026'!$Y$504)/('Mercado 2025 y 2026'!$O$478+'Mercado 2025 y 2026'!$Y$478) -> 0.0334485 | E35: 0.5 | F35: =E35*C35+(1-E35)*D35 -> 0.031433466
A36: Productos de Inversiones | B36: % de Primas Netas | C36: =SUMIFS('Informacion de Sam'!$38:$38,'Informacion de Sam'!$1:$1,">="&$B$10,'Informacion de Sam'!$1:$1,"<="&$B$9)/SUMIFS('Informacion de Sam'!$5:$5,'Informacion de Sam'!$1:$1,">="&$B$10,'Informacion de Sam'!$1:$1,"<="&$B$9) -> 0.022584921 | D36: =('Mercado 2025 y 2026'!$O$505+'Mercado 2025 y 2026'!$Y$505)/('Mercado 2025 y 2026'!$O$478+'Mercado 2025 y 2026'!$Y$478) -> 0.047123906 | E36: =$B$6 -> 0.5 | F36: =E36*C36+(1-E36)*D36 -> 0.034854413
A37: Otros Productos | B37: % de Primas Netas | C37: =SUMIFS('Informacion de Sam'!$43:$43,'Informacion de Sam'!$1:$1,">="&$B$10,'Informacion de Sam'!$1:$1,"<="&$B$9)/SUMIFS('Informacion de Sam'!$5:$5,'Informacion de Sam'!$1:$1,">="&$B$10,'Informacion de Sam'!$1:$1,"<="&$B$9) -> 0.0081960591 | D37: =('Mercado 2025 y 2026'!$O$509+'Mercado 2025 y 2026'!$Y$509)/('Mercado 2025 y 2026'!$O$478+'Mercado 2025 y 2026'!$Y$478) -> 0.03833898 | E37: =$B$6 -> 0.5 | F37: =E37*C37+(1-E37)*D37 -> 0.023267519
A38: Otros Gastos | B38: % de Primas Netas | C38: =SUMIFS('Informacion de Sam'!$45:$45,'Informacion de Sam'!$1:$1,">="&$B$10,'Informacion de Sam'!$1:$1,"<="&$B$9)/SUMIFS('Informacion de Sam'!$5:$5,'Informacion de Sam'!$1:$1,">="&$B$10,'Informacion de Sam'!$1:$1,"<="&$B$9) -> 0.0044285905 | D38: =('Mercado 2025 y 2026'!$O$510+'Mercado 2025 y 2026'!$Y$510)/('Mercado 2025 y 2026'!$O$478+'Mercado 2025 y 2026'!$Y$478) -> 0.015525864 | E38: =$B$6 -> 0.5 | F38: =E38*C38+(1-E38)*D38 -> 0.0099772271
A40: 4. CRECIMIENTO Y METAS POR AÑO (celdas amarillas editables)
A41: Año | B41: Crecimiento Primas Netas | C41: Primas Netas anuales | D41: Meta Utilidad Neta (opcional) | E41: Utilidad Neta proyectada | F41: Ajuste a Gastos de Administración | G41: Gastos Admin. % Primas Netas | H41: Crecimiento sugerido (referencia) | I41: Gastos Admin. % Primas Netas (editable) | J41: Meta Utilidad Neta % Primas Netas (opcional) | K41: Meta Utilidad Neta usada | L41: Utilidad Neta % Primas Netas (resultado)
A42: 2025 | C42: =SUMIFS('Informacion de Sam'!$5:$5,'Informacion de Sam'!$1:$1,">="&DATE(A42,1,1),'Informacion de Sam'!$1:$1,"<="&DATE(A42,12,31)) -> 6.6861134e+08 | E42: =SUMIFS('Informacion de Sam'!$50:$50,'Informacion de Sam'!$1:$1,">="&DATE(A42,1,1),'Informacion de Sam'!$1:$1,"<="&DATE(A42,12,31)) -> 17936246 | G42: =SUMIFS('Informacion de Sam'!$35:$35,'Informacion de Sam'!$1:$1,">="&DATE(A42,1,1),'Informacion de Sam'!$1:$1,"<="&DATE(A42,12,31))/C42 -> 0.27415227 | L42: =IFERROR(E42/C42,"") -> 0.026826117
A43: 2026 | B43: =C43/C42-1 -> -0.13224523 | C43: =SUMIFS('Informacion de Sam'!$5:$5,'Informacion de Sam'!$1:$1,">="&DATE(YEAR($B$9),1,1),'Informacion de Sam'!$1:$1,"<="&$B$9)/SUM(INDEX($B$20:$M$20,1):INDEX($B$20:$M$20,MONTH($B$9))) -> 5.8019068e+08 | E43: =SUMIFS('Proyeccion Agromercantil'!$B$55:$HA$55,'Proyeccion Agromercantil'!$B$4:$HA$4,A43,'Proyeccion Agromercantil'!$B$5:$HA$5,"Acumulado") -> 35708999 | F43: =SUMIFS('Proyeccion Agromercantil'!$B$60:$HA$60,'Proyeccion Agromercantil'!$B$4:$HA$4,A43,'Proyeccion Agromercantil'!$B$5:$HA$5,"Acumulado") -> 0 | G43: =SUMIFS('Proyeccion Agromercantil'!$B$40:$HA$40,'Proyeccion Agromercantil'!$B$4:$HA$4,A43,'Proyeccion Agromercantil'!$B$5:$HA$5,"Acumulado")/SUMIFS('Proyeccion Agromercantil'!$B$10:$HA$10,'Proyeccion Agromercantil'!$B$4:$HA$4,A43,'Proyeccion Agromercantil'!$B$5:$HA$5,"Acumulado") -> 0.26479079 | I43: =$F$34 -> 0.23809699 | K43: =IF(D43<>"",D43,IF(J43<>"",J43*C43,"")) | L43: =IFERROR(E43/C43,"") -> 0.061547006
A44: 2027 | B44: 0.25 | C44: =C43*(1+B44) -> 7.2523835e+08 | E44: =SUMIFS('Proyeccion Agromercantil'!$B$55:$HA$55,'Proyeccion Agromercantil'!$B$4:$HA$4,A44,'Proyeccion Agromercantil'!$B$5:$HA$5,"Acumulado") -> 19587971 | F44: =SUMIFS('Proyeccion Agromercantil'!$B$60:$HA$60,'Proyeccion Agromercantil'!$B$4:$HA$4,A44,'Proyeccion Agromercantil'!$B$5:$HA$5,"Acumulado") -> 0 | G44: =SUMIFS('Proyeccion Agromercantil'!$B$40:$HA$40,'Proyeccion Agromercantil'!$B$4:$HA$4,A44,'Proyeccion Agromercantil'!$B$5:$HA$5,"Acumulado")/SUMIFS('Proyeccion Agromercantil'!$B$10:$HA$10,'Proyeccion Agromercantil'!$B$4:$HA$4,A44,'Proyeccion Agromercantil'!$B$5:$HA$5,"Acumulado") -> 0.23809699 | H44: =$B$7+($B$5-$B$7)*(A44-2027)/(2035-2027) -> 0.08835976 | I44: =$F$34 -> 0.23809699 | K44: =IF(D44<>"",D44,IF(J44<>"",J44*C44,"")) | L44: =IFERROR(E44/C44,"") -> 0.027009011
A45: 2028 | B45: 0.25 | C45: =C44*(1+B45) -> 9.0654794e+08 | E45: =SUMIFS('Proyeccion Agromercantil'!$B$55:$HA$55,'Proyeccion Agromercantil'!$B$4:$HA$4,A45,'Proyeccion Agromercantil'!$B$5:$HA$5,"Acumulado") -> 24484964 | F45: =SUMIFS('Proyeccion Agromercantil'!$B$60:$HA$60,'Proyeccion Agromercantil'!$B$4:$HA$4,A45,'Proyeccion Agromercantil'!$B$5:$HA$5,"Acumulado") -> 0 | G45: =SUMIFS('Proyeccion Agromercantil'!$B$40:$HA$40,'Proyeccion Agromercantil'!$B$4:$HA$4,A45,'Proyeccion Agromercantil'!$B$5:$HA$5,"Acumulado")/SUMIFS('Proyeccion Agromercantil'!$B$10:$HA$10,'Proyeccion Agromercantil'!$B$4:$HA$4,A45,'Proyeccion Agromercantil'!$B$5:$HA$5,"Acumulado") -> 0.23809699 | H45: =$B$7+($B$5-$B$7)*(A45-2027)/(2035-2027) -> 0.086167101 | I45: =$F$34 -> 0.23809699 | K45: =IF(D45<>"",D45,IF(J45<>"",J45*C45,"")) | L45: =IFERROR(E45/C45,"") -> 0.027009011
A46: 2029 | B46: 0.25 | C46: =C45*(1+B46) -> 1.1331849e+09 | E46: =SUMIFS('Proyeccion Agromercantil'!$B$55:$HA$55,'Proyeccion Agromercantil'!$B$4:$HA$4,A46,'Proyeccion Agromercantil'!$B$5:$HA$5,"Acumulado") -> 30606205 | F46: =SUMIFS('Proyeccion Agromercantil'!$B$60:$HA$60,'Proyeccion Agromercantil'!$B$4:$HA$4,A46,'Proyeccion Agromercantil'!$B$5:$HA$5,"Acumulado") -> 0 | G46: =SUMIFS('Proyeccion Agromercantil'!$B$40:$HA$40,'Proyeccion Agromercantil'!$B$4:$HA$4,A46,'Proyeccion Agromercantil'!$B$5:$HA$5,"Acumulado")/SUMIFS('Proyeccion Agromercantil'!$B$10:$HA$10,'Proyeccion Agromercantil'!$B$4:$HA$4,A46,'Proyeccion Agromercantil'!$B$5:$HA$5,"Acumulado") -> 0.23809699 | H46: =$B$7+($B$5-$B$7)*(A46-2027)/(2035-2027) -> 0.083974442 | I46: =$F$34 -> 0.23809699 | K46: =IF(D46<>"",D46,IF(J46<>"",J46*C46,"")) | L46: =IFERROR(E46/C46,"") -> 0.027009011
A47: 2030 | B47: 0.25 | C47: =C46*(1+B47) -> 1.4164812e+09 | E47: =SUMIFS('Proyeccion Agromercantil'!$B$55:$HA$55,'Proyeccion Agromercantil'!$B$4:$HA$4,A47,'Proyeccion Agromercantil'!$B$5:$HA$5,"Acumulado") -> 38257756 | F47: =SUMIFS('Proyeccion Agromercantil'!$B$60:$HA$60,'Proyeccion Agromercantil'!$B$4:$HA$4,A47,'Proyeccion Agromercantil'!$B$5:$HA$5,"Acumulado") -> 0 | G47: =SUMIFS('Proyeccion Agromercantil'!$B$40:$HA$40,'Proyeccion Agromercantil'!$B$4:$HA$4,A47,'Proyeccion Agromercantil'!$B$5:$HA$5,"Acumulado")/SUMIFS('Proyeccion Agromercantil'!$B$10:$HA$10,'Proyeccion Agromercantil'!$B$4:$HA$4,A47,'Proyeccion Agromercantil'!$B$5:$HA$5,"Acumulado") -> 0.23809699 | H47: =$B$7+($B$5-$B$7)*(A47-2027)/(2035-2027) -> 0.081781783 | I47: =$F$34 -> 0.23809699 | K47: =IF(D47<>"",D47,IF(J47<>"",J47*C47,"")) | L47: =IFERROR(E47/C47,"") -> 0.027009011
A48: 2031 | B48: 0.25 | C48: =C47*(1+B48) -> 1.7706015e+09 | E48: =SUMIFS('Proyeccion Agromercantil'!$B$55:$HA$55,'Proyeccion Agromercantil'!$B$4:$HA$4,A48,'Proyeccion Agromercantil'!$B$5:$HA$5,"Acumulado") -> 47822195 | F48: =SUMIFS('Proyeccion Agromercantil'!$B$60:$HA$60,'Proyeccion Agromercantil'!$B$4:$HA$4,A48,'Proyeccion Agromercantil'!$B$5:$HA$5,"Acumulado") -> 0 | G48: =SUMIFS('Proyeccion Agromercantil'!$B$40:$HA$40,'Proyeccion Agromercantil'!$B$4:$HA$4,A48,'Proyeccion Agromercantil'!$B$5:$HA$5,"Acumulado")/SUMIFS('Proyeccion Agromercantil'!$B$10:$HA$10,'Proyeccion Agromercantil'!$B$4:$HA$4,A48,'Proyeccion Agromercantil'!$B$5:$HA$5,"Acumulado") -> 0.23809699 | H48: =$B$7+($B$5-$B$7)*(A48-2027)/(2035-2027) -> 0.079589123 | I48: =$F$34 -> 0.23809699 | K48: =IF(D48<>"",D48,IF(J48<>"",J48*C48,"")) | L48: =IFERROR(E48/C48,"") -> 0.027009011
A49: 2032 | B49: 0.25 | C49: =C48*(1+B49) -> 2.2132518e+09 | E49: =SUMIFS('Proyeccion Agromercantil'!$B$55:$HA$55,'Proyeccion Agromercantil'!$B$4:$HA$4,A49,'Proyeccion Agromercantil'!$B$5:$HA$5,"Acumulado") -> 59777743 | F49: =SUMIFS('Proyeccion Agromercantil'!$B$60:$HA$60,'Proyeccion Agromercantil'!$B$4:$HA$4,A49,'Proyeccion Agromercantil'!$B$5:$HA$5,"Acumulado") -> 0 | G49: =SUMIFS('Proyeccion Agromercantil'!$B$40:$HA$40,'Proyeccion Agromercantil'!$B$4:$HA$4,A49,'Proyeccion Agromercantil'!$B$5:$HA$5,"Acumulado")/SUMIFS('Proyeccion Agromercantil'!$B$10:$HA$10,'Proyeccion Agromercantil'!$B$4:$HA$4,A49,'Proyeccion Agromercantil'!$B$5:$HA$5,"Acumulado") -> 0.23809699 | H49: =$B$7+($B$5-$B$7)*(A49-2027)/(2035-2027) -> 0.077396464 | I49: =$F$34 -> 0.23809699 | K49: =IF(D49<>"",D49,IF(J49<>"",J49*C49,"")) | L49: =IFERROR(E49/C49,"") -> 0.027009011
A50: 2033 | B50: 0.25 | C50: =C49*(1+B50) -> 2.7665648e+09 | E50: =SUMIFS('Proyeccion Agromercantil'!$B$55:$HA$55,'Proyeccion Agromercantil'!$B$4:$HA$4,A50,'Proyeccion Agromercantil'!$B$5:$HA$5,"Acumulado") -> 74722179 | F50: =SUMIFS('Proyeccion Agromercantil'!$B$60:$HA$60,'Proyeccion Agromercantil'!$B$4:$HA$4,A50,'Proyeccion Agromercantil'!$B$5:$HA$5,"Acumulado") -> 0 | G50: =SUMIFS('Proyeccion Agromercantil'!$B$40:$HA$40,'Proyeccion Agromercantil'!$B$4:$HA$4,A50,'Proyeccion Agromercantil'!$B$5:$HA$5,"Acumulado")/SUMIFS('Proyeccion Agromercantil'!$B$10:$HA$10,'Proyeccion Agromercantil'!$B$4:$HA$4,A50,'Proyeccion Agromercantil'!$B$5:$HA$5,"Acumulado") -> 0.23809699 | H50: =$B$7+($B$5-$B$7)*(A50-2027)/(2035-2027) -> 0.075203805 | I50: =$F$34 -> 0.23809699 | K50: =IF(D50<>"",D50,IF(J50<>"",J50*C50,"")) | L50: =IFERROR(E50/C50,"") -> 0.027009011
A51: 2034 | B51: 0.25 | C51: =C50*(1+B51) -> 3.458206e+09 | E51: =SUMIFS('Proyeccion Agromercantil'!$B$55:$HA$55,'Proyeccion Agromercantil'!$B$4:$HA$4,A51,'Proyeccion Agromercantil'!$B$5:$HA$5,"Acumulado") -> 93402724 | F51: =SUMIFS('Proyeccion Agromercantil'!$B$60:$HA$60,'Proyeccion Agromercantil'!$B$4:$HA$4,A51,'Proyeccion Agromercantil'!$B$5:$HA$5,"Acumulado") -> 0 | G51: =SUMIFS('Proyeccion Agromercantil'!$B$40:$HA$40,'Proyeccion Agromercantil'!$B$4:$HA$4,A51,'Proyeccion Agromercantil'!$B$5:$HA$5,"Acumulado")/SUMIFS('Proyeccion Agromercantil'!$B$10:$HA$10,'Proyeccion Agromercantil'!$B$4:$HA$4,A51,'Proyeccion Agromercantil'!$B$5:$HA$5,"Acumulado") -> 0.23809699 | H51: =$B$7+($B$5-$B$7)*(A51-2027)/(2035-2027) -> 0.073011146 | I51: =$F$34 -> 0.23809699 | K51: =IF(D51<>"",D51,IF(J51<>"",J51*C51,"")) | L51: =IFERROR(E51/C51,"") -> 0.027009011
A52: 2035 | B52: 0.25 | C52: =C51*(1+B52) -> 4.3227575e+09 | E52: =SUMIFS('Proyeccion Agromercantil'!$B$55:$HA$55,'Proyeccion Agromercantil'!$B$4:$HA$4,A52,'Proyeccion Agromercantil'!$B$5:$HA$5,"Acumulado") -> 1.167534e+08 | F52: =SUMIFS('Proyeccion Agromercantil'!$B$60:$HA$60,'Proyeccion Agromercantil'!$B$4:$HA$4,A52,'Proyeccion Agromercantil'!$B$5:$HA$5,"Acumulado") -> 0 | G52: =SUMIFS('Proyeccion Agromercantil'!$B$40:$HA$40,'Proyeccion Agromercantil'!$B$4:$HA$4,A52,'Proyeccion Agromercantil'!$B$5:$HA$5,"Acumulado")/SUMIFS('Proyeccion Agromercantil'!$B$10:$HA$10,'Proyeccion Agromercantil'!$B$4:$HA$4,A52,'Proyeccion Agromercantil'!$B$5:$HA$5,"Acumulado") -> 0.23809699 | H52: =$B$7+($B$5-$B$7)*(A52-2027)/(2035-2027) -> 0.070818486 | I52: =$F$34 -> 0.23809699 | K52: =IF(D52<>"",D52,IF(J52<>"",J52*C52,"")) | L52: =IFERROR(E52/C52,"") -> 0.027009011
A54: Instrucciones: escriba el % de crecimiento de Primas Netas de cada año en las celdas amarillas B44:B52 (2027-2035). La columna H muestra la sugerencia inicial (converge del crecimiento combinado al del mercado). 2026 se calcula con los meses reales + proyección.
A55: Gastos de Administración: escriba en I43:I52 el % de Primas Netas deseado para cada año (por defecto = F34). Utilidad Neta: escriba en J43:J52 la meta como % de Primas Netas; el modelo ajusta los Gastos de Administración para alcanzarla (si hay meta en D o J, ésta prevalece sobre el % de I). La columna G y L son resultados, no se editan.
A59: 2027
A60: 2028
A61: 2029
A62: 2030
A63: 2031
A64: 2032
A65: 2033
A66: 2034
A67: 2035

Sheet Proyeccion Agromercantil
A1: SEGUROS AGROMERCANTIL – ESTADO DE RESULTADOS REAL Y PROYECTADO (ene-2020 a dic-2035)
A2: Blanco = Real | Naranja = Proyección | Azul = Acumulado anual. Supuestos y metas en la hoja "Supuestos Proyeccion".
A4: Año | B4: 2020 | C4: 2020 | D4: 2020 | E4: 2020 | F4: 2020 | G4: 2020 | H4: 2020 | I4: 2020 | J4: 2020 | K4: 2020 | L4: 2020 | M4: 2020 | N4: 2020 | O4: 2021 | P4: 2021 | Q4: 2021 | R4: 2021 | S4: 2021 | T4: 2021 | U4: 2021 | V4: 2021 | W4: 2021 | X4: 2021 | Y4: 2021 | Z4: 2021 | AA4: 2021 | AB4: 2022 | AC4: 2022 | AD4: 2022 | AE4: 2022 | AF4: 2022 | AG4: 2022 | AH4: 2022 | AI4: 2022 | AJ4: 2022 | AK4: 2022 | AL4: 2022 | AM4: 2022 | AN4: 2022 | AO4: 2023 | AP4: 2023 | AQ4: 2023 | AR4: 2023 | AS4: 2023 | AT4: 2023 | AU4: 2023 | AV4: 2023 | AW4: 2023 | AX4: 2023 | AY4: 2023 | AZ4: 2023 | BA4: 2023 | BB4: 2024 | BC4: 2024 | BD4: 2024 | BE4: 2024 | BF4: 2024 | BG4: 2024 | BH4: 2024 | BI4: 2024 | BJ4: 2024 | BK4: 2024 | BL4: 2024 | BM4: 2024 | BN4: 2024 | BO4: 2025 | BP4: 2025 | BQ4: 2025 | BR4: 2025 | BS4: 2025 | BT4: 2025 | BU4: 2025 | BV4: 2025 | BW4: 2025 | BX4: 2025 | BY4: 2025 | BZ4: 2025 | CA4: 2025 | CB4: 2026 | CC4: 2026 | CD4: 2026 | CE4: 2026 | CF4: 2026 | CG4: 2026 | CH4: 2026 | CI4: 2026 | CJ4: 2026 | CK4: 2026 | CL4: 2026 | CM4: 2026 | CN4: 2026 | CO4: 2027 | CP4: 2027 | CQ4: 2027 | CR4: 2027 | CS4: 2027 | CT4: 2027 | CU4: 2027 | CV4: 2027 | CW4: 2027 | CX4: 2027 | CY4: 2027 | CZ4: 2027 | DA4: 2027 | DB4: 2028 | DC4: 2028 | DD4: 2028 | DE4: 2028 | DF4: 2028 | DG4: 2028 | DH4: 2028 | DI4: 2028 | DJ4: 2028 | DK4: 2028 | DL4: 2028 | DM4: 2028 | DN4: 2028 | DO4: 2029 | DP4: 2029 | DQ4: 2029 | DR4: 2029 | DS4: 2029 | DT4: 2029 | DU4: 2029 | DV4: 2029 | DW4: 2029 | DX4: 2029 | DY4: 2029 | DZ4: 2029 | EA4: 2029 | EB4: 2030 | EC4: 2030 | ED4: 2030 | EE4: 2030 | EF4: 2030 | EG4: 2030 | EH4: 2030 | EI4: 2030 | EJ4: 2030 | EK4: 2030 | EL4: 2030 | EM4: 2030 | EN4: 2030 | EO4: 2031 | EP4: 2031 | EQ4: 2031 | ER4: 2031 | ES4: 2031 | ET4: 2031 | EU4: 2031 | EV4: 2031 | EW4: 2031 | EX4: 2031 | EY4: 2031 | EZ4: 2031 | FA4: 2031 | FB4: 2032 | FC4: 2032 | FD4: 2032 | FE4: 2032 | FF4: 2032 | FG4: 2032 | FH4: 2032 | FI4: 2032 | FJ4: 2032 | FK4: 2032 | FL4: 2032 | FM4: 2032 | FN4: 2032 | FO4: 2033 | FP4: 2033 | FQ4: 2033 | FR4: 2033 | FS4: 2033 | FT4: 2033 | FU4: 2033 | FV4: 2033 | FW4: 2033 | FX4: 2033 | FY4: 2033 | FZ4: 2033 | GA4: 2033 | GB4: 2034 | GC4: 2034 | GD4: 2034 | GE4: 2034 | GF4: 2034 | GG4: 2034 | GH4: 2034 | GI4: 2034 | GJ4: 2034 | GK4: 2034 | GL4: 2034 | GM4: 2034 | GN4: 2034 | GO4: 2035 | GP4: 2035 | GQ4: 2035 | GR4: 2035 | GS4: 2035 | GT4: 2035 | GU4: 2035 | GV4: 2035 | GW4: 2035 | GX4: 2035 | GY4: 2035 | GZ4: 2035 | HA4: 2035 | HC4: =IF(2020<YEAR('Supuestos Proyeccion'!$B$9),"Real",IF(2020=YEAR('Supuestos Proyeccion'!$B$9),"Real + Proy.","Proyección")) -> Real | HD4: =IF(2021<YEAR('Supuestos Proyeccion'!$B$9),"Real",IF(2021=YEAR('Supuestos Proyeccion'!$B$9),"Real + Proy.","Proyección")) -> Real | HE4: =IF(2022<YEAR('Supuestos Proyeccion'!$B$9),"Real",IF(2022=YEAR('Supuestos Proyeccion'!$B$9),"Real + Proy.","Proyección")) -> Real | HF4: =IF(2023<YEAR('Supuestos Proyeccion'!$B$9),"Real",IF(2023=YEAR('Supuestos Proyeccion'!$B$9),"Real + Proy.","Proyección")) -> Real | HG4: =IF(2024<YEAR('Supuestos Proyeccion'!$B$9),"Real",IF(2024=YEAR('Supuestos Proyeccion'!$B$9),"Real + Proy.","Proyección")) -> Real | HH4: =IF(2025<YEAR('Supuestos Proyeccion'!$B$9),"Real",IF(2025=YEAR('Supuestos Proyeccion'!$B$9),"Real + Proy.","Proyección")) -> Real | HI4: =IF(2026<YEAR('Supuestos Proyeccion'!$B$9),"Real",IF(2026=YEAR('Supuestos Proyeccion'!$B$9),"Real + Proy.","Proyección")) -> Real + Proy. | HJ4: =IF(2027<YEAR('Supuestos Proyeccion'!$B$9),"Real",IF(2027=YEAR('Supuestos Proyeccion'!$B$9),"Real + Proy.","Proyección")) -> Proyección | HK4: =IF(2028<YEAR('Supuestos Proyeccion'!$B$9),"Real",IF(2028=YEAR('Supuestos Proyeccion'!$B$9),"Real + Proy.","Proyección")) -> Proyección | HL4: =IF(2029<YEAR('Supuestos Proyeccion'!$B$9),"Real",IF(2029=YEAR('Supuestos Proyeccion'!$B$9),"Real + Proy.","Proyección")) -> Proyección | HM4: =IF(2030<YEAR('Supuestos Proyeccion'!$B$9),"Real",IF(2030=YEAR('Supuestos Proyeccion'!$B$9),"Real + Proy.","Proyección")) -> Proyección | HN4: =IF(2031<YEAR('Supuestos Proyeccion'!$B$9),"Real",IF(2031=YEAR('Supuestos Proyeccion'!$B$9),"Real + Proy.","Proyección")) -> Proyección | HO4: =IF(2032<YEAR('Supuestos Proyeccion'!$B$9),"Real",IF(2032=YEAR('Supuestos Proyeccion'!$B$9),"Real + Proy.","Proyección")) -> Proyección | HP4: =IF(2033<YEAR('Supuestos Proyeccion'!$B$9),"Real",IF(2033=YEAR('Supuestos Proyeccion'!$B$9),"Real + Proy.","Proyección")) -> Proyección | HQ4: =IF(2034<YEAR('Supuestos Proyeccion'!$B$9),"Real",IF(2034=YEAR('Supuestos Proyeccion'!$B$9),"Real + Proy.","Proyección")) -> Proyección | HR4: =IF(2035<YEAR('Supuestos Proyeccion'!$B$9),"Real",IF(2035=YEAR('Supuestos Proyeccion'!$B$9),"Real + Proy.","Proyección")) -> Proyección
A5: Tipo | B5: =IF(B$6<='Supuestos Proyeccion'!$B$9,"Real","Proyección") -> Real | C5: =IF(C$6<='Supuestos Proyeccion'!$B$9,"Real","Proyección") -> Real | D5: =IF(D$6<='Supuestos Proyeccion'!$B$9,"Real","Proyección") -> Real | E5: =IF(E$6<='Supuestos Proyeccion'!$B$9,"Real","Proyección") -> Real | F5: =IF(F$6<='Supuestos Proyeccion'!$B$9,"Real","Proyección") -> Real | G5: =IF(G$6<='Supuestos Proyeccion'!$B$9,"Real","Proyección") -> Real | H5: =IF(H$6<='Supuestos Proyeccion'!$B$9,"Real","Proyección") -> Real | I5: =IF(I$6<='Supuestos Proyeccion'!$B$9,"Real","Proyección") -> Real | ... M5: =IF(M$6<='Supuestos Proyeccion'!$B$9,"Real","Proyección") -> Real | N5: Acumulado | O5: =IF(O$6<='Supuestos Proyeccion'!$B$9,"Real","Proyección") -> Real | P5: =IF(P$6<='Supuestos Proyeccion'!$B$9,"Real","Proyección") -> Real | Q5: =IF(Q$6<='Supuestos Proyeccion'!$B$9,"Real","Proyección") -> Real | R5: =IF(R$6<='Supuestos Proyeccion'!$B$9,"Real","Proyección") -> Real | S5: =IF(S$6<='Supuestos Proyeccion'!$B$9,"Real","Proyección") -> Real | T5: =IF(T$6<='Supuestos Proyeccion'!$B$9,"Real","Proyección") -> Real | U5: =IF(U$6<='Supuestos Proyeccion'!$B$9,"Real","Proyección") -> Real | V5: =IF(V$6<='Supuestos Proyeccion'!$B$9,"Real","Proyección") -> Real | ... Z5: =IF(Z$6<='Supuestos Proyeccion'!$B$9,"Real","Proyección") -> Real | AA5: Acumulado | AB5: =IF(AB$6<='Supuestos Proyeccion'!$B$9,"Real","Proyección") -> Real | AC5: =IF(AC$6<='Supuestos Proyeccion'!$B$9,"Real","Proyección") -> Real | AD5: =IF(AD$6<='Supuestos Proyeccion'!$B$9,"Real","Proyección") -> Real | AE5: =IF(AE$6<='Supuestos Proyeccion'!$B$9,"Real","Proyección") -> Real | AF5: =IF(AF$6<='Supuestos Proyeccion'!$B$9,"Real","Proyección") -> Real | AG5: =IF(AG$6<='Supuestos Proyeccion'!$B$9,"Real","Proyección") -> Real | AH5: =IF(AH$6<='Supuestos Proyeccion'!$B$9,"Real","Proyección") -> Real | AI5: =IF(AI$6<='Supuestos Proyeccion'!$B$9,"Real","Proyección") -> Real | ... AM5: =IF(AM$6<='Supuestos Proyeccion'!$B$9,"Real","Proyección") -> Real | AN5: Acumulado | AO5: =IF(AO$6<='Supuestos Proyeccion'!$B$9,"Real","Proyección") -> Real | AP5: =IF(AP$6<='Supuestos Proyeccion'!$B$9,"Real","Proyección") -> Real | AQ5: =IF(AQ$6<='Supuestos Proyeccion'!$B$9,"Real","Proyección") -> Real | AR5: =IF(AR$6<='Supuestos Proyeccion'!$B$9,"Real","Proyección") -> Real | AS5: =IF(AS$6<='Supuestos Proyeccion'!$B$9,"Real","Proyección") -> Real | AT5: =IF(AT$6<='Supuestos Proyeccion'!$B$9,"Real","Proyección") -> Real | AU5: =IF(AU$6<='Supuestos Proyeccion'!$B$9,"Real","Proyección") -> Real | AV5: =IF(AV$6<='Supuestos Proyeccion'!$B$9,"Real","Proyección") -> Real | ... AZ5: =IF(AZ$6<='Supuestos Proyeccion'!$B$9,"Real","Proyección") -> Real | BA5: Acumulado | BB5: =IF(BB$6<='Supuestos Proyeccion'!$B$9,"Real","Proyección") -> Real | BC5: =IF(BC$6<='Supuestos Proyeccion'!$B$9,"Real","Proyección") -> Real | BD5: =IF(BD$6<='Supuestos Proyeccion'!$B$9,"Real","Proyección") -> Real | BE5: =IF(BE$6<='Supuestos Proyeccion'!$B$9,"Real","Proyección") -> Real | BF5: =IF(BF$6<='Supuestos Proyeccion'!$B$9,"Real","Proyección") -> Real | BG5: =IF(BG$6<='Supuestos Proyeccion'!$B$9,"Real","Proyección") -> Real | BH5: =IF(BH$6<='Supuestos Proyeccion'!$B$9,"Real","Proyección") -> Real | BI5: =IF(BI$6<='Supuestos Proyeccion'!$B$9,"Real","Proyección") -> Real | ... BM5: =IF(BM$6<='Supuestos Proyeccion'!$B$9,"Real","Proyección") -> Real | BN5: Acumulado | BO5: =IF(BO$6<='Supuestos Proyeccion'!$B$9,"Real","Proyección") -> Real | BP5: =IF(BP$6<='Supuestos Proyeccion'!$B$9,"Real","Proyección") -> Real | BQ5: =IF(BQ$6<='Supuestos Proyeccion'!$B$9,"Real","Proyección") -> Real | BR5: =IF(BR$6<='Supuestos Proyeccion'!$B$9,"Real","Proyección") -> Real | BS5: =IF(BS$6<='Supuestos Proyeccion'!$B$9,"Real","Proyección") -> Real | BT5: =IF(BT$6<='Supuestos Proyeccion'!$B$9,"Real","Proyección") -> Real | BU5: =IF(BU$6<='Supuestos Proyeccion'!$B$9,"Real","Proyección") -> Real | BV5: =IF(BV$6<='Supuestos Proyeccion'!$B$9,"Real","Proyección") -> Real | ... BZ5: =IF(BZ$6<='Supuestos Proyeccion'!$B$9,"Real","Proyección") -> Real | CA5: Acumulado | CB5: =IF(CB$6<='Supuestos Proyeccion'!$B$9,"Real","Proyección") -> Real | CC5: =IF(CC$6<='Supuestos Proyeccion'!$B$9,"Real","Proyección") -> Real | CD5: =IF(CD$6<='Supuestos Proyeccion'!$B$9,"Real","Proyección") -> Real | CE5: =IF(CE$6<='Supuestos Proyeccion'!$B$9,"Real","Proyección") -> Real | CF5: =IF(CF$6<='Supuestos Proyeccion'!$B$9,"Real","Proyección") -> Real | CG5: =IF(CG$6<='Supuestos Proyeccion'!$B$9,"Real","Proyección") -> Real | CH5: =IF(CH$6<='Supuestos Proyeccion'!$B$9,"Real","Proyección") -> Real | CI5: =IF(CI$6<='Supuestos Proyeccion'!$B$9,"Real","Proyección") -> Real | ... CM5: =IF(CM$6<='Supuestos Proyeccion'!$B$9,"Real","Proyección") -> Proyección | CN5: Acumulado | CO5: =IF(CO$6<='Supuestos Proyeccion'!$B$9,"Real","Proyección") -> Proyección | CP5: =IF(CP$6<='Supuestos Proyeccion'!$B$9,"Real","Proyección") -> Proyección | CQ5: =IF(CQ$6<='Supuestos Proyeccion'!$B$9,"Real","Proyección") -> Proyección | CR5: =IF(CR$6<='Supuestos Proyeccion'!$B$9,"Real","Proyección") -> Proyección | CS5: =IF(CS$6<='Supuestos Proyeccion'!$B$9,"Real","Proyección") -> Proyección | CT5: =IF(CT$6<='Supuestos Proyeccion'!$B$9,"Real","Proyección") -> Proyección | CU5: =IF(CU$6<='Supuestos Proyeccion'!$B$9,"Real","Proyección") -> Proyección | CV5: =IF(CV$6<='Supuestos Proyeccion'!$B$9,"Real","Proyección") -> Proyección | ... CZ5: =IF(CZ$6<='Supuestos Proyeccion'!$B$9,"Real","Proyección") -> Proyección | DA5: Acumulado | DB5: =IF(DB$6<='Supuestos Proyeccion'!$B$9,"Real","Proyección") -> Proyección | DC5: =IF(DC$6<='Supuestos Proyeccion'!$B$9,"Real","Proyección") -> Proyección | DD5: =IF(DD$6<='Supuestos Proyeccion'!$B$9,"Real","Proyección") -> Proyección | DE5: =IF(DE$6<='Supuestos Proyeccion'!$B$9,"Real","Proyección") -> Proyección | DF5: =IF(DF$6<='Supuestos Proyeccion'!$B$9,"Real","Proyección") -> Proyección | DG5: =IF(DG$6<='Supuestos Proyeccion'!$B$9,"Real","Proyección") -> Proyección | DH5: =IF(DH$6<='Supuestos Proyeccion'!$B$9,"Real","Proyección") -> Proyección | DI5: =IF(DI$6<='Supuestos Proyeccion'!$B$9,"Real","Proyección") -> Proyección | ... DM5: =IF(DM$6<='Supuestos Proyeccion'!$B$9,"Real","Proyección") -> Proyección | DN5: Acumulado | DO5: =IF(DO$6<='Supuestos Proyeccion'!$B$9,"Real","Proyección") -> Proyección | DP5: =IF(DP$6<='Supuestos Proyeccion'!$B$9,"Real","Proyección") -> Proyección | DQ5: =IF(DQ$6<='Supuestos Proyeccion'!$B$9,"Real","Proyección") -> Proyección | DR5: =IF(DR$6<='Supuestos Proyeccion'!$B$9,"Real","Proyección") -> Proyección | DS5: =IF(DS$6<='Supuestos Proyeccion'!$B$9,"Real","Proyección") -> Proyección | DT5: =IF(DT$6<='Supuestos Proyeccion'!$B$9,"Real","Proyección") -> Proyección | DU5: =IF(DU$6<='Supuestos Proyeccion'!$B$9,"Real","Proyección") -> Proyección | DV5: =IF(DV$6<='Supuestos Proyeccion'!$B$9,"Real","Proyección") -> Proyección | ... DZ5: =IF(DZ$6<='Supuestos Proyeccion'!$B$9,"Real","Proyección") -> Proyección | EA5: Acumulado | EB5: =IF(EB$6<='Supuestos Proyeccion'!$B$9,"Real","Proyección") -> Proyección | EC5: =IF(EC$6<='Supuestos Proyeccion'!$B$9,"Real","Proyección") -> Proyección | ED5: =IF(ED$6<='Supuestos Proyeccion'!$B$9,"Real","Proyección") -> Proyección | EE5: =IF(EE$6<='Supuestos Proyeccion'!$B$9,"Real","Proyección") -> Proyección | EF5: =IF(EF$6<='Supuestos Proyeccion'!$B$9,"Real","Proyección") -> Proyección | EG5: =IF(EG$6<='Supuestos Proyeccion'!$B$9,"Real","Proyección") -> Proyección | EH5: =IF(EH$6<='Supuestos Proyeccion'!$B$9,"Real","Proyección") -> Proyección | EI5: =IF(EI$6<='Supuestos Proyeccion'!$B$9,"Real","Proyección") -> Proyección | ... EM5: =IF(EM$6<='Supuestos Proyeccion'!$B$9,"Real","Proyección") -> Proyección | EN5: Acumulado | EO5: =IF(EO$6<='Supuestos Proyeccion'!$B$9,"Real","Proyección") -> Proyección | EP5: =IF(EP$6<='Supuestos Proyeccion'!$B$9,"Real","Proyección") -> Proyección | EQ5: =IF(EQ$6<='Supuestos Proyeccion'!$B$9,"Real","Proyección") -> Proyección | ER5: =IF(ER$6<='Supuestos Proyeccion'!$B$9,"Real","Proyección") -> Proyección | ES5: =IF(ES$6<='Supuestos Proyeccion'!$B$9,"Real","Proyección") -> Proyección | ET5: =IF(ET$6<='Supuestos Proyeccion'!$B$9,"Real","Proyección") -> Proyección | EU5: =IF(EU$6<='Supuestos Proyeccion'!$B$9,"Real","Proyección") -> Proyección | EV5: =IF(EV$6<='Supuestos Proyeccion'!$B$9,"Real","Proyección") -> Proyección | ... EZ5: =IF(EZ$6<='Supuestos Proyeccion'!$B$9,"Real","Proyección") -> Proyección | FA5: Acumulado | FB5: =IF(FB$6<='Supuestos Proyeccion'!$B$9,"Real","Proyección") -> Proyección | FC5: =IF(FC$6<='Supuestos Proyeccion'!$B$9,"Real","Proyección") -> Proyección | FD5: =IF(FD$6<='Supuestos Proyeccion'!$B$9,"Real","Proyección") -> Proyección | FE5: =IF(FE$6<='Supuestos Proyeccion'!$B$9,"Real","Proyección") -> Proyección | FF5: =IF(FF$6<='Supuestos Proyeccion'!$B$9,"Real","Proyección") -> Proyección | FG5: =IF(FG$6<='Supuestos Proyeccion'!$B$9,"Real","Proyección") -> Proyección | FH5: =IF(FH$6<='Supuestos Proyeccion'!$B$9,"Real","Proyección") -> Proyección | FI5: =IF(FI$6<='Supuestos Proyeccion'!$B$9,"Real","Proyección") -> Proyección | ... FM5: =IF(FM$6<='Supuestos Proyeccion'!$B$9,"Real","Proyección") -> Proyección | FN5: Acumulado | FO5: =IF(FO$6<='Supuestos Proyeccion'!$B$9,"Real","Proyección") -> Proyección | FP5: =IF(FP$6<='Supuestos Proyeccion'!$B$9,"Real","Proyección") -> Proyección | FQ5: =IF(FQ$6<='Supuestos Proyeccion'!$B$9,"Real","Proyección") -> Proyección | FR5: =IF(FR$6<='Supuestos Proyeccion'!$B$9,"Real","Proyección") -> Proyección | FS5: =IF(FS$6<='Supuestos Proyeccion'!$B$9,"Real","Proyección") -> Proyección | FT5: =IF(FT$6<='Supuestos Proyeccion'!$B$9,"Real","Proyección") -> Proyección | FU5: =IF(FU$6<='Supuestos Proyeccion'!$B$9,"Real","Proyección") -> Proyección | FV5: =IF(FV$6<='Supuestos Proyeccion'!$B$9,"Real","Proyección") -> Proyección | ... FZ5: =IF(FZ$6<='Supuestos Proyeccion'!$B$9,"Real","Proyección") -> Proyección | GA5: Acumulado | GB5: =IF(GB$6<='Supuestos Proyeccion'!$B$9,"Real","Proyección") -> Proyección | GC5: =IF(GC$6<='Supuestos Proyeccion'!$B$9,"Real","Proyección") -> Proyección | GD5: =IF(GD$6<='Supuestos Proyeccion'!$B$9,"Real","Proyección") -> Proyección | GE5: =IF(GE$6<='Supuestos Proyeccion'!$B$9,"Real","Proyección") -> Proyección | GF5: =IF(GF$6<='Supuestos Proyeccion'!$B$9,"Real","Proyección") -> Proyección | GG5: =IF(GG$6<='Supuestos Proyeccion'!$B$9,"Real","Proyección") -> Proyección | GH5: =IF(GH$6<='Supuestos Proyeccion'!$B$9,"Real","Proyección") -> Proyección | GI5: =IF(GI$6<='Supuestos Proyeccion'!$B$9,"Real","Proyección") -> Proyección | ... GM5: =IF(GM$6<='Supuestos Proyeccion'!$B$9,"Real","Proyección") -> Proyección | GN5: Acumulado | GO5: =IF(GO$6<='Supuestos Proyeccion'!$B$9,"Real","Proyección") -> Proyección | GP5: =IF(GP$6<='Supuestos Proyeccion'!$B$9,"Real","Proyección") -> Proyección | GQ5: =IF(GQ$6<='Supuestos Proyeccion'!$B$9,"Real","Proyección") -> Proyección | GR5: =IF(GR$6<='Supuestos Proyeccion'!$B$9,"Real","Proyección") -> Proyección | GS5: =IF(GS$6<='Supuestos Proyeccion'!$B$9,"Real","Proyección") -> Proyección | GT5: =IF(GT$6<='Supuestos Proyeccion'!$B$9,"Real","Proyección") -> Proyección | GU5: =IF(GU$6<='Supuestos Proyeccion'!$B$9,"Real","Proyección") -> Proyección | GV5: =IF(GV$6<='Supuestos Proyeccion'!$B$9,"Real","Proyección") -> Proyección | ... GZ5: =IF(GZ$6<='Supuestos Proyeccion'!$B$9,"Real","Proyección") -> Proyección | HA5: Acumulado | HC5: Resumen anual | HD5: Resumen anual | HE5: Resumen anual | HF5: Resumen anual | HG5: Resumen anual | HH5: Resumen anual | HI5: Resumen anual | HJ5: Resumen anual | HK5: Resumen anual | HL5: Resumen anual | HM5: Resumen anual | HN5: Resumen anual | HO5: Resumen anual | HP5: Resumen anual | HQ5: Resumen anual | HR5: Resumen anual
A6: Concepto | B6: 43831 | C6: 43862 | D6: 43891 | E6: 43922 | F6: 43952 | G6: 43983 | H6: 44013 | I6: 44044 | J6: 44075 | K6: 44105 | L6: 44136 | M6: 44166 | N6: Acumulado 2020 | O6: 44197 | P6: 44228 | Q6: 44256 | R6: 44287 | S6: 44317 | T6: 44348 | U6: 44378 | V6: 44409 | W6: 44440 | X6: 44470 | Y6: 44501 | Z6: 44531 | AA6: Acumulado 2021 | AB6: 44562 | AC6: 44593 | AD6: 44621 | AE6: 44652 | AF6: 44682 | AG6: 44713 | AH6: 44743 | AI6: 44774 | AJ6: 44805 | AK6: 44835 | AL6: 44866 | AM6: 44896 | AN6: Acumulado 2022 | AO6: 44927 | AP6: 44958 | AQ6: 44986 | AR6: 45017 | AS6: 45047 | AT6: 45078 | AU6: 45108 | AV6: 45139 | AW6: 45170 | AX6: 45200 | AY6: 45231 | AZ6: 45261 | BA6: Acumulado 2023 | BB6: 45292 | BC6: 45323 | BD6: 45352 | BE6: 45383 | BF6: 45413 | BG6: 45444 | BH6: 45474 | BI6: 45505 | BJ6: 45536 | BK6: 45566 | BL6: 45597 | BM6: 45627 | BN6: Acumulado 2024 | BO6: 45658 | BP6: 45689 | BQ6: 45717 | BR6: 45748 | BS6: 45778 | BT6: 45809 | BU6: 45839 | BV6: 45870 | BW6: 45901 | BX6: 45931 | BY6: 45962 | BZ6: 45992 | CA6: Acumulado 2025 | CB6: 46023 | CC6: 46054 | CD6: 46082 | CE6: 46113 | CF6: 46143 | CG6: 46174 | CH6: 46204 | CI6: 46235 | CJ6: 46266 | CK6: 46296 | CL6: 46327 | CM6: 46357 | CN6: Acumulado 2026 | CO6: 46388 | CP6: 46419 | CQ6: 46447 | CR6: 46478 | CS6: 46508 | CT6: 46539 | CU6: 46569 | CV6: 46600 | CW6: 46631 | CX6: 46661 | CY6: 46692 | CZ6: 46722 | DA6: Acumulado 2027 | DB6: 46753 | DC6: 46784 | DD6: 46813 | DE6: 46844 | DF6: 46874 | DG6: 46905 | DH6: 46935 | DI6: 46966 | DJ6: 46997 | DK6: 47027 | DL6: 47058 | DM6: 47088 | DN6: Acumulado 2028 | DO6: 47119 | DP6: 47150 | DQ6: 47178 | DR6: 47209 | DS6: 47239 | DT6: 47270 | DU6: 47300 | DV6: 47331 | DW6: 47362 | DX6: 47392 | DY6: 47423 | DZ6: 47453 | EA6: Acumulado 2029 | EB6: 47484 | EC6: 47515 | ED6: 47543 | EE6: 47574 | EF6: 47604 | EG6: 47635 | EH6: 47665 | EI6: 47696 | EJ6: 47727 | EK6: 47757 | EL6: 47788 | EM6: 47818 | EN6: Acumulado 2030 | EO6: 47849 | EP6: 47880 | EQ6: 47908 | ER6: 47939 | ES6: 47969 | ET6: 48000 | EU6: 48030 | EV6: 48061 | EW6: 48092 | EX6: 48122 | EY6: 48153 | EZ6: 48183 | FA6: Acumulado 2031 | FB6: 48214 | FC6: 48245 | FD6: 48274 | FE6: 48305 | FF6: 48335 | FG6: 48366 | FH6: 48396 | FI6: 48427 | FJ6: 48458 | FK6: 48488 | FL6: 48519 | FM6: 48549 | FN6: Acumulado 2032 | FO6: 48580 | FP6: 48611 | FQ6: 48639 | FR6: 48670 | FS6: 48700 | FT6: 48731 | FU6: 48761 | FV6: 48792 | FW6: 48823 | FX6: 48853 | FY6: 48884 | FZ6: 48914 | GA6: Acumulado 2033 | GB6: 48945 | GC6: 48976 | GD6: 49004 | GE6: 49035 | GF6: 49065 | GG6: 49096 | GH6: 49126 | GI6: 49157 | GJ6: 49188 | GK6: 49218 | GL6: 49249 | GM6: 49279 | GN6: Acumulado 2034 | GO6: 49310 | GP6: 49341 | GQ6: 49369 | GR6: 49400 | GS6: 49430 | GT6: 49461 | GU6: 49491 | GV6: 49522 | GW6: 49553 | GX6: 49583 | GY6: 49614 | GZ6: 49644 | HA6: Acumulado 2035 | HC6: 2020 | HD6: 2021 | HE6: 2022 | HF6: 2023 | HG6: 2024 | HH6: 2025 | HI6: 2026 | HJ6: 2027 | HK6: 2028 | HL6: 2029 | HM6: 2030 | HN6: 2031 | HO6: 2032 | HP6: 2033 | HQ6: 2034 | HR6: 2035
