Workbook
Name A: #REF!
Name A: #REF!
Name alex: [8]AGENCIA!#REF!
Name alex: [8]AGENCIA!#REF!
Name asdf: #REF!
Name asdf: #REF!

Sheet Mayo
A1: TARJETA BAM | B1: Pago | C1: Vigencia | D1: Tipo | E1: Poliza | F1: Certificado | G1: Nombre | H1: Fecha | I1: Fecha Cobro | J1: Zona | K1: Fuente | L1: Agencia | M1: Cod. Colaborador | N1: Nombre colaborador | O1: Prima | P1: Cod. Jefe | Q1: Nombre Jefe | R1: Producto | S1: Puesto | U1: Modificaciones | V1: Control | W1: Equipo | X1: Enviada | Y1: Meta campaña | Z1: Asesor
A2: SI | C2: 2 | D2: VIDA+SEGURO | E2: VCB-20220010 | F2: 1097 | G2: LEONIDAS BERNABE LOPEZ RAMOS | H2: 46266 | I2: 46266 | J2: =+VLOOKUP(K2,Datos!$A:$C,3,FALSE) -> SUROCCIDENTE | K2: 297 | L2: =+VLOOKUP(K2,Datos!$A:$C,2,FALSE) -> LA TRINIDAD COATEPEQUE | M2: 310220 | N2: =+VLOOKUP(M2,Datos!$F:$G,2,FALSE) -> Urias Samuel Velasquez Ardeano | O2: =IFERROR(IF(A2="SI",VLOOKUP(R2,Datos!$J$1:$K$50,2,FALSE)*C2,VLOOKUP(R2,Datos!$P$1:$T$13,2,FALSE)*C2),0) -> 1632 | P2: 311975 | Q2: =+VLOOKUP(P2,Datos!$F:$G,2,FALSE) -> Luis Eduardo Ramirez Arriaza | R2: VIDA+SEGURO | V2: =+COUNTIFS($G$2:$G$444,G2) -> 1 | W2: =+VLOOKUP(M2,Datos!$F:$H,3,FALSE) -> 0 | X2: 0 | Z2: =VLOOKUP(M2,'[1]INDIVIDUAL UN'!$C$6:$F$222,4,FALSE) -> #N/A
A3: SI | C3: 4 | D3: NUEVO | E3: VCB-20240008 | F3: 625 | G3: JAIME LEONEL DE LEON REYES | H3: 46266 | I3: 46266 | J3: =+VLOOKUP(K3,Datos!$A:$C,3,FALSE) -> SUROCCIDENTE | K3: 31 | L3: =+VLOOKUP(K3,Datos!$A:$C,2,FALSE) -> COATEPEQUE | M3: 316174 | N3: =+VLOOKUP(M3,Datos!$F:$G,2,FALSE) -> ENRIQUE ALFONSO LOPEZ RAMREZ | O3: =IFERROR(IF(A3="SI",VLOOKUP(R3,Datos!$J$1:$K$50,2,FALSE)*C3,VLOOKUP(R3,Datos!$P$1:$T$13,2,FALSE)*C3),0) -> 3264 | P3: 311258 | Q3: =+VLOOKUP(P3,Datos!$F:$G,2,FALSE) -> Victor Otoniel Sebastian Cardona | R3: VIDA+SEGURO | V3: =+COUNTIFS($G$2:$G$444,G3) -> 1 | W3: =+VLOOKUP(M3,Datos!$F:$H,3,FALSE) -> 0 | X3: 0 | Z3: =VLOOKUP(M3,'[1]INDIVIDUAL UN'!$C$6:$F$222,4,FALSE) -> #N/A
A4: SI | C4: 1 | D4: NUEVO | E4: VCB - 20210003 | F4: 4179 | G4: ERIKA MARINA ALONZO | H4: 46266 | I4: 46266 | J4: =+VLOOKUP(K4,Datos!$A:$C,3,FALSE) -> OCCIDENTE | K4: 28 | L4: =+VLOOKUP(K4,Datos!$A:$C,2,FALSE) -> SUCURSAL QUETZALTENANGO | M4: 90024418 | N4: =+VLOOKUP(M4,Datos!$F:$G,2,FALSE) -> EDNA GABRIELA RAMIREZ | O4: =IFERROR(IF(A4="SI",VLOOKUP(R4,Datos!$J$1:$K$50,2,FALSE)*C4,VLOOKUP(R4,Datos!$P$1:$T$13,2,FALSE)*C4),0) -> 816 | P4: 313644 | Q4: =+VLOOKUP(P4,Datos!$F:$G,2,FALSE) -> Estefani Elizabeth Tzul Macario | R4: VIDA+SEGURO | V4: =+COUNTIFS($G$2:$G$444,G4) -> 1 | W4: =+VLOOKUP(M4,Datos!$F:$H,3,FALSE) -> 0 | X4: 0 | Z4: =VLOOKUP(M4,'[1]INDIVIDUAL UN'!$C$6:$F$222,4,FALSE) -> #N/A
A5: SI | C5: 1 | D5: NUEVO | E5: APSS-20200009 | F5: 2938 | G5: JOSUE EZEQUIEL CAAL | H5: 46266 | I5: 46266 | J5: =+VLOOKUP(K5,Datos!$A:$C,3,FALSE) -> OCCIDENTE | K5: 126 | L5: =+VLOOKUP(K5,Datos!$A:$C,2,FALSE) -> CHICHICASTENANGO | M5: 314956 | N5: =+VLOOKUP(M5,Datos!$F:$G,2,FALSE) -> Sebastian Geovanny Calel Ixtuc | O5: =IFERROR(IF(A5="SI",VLOOKUP(R5,Datos!$J$1:$K$50,2,FALSE)*C5,VLOOKUP(R5,Datos!$P$1:$T$13,2,FALSE)*C5),0) -> 1428 | P5: 306497 | Q5: =+VLOOKUP(P5,Datos!$F:$G,2,FALSE) -> Erika Ixtan Canil | R5: CONSULTA BASICO | V5: =+COUNTIFS($G$2:$G$444,G5) -> 1 | W5: =+VLOOKUP(M5,Datos!$F:$H,3,FALSE) -> 0 | X5: 0 | Z5: =VLOOKUP(M5,'[1]INDIVIDUAL UN'!$C$6:$F$222,4,FALSE) -> #N/A
A6: SI | C6: 1 | D6: NUEVO | E6: VCB-20210003 | F6: 4168 | G6: CARLOS ALFREDO TECUN DOMINGUEZ | H6: 46266 | I6: 46266 | J6: =+VLOOKUP(K6,Datos!$A:$C,3,FALSE) -> OCCIDENTE | K6: 126 | L6: =+VLOOKUP(K6,Datos!$A:$C,2,FALSE) -> CHICHICASTENANGO | M6: 310610 | N6: =+VLOOKUP(M6,Datos!$F:$G,2,FALSE) -> Ricky Edson Lux Cassia | O6: =IFERROR(IF(A6="SI",VLOOKUP(R6,Datos!$J$1:$K$50,2,FALSE)*C6,VLOOKUP(R6,Datos!$P$1:$T$13,2,FALSE)*C6),0) -> 816 | P6: 303674 | Q6: =+VLOOKUP(P6,Datos!$F:$G,2,FALSE) -> Imelda Elizabeth Castro Rodas | R6: VIDA+SEGURO | V6: =+COUNTIFS($G$2:$G$444,G6) -> 1 | W6: =+VLOOKUP(M6,Datos!$F:$H,3,FALSE) -> 0 | X6: 0 | Z6: =VLOOKUP(M6,'[1]INDIVIDUAL UN'!$C$6:$F$222,4,FALSE) -> #N/A
A7: SI | C7: 1 | D7: NUEVO | E7: VCB-20210003 | F7: 4178 | G7: MARIA TERESA BOCEL TECUN | H7: 46266 | I7: 46266 | J7: =+VLOOKUP(K7,Datos!$A:$C,3,FALSE) -> OCCIDENTE | K7: 126 | L7: =+VLOOKUP(K7,Datos!$A:$C,2,FALSE) -> CHICHICASTENANGO | M7: 309989 | N7: =+VLOOKUP(M7,Datos!$F:$G,2,FALSE) -> Olga Maricela Guarcas Tol | O7: =IFERROR(IF(A7="SI",VLOOKUP(R7,Datos!$J$1:$K$50,2,FALSE)*C7,VLOOKUP(R7,Datos!$P$1:$T$13,2,FALSE)*C7),0) -> 816 | P7: 303674 | Q7: =+VLOOKUP(P7,Datos!$F:$G,2,FALSE) -> Imelda Elizabeth Castro Rodas | R7: VIDA+SEGURO | V7: =+COUNTIFS($G$2:$G$444,G7) -> 1 | W7: =+VLOOKUP(M7,Datos!$F:$H,3,FALSE) -> 0 | X7: 0 | Z7: =VLOOKUP(M7,'[1]INDIVIDUAL UN'!$C$6:$F$222,4,FALSE) -> #N/A
A8: SI | C8: 2 | D8: NUEVO | E8: VCB-20220010 | F8: 1093 | G8: MARIA ESPERANZA CANEL DIAZ | H8: 46266 | I8: 46266 | J8: =+VLOOKUP(K8,Datos!$A:$C,3,FALSE) -> SUROCCIDENTE | K8: 297 | L8: =+VLOOKUP(K8,Datos!$A:$C,2,FALSE) -> LA TRINIDAD COATEPEQUE | M8: 306248 | N8: =+VLOOKUP(M8,Datos!$F:$G,2,FALSE) -> Gladys Susana Marin De Leon | O8: =IFERROR(IF(A8="SI",VLOOKUP(R8,Datos!$J$1:$K$50,2,FALSE)*C8,VLOOKUP(R8,Datos!$P$1:$T$13,2,FALSE)*C8),0) -> 1632 | P8: 311975 | Q8: =+VLOOKUP(P8,Datos!$F:$G,2,FALSE) -> Luis Eduardo Ramirez Arriaza | R8: VIDA+SEGURO | V8: =+COUNTIFS($G$2:$G$444,G8) -> 1 | W8: =+VLOOKUP(M8,Datos!$F:$H,3,FALSE) -> 0 | X8: 0 | Z8: =VLOOKUP(M8,'[1]INDIVIDUAL UN'!$C$6:$F$222,4,FALSE) -> #N/A
A9: SI | C9: 3 | D9: NUEVO | E9: VCB-20220034 | F9: 600 | G9: JULIO ROBERTO CAJAS HERNANDEZ | H9: 46267 | I9: 46267 | J9: =+VLOOKUP(K9,Datos!$A:$C,3,FALSE) -> OCCIDENTE | K9: 56 | L9: =+VLOOKUP(K9,Datos!$A:$C,2,FALSE) -> LOS ALTOS | M9: 90040102 | N9: =+VLOOKUP(M9,Datos!$F:$G,2,FALSE) -> KAREN JASMIN PEREZ CORONADO | O9: =IFERROR(IF(A9="SI",VLOOKUP(R9,Datos!$J$1:$K$50,2,FALSE)*C9,VLOOKUP(R9,Datos!$P$1:$T$13,2,FALSE)*C9),0) -> 2448 | P9: 308266 | Q9: =+VLOOKUP(P9,Datos!$F:$G,2,FALSE) -> Julio Cesar De Leon Huinac | R9: VIDA+SEGURO | V9: =+COUNTIFS($G$2:$G$444,G9) -> 1 | W9: =+VLOOKUP(M9,Datos!$F:$H,3,FALSE) -> 0 | X9: 0 | Z9: =VLOOKUP(M9,'[1]INDIVIDUAL UN'!$C$6:$F$222,4,FALSE) -> #N/A
A10: SI | C10: 1 | D10: NUEVO | E10: ACPE-20210019 | F10: 2898 | G10: ISIAIAS OTONIEL LOPEZ SOTO | H10: 46267 | I10: 46266 | J10: =+VLOOKUP(K10,Datos!$A:$C,3,FALSE) -> SUROCCIDENTE | K10: 178 | L10: =+VLOOKUP(K10,Datos!$A:$C,2,FALSE) -> LA TRINIDAD MALACATAN | M10: 90019118 | N10: =+VLOOKUP(M10,Datos!$F:$G,2,FALSE) -> Angela Josefina Ramírez Chang | O10: =IFERROR(IF(A10="SI",VLOOKUP(R10,Datos!$J$1:$K$50,2,FALSE)*C10,VLOOKUP(R10,Datos!$P$1:$T$13,2,FALSE)*C10),0) -> 1308 | P10: 304805 | Q10: =+VLOOKUP(P10,Datos!$F:$G,2,FALSE) -> Sheily Raquel Angel Arreaga | R10: AP DENTAL INDIVIDUAL | V10: =+COUNTIFS($G$2:$G$444,G10) -> 1 | W10: =+VLOOKUP(M10,Datos!$F:$H,3,FALSE) -> 0 | X10: 0 | Z10: =VLOOKUP(M10,'[1]INDIVIDUAL UN'!$C$6:$F$222,4,FALSE) -> #N/A
A11: SI | C11: 2 | D11: NUEVO | E11: VCB-20220010 | F11: 1100 | G11: ENMA MISHELLE LOPEZ LOPEZ | H11: 46267 | I11: 46267 | J11: =+VLOOKUP(K11,Datos!$A:$C,3,FALSE) -> SUROCCIDENTE | K11: 178 | L11: =+VLOOKUP(K11,Datos!$A:$C,2,FALSE) -> LA TRINIDAD MALACATAN | M11: 90019118 | N11: =+VLOOKUP(M11,Datos!$F:$G,2,FALSE) -> Angela Josefina Ramírez Chang | O11: =IFERROR(IF(A11="SI",VLOOKUP(R11,Datos!$J$1:$K$50,2,FALSE)*C11,VLOOKUP(R11,Datos!$P$1:$T$13,2,FALSE)*C11),0) -> 1632 | P11: 304805 | Q11: =+VLOOKUP(P11,Datos!$F:$G,2,FALSE) -> Sheily Raquel Angel Arreaga | R11: VIDA+SEGURO | V11: =+COUNTIFS($G$2:$G$444,G11) -> 1 | W11: =+VLOOKUP(M11,Datos!$F:$H,3,FALSE) -> 0 | X11: 0 | Z11: =VLOOKUP(M11,'[1]INDIVIDUAL UN'!$C$6:$F$222,4,FALSE) -> #N/A
A12: SI | C12: 2 | D12: NUEVO | E12: VCB-20220010 | F12: 1114 | G12: JUAN JOSE RAMOS GOMEZ | H12: 46267 | I12: 46267 | J12: =+VLOOKUP(K12,Datos!$A:$C,3,FALSE) -> SUROCCIDENTE | K12: 178 | L12: =+VLOOKUP(K12,Datos!$A:$C,2,FALSE) -> LA TRINIDAD MALACATAN | M12: 316215 | N12: =+VLOOKUP(M12,Datos!$F:$G,2,FALSE) -> ANAYELI MARIBEL JIMENEZ GOMEZ | O12: =IFERROR(IF(A12="SI",VLOOKUP(R12,Datos!$J$1:$K$50,2,FALSE)*C12,VLOOKUP(R12,Datos!$P$1:$T$13,2,FALSE)*C12),0) -> 2736 | P12: 316487 | Q12: =+VLOOKUP(P12,Datos!$F:$G,2,FALSE) -> Wilmer Ovando Mejia Godínez | R12: VIDA+SEGURO PLAN 1 | V12: =+COUNTIFS($G$2:$G$444,G12) -> 1 | W12: =+VLOOKUP(M12,Datos!$F:$H,3,FALSE) -> 0 | X12: 0 | Z12: =VLOOKUP(M12,'[1]INDIVIDUAL UN'!$C$6:$F$222,4,FALSE) -> #N/A
A13: SI | C13: 1 | D13: NUEVO | E13: VCB-20210003 | F13: 4192 | G13: OSBALDO DAVID SAMAYOA RODRIGUEZ | H13: 46267 | I13: 46267 | J13: =+VLOOKUP(K13,Datos!$A:$C,3,FALSE) -> OCCIDENTE | K13: 55 | L13: =+VLOOKUP(K13,Datos!$A:$C,2,FALSE) -> ZENTROPLAZA | M13: 313671 | N13: =+VLOOKUP(M13,Datos!$F:$G,2,FALSE) -> Virginia Yesenia Merida Lopez De Lopez | O13: =IFERROR(IF(A13="SI",VLOOKUP(R13,Datos!$J$1:$K$50,2,FALSE)*C13,VLOOKUP(R13,Datos!$P$1:$T$13,2,FALSE)*C13),0) -> 1368 | P13: 311950 | Q13: =+VLOOKUP(P13,Datos!$F:$G,2,FALSE) -> Alan Javier Castillo Ordoñez | R13: VIDA+SEGURO PLAN 1 | V13: =+COUNTIFS($G$2:$G$444,G13) -> 1 | W13: =+VLOOKUP(M13,Datos!$F:$H,3,FALSE) -> 0 | X13: 0 | Z13: =VLOOKUP(M13,'[1]INDIVIDUAL UN'!$C$6:$F$222,4,FALSE) -> #N/A
... A22: SI | C22: 1 | D22: NUEVO | E22: VCB-20210003 | F22: 4203 | G22: MATILDE TOMAS PEDRO | H22: 46267 | I22: 46267 | J22: =+VLOOKUP(K22,Datos!$A:$C,3,FALSE) -> OCCIDENTE | K22: 246 | L22: =+VLOOKUP(K22,Datos!$A:$C,2,FALSE) -> SANTA CRUZ BARILLAS | M22: 313666 | N22: =+VLOOKUP(M22,Datos!$F:$G,2,FALSE) -> Avner Josue Merida Molina | O22: =IFERROR(IF(A22="SI",VLOOKUP(R22,Datos!$J$1:$K$50,2,FALSE)*C22,VLOOKUP(R22,Datos!$P$1:$T$13,2,FALSE)*C22),0) -> 1368 | P22: 304166 | Q22: =+VLOOKUP(P22,Datos!$F:$G,2,FALSE) -> Maviela Bibianeth Castillo Avila | R22: VIDA+SEGURO PLAN 1 | V22: =+COUNTIFS($G$2:$G$444,G22) -> 1 | W22: =+VLOOKUP(M22,Datos!$F:$H,3,FALSE) -> 0 | X22: 0 | Z22: =VLOOKUP(M22,'[1]INDIVIDUAL UN'!$C$6:$F$222,4,FALSE) -> #N/A
A23: SI | C23: 1 | D23: NUEVO | E23: VCB-20210003 | F23: 4185 | G23: CECILIA MARISOL SALES | H23: 46267 | I23: 46267 | J23: =+VLOOKUP(K23,Datos!$A:$C,3,FALSE) -> SUROCCIDENTE | K23: 31 | L23: =+VLOOKUP(K23,Datos!$A:$C,2,FALSE) -> COATEPEQUE | M23: 90065999 | N23: =+VLOOKUP(M23,Datos!$F:$G,2,FALSE) -> SEPHORA ABIGAIL SANCHEZ HERDOCIA | O23: =IFERROR(IF(A23="SI",VLOOKUP(R23,Datos!$J$1:$K$50,2,FALSE)*C23,VLOOKUP(R23,Datos!$P$1:$T$13,2,FALSE)*C23),0) -> 1368 | P23: 311258 | Q23: =+VLOOKUP(P23,Datos!$F:$G,2,FALSE) -> Victor Otoniel Sebastian Cardona | R23: VIDA+SEGURO PLAN 1 | V23: =+COUNTIFS($G$2:$G$444,G23) -> 1 | W23: =+VLOOKUP(M23,Datos!$F:$H,3,FALSE) -> 0 | X23: 0 | Z23: =VLOOKUP('[2]DICIEMBREE 2024'!M51,'[1]INDIVIDUAL UN'!$C$6:$F$222,4,FALSE) -> #N/A
A24: SI | C24: 1 | D24: NUEVO | E24: VCB-20210003 | F24: 4194 | G24: HENRRI AVILA SANTIZO | H24: 46267 | I24: 46267 | J24: =+VLOOKUP(K24,Datos!$A:$C,3,FALSE) -> SUROCCIDENTE | K24: 297 | L24: =+VLOOKUP(K24,Datos!$A:$C,2,FALSE) -> LA TRINIDAD COATEPEQUE | M24: 312831 | N24: =+VLOOKUP(M24,Datos!$F:$G,2,FALSE) -> Cindy Yojana Mendoza Cajas | O24: =IFERROR(IF(A24="SI",VLOOKUP(R24,Datos!$J$1:$K$50,2,FALSE)*C24,VLOOKUP(R24,Datos!$P$1:$T$13,2,FALSE)*C24),0) -> 816 | P24: 311975 | Q24: =+VLOOKUP(P24,Datos!$F:$G,2,FALSE) -> Luis Eduardo Ramirez Arriaza | R24: VIDA+SEGURO | V24: =+COUNTIFS($G$2:$G$444,G24) -> 1 | W24: =+VLOOKUP(M24,Datos!$F:$H,3,FALSE) -> 0 | X24: 0 | Z24: =VLOOKUP(M24,'[1]INDIVIDUAL UN'!$C$6:$F$222,4,FALSE) -> #N/A
A25: SI | C25: 1 | D25: NUEVO | E25: VCB 20220009 | F25: 4193 | G25: BAYRON NATTANAEL LOPEZ BARAN | H25: 46267 | I25: 46267 | J25: =+VLOOKUP(K25,Datos!$A:$C,3,FALSE) -> OCCIDENTE | K25: 28 | L25: =+VLOOKUP(K25,Datos!$A:$C,2,FALSE) -> SUCURSAL QUETZALTENANGO | M25: 304024 | N25: =+VLOOKUP(M25,Datos!$F:$G,2,FALSE) -> Vicky Roxana Lopez Hernandez | O25: =IFERROR(IF(A25="SI",VLOOKUP(R25,Datos!$J$1:$K$50,2,FALSE)*C25,VLOOKUP(R25,Datos!$P$1:$T$13,2,FALSE)*C25),0) -> 816 | P25: 313644 | Q25: =+VLOOKUP(P25,Datos!$F:$G,2,FALSE) -> Estefani Elizabeth Tzul Macario | R25: VIDA+SEGURO | V25: =+COUNTIFS($G$2:$G$444,G25) -> 1 | W25: =+VLOOKUP(M25,Datos!$F:$H,3,FALSE) -> 0 | X25: 0 | Z25: =VLOOKUP(M25,'[1]INDIVIDUAL UN'!$C$6:$F$222,4,FALSE) -> #N/A
A26: SI | C26: 1 | D26: NUEVO | E26: VCB 20210003 | F26: 4182 | G26: SAMUEL SOLIS MORALES | H26: 46267 | I26: 46267 | J26: =+VLOOKUP(K26,Datos!$A:$C,3,FALSE) -> OCCIDENTE | K26: 56 | L26: =+VLOOKUP(K26,Datos!$A:$C,2,FALSE) -> LOS ALTOS | M26: 315133 | N26: =+VLOOKUP(M26,Datos!$F:$G,2,FALSE) -> Bryan Daniel Milián De Leon | O26: =IFERROR(IF(A26="SI",VLOOKUP(R26,Datos!$J$1:$K$50,2,FALSE)*C26,VLOOKUP(R26,Datos!$P$1:$T$13,2,FALSE)*C26),0) -> 816 | P26: 308266 | Q26: =+VLOOKUP(P26,Datos!$F:$G,2,FALSE) -> Julio Cesar De Leon Huinac | R26: VIDA+SEGURO | V26: =+COUNTIFS($G$2:$G$444,G26) -> 1 | W26: =+VLOOKUP(M26,Datos!$F:$H,3,FALSE) -> 0 | X26: 0 | Z26: =VLOOKUP(M26,'[1]INDIVIDUAL UN'!$C$6:$F$222,4,FALSE) -> #N/A
A27: SI | C27: 2 | D27: NUEVO | E27: VCB-20220010 | F27: 1126 | G27: YOSELIN YESSENIA ALVAREZ PEREZ | H27: 46268 | I27: 46268 | J27: =+VLOOKUP(K27,Datos!$A:$C,3,FALSE) -> SUROCCIDENTE | K27: 89 | L27: =+VLOOKUP(K27,Datos!$A:$C,2,FALSE) -> LA TRINIDAD RETALHULEU | M27: 90064210 | N27: =+VLOOKUP(M27,Datos!$F:$G,2,FALSE) -> GEREMY ARMANDO HERNANDEZ CAMACHO | O27: =IFERROR(IF(A27="SI",VLOOKUP(R27,Datos!$J$1:$K$50,2,FALSE)*C27,VLOOKUP(R27,Datos!$P$1:$T$13,2,FALSE)*C27),0) -> 1632 | P27: 302841 | Q27: =+VLOOKUP(P27,Datos!$F:$G,2,FALSE) -> Jessica Maria Jose Santizo Guzman | R27: VIDA+SEGURO | V27: =+COUNTIFS($G$2:$G$444,G27) -> 1 | W27: =+VLOOKUP(M27,Datos!$F:$H,3,FALSE) -> 0 | X27: 0 | Z27: =VLOOKUP(M27,'[1]INDIVIDUAL UN'!$C$6:$F$222,4,FALSE) -> #N/A
A28: SI | C28: 3 | D28: NUEVO | E28: VCB-20220034 | F28: 602 | G28: ROSA ESPERANZA SIPAC CHIRIX | H28: 46268 | I28: 46268 | J28: =+VLOOKUP(K28,Datos!$A:$C,3,FALSE) -> OCCIDENTE | K28: 155 | L28: =+VLOOKUP(K28,Datos!$A:$C,2,FALSE) -> TECPAN | M28: 315629 | N28: =+VLOOKUP(M28,Datos!$F:$G,2,FALSE) -> Rucuch Choguaj, Miguel | O28: =IFERROR(IF(A28="SI",VLOOKUP(R28,Datos!$J$1:$K$50,2,FALSE)*C28,VLOOKUP(R28,Datos!$P$1:$T$13,2,FALSE)*C28),0) -> 2448 | P28: 305955 | Q28: =+VLOOKUP(P28,Datos!$F:$G,2,FALSE) -> Jorge Alfredo Gutierrez Rodriguez | R28: VIDA+SEGURO | V28: =+COUNTIFS($G$2:$G$444,G28) -> 1 | W28: =+VLOOKUP(M28,Datos!$F:$H,3,FALSE) -> 0 | X28: 0 | Z28: =VLOOKUP(M28,'[1]INDIVIDUAL UN'!$C$6:$F$222,4,FALSE) -> #N/A
A29: SI | C29: 1 | D29: NUEVO | E29: VCB-20210003 | F29: 4216 | G29: HENRY FERNANDO LOPEZ PASCUAL | H29: 46268 | I29: 03/29/2026 | J29: =+VLOOKUP(K29,Datos!$A:$C,3,FALSE) -> SUROCCIDENTE | K29: 31 | L29: =+VLOOKUP(K29,Datos!$A:$C,2,FALSE) -> COATEPEQUE | M29: 310671 | N29: =+VLOOKUP(M29,Datos!$F:$G,2,FALSE) -> Sucely Paola Godinez Gomez De Perez | O29: =IFERROR(IF(A29="SI",VLOOKUP(R29,Datos!$J$1:$K$50,2,FALSE)*C29,VLOOKUP(R29,Datos!$P$1:$T$13,2,FALSE)*C29),0) -> 1368 | P29: 306654 | Q29: =+VLOOKUP(P29,Datos!$F:$G,2,FALSE) -> Gerson Arcadio Hernandez Barrios | R29: VIDA+SEGURO PLAN 1 | V29: =+COUNTIFS($G$2:$G$444,G29) -> 1 | W29: =+VLOOKUP(M29,Datos!$F:$H,3,FALSE) -> 0 | X29: 0 | Z29: =VLOOKUP(M29,'[1]INDIVIDUAL UN'!$C$6:$F$222,4,FALSE) -> #N/A
A30: SI | C30: 1 | D30: NUEVO | E30: VCB-20210015 | F30: 407 | G30: BONIFILIO GUDIEL HUINIL CHAY | H30: 46268 | I30: 46268 | J30: =+VLOOKUP(K30,Datos!$A:$C,3,FALSE) -> SUROCCIDENTE | K30: 31 | L30: =+VLOOKUP(K30,Datos!$A:$C,2,FALSE) -> COATEPEQUE | M30: 315679 | N30: =+VLOOKUP(M30,Datos!$F:$G,2,FALSE) -> ANGELA XIOMARA PONCIANO GONZALEZ | O30: =IFERROR(IF(A30="SI",VLOOKUP(R30,Datos!$J$1:$K$50,2,FALSE)*C30,VLOOKUP(R30,Datos!$P$1:$T$13,2,FALSE)*C30),0) -> 1092 | P30: 311258 | Q30: =+VLOOKUP(P30,Datos!$F:$G,2,FALSE) -> Victor Otoniel Sebastian Cardona | R30: PREVENCION+SEGURA | V30: =+COUNTIFS($G$2:$G$444,G30) -> 1 | W30: =+VLOOKUP(M30,Datos!$F:$H,3,FALSE) -> 0 | X30: 0 | Z30: =VLOOKUP(M30,'[1]INDIVIDUAL UN'!$C$6:$F$222,4,FALSE) -> #N/A
A31: SI | C31: 1 | D31: NUEVO | E31: VCB-20210003 | F31: 4243 | G31: MARVIN ESTUARDO RIOS AGUSTIN | H31: 46268 | I31: 46268 | J31: =+VLOOKUP(K31,Datos!$A:$C,3,FALSE) -> OCCIDENTE | K31: 55 | L31: =+VLOOKUP(K31,Datos!$A:$C,2,FALSE) -> ZENTROPLAZA | M31: 315686 | N31: =+VLOOKUP(M31,Datos!$F:$G,2,FALSE) -> REINA NOHEMI PASCUAL | O31: =IFERROR(IF(A31="SI",VLOOKUP(R31,Datos!$J$1:$K$50,2,FALSE)*C31,VLOOKUP(R31,Datos!$P$1:$T$13,2,FALSE)*C31),0) -> 816 | P31: 311950 | Q31: =+VLOOKUP(P31,Datos!$F:$G,2,FALSE) -> Alan Javier Castillo Ordoñez | R31: VIDA+SEGURO | V31: =+COUNTIFS($G$2:$G$444,G31) -> 1 | W31: =+VLOOKUP(M31,Datos!$F:$H,3,FALSE) -> 0 | X31: 0 | Z31: =VLOOKUP(M31,'[1]INDIVIDUAL UN'!$C$6:$F$222,4,FALSE) -> #N/A
A32: SI | C32: 2 | D32: NUEVO | E32: VCB- 20220022 | F32: 133 | G32: JERONIMO ROSALES LOPEZ | H32: 46268 | I32: 46268 | J32: =+VLOOKUP(K32,Datos!$A:$C,3,FALSE) -> SUROCCIDENTE | K32: 297 | L32: =+VLOOKUP(K32,Datos!$A:$C,2,FALSE) -> LA TRINIDAD COATEPEQUE | M32: 306248 | N32: =+VLOOKUP(M32,Datos!$F:$G,2,FALSE) -> Gladys Susana Marin De Leon | O32: =IFERROR(IF(A32="SI",VLOOKUP(R32,Datos!$J$1:$K$50,2,FALSE)*C32,VLOOKUP(R32,Datos!$P$1:$T$13,2,FALSE)*C32),0) -> 2184 | P32: 311975 | Q32: =+VLOOKUP(P32,Datos!$F:$G,2,FALSE) -> Luis Eduardo Ramirez Arriaza | R32: PREVENCION+SEGURA | V32: =+COUNTIFS($G$2:$G$444,G32) -> 1 | W32: =+VLOOKUP(M32,Datos!$F:$H,3,FALSE) -> 0 | X32: 0 | Z32: =VLOOKUP(M32,'[1]INDIVIDUAL UN'!$C$6:$F$222,4,FALSE) -> #N/A
A33: SI | C33: 1 | D33: NUEVO | E33: VCB-20210003 | F33: 4229 | G33: TOMAS DOMINGO ZACARIAS DOMINGO | H33: 46268 | I33: 46268 | J33: =+VLOOKUP(K33,Datos!$A:$C,3,FALSE) -> OCCIDENTE | K33: 33 | L33: =+VLOOKUP(K33,Datos!$A:$C,2,FALSE) -> HUEHUETENANGO | M33: 314636 | N33: =+VLOOKUP(M33,Datos!$F:$G,2,FALSE) -> Walkiria Anais Herrera Castillo | O33: =IFERROR(IF(A33="SI",VLOOKUP(R33,Datos!$J$1:$K$50,2,FALSE)*C33,VLOOKUP(R33,Datos!$P$1:$T$13,2,FALSE)*C33),0) -> 1368 | P33: 313225 | Q33: =+VLOOKUP(P33,Datos!$F:$G,2,FALSE) -> Karen Deniss Lucas Chavez | R33: VIDA+SEGURO PLAN 1 | V33: =+COUNTIFS($G$2:$G$444,G33) -> 1 | W33: =+VLOOKUP(M33,Datos!$F:$H,3,FALSE) -> 0 | X33: 0 | Z33: =VLOOKUP(M33,'[1]INDIVIDUAL UN'!$C$6:$F$222,4,FALSE) -> #N/A
A34: SI | C34: 2 | D34: NUEVO | E34: VCB-20220010 | F34: 1115 | G34: LIDIA ESPERANZA REYES CIFUENTES | H34: 46268 | I34: 46267 | J34: =+VLOOKUP(K34,Datos!$A:$C,3,FALSE) -> SUROCCIDENTE | K34: 297 | L34: =+VLOOKUP(K34,Datos!$A:$C,2,FALSE) -> LA TRINIDAD COATEPEQUE | M34: 310220 | N34: =+VLOOKUP(M34,Datos!$F:$G,2,FALSE) -> Urias Samuel Velasquez Ardeano | O34: =IFERROR(IF(A34="SI",VLOOKUP(R34,Datos!$J$1:$K$50,2,FALSE)*C34,VLOOKUP(R34,Datos!$P$1:$T$13,2,FALSE)*C34),0) -> 1632 | P34: 311975 | Q34: =+VLOOKUP(P34,Datos!$F:$G,2,FALSE) -> Luis Eduardo Ramirez Arriaza | R34: VIDA+SEGURO | V34: =+COUNTIFS($G$2:$G$444,G34) -> 1 | W34: =+VLOOKUP(M34,Datos!$F:$H,3,FALSE) -> 0 | X34: 0 | Z34: =VLOOKUP(M34,'[1]INDIVIDUAL UN'!$C$6:$F$222,4,FALSE) -> #N/A
A35: SI | C35: 1 | D35: NUEVO | E35: VCB-20210003 | F35: 4233 | G35: RONI MARCOTULIO MIRANDA ORTEGA | H35: 46268 | I35: 46268 | J35: =+VLOOKUP(K35,Datos!$A:$C,3,FALSE) -> SUROCCIDENTE | K35: 297 | L35: =+VLOOKUP(K35,Datos!$A:$C,2,FALSE) -> LA TRINIDAD COATEPEQUE | M35: 310220 | N35: =+VLOOKUP(M35,Datos!$F:$G,2,FALSE) -> Urias Samuel Velasquez Ardeano | O35: =IFERROR(IF(A35="SI",VLOOKUP(R35,Datos!$J$1:$K$50,2,FALSE)*C35,VLOOKUP(R35,Datos!$P$1:$T$13,2,FALSE)*C35),0) -> 816 | P35: 311975 | Q35: =+VLOOKUP(P35,Datos!$F:$G,2,FALSE) -> Luis Eduardo Ramirez Arriaza | R35: VIDA+SEGURO | V35: =+COUNTIFS($G$2:$G$444,G35) -> 1 | W35: =+VLOOKUP(M35,Datos!$F:$H,3,FALSE) -> 0 | X35: 0 | Z35: =VLOOKUP(M35,'[1]INDIVIDUAL UN'!$C$6:$F$222,4,FALSE) -> #N/A
A36: SI | C36: 1 | D36: NUEVO | E36: VCB-20210003 | F36: 4221 | G36: JOSE LUIS CHOCHOM LOPEZ | H36: 46268 | I36: 46268 | J36: =+VLOOKUP(K36,Datos!$A:$C,3,FALSE) -> SUROCCIDENTE | K36: 143 | L36: =+VLOOKUP(K36,Datos!$A:$C,2,FALSE) -> RETALHULEU LA SIRENA | M36: 90087842 | N36: =+VLOOKUP(M36,Datos!$F:$G,2,FALSE) -> ANGEL DAVID BAMAC ORELLANA | O36: =IFERROR(IF(A36="SI",VLOOKUP(R36,Datos!$J$1:$K$50,2,FALSE)*C36,VLOOKUP(R36,Datos!$P$1:$T$13,2,FALSE)*C36),0) -> 816 | P36: 311380 | Q36: =+VLOOKUP(P36,Datos!$F:$G,2,FALSE) -> Andrea Lisbeth Ruiz Rodas | R36: VIDA+SEGURO | V36: =+COUNTIFS($G$2:$G$444,G36) -> 1 | W36: =+VLOOKUP(M36,Datos!$F:$H,3,FALSE) -> 0 | X36: 0 | Z36: =VLOOKUP(M36,'[1]INDIVIDUAL UN'!$C$6:$F$222,4,FALSE) -> #N/A
A37: SI | C37: 3 | D37: NUEVO | E37: VCB-20220034 | F37: 601 | G37: GIOVANA MARIANA MAZARIEGOS SERRANO | H37: 46268 | I37: 46268 | J37: =+VLOOKUP(K37,Datos!$A:$C,3,FALSE) -> OCCIDENTE | K37: 65 | L37: =+VLOOKUP(K37,Datos!$A:$C,2,FALSE) -> PANAJACHEL | M37: 312996 | N37: =+VLOOKUP(M37,Datos!$F:$G,2,FALSE) -> Marlen Aida Pelaez Ramirez | O37: =IFERROR(IF(A37="SI",VLOOKUP(R37,Datos!$J$1:$K$50,2,FALSE)*C37,VLOOKUP(R37,Datos!$P$1:$T$13,2,FALSE)*C37),0) -> 4104 | P37: 305532 | Q37: =+VLOOKUP(P37,Datos!$F:$G,2,FALSE) -> Nicolas Ajiquichi Ibate | R37: VIDA+SEGURO PLAN 1 | V37: =+COUNTIFS($G$2:$G$444,G37) -> 1 | W37: =+VLOOKUP(M37,Datos!$F:$H,3,FALSE) -> 0 | X37: 0 | Z37: =VLOOKUP(M37,'[1]INDIVIDUAL UN'!$C$6:$F$222,4,FALSE) -> #N/A
A38: SI | C38: 1 | D38: NUEVO | E38: VCB-20210003 | F38: 4217 | G38: ALMA PATRICIA GIRON REYES | H38: 46268 | I38: 46268 | J38: =+VLOOKUP(K38,Datos!$A:$C,3,FALSE) -> SUROCCIDENTE | K38: 297 | L38: =+VLOOKUP(K38,Datos!$A:$C,2,FALSE) -> LA TRINIDAD COATEPEQUE | M38: 312831 | N38: =+VLOOKUP(M38,Datos!$F:$G,2,FALSE) -> Cindy Yojana Mendoza Cajas | O38: =IFERROR(IF(A38="SI",VLOOKUP(R38,Datos!$J$1:$K$50,2,FALSE)*C38,VLOOKUP(R38,Datos!$P$1:$T$13,2,FALSE)*C38),0) -> 816 | P38: 311975 | Q38: =+VLOOKUP(P38,Datos!$F:$G,2,FALSE) -> Luis Eduardo Ramirez Arriaza | R38: VIDA+SEGURO | V38: =+COUNTIFS($G$2:$G$444,G38) -> 1 | W38: =+VLOOKUP(M38,Datos!$F:$H,3,FALSE) -> 0 | X38: 0 | Z38: =VLOOKUP(M38,'[1]INDIVIDUAL UN'!$C$6:$F$222,4,FALSE) -> #N/A
A39: SI | C39: 3 | D39: NUEVO | E39: VCB-20220034 | F39: 603 | G39: KAREN MELISA PEREZ CAN | H39: 46269 | I39: 46269 | J39: =+VLOOKUP(K39,Datos!$A:$C,3,FALSE) -> OCCIDENTE | K39: 155 | L39: =+VLOOKUP(K39,Datos!$A:$C,2,FALSE) -> TECPAN | M39: 315629 | N39: =+VLOOKUP(M39,Datos!$F:$G,2,FALSE) -> Rucuch Choguaj, Miguel | O39: =IFERROR(IF(A39="SI",VLOOKUP(R39,Datos!$J$1:$K$50,2,FALSE)*C39,VLOOKUP(R39,Datos!$P$1:$T$13,2,FALSE)*C39),0) -> 2448 | P39: 305955 | Q39: =+VLOOKUP(P39,Datos!$F:$G,2,FALSE) -> Jorge Alfredo Gutierrez Rodriguez | R39: VIDA+SEGURO | V39: =+COUNTIFS($G$2:$G$444,G39) -> 1 | W39: =+VLOOKUP(M39,Datos!$F:$H,3,FALSE) -> 0 | X39: 0 | Z39: =VLOOKUP(M39,'[1]INDIVIDUAL UN'!$C$6:$F$222,4,FALSE) -> #N/A
A40: SI | C40: 2 | D40: NUEVO | E40: VCB-20220010 | F40: 1133 | G40: DAVID ESTEBAN MENDOZA DOMINGUEZ | H40: 46269 | I40: 46269 | J40: =+VLOOKUP(K40,Datos!$A:$C,3,FALSE) -> OCCIDENTE | K40: 29 | L40: =+VLOOKUP(K40,Datos!$A:$C,2,FALSE) -> SAN PEDRO SACATEPEQUEZ S.M. | M40: 90027919 | N40: =+VLOOKUP(M40,Datos!$F:$G,2,FALSE) -> OFNY JOSELITO FUENTES | O40: =IFERROR(IF(A40="SI",VLOOKUP(R40,Datos!$J$1:$K$50,2,FALSE)*C40,VLOOKUP(R40,Datos!$P$1:$T$13,2,FALSE)*C40),0) -> 1632 | P40: 310641 | Q40: =+VLOOKUP(P40,Datos!$F:$G,2,FALSE) -> Jorge Antonio Ramirez Sicay | R40: VIDA+SEGURO | V40: =+COUNTIFS($G$2:$G$444,G40) -> 1 | W40: =+VLOOKUP(M40,Datos!$F:$H,3,FALSE) -> 0 | X40: 0 | Z40: =VLOOKUP(M40,'[1]INDIVIDUAL UN'!$C$6:$F$222,4,FALSE) -> #N/A
A41: SI | C41: 1 | D41: NUEVO | E41: APSS-20200009 | F41: 2944 | G41: FILIBERTO LOPEZ BUC | H41: 46269 | I41: 46269 | J41: =+VLOOKUP(K41,Datos!$A:$C,3,FALSE) -> OCCIDENTE | K41: 65 | L41: =+VLOOKUP(K41,Datos!$A:$C,2,FALSE) -> PANAJACHEL | M41: 312996 | N41: =+VLOOKUP(M41,Datos!$F:$G,2,FALSE) -> Marlen Aida Pelaez Ramirez | O41: =IFERROR(IF(A41="SI",VLOOKUP(R41,Datos!$J$1:$K$50,2,FALSE)*C41,VLOOKUP(R41,Datos!$P$1:$T$13,2,FALSE)*C41),0) -> 1908 | P41: 305532 | Q41: =+VLOOKUP(P41,Datos!$F:$G,2,FALSE) -> Nicolas Ajiquichi Ibate | R41: CONSULTA BASICO + BIENESTAR | V41: =+COUNTIFS($G$2:$G$444,G41) -> 1 | W41: =+VLOOKUP(M41,Datos!$F:$H,3,FALSE) -> 0 | X41: 0 | Z41: =VLOOKUP(M41,'[1]INDIVIDUAL UN'!$C$6:$F$222,4,FALSE) -> #N/A
... A44: SI | C44: 1 | D44: NUEVO | E44: APSS20200009 | F44: 2945 | G44: EFRAIN MANUEL JIMENEZ MENDEZ | H44: 46269 | I44: 46269 | J44: =+VLOOKUP(K44,Datos!$A:$C,3,FALSE) -> OCCIDENTE | K44: 33 | L44: =+VLOOKUP(K44,Datos!$A:$C,2,FALSE) -> HUEHUETENANGO | M44: 90084483 | N44: =+VLOOKUP(M44,Datos!$F:$G,2,FALSE) -> ASTRID MILETCHA RAYMUNDO HIDALGO | O44: =IFERROR(IF(A44="SI",VLOOKUP(R44,Datos!$J$1:$K$50,2,FALSE)*C44,VLOOKUP(R44,Datos!$P$1:$T$13,2,FALSE)*C44),0) -> 2004 | P44: 301644 | Q44: =+VLOOKUP(P44,Datos!$F:$G,2,FALSE) -> Imelda Eugenia Recinos Martinez | R44: CONSULTA COMPLETO | V44: =+COUNTIFS($G$2:$G$444,G44) -> 1 | W44: =+VLOOKUP(M44,Datos!$F:$H,3,FALSE) -> 0 | X44: 0 | Z44: =VLOOKUP(M44,'[1]INDIVIDUAL UN'!$C$6:$F$222,4,FALSE) -> #N/A
A45: SI | C45: 4 | D45: NUEVO | E45: VCB-20240008 | F45: 647 | G45: JUANA SANTIAGO PANJOJ SALVADOR | H45: 46269 | I45: 46269 | J45: =+VLOOKUP(K45,Datos!$A:$C,3,FALSE) -> OCCIDENTE | K45: 126 | L45: =+VLOOKUP(K45,Datos!$A:$C,2,FALSE) -> CHICHICASTENANGO | M45: 90040633 | N45: =+VLOOKUP(M45,Datos!$F:$G,2,FALSE) -> MANUELA LUCRECIA SALVADOR SICAL | O45: =IFERROR(IF(A45="SI",VLOOKUP(R45,Datos!$J$1:$K$50,2,FALSE)*C45,VLOOKUP(R45,Datos!$P$1:$T$13,2,FALSE)*C45),0) -> 3264 | P45: 306497 | Q45: =+VLOOKUP(P45,Datos!$F:$G,2,FALSE) -> Erika Ixtan Canil | R45: VIDA+SEGURO | V45: =+COUNTIFS($G$2:$G$444,G45) -> 2 | W45: =+VLOOKUP(M45,Datos!$F:$H,3,FALSE) -> 0 | X45: 0 | Y45: 2 polia | Z45: =VLOOKUP(M45,'[1]INDIVIDUAL UN'!$C$6:$F$222,4,FALSE) -> #N/A
A46: SI | C46: 3 | D46: NUEVO | E46: VCB-20220046 | F46: 106 | G46: JUANA SANTIAGO PANJOJ SALVADOR | H46: 46269 | I46: 46269 | J46: =+VLOOKUP(K46,Datos!$A:$C,3,FALSE) -> OCCIDENTE | K46: 126 | L46: =+VLOOKUP(K46,Datos!$A:$C,2,FALSE) -> CHICHICASTENANGO | M46: 90040633 | N46: =+VLOOKUP(M46,Datos!$F:$G,2,FALSE) -> MANUELA LUCRECIA SALVADOR SICAL | O46: =IFERROR(IF(A46="SI",VLOOKUP(R46,Datos!$J$1:$K$50,2,FALSE)*C46,VLOOKUP(R46,Datos!$P$1:$T$13,2,FALSE)*C46),0) -> 3276 | P46: 306497 | Q46: =+VLOOKUP(P46,Datos!$F:$G,2,FALSE) -> Erika Ixtan Canil | R46: PREVENCION+SEGURA | V46: =+COUNTIFS($G$2:$G$444,G46) -> 2 | W46: =+VLOOKUP(M46,Datos!$F:$H,3,FALSE) -> 0 | X46: 0 | Y46: 2 poliza | Z46: =VLOOKUP(M46,'[1]INDIVIDUAL UN'!$C$6:$F$222,4,FALSE) -> #N/A
A47: SI | C47: 4 | D47: NUEVO | E47: VCB-20240008 | F47: 655 | G47: EDIL WOSBELI GOMEZ GOMEZ | H47: 46269 | I47: 46269 | J47: =+VLOOKUP(K47,Datos!$A:$C,3,FALSE) -> SUROCCIDENTE | K47: 31 | L47: =+VLOOKUP(K47,Datos!$A:$C,2,FALSE) -> COATEPEQUE | M47: 315882 | N47: =+VLOOKUP(M47,Datos!$F:$G,2,FALSE) -> RUTH ANAI GOMEZ RAMIREZ | O47: =IFERROR(IF(A47="SI",VLOOKUP(R47,Datos!$J$1:$K$50,2,FALSE)*C47,VLOOKUP(R47,Datos!$P$1:$T$13,2,FALSE)*C47),0) -> 5472 | P47: 306656 | Q47: =+VLOOKUP(P47,Datos!$F:$G,2,FALSE) -> Wilmer Benjamin Vasquez Puac | R47: VIDA+SEGURO PLAN 1 | V47: =+COUNTIFS($G$2:$G$444,G47) -> 1 | W47: =+VLOOKUP(M47,Datos!$F:$H,3,FALSE) -> 0 | X47: 0 | Z47: =VLOOKUP(M47,'[1]INDIVIDUAL UN'!$C$6:$F$222,4,FALSE) -> #N/A
A48: SI | C48: 1 | D48: NUEVO | E48: VCB-20210003 | F48: 4261 | G48: DOMINGO MATEO SEBASTIAN | H48: 46269 | I48: 46269 | J48: =+VLOOKUP(K48,Datos!$A:$C,3,FALSE) -> OCCIDENTE | K48: 246 | L48: =+VLOOKUP(K48,Datos!$A:$C,2,FALSE) -> SANTA CRUZ BARILLAS | M48: 312087 | N48: =+VLOOKUP(M48,Datos!$F:$G,2,FALSE) -> Yoni Yosuen Rodriguez Sosa | O48: =IFERROR(IF(A48="SI",VLOOKUP(R48,Datos!$J$1:$K$50,2,FALSE)*C48,VLOOKUP(R48,Datos!$P$1:$T$13,2,FALSE)*C48),0) -> 816 | P48: 304166 | Q48: =+VLOOKUP(P48,Datos!$F:$G,2,FALSE) -> Maviela Bibianeth Castillo Avila | R48: VIDA+SEGURO | V48: =+COUNTIFS($G$2:$G$444,G48) -> 1 | W48: =+VLOOKUP(M48,Datos!$F:$H,3,FALSE) -> 0 | X48: 0 | Z48: =VLOOKUP(M48,'[1]INDIVIDUAL UN'!$C$6:$F$222,4,FALSE) -> #N/A
A49: SI | C49: 1 | D49: NUEVO | E49: VCB-20210003 | F49: 4265 | G49: RONY FIDEL AGUILAR AJTUN | H49: 46269 | I49: 46269 | J49: =+VLOOKUP(K49,Datos!$A:$C,3,FALSE) -> OCCIDENTE | K49: 243 | L49: =+VLOOKUP(K49,Datos!$A:$C,2,FALSE) -> PRADERA XELA | M49: 316039 | N49: =+VLOOKUP(M49,Datos!$F:$G,2,FALSE) -> Edgar Francisco Garcia | O49: =IFERROR(IF(A49="SI",VLOOKUP(R49,Datos!$J$1:$K$50,2,FALSE)*C49,VLOOKUP(R49,Datos!$P$1:$T$13,2,FALSE)*C49),0) -> 816 | P49: 315174 | Q49: =+VLOOKUP(P49,Datos!$F:$G,2,FALSE) -> Edwin Adolfo Soberanis Mazariegos | R49: VIDA+SEGURO | V49: =+COUNTIFS($G$2:$G$444,G49) -> 1 | W49: =+VLOOKUP(M49,Datos!$F:$H,3,FALSE) -> 0 | X49: 0 | Z49: =VLOOKUP(M49,'[1]INDIVIDUAL UN'!$C$6:$F$222,4,FALSE) -> #N/A
A50: SI | C50: 1 | D50: NUEVO | E50: ACPE-20210007 | F50: 2580 | G50: ERVIN HOMERO LOPEZ REYES | H50: 46269 | I50: 46269 | J50: =+VLOOKUP(K50,Datos!$A:$C,3,FALSE) -> SUROCCIDENTE | K50: 31 | L50: =+VLOOKUP(K50,Datos!$A:$C,2,FALSE) -> COATEPEQUE | M50: 315882 | N50: =+VLOOKUP(M50,Datos!$F:$G,2,FALSE) -> RUTH ANAI GOMEZ RAMIREZ | O50: =IFERROR(IF(A50="SI",VLOOKUP(R50,Datos!$J$1:$K$50,2,FALSE)*C50,VLOOKUP(R50,Datos!$P$1:$T$13,2,FALSE)*C50),0) -> 1008 | P50: 306656 | Q50: =+VLOOKUP(P50,Datos!$F:$G,2,FALSE) -> Wilmer Benjamin Vasquez Puac | R50: AP BIENESTAR | V50: =+COUNTIFS($G$2:$G$444,G50) -> 1 | W50: =+VLOOKUP(M50,Datos!$F:$H,3,FALSE) -> 0 | X50: 0 | Z50: =VLOOKUP(M50,'[1]INDIVIDUAL UN'!$C$6:$F$222,4,FALSE) -> #N/A
A51: SI | C51: 2 | D51: NUEVO | E51: VCB-20220010 | F51: 1134 | G51: LUIS ALFREDO DE LEON RUIZ | H51: 46269 | I51: 46269 | J51: =+VLOOKUP(K51,Datos!$A:$C,3,FALSE) -> SUROCCIDENTE | K51: 297 | L51: =+VLOOKUP(K51,Datos!$A:$C,2,FALSE) -> LA TRINIDAD COATEPEQUE | M51: 90051368 | N51: =+VLOOKUP(M51,Datos!$F:$G,2,FALSE) -> EMERSON ENRIQUE VASQUEZ GARCIA | O51: =IFERROR(IF(A51="SI",VLOOKUP(R51,Datos!$J$1:$K$50,2,FALSE)*C51,VLOOKUP(R51,Datos!$P$1:$T$13,2,FALSE)*C51),0) -> 1632 | P51: 315175 | Q51: =+VLOOKUP(P51,Datos!$F:$G,2,FALSE) -> Heber Nehemias Velasquez Lorenzo | R51: VIDA+SEGURO | V51: =+COUNTIFS($G$2:$G$444,G51) -> 1 | W51: =+VLOOKUP(M51,Datos!$F:$H,3,FALSE) -> 0 | X51: 0 | Z51: =VLOOKUP(M51,'[1]INDIVIDUAL UN'!$C$6:$F$222,4,FALSE) -> #N/A
A52: SI | C52: 4 | D52: NUEVO | E52: VCB-20240008 | F52: 845 | G52: ANADILIA TELON MAZARIEGOS | H52: 46270 | I52: 46270 | J52: =+VLOOKUP(K52,Datos!$A:$C,3,FALSE) -> OCCIDENTE | K52: 243 | L52: =+VLOOKUP(K52,Datos!$A:$C,2,FALSE) -> PRADERA XELA | M52: 90081008 | N52: =+VLOOKUP(M52,Datos!$F:$G,2,FALSE) -> Randy Antonio Lopez Huinac | O52: =IFERROR(IF(A52="SI",VLOOKUP(R52,Datos!$J$1:$K$50,2,FALSE)*C52,VLOOKUP(R52,Datos!$P$1:$T$13,2,FALSE)*C52),0) -> 3264 | P52: 315174 | Q52: =+VLOOKUP(P52,Datos!$F:$G,2,FALSE) -> Edwin Adolfo Soberanis Mazariegos | R52: VIDA+SEGURO | V52: =+COUNTIFS($G$2:$G$444,G52) -> 1 | W52: =+VLOOKUP(M52,Datos!$F:$H,3,FALSE) -> 0 | X52: 0 | Z52: =VLOOKUP(M52,'[1]INDIVIDUAL UN'!$C$6:$F$222,4,FALSE) -> #N/A
A53: SI | C53: 4 | D53: NUEVO | E53: ACPE-20240016 | F53: 36 | G53: ISAAC PEREZ ACABAL | H53: 46270 | I53: 46270 | J53: =+VLOOKUP(K53,Datos!$A:$C,3,FALSE) -> SUROCCIDENTE | K53: 31 | L53: =+VLOOKUP(K53,Datos!$A:$C,2,FALSE) -> COATEPEQUE | M53: 310671 | N53: =+VLOOKUP(M53,Datos!$F:$G,2,FALSE) -> Sucely Paola Godinez Gomez De Perez | O53: =IFERROR(IF(A53="SI",VLOOKUP(R53,Datos!$J$1:$K$50,2,FALSE)*C53,VLOOKUP(R53,Datos!$P$1:$T$13,2,FALSE)*C53),0) -> 4032 | P53: 306654 | Q53: =+VLOOKUP(P53,Datos!$F:$G,2,FALSE) -> Gerson Arcadio Hernandez Barrios | R53: AP BIENESTAR | V53: =+COUNTIFS($G$2:$G$444,G53) -> 1 | W53: =+VLOOKUP(M53,Datos!$F:$H,3,FALSE) -> 0 | X53: 0 | Z53: =VLOOKUP(M53,'[1]INDIVIDUAL UN'!$C$6:$F$222,4,FALSE) -> #N/A
A54: SI | C54: 1 | D54: NUEVO | E54: VCB20210003 | F54: 4255 | G54: EMERSON DENILSON FUNES RIVERA | H54: 46270 | I54: 46269 | J54: =+VLOOKUP(K54,Datos!$A:$C,3,FALSE) -> SUROCCIDENTE | K54: 89 | L54: =+VLOOKUP(K54,Datos!$A:$C,2,FALSE) -> LA TRINIDAD RETALHULEU | M54: 90009266 | N54: =+VLOOKUP(M54,Datos!$F:$G,2,FALSE) -> AURA MARIAN MEJIA REYES | O54: =IFERROR(IF(A54="SI",VLOOKUP(R54,Datos!$J$1:$K$50,2,FALSE)*C54,VLOOKUP(R54,Datos!$P$1:$T$13,2,FALSE)*C54),0) -> 816 | P54: 311261 | Q54: =+VLOOKUP(P54,Datos!$F:$G,2,FALSE) -> Nasly Abigail Cazian Lopez | R54: VIDA+SEGURO | V54: =+COUNTIFS($G$2:$G$444,G54) -> 1 | W54: =+VLOOKUP(M54,Datos!$F:$H,3,FALSE) -> 0 | X54: 0 | Z54: =VLOOKUP(M54,'[1]INDIVIDUAL UN'!$C$6:$F$222,4,FALSE) -> #N/A
A55: SI | C55: 1 | D55: NUEVO | E55: VCB20210003 | F55: 4287 | G55: RIGOBERTO LIMA VASQUEZ | H55: 46270 | I55: 46270 | J55: =+VLOOKUP(K55,Datos!$A:$C,3,FALSE) -> SUROCCIDENTE | K55: 89 | L55: =+VLOOKUP(K55,Datos!$A:$C,2,FALSE) -> LA TRINIDAD RETALHULEU | M55: 90009266 | N55: =+VLOOKUP(M55,Datos!$F:$G,2,FALSE) -> AURA MARIAN MEJIA REYES | O55: =IFERROR(IF(A55="SI",VLOOKUP(R55,Datos!$J$1:$K$50,2,FALSE)*C55,VLOOKUP(R55,Datos!$P$1:$T$13,2,FALSE)*C55),0) -> 816 | P55: 311261 | Q55: =+VLOOKUP(P55,Datos!$F:$G,2,FALSE) -> Nasly Abigail Cazian Lopez | R55: VIDA+SEGURO | V55: =+COUNTIFS($G$2:$G$444,G55) -> 1 | W55: =+VLOOKUP(M55,Datos!$F:$H,3,FALSE) -> 0 | X55: 0 | Z55: =VLOOKUP(M55,'[1]INDIVIDUAL UN'!$C$6:$F$222,4,FALSE) -> #N/A
A56: SI | C56: 1 | D56: NUEVO | E56: VCB-20210003 | F56: 4280 | G56: GENDRI ELIAZAR REYES BARRIOS | H56: 46270 | I56: 46270 | J56: =+VLOOKUP(K56,Datos!$A:$C,3,FALSE) -> SUROCCIDENTE | K56: 31 | L56: =+VLOOKUP(K56,Datos!$A:$C,2,FALSE) -> COATEPEQUE | M56: 90047699 | N56: =+VLOOKUP(M56,Datos!$F:$G,2,FALSE) -> ANDERSON JOSUE OXLAJ BAMACA | O56: =IFERROR(IF(A56="SI",VLOOKUP(R56,Datos!$J$1:$K$50,2,FALSE)*C56,VLOOKUP(R56,Datos!$P$1:$T$13,2,FALSE)*C56),0) -> 816 | P56: 311258 | Q56: =+VLOOKUP(P56,Datos!$F:$G,2,FALSE) -> Victor Otoniel Sebastian Cardona | R56: VIDA+SEGURO | V56: =+COUNTIFS($G$2:$G$444,G56) -> 2 | W56: =+VLOOKUP(M56,Datos!$F:$H,3,FALSE) -> 0 | X56: 0 | Z56: =VLOOKUP(M56,'[1]INDIVIDUAL UN'!$C$6:$F$222,4,FALSE) -> #N/A
A57: SI | C57: 2 | D57: NUEVO | E57: ACPE-20220038 | F57: 163 | G57: MARVIN GERARDO CHAPETON SARMIENTOS | H57: 46270 | I57: 46270 | J57: =+VLOOKUP(K57,Datos!$A:$C,3,FALSE) -> SUROCCIDENTE | K57: 31 | L57: =+VLOOKUP(K57,Datos!$A:$C,2,FALSE) -> COATEPEQUE | M57: 90046882 | N57: =+VLOOKUP(M57,Datos!$F:$G,2,FALSE) -> MARICRUZ MENDEZ LOPEZ | O57: =IFERROR(IF(A57="SI",VLOOKUP(R57,Datos!$J$1:$K$50,2,FALSE)*C57,VLOOKUP(R57,Datos!$P$1:$T$13,2,FALSE)*C57),0) -> 2016 | P57: 306656 | Q57: =+VLOOKUP(P57,Datos!$F:$G,2,FALSE) -> Wilmer Benjamin Vasquez Puac | R57: AP BIENESTAR | V57: =+COUNTIFS($G$2:$G$444,G57) -> 1 | W57: =+VLOOKUP(M57,Datos!$F:$H,3,FALSE) -> 0 | X57: 0 | Z57: =VLOOKUP(M57,'[1]INDIVIDUAL UN'!$C$6:$F$222,4,FALSE) -> #N/A
A58: SI | C58: 3 | D58: NUEVO | E58: VCB-20220034 | F58: 606 | G58: BYRON RENE HIGUEROS LUARTE | H58: 46270 | I58: 46270 | J58: =+VLOOKUP(K58,Datos!$A:$C,3,FALSE) -> OCCIDENTE | K58: 155 | L58: =+VLOOKUP(K58,Datos!$A:$C,2,FALSE) -> TECPAN | M58: 315629 | N58: =+VLOOKUP(M58,Datos!$F:$G,2,FALSE) -> Rucuch Choguaj, Miguel | O58: =IFERROR(IF(A58="SI",VLOOKUP(R58,Datos!$J$1:$K$50,2,FALSE)*C58,VLOOKUP(R58,Datos!$P$1:$T$13,2,FALSE)*C58),0) -> 2448 | P58: 305955 | Q58: =+VLOOKUP(P58,Datos!$F:$G,2,FALSE) -> Jorge Alfredo Gutierrez Rodriguez | R58: VIDA+SEGURO | V58: =+COUNTIFS($G$2:$G$444,G58) -> 1 | W58: =+VLOOKUP(M58,Datos!$F:$H,3,FALSE) -> 0 | X58: 0 | Z58: =VLOOKUP(M58,'[1]INDIVIDUAL UN'!$C$6:$F$222,4,FALSE) -> #N/A
... A60: SI | C60: 1 | D60: NUEVO | E60: VCB-20210003 | F60: 4288 | G60: NOE NERY RIVERA ALVARADO | H60: 46270 | I60: 46270 | J60: =+VLOOKUP(K60,Datos!$A:$C,3,FALSE) -> SUROCCIDENTE | K60: 227 | L60: =+VLOOKUP(K60,Datos!$A:$C,2,FALSE) -> PAJAPITA | M60: 90023752 | N60: =+VLOOKUP(M60,Datos!$F:$G,2,FALSE) -> EDY DIONISIO FUENTES MARTINEZ | O60: =IFERROR(IF(A60="SI",VLOOKUP(R60,Datos!$J$1:$K$50,2,FALSE)*C60,VLOOKUP(R60,Datos!$P$1:$T$13,2,FALSE)*C60),0) -> 1368 | P60: 314738 | Q60: =+VLOOKUP(P60,Datos!$F:$G,2,FALSE) -> Carlos David Castillo Gamboa | R60: VIDA+SEGURO PLAN 1 | V60: =+COUNTIFS($G$2:$G$444,G60) -> 1 | W60: =+VLOOKUP(M60,Datos!$F:$H,3,FALSE) -> 0 | X60: 0 | Z60: =VLOOKUP(M60,'[1]INDIVIDUAL UN'!$C$6:$F$222,4,FALSE) -> #N/A
A61: SI | C61: 1 | D61: NUEVO | E61: VCB-20210003 | F61: 4270 | G61: GLORIA MARIA CASTELLANOS MERIDA | H61: 46271 | I61: 46269 | J61: =+VLOOKUP(K61,Datos!$A:$C,3,FALSE) -> SUROCCIDENTE | K61: 178 | L61: =+VLOOKUP(K61,Datos!$A:$C,2,FALSE) -> LA TRINIDAD MALACATAN | M61: 90049252 | N61: =+VLOOKUP(M61,Datos!$F:$G,2,FALSE) -> ANGELA YANETH CHILEL GONZALEZ | O61: =IFERROR(IF(A61="SI",VLOOKUP(R61,Datos!$J$1:$K$50,2,FALSE)*C61,VLOOKUP(R61,Datos!$P$1:$T$13,2,FALSE)*C61),0) -> 816 | P61: 316487 | Q61: =+VLOOKUP(P61,Datos!$F:$G,2,FALSE) -> Wilmer Ovando Mejia Godínez | R61: VIDA+SEGURO | V61: =+COUNTIFS($G$2:$G$444,G61) -> 2 | W61: =+VLOOKUP(M61,Datos!$F:$H,3,FALSE) -> 0 | X61: 0 | Y61: 2 poliza | Z61: =VLOOKUP(M61,'[1]INDIVIDUAL UN'!$C$6:$F$222,4,FALSE) -> #N/A
A62: SI | C62: 4 | D62: NUEVO | E62: VCB-20240008 | F62: 658 | G62: ADONIAS ISAI PEREZ BONILLA | H62: 46271 | I62: 46270 | J62: =+VLOOKUP(K62,Datos!$A:$C,3,FALSE) -> SUROCCIDENTE | K62: 178 | L62: =+VLOOKUP(K62,Datos!$A:$C,2,FALSE) -> LA TRINIDAD MALACATAN | M62: 316215 | N62: =+VLOOKUP(M62,Datos!$F:$G,2,FALSE) -> ANAYELI MARIBEL JIMENEZ GOMEZ | O62: =IFERROR(IF(A62="SI",VLOOKUP(R62,Datos!$J$1:$K$50,2,FALSE)*C62,VLOOKUP(R62,Datos!$P$1:$T$13,2,FALSE)*C62),0) -> 3264 | P62: 304805 | Q62: =+VLOOKUP(P62,Datos!$F:$G,2,FALSE) -> Sheily Raquel Angel Arreaga | R62: VIDA+SEGURO | V62: =+COUNTIFS($G$2:$G$444,G62) -> 1 | W62: =+VLOOKUP(M62,Datos!$F:$H,3,FALSE) -> 0 | X62: 0 | Z62: =VLOOKUP(M62,'[1]INDIVIDUAL UN'!$C$6:$F$222,4,FALSE) -> #N/A
A63: SI | C63: 1 | D63: NUEVO | E63: VCB-20210003 | F63: 4307 | G63: KAREN YAZMIN PEREZ ROMERO | H63: 46271 | I63: 46271 | J63: =+VLOOKUP(K63,Datos!$A:$C,3,FALSE) -> SUROCCIDENTE | K63: 89 | L63: =+VLOOKUP(K63,Datos!$A:$C,2,FALSE) -> LA TRINIDAD RETALHULEU | M63: 90064210 | N63: =+VLOOKUP(M63,Datos!$F:$G,2,FALSE) -> GEREMY ARMANDO HERNANDEZ CAMACHO | O63: =IFERROR(IF(A63="SI",VLOOKUP(R63,Datos!$J$1:$K$50,2,FALSE)*C63,VLOOKUP(R63,Datos!$P$1:$T$13,2,FALSE)*C63),0) -> 816 | P63: 302841 | Q63: =+VLOOKUP(P63,Datos!$F:$G,2,FALSE) -> Jessica Maria Jose Santizo Guzman | R63: VIDA+SEGURO | V63: =+COUNTIFS($G$2:$G$444,G63) -> 1 | W63: =+VLOOKUP(M63,Datos!$F:$H,3,FALSE) -> 0 | X63: 0 | Z63: =VLOOKUP(M63,'[1]INDIVIDUAL UN'!$C$6:$F$222,4,FALSE) -> #N/A
A64: SI | C64: 3 | D64: NUEVO | E64: VCB-20220034 | F64: 611 | G64: FRANCISCO LOPEZ PEREZ | H64: 46271 | I64: 46271 | J64: =+VLOOKUP(K64,Datos!$A:$C,3,FALSE) -> SUROCCIDENTE | K64: 89 | L64: =+VLOOKUP(K64,Datos!$A:$C,2,FALSE) -> LA TRINIDAD RETALHULEU | M64: 90064210 | N64: =+VLOOKUP(M64,Datos!$F:$G,2,FALSE) -> GEREMY ARMANDO HERNANDEZ CAMACHO | O64: =IFERROR(IF(A64="SI",VLOOKUP(R64,Datos!$J$1:$K$50,2,FALSE)*C64,VLOOKUP(R64,Datos!$P$1:$T$13,2,FALSE)*C64),0) -> 2448 | P64: 302841 | Q64: =+VLOOKUP(P64,Datos!$F:$G,2,FALSE) -> Jessica Maria Jose Santizo Guzman | R64: VIDA+SEGURO | V64: =+COUNTIFS($G$2:$G$444,G64) -> 1 | W64: =+VLOOKUP(M64,Datos!$F:$H,3,FALSE) -> 0 | X64: 0 | Z64: =VLOOKUP(M64,'[1]INDIVIDUAL UN'!$C$6:$F$222,4,FALSE) -> #N/A
A65: SI | C65: 2 | D65: NUEVO | E65: VCB-20220010 | F65: 1155 | G65: HENRY MARGOS RALON | H65: 46272 | I65: 46271 | J65: =+VLOOKUP(K65,Datos!$A:$C,3,FALSE) -> SUROCCIDENTE | K65: 31 | L65: =+VLOOKUP(K65,Datos!$A:$C,2,FALSE) -> COATEPEQUE | M65: 310731 | N65: =+VLOOKUP(M65,Datos!$F:$G,2,FALSE) -> Sofia Etelvina Lopez Perez | O65: =IFERROR(IF(A65="SI",VLOOKUP(R65,Datos!$J$1:$K$50,2,FALSE)*C65,VLOOKUP(R65,Datos!$P$1:$T$13,2,FALSE)*C65),0) -> 1632 | P65: 306654 | Q65: =+VLOOKUP(P65,Datos!$F:$G,2,FALSE) -> Gerson Arcadio Hernandez Barrios | R65: VIDA+SEGURO | V65: =+COUNTIFS($G$2:$G$444,G65) -> 1 | W65: =+VLOOKUP(M65,Datos!$F:$H,3,FALSE) -> 0 | X65: 0 | Z65: =VLOOKUP(M65,'[1]INDIVIDUAL UN'!$C$6:$F$222,4,FALSE) -> #N/A
A66: SI | C66: 1 | D66: NUEVO | E66: VCB-20210003 | F66: 4308 | G66: CARMEN GOMEZ VASQUEZ | H66: 46272 | I66: 46271 | J66: =+VLOOKUP(K66,Datos!$A:$C,3,FALSE) -> SUROCCIDENTE | K66: 31 | L66: =+VLOOKUP(K66,Datos!$A:$C,2,FALSE) -> COATEPEQUE | M66: 310731 | N66: =+VLOOKUP(M66,Datos!$F:$G,2,FALSE) -> Sofia Etelvina Lopez Perez | O66: =IFERROR(IF(A66="SI",VLOOKUP(R66,Datos!$J$1:$K$50,2,FALSE)*C66,VLOOKUP(R66,Datos!$P$1:$T$13,2,FALSE)*C66),0) -> 816 | P66: 306654 | Q66: =+VLOOKUP(P66,Datos!$F:$G,2,FALSE) -> Gerson Arcadio Hernandez Barrios | R66: VIDA+SEGURO | V66: =+COUNTIFS($G$2:$G$444,G66) -> 1 | W66: =+VLOOKUP(M66,Datos!$F:$H,3,FALSE) -> 0 | X66: 0 | Z66: =VLOOKUP(M66,'[1]INDIVIDUAL UN'!$C$6:$F$222,4,FALSE) -> #N/A
A67: SI | C67: 1 | D67: NUEVO | E67: VCB-20210003 | F67: 4311 | G67: MIGUEL ANGEL VELASQUEZ PEREZ | H67: 46272 | I67: 46271 | J67: =+VLOOKUP(K67,Datos!$A:$C,3,FALSE) -> SUROCCIDENTE | K67: 31 | L67: =+VLOOKUP(K67,Datos!$A:$C,2,FALSE) -> COATEPEQUE | M67: 310731 | N67: =+VLOOKUP(M67,Datos!$F:$G,2,FALSE) -> Sofia Etelvina Lopez Perez | O67: =IFERROR(IF(A67="SI",VLOOKUP(R67,Datos!$J$1:$K$50,2,FALSE)*C67,VLOOKUP(R67,Datos!$P$1:$T$13,2,FALSE)*C67),0) -> 816 | P67: 306654 | Q67: =+VLOOKUP(P67,Datos!$F:$G,2,FALSE) -> Gerson Arcadio Hernandez Barrios | R67: VIDA+SEGURO | V67: =+COUNTIFS($G$2:$G$444,G67) -> 1 | W67: =+VLOOKUP(M67,Datos!$F:$H,3,FALSE) -> 0 | X67: 0 | Z67: =VLOOKUP(M67,'[1]INDIVIDUAL UN'!$C$6:$F$222,4,FALSE) -> #N/A
A68: SI | C68: 1 | D68: NUEVO | E68: VCB-20210003 | F68: 4324 | G68: GUMERCINDO MACARIO VASQUEZ | H68: 46272 | I68: 46272 | J68: =+VLOOKUP(K68,Datos!$A:$C,3,FALSE) -> SUROCCIDENTE | K68: 31 | L68: =+VLOOKUP(K68,Datos!$A:$C,2,FALSE) -> COATEPEQUE | M68: 310671 | N68: =+VLOOKUP(M68,Datos!$F:$G,2,FALSE) -> Sucely Paola Godinez Gomez De Perez | O68: =IFERROR(IF(A68="SI",VLOOKUP(R68,Datos!$J$1:$K$50,2,FALSE)*C68,VLOOKUP(R68,Datos!$P$1:$T$13,2,FALSE)*C68),0) -> 1368 | P68: 306654 | Q68: =+VLOOKUP(P68,Datos!$F:$G,2,FALSE) -> Gerson Arcadio Hernandez Barrios | R68: VIDA+SEGURO PLAN 1 | V68: =+COUNTIFS($G$2:$G$444,G68) -> 1 | W68: =+VLOOKUP(M68,Datos!$F:$H,3,FALSE) -> 0 | X68: 0 | Z68: =VLOOKUP(M68,'[1]INDIVIDUAL UN'!$C$6:$F$222,4,FALSE) -> #N/A
A69: SI | C69: 4 | D69: NUEVO | E69: VCB-20240008 | F69: 680 | G69: BRENDA NICTE PEREZ MENDOZA | H69: 46272 | I69: 46272 | J69: =+VLOOKUP(K69,Datos!$A:$C,3,FALSE) -> SUROCCIDENTE | K69: 31 | L69: =+VLOOKUP(K69,Datos!$A:$C,2,FALSE) -> COATEPEQUE | M69: 90065999 | N69: =+VLOOKUP(M69,Datos!$F:$G,2,FALSE) -> SEPHORA ABIGAIL SANCHEZ HERDOCIA | O69: =IFERROR(IF(A69="SI",VLOOKUP(R69,Datos!$J$1:$K$50,2,FALSE)*C69,VLOOKUP(R69,Datos!$P$1:$T$13,2,FALSE)*C69),0) -> 3264 | P69: 311258 | Q69: =+VLOOKUP(P69,Datos!$F:$G,2,FALSE) -> Victor Otoniel Sebastian Cardona | R69: VIDA+SEGURO | V69: =+COUNTIFS($G$2:$G$444,G69) -> 1 | W69: =+VLOOKUP(M69,Datos!$F:$H,3,FALSE) -> 0 | X69: 0 | Z69: =VLOOKUP(M69,'[1]INDIVIDUAL UN'!$C$6:$F$222,4,FALSE) -> #N/A
A70: NO | C70: 1 | D70: NUEVO | E70: MOBS-22000361 | F70: 1 | G70: OTTO RODOLFO MAZARIEGOS GOMEZ | H70: 46272 | I70: 46272 | J70: =+VLOOKUP(K70,Datos!$A:$C,3,FALSE) -> OCCIDENTE | K70: 243 | L70: =+VLOOKUP(K70,Datos!$A:$C,2,FALSE) -> PRADERA XELA | M70: 316039 | N70: =+VLOOKUP(M70,Datos!$F:$G,2,FALSE) -> Edgar Francisco Garcia | O70: 1620 | P70: 315174 | Q70: =+VLOOKUP(P70,Datos!$F:$G,2,FALSE) -> Edwin Adolfo Soberanis Mazariegos | R70: MOTO+SEGURA | V70: =+COUNTIFS($G$2:$G$444,G70) -> 1 | W70: =+VLOOKUP(M70,Datos!$F:$H,3,FALSE) -> 0 | X70: 0 | Z70: =VLOOKUP(M70,'[1]INDIVIDUAL UN'!$C$6:$F$222,4,FALSE) -> #N/A
A71: SI | C71: 1 | D71: NUEVO | E71: VCB-20210003 | F71: 4320 | G71: TOMAS ALEXANDER AJANEL RAMOS | H71: 46272 | I71: 46272 | J71: =+VLOOKUP(K71,Datos!$A:$C,3,FALSE) -> OCCIDENTE | K71: 126 | L71: =+VLOOKUP(K71,Datos!$A:$C,2,FALSE) -> CHICHICASTENANGO | M71: 310610 | N71: =+VLOOKUP(M71,Datos!$F:$G,2,FALSE) -> Ricky Edson Lux Cassia | O71: =IFERROR(IF(A71="SI",VLOOKUP(R71,Datos!$J$1:$K$50,2,FALSE)*C71,VLOOKUP(R71,Datos!$P$1:$T$13,2,FALSE)*C71),0) -> 816 | P71: 303674 | Q71: =+VLOOKUP(P71,Datos!$F:$G,2,FALSE) -> Imelda Elizabeth Castro Rodas | R71: VIDA+SEGURO | V71: =+COUNTIFS($G$2:$G$444,G71) -> 1 | W71: =+VLOOKUP(M71,Datos!$F:$H,3,FALSE) -> 0 | X71: 0 | Z71: =VLOOKUP(M71,'[1]INDIVIDUAL UN'!$C$6:$F$222,4,FALSE) -> #N/A
A72: SI | C72: 3 | D72: NUEVO | E72: VCB- 20220034 | F72: 610 | G72: MARTA JOSEFINA HERNANDEZ GOMEZ | H72: 46272 | I72: 46272 | J72: =+VLOOKUP(K72,Datos!$A:$C,3,FALSE) -> SUROCCIDENTE | K72: 227 | L72: =+VLOOKUP(K72,Datos!$A:$C,2,FALSE) -> PAJAPITA | M72: 315734 | N72: =+VLOOKUP(M72,Datos!$F:$G,2,FALSE) -> DULCE MARINA LOPEZ SOLIS | O72: =IFERROR(IF(A72="SI",VLOOKUP(R72,Datos!$J$1:$K$50,2,FALSE)*C72,VLOOKUP(R72,Datos!$P$1:$T$13,2,FALSE)*C72),0) -> 2448 | P72: 314738 | Q72: =+VLOOKUP(P72,Datos!$F:$G,2,FALSE) -> Carlos David Castillo Gamboa | R72: VIDA+SEGURO | V72: =+COUNTIFS($G$2:$G$444,G72) -> 1 | W72: =+VLOOKUP(M72,Datos!$F:$H,3,FALSE) -> 0 | X72: 0 | Z72: =VLOOKUP(M72,'[1]INDIVIDUAL UN'!$C$6:$F$222,4,FALSE) -> #N/A
A73: SI | C73: 1 | D73: NUEVO | E73: PENDIENTE | F73: PENDIENTE | G73: MARCO VINICIO CASTILLO GOMEZ | H73: 46272 | I73: 46272 | J73: =+VLOOKUP(K73,Datos!$A:$C,3,FALSE) -> SUROCCIDENTE | K73: 227 | L73: =+VLOOKUP(K73,Datos!$A:$C,2,FALSE) -> PAJAPITA | M73: 90023752 | N73: =+VLOOKUP(M73,Datos!$F:$G,2,FALSE) -> EDY DIONISIO FUENTES MARTINEZ | O73: =IFERROR(IF(A73="SI",VLOOKUP(R73,Datos!$J$1:$K$50,2,FALSE)*C73,VLOOKUP(R73,Datos!$P$1:$T$13,2,FALSE)*C73),0) -> 1368 | P73: 314738 | Q73: =+VLOOKUP(P73,Datos!$F:$G,2,FALSE) -> Carlos David Castillo Gamboa | R73: VIDA+SEGURO PLAN 1 | V73: =+COUNTIFS($G$2:$G$444,G73) -> 1 | W73: =+VLOOKUP(M73,Datos!$F:$H,3,FALSE) -> 0 | X73: 0 | Z73: =VLOOKUP(M73,'[1]INDIVIDUAL UN'!$C$6:$F$222,4,FALSE) -> #N/A
A74: SI | C74: 3 | D74: NUEVO | E74: VCB 20220034 | F74: 616 | G74: RONALD IVAN DE LEON BARRIOS | H74: 46272 | I74: 46272 | J74: =+VLOOKUP(K74,Datos!$A:$C,3,FALSE) -> OCCIDENTE | K74: 56 | L74: =+VLOOKUP(K74,Datos!$A:$C,2,FALSE) -> LOS ALTOS | M74: 90040102 | N74: =+VLOOKUP(M74,Datos!$F:$G,2,FALSE) -> KAREN JASMIN PEREZ CORONADO | O74: =IFERROR(IF(A74="SI",VLOOKUP(R74,Datos!$J$1:$K$50,2,FALSE)*C74,VLOOKUP(R74,Datos!$P$1:$T$13,2,FALSE)*C74),0) -> 12312 | P74: 308266 | Q74: =+VLOOKUP(P74,Datos!$F:$G,2,FALSE) -> Julio Cesar De Leon Huinac | R74: VIDA+SEGURO PLAN 3 | V74: =+COUNTIFS($G$2:$G$444,G74) -> 1 | W74: =+VLOOKUP(M74,Datos!$F:$H,3,FALSE) -> 0 | X74: 0 | Z74: =VLOOKUP(M74,'[1]INDIVIDUAL UN'!$C$6:$F$222,4,FALSE) -> #N/A
A75: SI | C75: 1 | D75: NUEVO | E75: ACPE-20210019 | F75: 2900 | G75: ELVIRA DARINETH RECINOIS ESCALANTE | H75: 46272 | I75: 46272 | J75: =+VLOOKUP(K75,Datos!$A:$C,3,FALSE) -> OCCIDENTE | K75: 246 | L75: =+VLOOKUP(K75,Datos!$A:$C,2,FALSE) -> SANTA CRUZ BARILLAS | M75: 316120 | N75: =+VLOOKUP(M75,Datos!$F:$G,2,FALSE) -> JUANA CANDELARIA LORENZO MATEO | O75: =IFERROR(IF(A75="SI",VLOOKUP(R75,Datos!$J$1:$K$50,2,FALSE)*C75,VLOOKUP(R75,Datos!$P$1:$T$13,2,FALSE)*C75),0) -> 1308 | P75: 304166 | Q75: =+VLOOKUP(P75,Datos!$F:$G,2,FALSE) -> Maviela Bibianeth Castillo Avila | R75: AP DENTAL INDIVIDUAL | V75: =+COUNTIFS($G$2:$G$444,G75) -> 1 | W75: =+VLOOKUP(M75,Datos!$F:$H,3,FALSE) -> 0 | X75: 0 | Z75: =VLOOKUP(M75,'[1]INDIVIDUAL UN'!$C$6:$F$222,4,FALSE) -> #N/A
A76: -- | C76: 4 | D76: NUEVO | E76: VCB-20240008 | F76: 675 | G76: NICOLAS HERNANDEZ LOPEZ | H76: 46272 | I76: 46272 | J76: =+VLOOKUP(K76,Datos!$A:$C,3,FALSE) -> SUROCCIDENTE | K76: 48 | L76: =+VLOOKUP(K76,Datos!$A:$C,2,FALSE) -> TECUN UMAN SAN MARCOS | M76: 315651 | N76: =+VLOOKUP(M76,Datos!$F:$G,2,FALSE) -> WALTER EDUARDO RODAS RIOS | O76: =IFERROR(IF(A76="SI",VLOOKUP(R76,Datos!$J$1:$K$50,2,FALSE)*C76,VLOOKUP(R76,Datos!$P$1:$T$13,2,FALSE)*C76),0) -> 3552 | P76: 302285 | Q76: =+VLOOKUP(P76,Datos!$F:$G,2,FALSE) -> Heydi Yaneth Sales Mazariegos | R76: VIDA+SEGURO | V76: =+COUNTIFS($G$2:$G$444,G76) -> 1 | W76: =+VLOOKUP(M76,Datos!$F:$H,3,FALSE) -> 0 | X76: 0 | Z76: =VLOOKUP(M76,'[1]INDIVIDUAL UN'!$C$6:$F$222,4,FALSE) -> #N/A
A77: SI | C77: 4 | D77: NUEVO | E77: VCB-20240008 | F77: 673 | G77: MIGUEL FILOMENO TZUL VICENTE | H77: 46272 | I77: 46272 | J77: =+VLOOKUP(K77,Datos!$A:$C,3,FALSE) -> SUROCCIDENTE | K77: 31 | L77: =+VLOOKUP(K77,Datos!$A:$C,2,FALSE) -> COATEPEQUE | M77: 90046882 | N77: =+VLOOKUP(M77,Datos!$F:$G,2,FALSE) -> MARICRUZ MENDEZ LOPEZ | O77: =IFERROR(IF(A77="SI",VLOOKUP(R77,Datos!$J$1:$K$50,2,FALSE)*C77,VLOOKUP(R77,Datos!$P$1:$T$13,2,FALSE)*C77),0) -> 3264 | P77: 306656 | Q77: =+VLOOKUP(P77,Datos!$F:$G,2,FALSE) -> Wilmer Benjamin Vasquez Puac | R77: VIDA+SEGURO | V77: =+COUNTIFS($G$2:$G$444,G77) -> 1 | W77: =+VLOOKUP(M77,Datos!$F:$H,3,FALSE) -> 0 | X77: 0 | Z77: =VLOOKUP(M77,'[1]INDIVIDUAL UN'!$C$6:$F$222,4,FALSE) -> #N/A
A78: SI | C78: 4 | D78: NUEVO | E78: VCB-20240020 | F78: 179 | G78: GERBER ABIGAIL ESCOBAR GARCIA | H78: 46272 | I78: 46272 | J78: =+VLOOKUP(K78,Datos!$A:$C,3,FALSE) -> SUROCCIDENTE | K78: 31 | L78: =+VLOOKUP(K78,Datos!$A:$C,2,FALSE) -> COATEPEQUE | M78: 90046882 | N78: =+VLOOKUP(M78,Datos!$F:$G,2,FALSE) -> MARICRUZ MENDEZ LOPEZ | O78: =IFERROR(IF(A78="SI",VLOOKUP(R78,Datos!$J$1:$K$50,2,FALSE)*C78,VLOOKUP(R78,Datos!$P$1:$T$13,2,FALSE)*C78),0) -> 4368 | P78: 306656 | Q78: =+VLOOKUP(P78,Datos!$F:$G,2,FALSE) -> Wilmer Benjamin Vasquez Puac | R78: PREVENCION+SEGURA | V78: =+COUNTIFS($G$2:$G$444,G78) -> 1 | W78: =+VLOOKUP(M78,Datos!$F:$H,3,FALSE) -> 0 | X78: 0 | Z78: =VLOOKUP(M78,'[1]INDIVIDUAL UN'!$C$6:$F$222,4,FALSE) -> #N/A
A79: SI | C79: 3 | D79: NUEVO | E79: VCB-20220034 | F79: 613 | G79: FANNY ELISA AJPOP TELEGUARIO | H79: 46272 | I79: 46272 | J79: =+VLOOKUP(K79,Datos!$A:$C,3,FALSE) -> OCCIDENTE | K79: 155 | L79: =+VLOOKUP(K79,Datos!$A:$C,2,FALSE) -> TECPAN | M79: 314450 | N79: =+VLOOKUP(M79,Datos!$F:$G,2,FALSE) -> Rafael Anibal Sut Tucubal | O79: =IFERROR(IF(A79="SI",VLOOKUP(R79,Datos!$J$1:$K$50,2,FALSE)*C79,VLOOKUP(R79,Datos!$P$1:$T$13,2,FALSE)*C79),0) -> 2448 | P79: 305955 | Q79: =+VLOOKUP(P79,Datos!$F:$G,2,FALSE) -> Jorge Alfredo Gutierrez Rodriguez | R79: VIDA+SEGURO | V79: =+COUNTIFS($G$2:$G$444,G79) -> 1 | W79: =+VLOOKUP(M79,Datos!$F:$H,3,FALSE) -> 0 | X79: 0 | Z79: =VLOOKUP(M79,'[1]INDIVIDUAL UN'!$C$6:$F$222,4,FALSE) -> #N/A
A80: SI | C80: 1 | D80: NUEVO | E80: VCB-20210003 | F80: 4312 | G80: CRISTIAN SAMUEL VELASQUEZ MENDEZ | H80: 46272 | I80: =+H80 -> 46272 | J80: =+VLOOKUP(K80,Datos!$A:$C,3,FALSE) -> OCCIDENTE | K80: 243 | L80: =+VLOOKUP(K80,Datos!$A:$C,2,FALSE) -> PRADERA XELA | M80: 316039 | N80: =+VLOOKUP(M80,Datos!$F:$G,2,FALSE) -> Edgar Francisco Garcia | O80: =IFERROR(IF(A80="SI",VLOOKUP(R80,Datos!$J$1:$K$50,2,FALSE)*C80,VLOOKUP(R80,Datos!$P$1:$T$13,2,FALSE)*C80),0) -> 816 | P80: 315174 | Q80: =+VLOOKUP(P80,Datos!$F:$G,2,FALSE) -> Edwin Adolfo Soberanis Mazariegos | R80: VIDA+SEGURO | V80: =+COUNTIFS($G$2:$G$444,G80) -> 1 | W80: =+VLOOKUP(M80,Datos!$F:$H,3,FALSE) -> 0 | X80: 0 | Z80: =VLOOKUP(M80,'[1]INDIVIDUAL UN'!$C$6:$F$222,4,FALSE) -> #N/A
A81: SI | C81: 1 | D81: NUEVO | E81: VCB-20210003 | F81: 4319 | G81: ANTOLIN TOMAS REYNOSO | H81: 46272 | I81: 46272 | J81: =+VLOOKUP(K81,Datos!$A:$C,3,FALSE) -> OCCIDENTE | K81: 29 | L81: =+VLOOKUP(K81,Datos!$A:$C,2,FALSE) -> SAN PEDRO SACATEPEQUEZ S.M. | M81: 90086179 | N81: =+VLOOKUP(M81,Datos!$F:$G,2,FALSE) -> GERSON NOE MARTIN RAMIREZ | O81: =IFERROR(IF(A81="SI",VLOOKUP(R81,Datos!$J$1:$K$50,2,FALSE)*C81,VLOOKUP(R81,Datos!$P$1:$T$13,2,FALSE)*C81),0) -> 816 | P81: 310641 | Q81: =+VLOOKUP(P81,Datos!$F:$G,2,FALSE) -> Jorge Antonio Ramirez Sicay | R81: VIDA+SEGURO | V81: =+COUNTIFS($G$2:$G$444,G81) -> 1 | W81: =+VLOOKUP(M81,Datos!$F:$H,3,FALSE) -> 0 | X81: 0 | Z81: =VLOOKUP(M81,'[1]INDIVIDUAL UN'!$C$6:$F$222,4,FALSE) -> #N/A
A82: SI | C82: 4 | D82: NUEVO | E82: VCB-20240008 | F82: 681 | G82: KEVIN DANIEL BELETZUY DE LA CRUZ | H82: 46272 | I82: 46272 | J82: =+VLOOKUP(K82,Datos!$A:$C,3,FALSE) -> SUROCCIDENTE | K82: 143 | L82: =+VLOOKUP(K82,Datos!$A:$C,2,FALSE) -> RETALHULEU LA SIRENA | M82: 312294 | N82: =+VLOOKUP(M82,Datos!$F:$G,2,FALSE) -> Selvin Geronimo Aguilar | O82: =IFERROR(IF(A82="SI",VLOOKUP(R82,Datos!$J$1:$K$50,2,FALSE)*C82,VLOOKUP(R82,Datos!$P$1:$T$13,2,FALSE)*C82),0) -> 3264 | P82: 313194 | Q82: =+VLOOKUP(P82,Datos!$F:$G,2,FALSE) -> Mary Isabel Xiloj Tajiboy | R82: VIDA+SEGURO | V82: =+COUNTIFS($G$2:$G$444,G82) -> 1 | W82: =+VLOOKUP(M82,Datos!$F:$H,3,FALSE) -> 0 | X82: 0 | Z82: =VLOOKUP(M82,'[1]INDIVIDUAL UN'!$C$6:$F$222,4,FALSE) -> #N/A
A83: SI | C83: 2 | D83: NUEVO | E83: VCB-20220010 | F83: 1166 | G83: ENGEMBER TERESO MARTINEZ DE LEON | H83: 46272 | I83: 46272 | J83: =+VLOOKUP(K83,Datos!$A:$C,3,FALSE) -> SUROCCIDENTE | K83: 297 | L83: =+VLOOKUP(K83,Datos!$A:$C,2,FALSE) -> LA TRINIDAD COATEPEQUE | M83: 306248 | N83: =+VLOOKUP(M83,Datos!$F:$G,2,FALSE) -> Gladys Susana Marin De Leon | O83: =IFERROR(IF(A83="SI",VLOOKUP(R83,Datos!$J$1:$K$50,2,FALSE)*C83,VLOOKUP(R83,Datos!$P$1:$T$13,2,FALSE)*C83),0) -> 2736 | P83: 311975 | Q83: =+VLOOKUP(P83,Datos!$F:$G,2,FALSE) -> Luis Eduardo Ramirez Arriaza | R83: VIDA+SEGURO PLAN 1 | V83: =+COUNTIFS($G$2:$G$444,G83) -> 1 | W83: =+VLOOKUP(M83,Datos!$F:$H,3,FALSE) -> 0 | X83: 0 | Z83: =VLOOKUP(M83,'[1]INDIVIDUAL UN'!$C$6:$F$222,4,FALSE) -> #N/A
A84: SI | C84: 1 | D84: NUEVO | E84: VCB-20210015 | F84: 414 | G84: GLORIA MARIA CASTELLANOS MERIDA | H84: 46272 | I84: 46272 | J84: =+VLOOKUP(K84,Datos!$A:$C,3,FALSE) -> SUROCCIDENTE | K84: 178 | L84: =+VLOOKUP(K84,Datos!$A:$C,2,FALSE) -> LA TRINIDAD MALACATAN | M84: 90049252 | N84: =+VLOOKUP(M84,Datos!$F:$G,2,FALSE) -> ANGELA YANETH CHILEL GONZALEZ | O84: =IFERROR(IF(A84="SI",VLOOKUP(R84,Datos!$J$1:$K$50,2,FALSE)*C84,VLOOKUP(R84,Datos!$P$1:$T$13,2,FALSE)*C84),0) -> 1092 | P84: 316487 | Q84: =+VLOOKUP(P84,Datos!$F:$G,2,FALSE) -> Wilmer Ovando Mejia Godínez | R84: PREVENCION+SEGURA | V84: =+COUNTIFS($G$2:$G$444,G84) -> 2 | W84: =+VLOOKUP(M84,Datos!$F:$H,3,FALSE) -> 0 | X84: 0 | Z84: =VLOOKUP(M84,'[1]INDIVIDUAL UN'!$C$6:$F$222,4,FALSE) -> #N/A
A85: SI | C85: 1 | D85: NUEVO | E85: VCB-20210003 | F85: 4340 | G85: AIDA CORONITA MANZO DE LEON | H85: 46272 | I85: 46272 | J85: =+VLOOKUP(K85,Datos!$A:$C,3,FALSE) -> SUROCCIDENTE | K85: 178 | L85: =+VLOOKUP(K85,Datos!$A:$C,2,FALSE) -> LA TRINIDAD MALACATAN | M85: 90087115 | N85: =+VLOOKUP(M85,Datos!$F:$G,2,FALSE) -> ALMA DINORA MACARIO RIXTUN | O85: =IFERROR(IF(A85="SI",VLOOKUP(R85,Datos!$J$1:$K$50,2,FALSE)*C85,VLOOKUP(R85,Datos!$P$1:$T$13,2,FALSE)*C85),0) -> 816 | P85: 306697 | Q85: =+VLOOKUP(P85,Datos!$F:$G,2,FALSE) -> Maria Luisa Ramos Lopez | R85: VIDA+SEGURO | V85: =+COUNTIFS($G$2:$G$444,G85) -> 1 | W85: =+VLOOKUP(M85,Datos!$F:$H,3,FALSE) -> 0 | X85: 0 | Y85: 2 poliza | Z85: =VLOOKUP(M85,'[1]INDIVIDUAL UN'!$C$6:$F$222,4,FALSE) -> #N/A
A86: SI | C86: 3 | D86: NUEVO | E86: ACPE-20220074 | F86: 63 | G86: FELIPE ROBERTO OXLAJ GONZALEZ | H86: 46272 | I86: 46272 | J86: =+VLOOKUP(K86,Datos!$A:$C,3,FALSE) -> SUROCCIDENTE | K86: 31 | L86: =+VLOOKUP(K86,Datos!$A:$C,2,FALSE) -> COATEPEQUE | M86: 315679 | N86: =+VLOOKUP(M86,Datos!$F:$G,2,FALSE) -> ANGELA XIOMARA PONCIANO GONZALEZ | O86: =IFERROR(IF(A86="SI",VLOOKUP(R86,Datos!$J$1:$K$50,2,FALSE)*C86,VLOOKUP(R86,Datos!$P$1:$T$13,2,FALSE)*C86),0) -> 3024 | P86: 311258 | Q86: =+VLOOKUP(P86,Datos!$F:$G,2,FALSE) -> Victor Otoniel Sebastian Cardona | R86: AP BIENESTAR | V86: =+COUNTIFS($G$2:$G$444,G86) -> 1 | W86: =+VLOOKUP(M86,Datos!$F:$H,3,FALSE) -> 0 | X86: 0 | Z86: =VLOOKUP(M86,'[1]INDIVIDUAL UN'!$C$6:$F$222,4,FALSE) -> #N/A
A87: SI | C87: 1 | D87: NUEVO | E87: VCB-20210003 | F87: 4341 | G87: CELESTINA CHAPERON MENDOZA | H87: 46272 | I87: 46272 | J87: =+VLOOKUP(K87,Datos!$A:$C,3,FALSE) -> SUROCCIDENTE | K87: 31 | L87: =+VLOOKUP(K87,Datos!$A:$C,2,FALSE) -> COATEPEQUE | M87: 90047699 | N87: =+VLOOKUP(M87,Datos!$F:$G,2,FALSE) -> ANDERSON JOSUE OXLAJ BAMACA | O87: =IFERROR(IF(A87="SI",VLOOKUP(R87,Datos!$J$1:$K$50,2,FALSE)*C87,VLOOKUP(R87,Datos!$P$1:$T$13,2,FALSE)*C87),0) -> 816 | P87: 311258 | Q87: =+VLOOKUP(P87,Datos!$F:$G,2,FALSE) -> Victor Otoniel Sebastian Cardona | R87: VIDA+SEGURO | V87: =+COUNTIFS($G$2:$G$444,G87) -> 1 | W87: =+VLOOKUP(M87,Datos!$F:$H,3,FALSE) -> 0 | X87: 0 | Z87: =VLOOKUP(M87,'[1]INDIVIDUAL UN'!$C$6:$F$222,4,FALSE) -> #N/A
A88: SI | C88: 2 | D88: NUEVO | E88: ACPE-20220038 | F88: 164 | G88: PEDRO GARCIA OXLAJ | H88: 46272 | I88: 46272 | J88: =+VLOOKUP(K88,Datos!$A:$C,3,FALSE) -> SUROCCIDENTE | K88: 31 | L88: =+VLOOKUP(K88,Datos!$A:$C,2,FALSE) -> COATEPEQUE | M88: 310671 | N88: =+VLOOKUP(M88,Datos!$F:$G,2,FALSE) -> Sucely Paola Godinez Gomez De Perez | O88: =IFERROR(IF(A88="SI",VLOOKUP(R88,Datos!$J$1:$K$50,2,FALSE)*C88,VLOOKUP(R88,Datos!$P$1:$T$13,2,FALSE)*C88),0) -> 2016 | P88: 306654 | Q88: =+VLOOKUP(P88,Datos!$F:$G,2,FALSE) -> Gerson Arcadio Hernandez Barrios | R88: AP BIENESTAR | V88: =+COUNTIFS($G$2:$G$444,G88) -> 1 | W88: =+VLOOKUP(M88,Datos!$F:$H,3,FALSE) -> 0 | X88: 0 | Z88: =VLOOKUP(M88,'[1]INDIVIDUAL UN'!$C$6:$F$222,4,FALSE) -> #N/A
A89: SI | C89: 1 | D89: NUEVO | E89: ACPE-20210007 | F89: 2584 | G89: MARIA ROSARIO TISTOJ RACANCOJ | H89: 46273 | I89: 46273 | J89: =+VLOOKUP(K89,Datos!$A:$C,3,FALSE) -> OCCIDENTE | K89: 56 | L89: =+VLOOKUP(K89,Datos!$A:$C,2,FALSE) -> LOS ALTOS | M89: 90081234 | N89: =+VLOOKUP(M89,Datos!$F:$G,2,FALSE) -> FRANCISCA CARINA SANCHEZ MACHIC | O89: =IFERROR(IF(A89="SI",VLOOKUP(R89,Datos!$J$1:$K$50,2,FALSE)*C89,VLOOKUP(R89,Datos!$P$1:$T$13,2,FALSE)*C89),0) -> 1008 | P89: 90027915 | Q89: =+VLOOKUP(P89,Datos!$F:$G,2,FALSE) -> FRANDI MAZARIEGOS | R89: AP BIENESTAR | V89: =+COUNTIFS($G$2:$G$444,G89) -> 1 | W89: =+VLOOKUP(M89,Datos!$F:$H,3,FALSE) -> 0 | X89: 0 | Z89: =VLOOKUP(M89,'[1]INDIVIDUAL UN'!$C$6:$F$222,4,FALSE) -> #N/A
A90: SI | C90: 2 | D90: NUEVO | E90: VCB-20220010 | F90: 1180 | G90: DARWIN VICENTE VELASQUEZ VELASQUEZ | H90: 46273 | I90: 46273 | J90: =+VLOOKUP(K90,Datos!$A:$C,3,FALSE) -> SUROCCIDENTE | K90: 178 | L90: =+VLOOKUP(K90,Datos!$A:$C,2,FALSE) -> LA TRINIDAD MALACATAN | M90: 316215 | N90: =+VLOOKUP(M90,Datos!$F:$G,2,FALSE) -> ANAYELI MARIBEL JIMENEZ GOMEZ | O90: =IFERROR(IF(A90="SI",VLOOKUP(R90,Datos!$J$1:$K$50,2,FALSE)*C90,VLOOKUP(R90,Datos!$P$1:$T$13,2,FALSE)*C90),0) -> 1632 | P90: 316487 | Q90: =+VLOOKUP(P90,Datos!$F:$G,2,FALSE) -> Wilmer Ovando Mejia Godínez | R90: VIDA+SEGURO | V90: =+COUNTIFS($G$2:$G$444,G90) -> 1 | W90: =+VLOOKUP(M90,Datos!$F:$H,3,FALSE) -> 0 | X90: 0 | Z90: =VLOOKUP(M90,'[1]INDIVIDUAL UN'!$C$6:$F$222,4,FALSE) -> #N/A
A91: SI | C91: 3 | D91: NUEVO | E91: VCB-20220034 | F91: 614 | G91: ABDONIA BEATRIZ LOPEZ Y LOPEZ | H91: 46273 | I91: 46272 | J91: =+VLOOKUP(K91,Datos!$A:$C,3,FALSE) -> SUROCCIDENTE | K91: 297 | L91: =+VLOOKUP(K91,Datos!$A:$C,2,FALSE) -> LA TRINIDAD COATEPEQUE | M91: 310220 | N91: =+VLOOKUP(M91,Datos!$F:$G,2,FALSE) -> Urias Samuel Velasquez Ardeano | O91: =IFERROR(IF(A91="SI",VLOOKUP(R91,Datos!$J$1:$K$50,2,FALSE)*C91,VLOOKUP(R91,Datos!$P$1:$T$13,2,FALSE)*C91),0) -> 2448 | P91: 311975 | Q91: =+VLOOKUP(P91,Datos!$F:$G,2,FALSE) -> Luis Eduardo Ramirez Arriaza | R91: VIDA+SEGURO | V91: =+COUNTIFS($G$2:$G$444,G91) -> 1 | W91: =+VLOOKUP(M91,Datos!$F:$H,3,FALSE) -> 0 | X91: 0 | Z91: =VLOOKUP(M91,'[1]INDIVIDUAL UN'!$C$6:$F$222,4,FALSE) -> #N/A
A92: SI | C92: 4 | D92: NUEVO | E92: VCB-20240008 | F92: 690 | G92: JOSE ALFREDO DE LEON BATZ | H92: 46273 | I92: 46273 | J92: =+VLOOKUP(K92,Datos!$A:$C,3,FALSE) -> OCCIDENTE | K92: 155 | L92: =+VLOOKUP(K92,Datos!$A:$C,2,FALSE) -> TECPAN | M92: 314450 | N92: =+VLOOKUP(M92,Datos!$F:$G,2,FALSE) -> Rafael Anibal Sut Tucubal | O92: =IFERROR(IF(A92="SI",VLOOKUP(R92,Datos!$J$1:$K$50,2,FALSE)*C92,VLOOKUP(R92,Datos!$P$1:$T$13,2,FALSE)*C92),0) -> 10944 | P92: 305955 | Q92: =+VLOOKUP(P92,Datos!$F:$G,2,FALSE) -> Jorge Alfredo Gutierrez Rodriguez | R92: VIDA+SEGURO PLAN 2 | V92: =+COUNTIFS($G$2:$G$444,G92) -> 1 | W92: =+VLOOKUP(M92,Datos!$F:$H,3,FALSE) -> 0 | X92: 0 | Z92: =VLOOKUP(M92,'[1]INDIVIDUAL UN'!$C$6:$F$222,4,FALSE) -> #N/A
A93: SI | C93: 3 | D93: NUEVO | E93: VCB-20220034 | F93: 619 | G93: EDGAR DIONEL ROJAS VASQUEZ | H93: 46273 | I93: 46273 | J93: =+VLOOKUP(K93,Datos!$A:$C,3,FALSE) -> SUROCCIDENTE | K93: 31 | L93: =+VLOOKUP(K93,Datos!$A:$C,2,FALSE) -> COATEPEQUE | M93: 90047699 | N93: =+VLOOKUP(M93,Datos!$F:$G,2,FALSE) -> ANDERSON JOSUE OXLAJ BAMACA | O93: =IFERROR(IF(A93="SI",VLOOKUP(R93,Datos!$J$1:$K$50,2,FALSE)*C93,VLOOKUP(R93,Datos!$P$1:$T$13,2,FALSE)*C93),0) -> 2448 | P93: 311258 | Q93: =+VLOOKUP(P93,Datos!$F:$G,2,FALSE) -> Victor Otoniel Sebastian Cardona | R93: VIDA+SEGURO | V93: =+COUNTIFS($G$2:$G$444,G93) -> 1 | W93: =+VLOOKUP(M93,Datos!$F:$H,3,FALSE) -> 0 | X93: 0 | Z93: =VLOOKUP(M93,'[1]INDIVIDUAL UN'!$C$6:$F$222,4,FALSE) -> #N/A
A94: SI | C94: 4 | D94: NUEVO | E94: VCB-20240008 | F94: 688 | G94: HUGO ALEXANDER MORGA RODAS | H94: 46273 | I94: 46273 | J94: =+VLOOKUP(K94,Datos!$A:$C,3,FALSE) -> SUROCCIDENTE | K94: 227 | L94: =+VLOOKUP(K94,Datos!$A:$C,2,FALSE) -> PAJAPITA | M94: 90023752 | N94: =+VLOOKUP(M94,Datos!$F:$G,2,FALSE) -> EDY DIONISIO FUENTES MARTINEZ | O94: =IFERROR(IF(A94="SI",VLOOKUP(R94,Datos!$J$1:$K$50,2,FALSE)*C94,VLOOKUP(R94,Datos!$P$1:$T$13,2,FALSE)*C94),0) -> 3264 | P94: 314738 | Q94: =+VLOOKUP(P94,Datos!$F:$G,2,FALSE) -> Carlos David Castillo Gamboa | R94: VIDA+SEGURO | V94: =+COUNTIFS($G$2:$G$444,G94) -> 1 | W94: =+VLOOKUP(M94,Datos!$F:$H,3,FALSE) -> 0 | X94: 0 | Z94: =VLOOKUP(M94,'[1]INDIVIDUAL UN'!$C$6:$F$222,4,FALSE) -> #N/A
A95: SI | C95: 2 | D95: NUEVO | E95: VCB-20220010 | F95: 1170 | G95: EVELYN ARELY HERNANDEZ LOPEZ CHAVEZ | H95: 46273 | I95: 46272 | J95: =+VLOOKUP(K95,Datos!$A:$C,3,FALSE) -> OCCIDENTE | K95: 28 | L95: =+VLOOKUP(K95,Datos!$A:$C,2,FALSE) -> SUCURSAL QUETZALTENANGO | M95: 90024418 | N95: =+VLOOKUP(M95,Datos!$F:$G,2,FALSE) -> EDNA GABRIELA RAMIREZ | O95: =IFERROR(IF(A95="SI",VLOOKUP(R95,Datos!$J$1:$K$50,2,FALSE)*C95,VLOOKUP(R95,Datos!$P$1:$T$13,2,FALSE)*C95),0) -> 1632 | P95: 313644 | Q95: =+VLOOKUP(P95,Datos!$F:$G,2,FALSE) -> Estefani Elizabeth Tzul Macario | R95: VIDA+SEGURO | V95: =+COUNTIFS($G$2:$G$444,G95) -> 1 | W95: =+VLOOKUP(M95,Datos!$F:$H,3,FALSE) -> 0 | X95: 0 | Z95: =VLOOKUP(M95,'[1]INDIVIDUAL UN'!$C$6:$F$222,4,FALSE) -> #N/A
A96: SI | C96: 1 | D96: NUEVO | E96: VCB-20210003 | F96: 4353 | G96: MATEO GOMEZ HERNANDEZ | H96: 46273 | I96: 46273 | J96: =+VLOOKUP(K96,Datos!$A:$C,3,FALSE) -> OCCIDENTE | K96: 246 | L96: =+VLOOKUP(K96,Datos!$A:$C,2,FALSE) -> SANTA CRUZ BARILLAS | M96: 316120 | N96: =+VLOOKUP(M96,Datos!$F:$G,2,FALSE) -> JUANA CANDELARIA LORENZO MATEO | O96: =IFERROR(IF(A96="SI",VLOOKUP(R96,Datos!$J$1:$K$50,2,FALSE)*C96,VLOOKUP(R96,Datos!$P$1:$T$13,2,FALSE)*C96),0) -> 2736 | P96: 304166 | Q96: =+VLOOKUP(P96,Datos!$F:$G,2,FALSE) -> Maviela Bibianeth Castillo Avila | R96: VIDA+SEGURO PLAN 2 | V96: =+COUNTIFS($G$2:$G$444,G96) -> 1 | W96: =+VLOOKUP(M96,Datos!$F:$H,3,FALSE) -> 0 | X96: 0 | Z96: =VLOOKUP(M96,'[1]INDIVIDUAL UN'!$C$6:$F$222,4,FALSE) -> #N/A
A97: SI | C97: 1 | D97: NUEVO | E97: ACPE-20210019 | F97: 2901 | G97: ISAIAS LUIS BAQUIAX TULUJAN | H97: 46273 | I97: 46273 | J97: =+VLOOKUP(K97,Datos!$A:$C,3,FALSE) -> OCCIDENTE | K97: 150 | L97: =+VLOOKUP(K97,Datos!$A:$C,2,FALSE) -> SANTA CRUZ DEL QUICHE | M97: 90034373 | N97: =+VLOOKUP(M97,Datos!$F:$G,2,FALSE) -> SILVIA PATRICIA MENDOZA GOMEZ | O97: =IFERROR(IF(A97="SI",VLOOKUP(R97,Datos!$J$1:$K$50,2,FALSE)*C97,VLOOKUP(R97,Datos!$P$1:$T$13,2,FALSE)*C97),0) -> 1308 | P97: 310329 | Q97: =+VLOOKUP(P97,Datos!$F:$G,2,FALSE) -> Ana Leticia Lux Say | R97: AP DENTAL INDIVIDUAL | V97: =+COUNTIFS($G$2:$G$444,G97) -> 1 | W97: =+VLOOKUP(M97,Datos!$F:$H,3,FALSE) -> 0 | X97: 0 | Z97: =VLOOKUP(M97,'[1]INDIVIDUAL UN'!$C$6:$F$222,4,FALSE) -> #N/A
... A110: SI | C110: 2 | D110: VCB | E110: VCB-20220010 | F110: 1185 | G110: ROBERTO BAMAC RAMOS | H110: 46274 | I110: 46274 | J110: =+VLOOKUP(K110,Datos!$A:$C,3,FALSE) -> OCCIDENTE | K110: 243 | L110: =+VLOOKUP(K110,Datos!$A:$C,2,FALSE) -> PRADERA XELA | M110: 90081008 | N110: =+VLOOKUP(M110,Datos!$F:$G,2,FALSE) -> Randy Antonio Lopez Huinac | O110: =IFERROR(IF(A110="SI",VLOOKUP(R110,Datos!$J$1:$K$50,2,FALSE)*C110,VLOOKUP(R110,Datos!$P$1:$T$13,2,FALSE)*C110),0) -> 1632 | P110: 305174 | Q110: =+VLOOKUP(P110,Datos!$F:$G,2,FALSE) -> #N/A | R110: VIDA+SEGURO | V110: =+COUNTIFS($G$2:$G$444,G110) -> 1 | W110: =+VLOOKUP(M110,Datos!$F:$H,3,FALSE) -> 0 | X110: 0 | Z110: =VLOOKUP(M110,'[1]INDIVIDUAL UN'!$C$6:$F$222,4,FALSE) -> #N/A
A111: SI | C111: 4 | D111: NUEVO | E111: VCB-20240008 | F111: 701 | G111: FRANCISCO ANDRES IXCOT MEJIA | H111: 46274 | I111: 46274 | J111: =+VLOOKUP(K111,Datos!$A:$C,3,FALSE) -> SUROCCIDENTE | K111: 143 | L111: =+VLOOKUP(K111,Datos!$A:$C,2,FALSE) -> RETALHULEU LA SIRENA | M111: 313636 | N111: =+VLOOKUP(M111,Datos!$F:$G,2,FALSE) -> Pablo Cesar Oliva Lopez | O111: =IFERROR(IF(A111="SI",VLOOKUP(R111,Datos!$J$1:$K$50,2,FALSE)*C111,VLOOKUP(R111,Datos!$P$1:$T$13,2,FALSE)*C111),0) -> 3264 | P111: OPTIMA | Q111: =+VLOOKUP(P111,Datos!$F:$G,2,FALSE) -> #N/A | R111: VIDA+SEGURO | V111: =+COUNTIFS($G$2:$G$444,G111) -> 1 | W111: =+VLOOKUP(M111,Datos!$F:$H,3,FALSE) -> 0 | X111: 0 | Z111: =VLOOKUP(M111,'[1]INDIVIDUAL UN'!$C$6:$F$222,4,FALSE) -> #N/A
A112: SI | C112: 4 | D112: NUEVO | E112: VCB-20240008 | F112: 703 | G112: TOMAS ANTONIO VASQUEZ RAMOS | H112: 46274 | I112: 46274 | J112: =+VLOOKUP(K112,Datos!$A:$C,3,FALSE) -> SUROCCIDENTE | K112: 31 | L112: =+VLOOKUP(K112,Datos!$A:$C,2,FALSE) -> COATEPEQUE | M112: 90065999 | N112: =+VLOOKUP(M112,Datos!$F:$G,2,FALSE) -> SEPHORA ABIGAIL SANCHEZ HERDOCIA | O112: =IFERROR(IF(A112="SI",VLOOKUP(R112,Datos!$J$1:$K$50,2,FALSE)*C112,VLOOKUP(R112,Datos!$P$1:$T$13,2,FALSE)*C112),0) -> 5472 | P112: 311258 | Q112: =+VLOOKUP(P112,Datos!$F:$G,2,FALSE) -> Victor Otoniel Sebastian Cardona | R112: VIDA+SEGURO PLAN 1 | V112: =+COUNTIFS($G$2:$G$444,G112) -> 1 | W112: =+VLOOKUP(M112,Datos!$F:$H,3,FALSE) -> 0 | X112: 0 | Z112: =VLOOKUP(M112,'[1]INDIVIDUAL UN'!$C$6:$F$222,4,FALSE) -> #N/A
A113: SI | C113: 1 | D113: NUEVO | E113: VCB-20210003 | F113: 4362 | G113: LORENZO DIEGO JUAN | H113: 46274 | I113: 46273 | J113: =+VLOOKUP(K113,Datos!$A:$C,3,FALSE) -> OCCIDENTE | K113: 55 | L113: =+VLOOKUP(K113,Datos!$A:$C,2,FALSE) -> ZENTROPLAZA | M113: 90040629 | N113: =+VLOOKUP(M113,Datos!$F:$G,2,FALSE) -> FRANCIS JOSUE TOMAS ESCALANTE | O113: =IFERROR(IF(A113="SI",VLOOKUP(R113,Datos!$J$1:$K$50,2,FALSE)*C113,VLOOKUP(R113,Datos!$P$1:$T$13,2,FALSE)*C113),0) -> 816 | P113: 309191 | Q113: =+VLOOKUP(P113,Datos!$F:$G,2,FALSE) -> Raul Matias Matias | R113: VIDA+SEGURO | V113: =+COUNTIFS($G$2:$G$444,G113) -> 1 | W113: =+VLOOKUP(M113,Datos!$F:$H,3,FALSE) -> 0 | X113: 0 | Z113: =VLOOKUP(M113,'[1]INDIVIDUAL UN'!$C$6:$F$222,4,FALSE) -> #N/A
A114: SI | C114: 1 | D114: c | E114: ACPE20210031 | F114: 2477 | G114: ELIEL ADONY LOPEZ DEL VALLE | H114: 46274 | I114: 46274 | J114: =+VLOOKUP(K114,Datos!$A:$C,3,FALSE) -> OCCIDENTE | K114: 33 | L114: =+VLOOKUP(K114,Datos!$A:$C,2,FALSE) -> HUEHUETENANGO | M114: 90045663 | N114: =+VLOOKUP(M114,Datos!$F:$G,2,FALSE) -> MICHELLE JAMILETH MARTINEZ GARCIA | O114: =IFERROR(IF(A114="SI",VLOOKUP(R114,Datos!$J$1:$K$50,2,FALSE)*C114,VLOOKUP(R114,Datos!$P$1:$T$13,2,FALSE)*C114),0) -> 1704 | P114: 301644 | Q114: =+VLOOKUP(P114,Datos!$F:$G,2,FALSE) -> Imelda Eugenia Recinos Martinez | R114: MULTIASISTENCIAS | V114: =+COUNTIFS($G$2:$G$444,G114) -> 1 | W114: =+VLOOKUP(M114,Datos!$F:$H,3,FALSE) -> 0 | X114: 0 | Z114: =VLOOKUP(M114,'[1]INDIVIDUAL UN'!$C$6:$F$222,4,FALSE) -> #N/A
A115: SI | C115: 2 | D115: NUEVO | E115: VCB-20220010 | F115: 1187 | G115: DIONISIO PANJOJ CONOZ | H115: 46274 | I115: 46274 | J115: =+VLOOKUP(K115,Datos!$A:$C,3,FALSE) -> OCCIDENTE | K115: 126 | L115: =+VLOOKUP(K115,Datos!$A:$C,2,FALSE) -> CHICHICASTENANGO | M115: 310610 | N115: =+VLOOKUP(M115,Datos!$F:$G,2,FALSE) -> Ricky Edson Lux Cassia | O115: =IFERROR(IF(A115="SI",VLOOKUP(R115,Datos!$J$1:$K$50,2,FALSE)*C115,VLOOKUP(R115,Datos!$P$1:$T$13,2,FALSE)*C115),0) -> 2736 | P115: 303674 | Q115: =+VLOOKUP(P115,Datos!$F:$G,2,FALSE) -> Imelda Elizabeth Castro Rodas | R115: VIDA+SEGURO PLAN 1 | V115: =+COUNTIFS($G$2:$G$444,G115) -> 1 | W115: =+VLOOKUP(M115,Datos!$F:$H,3,FALSE) -> 0 | X115: 0 | Z115: =VLOOKUP(M115,'[1]INDIVIDUAL UN'!$C$6:$F$222,4,FALSE) -> #N/A
A116: SI | C116: 3 | D116: NUEVO | E116: VCB-20220034 | F116: 625 | G116: SEBASTIAN MORALES MATEO | H116: 46274 | I116: 46274 | J116: =+VLOOKUP(K116,Datos!$A:$C,3,FALSE) -> OCCIDENTE | K116: 126 | L116: =+VLOOKUP(K116,Datos!$A:$C,2,FALSE) -> CHICHICASTENANGO | M116: 310610 | N116: =+VLOOKUP(M116,Datos!$F:$G,2,FALSE) -> Ricky Edson Lux Cassia | O116: =IFERROR(IF(A116="SI",VLOOKUP(R116,Datos!$J$1:$K$50,2,FALSE)*C116,VLOOKUP(R116,Datos!$P$1:$T$13,2,FALSE)*C116),0) -> 2448 | P116: 303674 | Q116: =+VLOOKUP(P116,Datos!$F:$G,2,FALSE) -> Imelda Elizabeth Castro Rodas | R116: VIDA+SEGURO | V116: =+COUNTIFS($G$2:$G$444,G116) -> 1 | W116: =+VLOOKUP(M116,Datos!$F:$H,3,FALSE) -> 0 | X116: 0 | Z116: =VLOOKUP(M116,'[1]INDIVIDUAL UN'!$C$6:$F$222,4,FALSE) -> #N/A
A117: SI | C117: 3 | D117: VIDA PLAN 2 | E117: VCB 20220034 | F117: 622 | G117: CARLOS DANIEL LEIVA COYOY | H117: 46274 | I117: 46274 | J117: =+VLOOKUP(K117,Datos!$A:$C,3,FALSE) -> OCCIDENTE | K117: 56 | L117: =+VLOOKUP(K117,Datos!$A:$C,2,FALSE) -> LOS ALTOS | M117: 315133 | N117: =+VLOOKUP(M117,Datos!$F:$G,2,FALSE) -> Bryan Daniel Milián De Leon | O117: =IFERROR(IF(A117="SI",VLOOKUP(R117,Datos!$J$1:$K$50,2,FALSE)*C117,VLOOKUP(R117,Datos!$P$1:$T$13,2,FALSE)*C117),0) -> 8208 | P117: 308266 | Q117: =+VLOOKUP(P117,Datos!$F:$G,2,FALSE) -> Julio Cesar De Leon Huinac | R117: VIDA+SEGURO PLAN 2 | V117: =+COUNTIFS($G$2:$G$444,G117) -> 1 | W117: =+VLOOKUP(M117,Datos!$F:$H,3,FALSE) -> 0 | X117: 0 | Z117: =VLOOKUP(M117,'[1]INDIVIDUAL UN'!$C$6:$F$222,4,FALSE) -> #N/A
A118: SI | C118: 4 | D118: NUEVO | E118: APSS-20240009 | F118: 243 | G118: ANA ESTEBAN RAMON | H118: 46274 | I118: 46274 | J118: =+VLOOKUP(K118,Datos!$A:$C,3,FALSE) -> OCCIDENTE | K118: 246 | L118: =+VLOOKUP(K118,Datos!$A:$C,2,FALSE) -> SANTA CRUZ BARILLAS | M118: 312087 | N118: =+VLOOKUP(M118,Datos!$F:$G,2,FALSE) -> Yoni Yosuen Rodriguez Sosa | O118: =IFERROR(IF(A118="SI",VLOOKUP(R118,Datos!$J$1:$K$50,2,FALSE)*C118,VLOOKUP(R118,Datos!$P$1:$T$13,2,FALSE)*C118),0) -> 8016 | P118: 304166 | Q118: =+VLOOKUP(P118,Datos!$F:$G,2,FALSE) -> Maviela Bibianeth Castillo Avila | R118: CONSULTA COMPLETO | V118: =+COUNTIFS($G$2:$G$444,G118) -> 1 | W118: =+VLOOKUP(M118,Datos!$F:$H,3,FALSE) -> 0 | X118: 0 | Z118: =VLOOKUP(M118,'[1]INDIVIDUAL UN'!$C$6:$F$222,4,FALSE) -> #N/A
A119: SI | C119: 2 | D119: NUEVO | E119: VCB- 20220010 | F119: 1190 | G119: GLORIA ERMINIA HERNANDEZ RIVERA | H119: 46274 | I119: 46274 | J119: =+VLOOKUP(K119,Datos!$A:$C,3,FALSE) -> SUROCCIDENTE | K119: 227 | L119: =+VLOOKUP(K119,Datos!$A:$C,2,FALSE) -> PAJAPITA | M119: 90019192 | N119: =+VLOOKUP(M119,Datos!$F:$G,2,FALSE) -> AXEL YONELDIS GASPAR JUAREZ | O119: =IFERROR(IF(A119="SI",VLOOKUP(R119,Datos!$J$1:$K$50,2,FALSE)*C119,VLOOKUP(R119,Datos!$P$1:$T$13,2,FALSE)*C119),0) -> 1632 | P119: 316011 | Q119: =+VLOOKUP(P119,Datos!$F:$G,2,FALSE) -> KEVIN MAUEL PEREZ OROZCO | R119: VIDA+SEGURO | V119: =+COUNTIFS($G$2:$G$444,G119) -> 1 | W119: =+VLOOKUP(M119,Datos!$F:$H,3,FALSE) -> 0 | X119: 0 | Z119: =VLOOKUP(M119,'[1]INDIVIDUAL UN'!$C$6:$F$222,4,FALSE) -> #N/A
A120: SI | C120: 3 | D120: NUEVO | E120: VCB-20220046 | F120: 110 | G120: ROGER DENIS CASTILLO LOPEZ | H120: 46274 | I120: 46274 | J120: =+VLOOKUP(K120,Datos!$A:$C,3,FALSE) -> SUROCCIDENTE | K120: 31 | L120: =+VLOOKUP(K120,Datos!$A:$C,2,FALSE) -> COATEPEQUE | M120: 90046882 | N120: =+VLOOKUP(M120,Datos!$F:$G,2,FALSE) -> MARICRUZ MENDEZ LOPEZ | O120: =IFERROR(IF(A120="SI",VLOOKUP(R120,Datos!$J$1:$K$50,2,FALSE)*C120,VLOOKUP(R120,Datos!$P$1:$T$13,2,FALSE)*C120),0) -> 3276 | P120: 306656 | Q120: =+VLOOKUP(P120,Datos!$F:$G,2,FALSE) -> Wilmer Benjamin Vasquez Puac | R120: PREVENCION+SEGURA | V120: =+COUNTIFS($G$2:$G$444,G120) -> 1 | W120: =+VLOOKUP(M120,Datos!$F:$H,3,FALSE) -> 0 | X120: 0 | Z120: =VLOOKUP(M120,'[1]INDIVIDUAL UN'!$C$6:$F$222,4,FALSE) -> #N/A
A121: SI | C121: 4 | D121: VCB | E121: VCB20240008 | F121: 705 | G121: MIGUEL ANGEL RODRIGUEZ VASQUEZ | H121: 46275 | I121: 46275 | J121: =+VLOOKUP(K121,Datos!$A:$C,3,FALSE) -> SUROCCIDENTE | K121: 31 | L121: =+VLOOKUP(K121,Datos!$A:$C,2,FALSE) -> COATEPEQUE | M121: 309812 | N121: =+VLOOKUP(M121,Datos!$F:$G,2,FALSE) -> Elena Yazmin Valdez Gallegos | O121: =IFERROR(IF(A121="SI",VLOOKUP(R121,Datos!$J$1:$K$50,2,FALSE)*C121,VLOOKUP(R121,Datos!$P$1:$T$13,2,FALSE)*C121),0) -> 10944 | P121: 306654 | Q121: =+VLOOKUP(P121,Datos!$F:$G,2,FALSE) -> Gerson Arcadio Hernandez Barrios | R121: VIDA+SEGURO PLAN 2 | V121: =+COUNTIFS($G$2:$G$444,G121) -> 1 | W121: =+VLOOKUP(M121,Datos!$F:$H,3,FALSE) -> 0 | X121: 0 | Z121: =VLOOKUP(M121,'[1]INDIVIDUAL UN'!$C$6:$F$222,4,FALSE) -> #N/A
A122: SI | C122: 1 | D122: NUEVO | E122: VCB-20210003 | F122: 4397 | G122: FELIX FERNANDO BATZ SOCOP | H122: 46275 | I122: 46275 | J122: =+VLOOKUP(K122,Datos!$A:$C,3,FALSE) -> OCCIDENTE | K122: 157 | L122: =+VLOOKUP(K122,Datos!$A:$C,2,FALSE) -> TOTONICAPAN | M122: 315460 | N122: =+VLOOKUP(M122,Datos!$F:$G,2,FALSE) -> Marvin Leonel Hernandez Alvarez | O122: =IFERROR(IF(A122="SI",VLOOKUP(R122,Datos!$J$1:$K$50,2,FALSE)*C122,VLOOKUP(R122,Datos!$P$1:$T$13,2,FALSE)*C122),0) -> 816 | P122: 312665 | Q122: =+VLOOKUP(P122,Datos!$F:$G,2,FALSE) -> Zulma Damaris Menchu Mendez | R122: VIDA+SEGURO | V122: =+COUNTIFS($G$2:$G$444,G122) -> 1 | W122: =+VLOOKUP(M122,Datos!$F:$H,3,FALSE) -> 0 | X122: 0 | Z122: =VLOOKUP(M122,'[1]INDIVIDUAL UN'!$C$6:$F$222,4,FALSE) -> #N/A
A123: SI | C123: 4 | D123: NUEVO | E123: VCB-20240008 | F123: 704 | G123: ROMULO CORDOVA GUZMAN | H123: 46275 | I123: 46275 | J123: =+VLOOKUP(K123,Datos!$A:$C,3,FALSE) -> SUROCCIDENTE | K123: 297 | L123: =+VLOOKUP(K123,Datos!$A:$C,2,FALSE) -> LA TRINIDAD COATEPEQUE | M123: 312831 | N123: =+VLOOKUP(M123,Datos!$F:$G,2,FALSE) -> Cindy Yojana Mendoza Cajas | O123: =IFERROR(IF(A123="SI",VLOOKUP(R123,Datos!$J$1:$K$50,2,FALSE)*C123,VLOOKUP(R123,Datos!$P$1:$T$13,2,FALSE)*C123),0) -> 3264 | P123: 311975 | Q123: =+VLOOKUP(P123,Datos!$F:$G,2,FALSE) -> Luis Eduardo Ramirez Arriaza | R123: VIDA+SEGURO | V123: =+COUNTIFS($G$2:$G$444,G123) -> 1 | W123: =+VLOOKUP(M123,Datos!$F:$H,3,FALSE) -> 0 | X123: 0 | Z123: =VLOOKUP(M123,'[1]INDIVIDUAL UN'!$C$6:$F$222,4,FALSE) -> #N/A
...

Sheet Datos
A1: FTE. | B1: AGENCIA | C1: ZONA | F1: Codigo Empleado | G1: Nombre Empleado | H1: Codigo Empleado | I1: BAM | J1: Producto | K1: 1 año | L1: 2 años | M1: 3 años | N1: 4 años | O1: OTRO BANCO | P1: Producto | Q1: 1 año | R1: 2 años | S1: 3 años | T1: 4 años
A2: 14 | B2: PRADERA | C2: AMERICAS | F2: 314692 | G2: Abi Susana Santos Alvarado | H2: 0 | J2: VIDA+SEGURO | K2: 816 | L2: =+K2*2 -> 1632 | M2: =+K2*3 -> 2448 | N2: =+K2*4 -> 3264 | P2: VIDA+SEGURO | Q2: 888 | R2: =+Q2*2 -> 1776 | S2: =+Q2*3 -> 2664 | T2: =+Q2*4 -> 3552
A3: 53 | B3: PUERTA PARADA | C3: AMERICAS | F3: 313537 | G3: Abigail Nohemi Letona Lopez | H3: 0 | J3: CONSULTA COMPLETO + BIENESTAR | K3: 2472 | L3: =+K3*2 -> 4944 | M3: =+K3*3 -> 7416 | N3: =+K3*4 -> 9888 | P3: CONSULTA COMPLETO + BIENESTAR | Q3: 2676 | R3: =+Q3*2 -> 5352 | S3: =+Q3*3 -> 8028 | T3: =+Q3*4 -> 10704
A4: 54 | B4: LAS CONCHAS ZONA 14 | C4: AMERICAS | F4: 314163 | G4: Abner Amilcar Miguel Pedro | H4: 0 | J4: CONSULTA BASICO | K4: 1428 | L4: =+K4*2 -> 2856 | M4: =+K4*3 -> 4284 | N4: =+K4*4 -> 5712 | P4: CONSULTA BASICO | Q4: 1548 | R4: =+Q4*2 -> 3096 | S4: =+Q4*3 -> 4644 | T4: =+Q4*4 -> 6192
A5: 58 | B5: EUROPLAZA | C5: AMERICAS | F5: 300544 | G5: Abner Enmanuel Perez Rodriguez | H5: 0 | J5: CONSULTA BASICO + BIENESTAR | K5: 1908 | L5: =+K5*2 -> 3816 | M5: =+K5*3 -> 5724 | N5: =+K5*4 -> 7632 | P5: CONSULTA BASICO + BIENESTAR | Q5: 2064 | R5: =+Q5*2 -> 4128 | S5: =+Q5*3 -> 6192 | T5: =+Q5*4 -> 8256
A6: 71 | B6: VISTA HERMOSA | C6: AMERICAS | F6: 315208 | G6: Abner Juan Alexander Menchu Tiu | H6: 0 | J6: MULTIASISTENCIAS | K6: 1704 | L6: =+K6*2 -> 3408 | M6: =+K6*3 -> 5112 | N6: =+K6*4 -> 6816 | P6: MULTIASISTENCIAS | Q6: 1848 | R6: =+Q6*2 -> 3696 | S6: =+Q6*3 -> 5544 | T6: =+Q6*4 -> 7392
A7: 90 | B7: CENTRO MEDICO | C7: AMERICAS | F7: 315069 | G7: Abner Rocael Sosa Escobar | H7: 0 | J7: AP DENTAL FAMILIAR | K7: 1332 | L7: =+K7*2 -> 2664 | M7: =+K7*3 -> 3996 | N7: =+K7*4 -> 5328 | P7: AP DENTAL FAMILIAR | Q7: 1440 | R7: =+Q7*2 -> 2880 | S7: =+Q7*3 -> 4320 | T7: =+Q7*4 -> 5760
A8: 92 | B8: CONDADO CONCEPCION | C8: AMERICAS | F8: 310864 | G8: Adelaida Garcia Hernandez | H8: 0 | J8: AP BIENESTAR | K8: 1008 | L8: =+K8*2 -> 2016 | M8: =+K8*3 -> 3024 | N8: =+K8*4 -> 4032 | P8: AP BIENESTAR | Q8: 1092 | R8: =+Q8*2 -> 2184 | S8: =+Q8*3 -> 3276 | T8: =+Q8*4 -> 4368
A9: 224 | B9: MINUTO CARRETERA A EL SALVADOR | C9: AMERICAS | F9: 314604 | G9: Adieny Moren Ramirez Gamboa | H9: 0 | J9: AUTO+SEGURO (AUTO) | K9: 1308 | L9: =+K9*2 -> 2616 | M9: =+K9*3 -> 3924 | N9: =+K9*4 -> 5232 | P9: AUTO+SEGURO (AUTO) | Q9: 1417 | R9: =+Q9*2 -> 2834 | S9: =+Q9*3 -> 4251 | T9: =+Q9*4 -> 5668
A10: 226 | B10: SAN JOSE PINULA | C10: AMERICAS | F10: 311687 | G10: Aida Gabriela De Leon Carrascoza | H10: 0 | J10: PREVENCION+SEGURA | K10: 1092 | L10: =+K10*2 -> 2184 | M10: =+K10*3 -> 3276 | N10: =+K10*4 -> 4368 | P10: PREVENCION+SEGURA | Q10: 1200 | R10: =+Q10*2 -> 2400 | S10: =+Q10*3 -> 3600 | T10: =+Q10*4 -> 4800
A11: 231 | B11: SANTA AMELIA ZONA 16 | C11: AMERICAS | F11: 315221 | G11: Alan David Perez Muyus | H11: 0 | J11: AP DENTAL INDIVIDUAL | K11: 1308 | L11: =+K11*2 -> 2616 | M11: =+K11*3 -> 3924 | N11: =+K11*4 -> 5232 | P11: AP DENTAL INDIVIDUAL | Q11: 1416 | R11: =+Q11*2 -> 2832 | S11: =+Q11*3 -> 4248 | T11: =+Q11*4 -> 5664
A12: 278 | B12: HINCAPIE | C12: AMERICAS | F12: 311950 | G12: Alan Javier Castillo Ordoñez | H12: 0 | J12: CONSULTA COMPLETO | K12: 2004 | L12: =+K12*2 -> 4008 | M12: =+K12*3 -> 6012 | N12: =+K12*4 -> 8016 | P12: CONSULTA COMPLETO | Q12: 2172 | R12: =+Q12*2 -> 4344 | S12: =+Q12*3 -> 6516 | T12: =+Q12*4 -> 8688
A13: 294 | B13: PLAZA ZONA 14 | C13: AMERICAS | F13: 313765 | G13: Alan Ricardo Flores Diaz | H13: 0 | J13: AUTO+SEGURO (PICK UP) | K13: 1788 | L13: =+K13*2 -> 3576 | M13: =+K13*3 -> 5364 | N13: =+K13*4 -> 7152 | P13: AUTO+SEGURO (PICK UP) | Q13: 1937 | R13: =+Q13*2 -> 3874 | S13: =+Q13*3 -> 5811 | T13: =+Q13*4 -> 7748
... A19: 12 | B19: PLAZA FLORIDA | C19: CENTRO HISTORICO | F19: 315220 | G19: Alejandro Jose Mont Diaz | H19: 0 | J19: MIGRANTE BAM | K19: 1380 | L19: =+K19*2 -> 2760 | M19: =+K19*3 -> 4140 | N19: =+K19*4 -> 5520 | P19: MIGRANTE BAM | Q19: 1500 | R19: =+Q19*2 -> 3000 | S19: =+Q19*3 -> 4500 | T19: =+Q19*4 -> 6000
A20: 13 | B20: METANORTE | C20: CENTRO HISTORICO | F20: 311810 | G20: Alexander Macario Gonzalez Monterroso | H20: 0 | J20: MOTO+SEGURA | K20: 1500 | L20: 3000 | M20: 4500 | N20: 6000 | P20: MOTO+SEGURA | Q20: 1620 | R20: 3240 | S20: 4860 | T20: 6480
A21: 19 | B21: MORAZAN ZONA 2 | C21: CENTRO HISTORICO | F21: 300907 | G21: Alexangel Quan Urrutia | H21: 0
A22: 37 | B22: SAN JUAN SACATEPEQUEZ | C22: ROOSEVELT | F22: 312962 | G22: Alexia Paola Marroquin Lopez | H22: 0
A23: 61 | B23: DEL CENTRO | C23: CENTRO HISTORICO | F23: 314671 | G23: Alexsandra Daniela Cano Garcia | H23: 0
A24: 81 | B24: PEDRERA | C24: CENTRO HISTORICO | F24: 311103 | G24: Alfredo Chiyal Bocel | H24: 0
A25: 83 | B25: DISAGRO | C25: CENTRO HISTORICO | F25: 311576 | G25: Alfredo Gomez Lancerio | H25: 0
A26: 87 | B26: EL NARANJO | C26: CENTRO HISTORICO | F26: 313014 | G26: Alfredo Monsanto Santos | H26: 0
A27: 98 | B27: CALLE MARTI | C27: CENTRO HISTORICO | F27: 315223 | G27: Alicia Magaly Juarez Quiacain | H27: 0
A28: 103 | B28: LOS ALAMOS | C28: CENTRO HISTORICO | F28: 314035 | G28: Alisson Andrea Jacobo Castro | H28: 0
A29: 113 | B29: PARQUE COLON | C29: CENTRO HISTORICO | F29: 315214 | G29: Allan David Galdamez De Leon | H29: 0
A30: 166 | B30: 23 CALLE | C30: CENTRO HISTORICO | F30: 306902 | G30: Allan Kalleb Garcia Cahuex | H30: 0
A31: 296 | B31: PORTALES | C31: CENTRO HISTORICO | F31: 315434 | G31: Alma Carolina Herrera Pirir | H31: 0
A32: 302 | B32: CENTRANORTE | C32: CENTRO HISTORICO | F32: 315280 | G32: Alma Rosa Valle Blandon | H32: 0
... A170: 355 | B170: PARADOR DEL MAR | C170: COSTA SUR | F170: 315158 | G170: Carlos Emilio Cumez Chenol | H170: 0
F171: 312533 | G171: Carlos Enrique Coz Toc | H171: 0
F172: 314773 | G172: Carlos Enrique Ramirez Lopez | H172: 0
F173: 313303 | G173: Carlos Enrique Vasquez Esteban | H173: 0
F174: 314841 | G174: Carlos Estuardo Campos Asig | H174: 0
F175: 308075 | G175: Carlos Humberto De Paz Paiz | H175: 0
F176: 314441 | G176: Carlos Josue Perez Garcia | H176: 0
F177: 202153 | G177: Carlos Leonel Corado Sosa | H177: 0
F178: 313324 | G178: Carlos Miguel Carrillo Perez | H178: 0
F179: 310535 | G179: Carlos Oliverio Ortiz Villalobos | H179: 0
F180: 315501 | G180: Carlos Onofre Sierra Vasquez | H180: 0
F181: 313844 | G181: Carlos Raul Pedroza Lopez | H181: 0
F182: 315111 | G182: Carlos Roberto Arana Garcia | H182: 0
... F499: 315154 | G499: Hector Estuardo Velasquez Carvajal | H499: 0
F500: 312588 | G500: Hector Manuel Pojoy Berduo | H500: Phoenix
F501: 309925 | G501: Hector Marco Tulio Torres Garcia | H501: 0
F502: 312114 | G502: Hegner Aquino Mateo Recinos | H502: 0
F503: 310694 | G503: Heidy Carolina Monterroso Monterroso | H503: 0
F504: 315300 | G504: Heidy Karina Gil Quinti | H504: 0
F505: 314029 | G505: Heidy Noely Yupe Hernandez | H505: 0
F506: 313510 | G506: Heidy Patricia Santizo López | H506: 0
F507: 308951 | G507: Heidy Sucely Boc Monroy | H507: 0
F508: 301847 | G508: Heidy Yanet Reyes Presencin | H508: 0
F509: 314009 | G509: Heily Marie Taracena Diaz | H509: 0
F510: 303959 | G510: Helen Editt Solorzano Estrada | H510: 0
F511: 308028 | G511: Helen Eunice Hernandez Recinos | H511: 0
F512: 302479 | G512: Helen Xiomara Roldan Sagastume | H512: 0
... F1555: 314769 | G1555: Abel Eduardo Lopez Lopez | H1555: 0
F1556: 314839 | G1556: Ana Gabriela Samayoa Lopez | H1556: Elements
F1557: 315422 | G1557: Carlos Alberto Roque | H1557: 0
F1558: 314836 | G1558: Carlos David Ajmac | H1558: 0
F1559: 314759 | G1559: Carlos Roberto Hernandez Gonzalez | H1559: 0
F1560: 314757 | G1560: Cristal Estephania Juarroz Muñoz | H1560: 0
F1561: 314817 | G1561: Cristian Orlando Monzon De Leon | H1561: 0
F1562: 314815 | G1562: Gabriela Elizabeth Alvarez Mix | H1562: Phoenix
F1563: 315421 | G1563: Gladis Morales Cutzal | H1563: 0
F1564: 314794 | G1564: Herbert Wellington Rodriguez Ramirez | H1564: Espartanos
F1565: 314760 | G1565: Jadurani Devi Dasi Archila Lool | H1565: 0
F1566: 314838 | G1566: Jenifer Lucerito Sique Mayorga | H1566: 0
F1567: 314790 | G1567: Johana Vidalia Chach Ixcoy | H1567: Phoenix
F1568: 314846 | G1568: Jonnathan Josue Rodas Florian | H1568: 0
F1569: 314761 | G1569: Jorge Eduardo Fonseca Palacios | H1569: 0
F1570: 314842 | G1570: Jose Geovanni Castañeda Galindo | H1570: 0
F1571: 314756 | G1571: Juan Manuel Gomez Sampuel | H1571: 0
F1572: 315366 | G1572: Mario Enrique Morales Escobar | H1572: 0
F1573: 315392 | G1573: Mijail Erick Joaquín Morales Ortiz | H1573: 0
F1574: 314843 | G1574: Nancy Pahola Arevalo Yuman | H1574: 0
F1575: 314791 | G1575: Norman Scott Castillo Rivera | H1575: 0
F1576: 314799 | G1576: Rusbelindo Miguel Lopez | H1576: 0
F1577: 314751 | G1577: Ana Lucia Veliz Solares | H1577: 0
F1578: 315169 | G1578: Andy Oswaldo Pineda Arriola | H1578: 0
F1579: 314903 | G1579: Cindy Julissa Herrera | H1579: 0
... F1592: 311961 | G1592: Abner Eli Gonzalez Gonzalez | H1592: 0
F1593: 311188 | G1593: Ana Ester Cuyan Aguilar De Dominguez | H1593: Elements
F1594: 311894 | G1594: Christyan Stuardo Ronquillo Saravia | H1594: Elements
F1595: 308901 | G1595: David Estuardo Rosales Corado | H1595: 0
F1596: 312069 | G1596: De Leon Cach Roberto Carlos | H1596: 0
F1597: 310331 | G1597: Elda Luzbina Valdez Guerra De Fuentes | H1597: Elements
F1598: 310822 | G1598: Jennifer Leticia Gonzalez Pineda | H1598: Elements
F1599: 308012 | G1599: Jocelyn Sucel Yantuche Chin | H1599: 0
F1600: 312160 | G1600: Jose Rigoberto Osorio Abarca | H1600: Elements
F1601: 311465 | G1601: Kevin Alejandro Corado Estrada | H1601: 0
F1602: 311294 | G1602: Lotar Robson Araujo Perez | H1602: 0
F1603: 310910 | G1603: Luis Fernando Lopez Vasquez | H1603: 0
F1604: 304279 | G1604: Marlon Estuardo Hernandez | H1604: 0
F1605: 308911 | G1605: Rudy Fernando Orozco Tejeda | H1605: 0
F1606: 310214 | G1606: Vivian Pamela Rodas Lopez | H1606: Elements
F1607: 314928 | G1607: Brandon Steve Juarez Arrazola | H1607: Elements
F1608: 313239 | G1608: Addy Aida Cifuentes Coronado | H1608: 0
F1609: 313694 | G1609: Alex Humberto Montezuma | H1609: Elements
F1610: 313241 | G1610: Angel Arturo Mauricio Ayapan | H1610: 0
F1611: 314323 | G1611: Angel Arturo Mauricio Ayapan | H1611: Elements
F1612: 312327 | G1612: Armando Andree Quiñonez Flores | H1612: 0
...
